Workbook

Sheet games
A1: Name | B1: Year | C1: Type | D1: Connected? | E1: Influencer? | F1: Tags | G1: File | H1: Owned | I1: File Location | J1: Steam Page
A2: [Redacted] | B2: 2024 | C2: Action | D2: =TRUE() -> TRUE | E2: =COUNTIF(connections!A:A, A2) > 0 -> FALSE | G2: redacted
A3: 100 Rogues | B3: 2010 | C3: Traditional | D3: =TRUE() -> TRUE | E3: =COUNTIF(connections!A:A, A3) > 0 -> TRUE | G3: 100-rogues
A4: 2 Fights in 2 Tight Spaces | B4: 2026 | C4: Deckbuilder | D4: =TRUE() -> TRUE | E4: =COUNTIF(connections!A:A, A4) > 0 -> FALSE | G4: 2-fights-in-2-tight-spaces | J4: https://store.steampowered.com/app/3734890/2_Fights_in_2_Tight_Spaces/
A5: 20 Minutes Till Dawn | B5: 2022 | C5: Action | D5: =TRUE() -> TRUE | E5: =COUNTIF(connections!A:A, A5) > 0 -> TRUE | G5: 20-minutes-till-dawn | H5: Yes | I5: C:\Users\Owner\Documents\Roguelike Roguelike\Roguelikes\20 Minutes Till Dawn.url | J5: https://store.steampowered.com/app/1966900/20_Minutes_Till_Dawn/
A6: 20XX | B6: 2017 | C6: Action | D6: =TRUE() -> TRUE | E6: =COUNTIF(connections!A:A, A6) > 0 -> TRUE | G6: 20xx | H6: Yes | I6: C:\Users\Owner\Documents\Roguelike Roguelike\Roguelikes\20XX.url | J6: https://store.steampowered.com/app/322110/20XX/
A7: 30XX | B7: 2021 | C7: Action | D7: =TRUE() -> TRUE | E7: =COUNTIF(connections!A:A, A7) > 0 -> FALSE | G7: 30xx | H7: Yes | I7: C:\Users\Owner\Documents\Roguelike Roguelike\Roguelikes\30XX.url | J7: https://store.steampowered.com/app/1029210/30XX/
A8: 33 Immortals | B8: 2026 | C8: Action | D8: =TRUE() -> TRUE | E8: =COUNTIF(connections!A:A, A8) > 0 -> FALSE | F8: hell | G8: 33-immortals | H8: Yes | I8: C:\Users\Owner\Documents\Roguelike Roguelike\Roguelikes\33 Immortals.url | J8: https://store.steampowered.com/app/958520/33_Immortals/
A9: 868-Back | B9: 2026 | C9: Traditional | D9: =TRUE() -> TRUE | E9: =COUNTIF(connections!A:A, A9) > 0 -> FALSE | G9: 868-back | J9: https://store.steampowered.com/app/3304110/868BACK/
A10: 868-Hack | B10: 2015 | C10: Traditional | D10: =TRUE() -> TRUE | E10: =COUNTIF(connections!A:A, A10) > 0 -> TRUE | G10: 868-hack | H10: Yes | I10: C:\Users\Owner\Documents\Roguelike Roguelike\Roguelikes\868-HACK.url | J10: https://store.steampowered.com/app/274700/868HACK/
A11: 9 Kings | B11: 2024 | C11: Deckbuilder | D11: =TRUE() -> TRUE | E11: =COUNTIF(connections!A:A, A11) > 0 -> TRUE | G11: 9-kings | H11: Yes | I11: C:\Users\Owner\Documents\Roguelike Roguelike\Roguelikes\9 Kings.url | J11: https://store.steampowered.com/app/2784470/9_Kings/
A12: 99 Levels to Hell | B12: 2013 | C12: Action | D12: =TRUE() -> TRUE | E12: =COUNTIF(connections!A:A, A12) > 0 -> FALSE | F12: hell | G12: 99-levels-to-hell
A13: A la Card | B13: 2025 | C13: Deckbuilder | D13: =TRUE() -> TRUE | E13: =COUNTIF(connections!A:A, A13) > 0 -> FALSE | G13: a-la-card
A14: A Robot Named Fight! | B14: 2017 | C14: Action | D14: =TRUE() -> TRUE | E14: =COUNTIF(connections!A:A, A14) > 0 -> FALSE | G14: a-robot-named-fight | H14: Yes | I14: C:\Users\Owner\Documents\Roguelike Roguelike\Roguelikes\A Robot Named Fight.url | J14: https://store.steampowered.com/app/603530/A_Robot_Named_Fight/
A15: Abandon Ship | B15: 2019 | C15: Strategy | D15: =TRUE() -> TRUE | E15: =COUNTIF(connections!A:A, A15) > 0 -> FALSE | G15: abandon-ship | H15: Yes | I15: C:\Users\Owner\Documents\Roguelike Roguelike\Roguelikes\Abandon Ship.url | J15: https://store.steampowered.com/app/551860/Abandon_Ship/
A16: Abandoned Archive | B16: 2025 | C16: Action | D16: =TRUE() -> TRUE | E16: =COUNTIF(connections!A:A, A16) > 0 -> FALSE | G16: abandoned-archive
A17: Absolum | B17: 2025 | C17: Action | D17: =TRUE() -> TRUE | E17: =COUNTIF(connections!A:A, A17) > 0 -> FALSE | F17: beat 'em up | G17: absolum | H17: Yes | I17: C:\Users\Owner\Documents\Roguelike Roguelike\Roguelikes\Absolum.url | J17: https://store.steampowered.com/app/1904480/Absolum/
A18: Abyssus | B18: 2025 | C18: Action | D18: =TRUE() -> TRUE | E18: =COUNTIF(connections!A:A, A18) > 0 -> FALSE | G18: abyssus | H18: Yes | I18: C:\Users\Owner\Documents\Roguelike Roguelike\Roguelikes\Abyssus.url | J18: https://store.steampowered.com/app/1721110/Abyssus/
A19: Aces & Adventures | B19: 2023 | C19: Deckbuilder | D19: =TRUE() -> TRUE | E19: =COUNTIF(connections!A:A, A19) > 0 -> FALSE | G19: aces-adventures | H19: Yes | I19: C:\Users\Owner\Documents\Roguelike Roguelike\Roguelikes\Aces and Adventures.url | J19: https://store.steampowered.com/app/1815570/Aces__Adventures/
A20: Across the Obelisk | B20: 2021 | C20: Deckbuilder | D20: =TRUE() -> TRUE | E20: =COUNTIF(connections!A:A, A20) > 0 -> TRUE | G20: across-the-obelisk | H20: Yes | I20: C:\Users\Owner\Documents\Roguelike Roguelike\Roguelikes\Across the Obelisk.url | J20: https://store.steampowered.com/app/1385380/Across_the_Obelisk/
A21: Aethermancer | B21: 2025 | C21: Strategy | D21: =TRUE() -> TRUE | E21: =COUNTIF(connections!A:A, A21) > 0 -> TRUE | G21: aethermancer | H21: Yes | I21: C:\Users\Owner\Documents\Roguelike Roguelike\Roguelikes\Aethermancer.url | J21: https://store.steampowered.com/app/2288470/Aethermancer/
A22: AK-xolotl | B22: 2023 | C22: Action | D22: =TRUE() -> TRUE | E22: =COUNTIF(connections!A:A, A22) > 0 -> FALSE | G22: ak-xolotl | H22: Yes | I22: C:\Users\Owner\Documents\Roguelike Roguelike\Roguelikes\AK-xolotl Together.url | J22: https://store.steampowered.com/app/1479140/AKxolotl_Together/
A23: Alina of the Arena | B23: 2022 | C23: Deckbuilder | D23: =TRUE() -> TRUE | E23: =COUNTIF(connections!A:A, A23) > 0 -> FALSE | G23: alina-of-the-arena | H23: Yes | I23: C:\Users\Owner\Documents\Roguelike Roguelike\Roguelikes\Alina of the Arena.url | J23: https://store.steampowered.com/app/1668690/Alina_of_the_Arena/
A24: An Amazing Wizard | B24: 2025 | C24: Action | D24: =TRUE() -> TRUE | E24: =COUNTIF(connections!A:A, A24) > 0 -> FALSE | G24: an-amazing-wizard | J24: https://store.steampowered.com/app/1372660/An_Amazing_Wizard/
A25: Ancient Domains of Mystery | B25: 1994 | C25: Traditional | D25: =TRUE() -> TRUE | E25: =COUNTIF(connections!A:A, A25) > 0 -> TRUE | G25: ancient-domains-of-mystery | H25: Yes | I25: C:\Users\Owner\Documents\Roguelike Roguelike\Roguelikes\ADOM (Ancient Domains Of Mystery).url | J25: https://store.steampowered.com/app/333300/ADOM_Ancient_Domains_Of_Mystery/
A26: Angband | B26: 1990 | C26: Traditional | D26: =TRUE() -> TRUE | E26: =COUNTIF(connections!A:A, A26) > 0 -> TRUE | G26: angband | H26: Yes | I26: C:\Users\Owner\Documents\Roguelike Roguelike\Roguelikes\angband.lnk
A27: Anomaly Collapse | B27: 2024 | C27: Strategy | D27: =TRUE() -> TRUE | E27: =COUNTIF(connections!A:A, A27) > 0 -> FALSE | G27: anomaly-collapse | J27: https://store.steampowered.com/app/2082410/Anomaly_Collapse/
A28: Another Farm Roguelike | B28: 2022 | C28: Strategy | D28: =FALSE() -> FALSE | E28: =COUNTIF(connections!A:A, A28) > 0 -> TRUE | F28: food | G28: another-farm-roguelike | H28: Yes | I28: C:\Users\Owner\Documents\Roguelike Roguelike\Roguelikes\Another Farm Roguelike.url | J28: https://store.steampowered.com/app/2116850/Another_Farm_Roguelike/
A29: Another Farm Roguelike: Rebirth | B29: 2025 | C29: Strategy | D29: =FALSE() -> FALSE | E29: =COUNTIF(connections!A:A, A29) > 0 -> FALSE | F29: food | G29: another-farm-roguelike-rebirth
A30: Aotenjo: Infinite Hands | B30: 2024 | C30: Deckbuilder | D30: =TRUE() -> TRUE | E30: =COUNTIF(connections!A:A, A30) > 0 -> FALSE | F30: mahjong | G30: aotenjo-infinite-hands
A31: Approaching Infinity | B31: 2020 | C31: Traditional | D31: =TRUE() -> TRUE | E31: =COUNTIF(connections!A:A, A31) > 0 -> FALSE | F31: space | G31: approaching-infinity
A32: Arc Seed | B32: 2024 | C32: Deckbuilder | D32: =TRUE() -> TRUE | E32: =COUNTIF(connections!A:A, A32) > 0 -> FALSE | F32: mecha | G32: arc-seed | H32: Yes | I32: C:\Users\Owner\Documents\Roguelike Roguelike\Roguelikes\ARC SEED.url | J32: https://store.steampowered.com/app/2332970/ARC_SEED/
A33: Arcane Trigger | B33: 2025 | C33: Action | D33: TRUE | E33: =COUNTIF(connections!A:A, A33) > 0 -> FALSE | G33: arcane-trigger
A34: Arcanium: Rise of Akhan | B34: 2020 | C34: Deckbuilder | D34: =TRUE() -> TRUE | E34: =COUNTIF(connections!A:A, A34) > 0 -> FALSE | G34: arcanium-rise-of-akhan | H34: Yes | I34: C:\Users\Owner\Documents\Roguelike Roguelike\Roguelikes\Arcanium.url | J34: https://store.steampowered.com/app/1056840/Arcanium_Rise_of_Akhan/
A35: Archon Soul | B35: 2026 | C35: Deckbuilder | D35: =TRUE() -> TRUE | E35: =COUNTIF(connections!A:A, A35) > 0 -> FALSE | G35: archon-soul | J35: https://store.steampowered.com/app/4252700/Archon_Soul/
A36: Archons | B36: 2024 | C36: Action | D36: =TRUE() -> TRUE | E36: =COUNTIF(connections!A:A, A36) > 0 -> FALSE | G36: archons | H36: Yes | I36: C:\Users\Owner\Documents\Roguelike Roguelike\Roguelikes\Archons.url | J36: https://store.steampowered.com/app/2779570/Archons/
A37: Arms of God | B37: 2026 | C37: Action | D37: =TRUE() -> TRUE | E37: =COUNTIF(connections!A:A, A37) > 0 -> FALSE | G37: arms-of-god | J37: https://store.steampowered.com/app/3100310/Arms_of_God/
A38: Army of Ruin | B38: 2022 | C38: Action | D38: =TRUE() -> TRUE | E38: =COUNTIF(connections!A:A, A38) > 0 -> FALSE | G38: army-of-ruin | H38: Yes | I38: C:\Users\Owner\Documents\Roguelike Roguelike\Roguelikes\Army of Ruin.url | J38: https://store.steampowered.com/app/1918040/Army_of_Ruin/
A39: Arrogue | B39: 2025 | C39: Deckbuilder | D39: =TRUE() -> TRUE | E39: =COUNTIF(connections!A:A, A39) > 0 -> FALSE | G39: arrogue
A40: As We Descend | B40: 2025 | C40: Deckbuilder | D40: =TRUE() -> TRUE | E40: =COUNTIF(connections!A:A, A40) > 0 -> FALSE | G40: as-we-descend
A41: Asgard's Fall: Viking Survivors | B41: 2025 | C41: Action | D41: =TRUE() -> TRUE | E41: =COUNTIF(connections!A:A, A41) > 0 -> FALSE | F41: viking | G41: asgards-fall-viking-survivors | H41: Yes | I41: C:\Users\Owner\Documents\Roguelike Roguelike\Roguelikes\Asgard's Fall — Viking Survivors.url | J41: https://store.steampowered.com/app/2780710/Asgards_Fall__Viking_Survivors/
A42: Asterogues | B42: 2023 | C42: Action | D42: =TRUE() -> TRUE | E42: =COUNTIF(connections!A:A, A42) > 0 -> FALSE | F42: space | G42: asterogues
A43: Astral Ascent | B43: 2022 | C43: Action | D43: =TRUE() -> TRUE | E43: =COUNTIF(connections!A:A, A43) > 0 -> FALSE | G43: astral-ascent | H43: Yes | I43: C:\Users\Owner\Documents\Roguelike Roguelike\Roguelikes\Astral Ascent.url | J43: https://store.steampowered.com/app/1280930/Astral_Ascent/
A44: Astrea: Six-Sided Oracles | B44: 2023 | C44: Deckbuilder | D44: =TRUE() -> TRUE | E44: =COUNTIF(connections!A:A, A44) > 0 -> FALSE | F44: dice | G44: astrea-six-sided-oracles | H44: Yes | I44: C:\Users\Owner\Documents\Roguelike Roguelike\Roguelikes\Astrea Six-Sided Oracles.url | J44: https://store.steampowered.com/app/1755830/Astrea_SixSided_Oracles/
A45: Astro Prospector | B45: 2025 | C45: Action | D45: =TRUE() -> TRUE | E45: =COUNTIF(connections!A:A, A45) > 0 -> FALSE | F45: space | G45: astro-prospector | H45: Yes | I45: C:\Users\Owner\Documents\Roguelike Roguelike\Roguelikes\Astro Prospector.url | J45: https://store.steampowered.com/app/3503440/Astro_Prospector/
A46: Astronarch | B46: 2020 | C46: Strategy | D46: =TRUE() -> TRUE | E46: =COUNTIF(connections!A:A, A46) > 0 -> TRUE | G46: astronarch | H46: Yes | I46: C:\Users\Owner\Documents\Roguelike Roguelike\Roguelikes\Astronarch.url | J46: https://store.steampowered.com/app/1234940/Astronarch/
A47: Atai no Gensoukyou | B47: 2010 | C47: Traditional | D47: =TRUE() -> TRUE | E47: =COUNTIF(connections!A:A, A47) > 0 -> FALSE | F47: touhou | G47: atai-no-gensoukyou
A48: Atomic Owl | B48: 2025 | C48: Action | D48: =TRUE() -> TRUE | E48: =COUNTIF(connections!A:A, A48) > 0 -> FALSE | G48: atomic-owl | J48: https://store.steampowered.com/app/2228490/Atomic_Owl/
A49: Atomicrops | B49: 2020 | C49: Action | D49: =TRUE() -> TRUE | E49: =COUNTIF(connections!A:A, A49) > 0 -> TRUE | F49: food | G49: atomicrops | H49: Yes | I49: C:\Users\Owner\Documents\Roguelike Roguelike\Roguelikes\Atomicrops.url | J49: https://store.steampowered.com/app/757320/Atomicrops/
A50: Auro: A Monster-Bumping Adventure | B50: 2014 | C50: Strategy | D50: =TRUE() -> TRUE | E50: =COUNTIF(connections!A:A, A50) > 0 -> TRUE | G50: auro-a-monster-bumping-adventure
A51: Auto Rogue | B51: 2025 | C51: Strategy | D51: =FALSE() -> FALSE | E51: =COUNTIF(connections!A:A, A51) > 0 -> FALSE | G51: auto-rogue
A52: Azure Dreams | B52: 1997 | C52: Traditional | D52: =TRUE() -> TRUE | E52: =COUNTIF(connections!A:A, A52) > 0 -> TRUE | G52: azure-dreams | H52: Yes | I52: C:\Users\Owner\Documents\Roguelike Roguelike\Roguelikes\Azure Dreams.lnk
A53: Backpack Battles | B53: 2023 | C53: Strategy | D53: =TRUE() -> TRUE | E53: =COUNTIF(connections!A:A, A53) > 0 -> TRUE | G53: backpack-battles | H53: Yes | I53: C:\Users\Owner\Documents\Roguelike Roguelike\Roguelikes\Backpack Battles.url | J53: https://store.steampowered.com/app/2427700/Backpack_Battles/
A54: Backpack Hero | B54: 2022 | C54: Deckbuilder | D54: =TRUE() -> TRUE | E54: =COUNTIF(connections!A:A, A54) > 0 -> TRUE | G54: backpack-hero | H54: Yes | I54: C:\Users\Owner\Documents\Roguelike Roguelike\Roguelikes\Backpack Hero.url | J54: https://store.steampowered.com/app/1970580/Backpack_Hero/
A55: Bad North | B55: 2018 | C55: Strategy | D55: =TRUE() -> TRUE | E55: =COUNTIF(connections!A:A, A55) > 0 -> TRUE | G55: bad-north | H55: Yes | I55: https://store.steampowered.com/app/688420/Bad_North_Jotunn_Edition/ | J55: https://store.steampowered.com/app/688420/Bad_North_Jotunn_Edition/
A56: Balatro | B56: 2023 | C56: Deckbuilder | D56: =TRUE() -> TRUE | E56: =COUNTIF(connections!A:A, A56) > 0 -> TRUE | F56: casino | G56: balatro | H56: Yes | I56: C:\Users\Owner\Documents\Roguelike Roguelike\Roguelikes\Balatro.url | J56: https://store.steampowered.com/app/2379780/Balatro/
A57: Baldi's Basics Plus | B57: 2020 | C57: Strategy | D57: =TRUE() -> TRUE | E57: =COUNTIF(connections!A:A, A57) > 0 -> FALSE | G57: baldis-basics-plus
A58: Ball x Pit | B58: 2025 | C58: Action | D58: =TRUE() -> TRUE | E58: =COUNTIF(connections!A:A, A58) > 0 -> TRUE | G58: ball-x-pit | H58: Yes | I58: C:\Users\Owner\Documents\Roguelike Roguelike\Roguelikes\BALL x PIT.url | J58: https://store.steampowered.com/app/2062430/BALL_x_PIT/
A59: Ballionaire | B59: 2024 | C59: Deckbuilder | D59: =TRUE() -> TRUE | E59: =COUNTIF(connections!A:A, A59) > 0 -> TRUE | F59: casino | G59: ballionaire | H59: Yes | I59: C:\Users\Owner\Documents\Roguelike Roguelike\Roguelikes\Ballionaire.url | J59: https://store.steampowered.com/app/2667120/Ballionaire/
A60: Banners of Ruin | B60: 2020 | C60: Deckbuilder | D60: =TRUE() -> TRUE | E60: =COUNTIF(connections!A:A, A60) > 0 -> FALSE | G60: banners-of-ruin | H60: Yes | I60: C:\Users\Owner\Documents\Roguelike Roguelike\Roguelikes\Banners of Ruin.url | J60: https://store.steampowered.com/app/1075740/Banners_of_Ruin/
A61: Barda | B61: 2026 | C61: Strategy | D61: =TRUE() -> TRUE | E61: =COUNTIF(connections!A:A, A61) > 0 -> FALSE | G61: barda | J61: https://store.steampowered.com/app/3664320/BARDA_Backpack_Roguelike/
A62: Barony | B62: 2015 | C62: Action | D62: =TRUE() -> TRUE | E62: =COUNTIF(connections!A:A, A62) > 0 -> FALSE | G62: barony | H62: Yes | I62: C:\Users\Owner\Documents\Roguelike Roguelike\Roguelikes\Barony.url | J62: https://store.steampowered.com/app/371970/Barony/
A63: Baroque | B63: 1998 | C63: Action | D63: =TRUE() -> TRUE | E63: =COUNTIF(connections!A:A, A63) > 0 -> TRUE | G63: baroque
A64: Baroque (2007) | B64: 2007 | C64: Action | D64: =FALSE() -> FALSE | E64: =COUNTIF(connections!A:A, A64) > 0 -> FALSE | G64: baroque-2007
A65: Batomon Showdown | B65: 2026 | C65: Strategy | D65: =TRUE() -> TRUE | E65: =COUNTIF(connections!A:A, A65) > 0 -> FALSE | G65: batomon-showdown | H65: Yes | I65: C:\Users\Owner\Documents\Roguelike Roguelike\Roguelikes\Batomon Showdown.url | J65: https://store.steampowered.com/app/4557380/Batomon_Showdown/
A66: Battle Brothers | B66: 2017 | C66: Strategy | D66: =TRUE() -> TRUE | E66: =COUNTIF(connections!A:A, A66) > 0 -> TRUE | G66: battle-brothers | H66: Yes | I66: C:\Users\Owner\Documents\Roguelike Roguelike\Roguelikes\BattleBrothers.lnk | J66: https://store.steampowered.com/app/365360/Battle_Brothers/
A67: Battle Shapers | B67: 2023 | C67: Action | D67: =TRUE() -> TRUE | E67: =COUNTIF(connections!A:A, A67) > 0 -> FALSE | G67: battle-shapers | H67: Yes | I67: C:\Users\Owner\Documents\Roguelike Roguelike\Roguelikes\Battle Shapers.url | J67: https://store.steampowered.com/app/1421290/Battle_Shapers/
A68: BAZR | B68: 2025 | C68: Deckbuilder | D68: =TRUE() -> TRUE | E68: =COUNTIF(connections!A:A, A68) > 0 -> FALSE | G68: bazr | H68: Yes | I68: C:\Users\Owner\Documents\Roguelike Roguelike\Roguelikes\BAZR.lnk
A69: Be My Horde | B69: 2024 | C69: Action | D69: =TRUE() -> TRUE | E69: =COUNTIF(connections!A:A, A69) > 0 -> FALSE | G69: be-my-horde | H69: Yes | I69: C:\Users\Owner\Documents\Roguelike Roguelike\Roguelikes\Be My Horde.url | J69: https://store.steampowered.com/app/2499520/Be_My_Horde/
A70: Beat Blast | B70: 2020 | C70: Action | D70: =FALSE() -> FALSE | E70: =COUNTIF(connections!A:A, A70) > 0 -> FALSE | F70: rhythm | G70: beat-blast | H70: Yes | I70: C:\Users\Owner\Documents\Roguelike Roguelike\Roguelikes\Beat Blast.url | J70: https://store.steampowered.com/app/1072640/Beat_Blast/
A71: Bella Wants Blood | B71: 2024 | C71: Strategy | D71: =TRUE() -> TRUE | E71: =COUNTIF(connections!A:A, A71) > 0 -> FALSE | F71: tower defense | G71: bella-wants-blood | H71: Yes | I71: C:\Users\Owner\Documents\Roguelike Roguelike\Roguelikes\Bella Wants Blood.url | J71: https://store.steampowered.com/app/3007660/Bella_Wants_Blood/
A72: Beneath Apple Manor | B72: 1978 | C72: Traditional | D72: =FALSE() -> FALSE | E72: =COUNTIF(connections!A:A, A72) > 0 -> FALSE | G72: beneath-apple-manor | H72: Yes | I72: C:\Users\Owner\Documents\Roguelike Roguelike\Roguelikes\Beneath Apple Manor.lnk
A73: Beneath Oresa | B73: 2022 | C73: Deckbuilder | D73: =TRUE() -> TRUE | E73: =COUNTIF(connections!A:A, A73) > 0 -> FALSE | G73: beneath-oresa | H73: Yes | I73: C:\Users\Owner\Documents\Roguelike Roguelike\Roguelikes\Beneath Oresa.url | J73: https://store.steampowered.com/app/1803400/Beneath_Oresa/
A74: Beyond the Long Night | B74: 2023 | C74: Action | D74: =TRUE() -> TRUE | E74: =COUNTIF(connections!A:A, A74) > 0 -> FALSE | G74: beyond-the-long-night | H74: Yes | I74: C:\Users\Owner\Documents\Roguelike Roguelike\Roguelikes\Beyond the Long Night.url | J74: https://store.steampowered.com/app/1730080/Beyond_the_Long_Night/
A75: Beyond Words | B75: 2026 | C75: Deckbuilder | D75: =TRUE() -> TRUE | E75: =COUNTIF(connections!A:A, A75) > 0 -> FALSE | G75: beyond-words | J75: https://store.steampowered.com/app/3823370/Beyond_Words/
A76: Bingle Bingle | B76: 2024 | C76: Deckbuilder | D76: =TRUE() -> TRUE | E76: =COUNTIF(connections!A:A, A76) > 0 -> FALSE | F76: casino | G76: bingle-bingle | H76: Yes | I76: C:\Users\Owner\Documents\Roguelike Roguelike\Roguelikes\Bingle Bingle.url | J76: https://store.steampowered.com/app/2789810/Bingle_Bingle/
A77: Bioprototype | B77: 2022 | C77: Action | D77: =TRUE() -> TRUE | E77: =COUNTIF(connections!A:A, A77) > 0 -> FALSE | G77: bioprototype | J77: https://store.steampowered.com/app/3689520/Bioprototype/
A78: Black Jacket | B78: 2026 | C78: Deckbuilder | D78: =TRUE() -> TRUE | E78: =COUNTIF(connections!A:A, A78) > 0 -> FALSE | F78: casino | G78: black-jacket | J78: https://store.steampowered.com/app/3100370/Black_Jacket/
A79: Blade Assault | B79: 2021 | C79: Action | D79: FALSE | E79: =COUNTIF(connections!A:A, A79) > 0 -> FALSE | F79: cyberpunk | G79: blade-assault | H79: Yes | I79: C:\Users\Owner\Documents\Roguelike Roguelike\Roguelikes\Blade Assault.url | J79: https://store.steampowered.com/app/1367300/Blade_Assault/
A80: Blazing Beaks | B80: 2019 | C80: Action | D80: =TRUE() -> TRUE | E80: =COUNTIF(connections!A:A, A80) > 0 -> FALSE | G80: blazing-beaks | H80: Yes | I80: C:\Users\Owner\Documents\Roguelike Roguelike\Roguelikes\Blazing Beaks.url | J80: https://store.steampowered.com/app/585710/Blazing_Beaks/
A81: Bleak Sword | B81: 2019 | C81: Action | D81: =TRUE() -> TRUE | E81: =COUNTIF(connections!A:A, A81) > 0 -> TRUE | G81: bleak-sword | H81: Yes | I81: C:\Users\Owner\Documents\Roguelike Roguelike\Roguelikes\Bleak Sword DX.url | J81: https://store.steampowered.com/app/2193050/Bleak_Sword_DX/
A82: Block Tower TD | B82: 2023 | C82: Strategy | D82: =FALSE() -> FALSE | E82: =COUNTIF(connections!A:A, A82) > 0 -> TRUE | F82: tower defense | G82: block-tower-td | H82: Yes | I82: C:\Users\Owner\Documents\Roguelike Roguelike\Roguelikes\Block Tower TD.url | J82: https://store.steampowered.com/app/2427570/Block_Tower_TD/
A83: Block Tower TD 2 | B83: 2024 | C83: Strategy | D83: =FALSE() -> FALSE | E83: =COUNTIF(connections!A:A, A83) > 0 -> FALSE | F83: tower defense | G83: block-tower-td-2 | H83: Yes | I83: C:\Users\Owner\Documents\Roguelike Roguelike\Roguelikes\Block Tower TD 2.url | J83: https://store.steampowered.com/app/2837350/Block_Tower_TD_2/
A84: Blood Dungeon | B84: 2026 | C84: Action | D84: TRUE | E84: =COUNTIF(connections!A:A, A84) > 0 -> FALSE | G84: blood-dungeon | H84: Yes | I84: C:\Users\Owner\Documents\Roguelike Roguelike\Roguelikes\Blood Dungeon.url | J84: https://store.steampowered.com/app/2431080/Blood_Dungeon/
A85: BloodDome99 | B85: 2023 | C85: Action | D85: =TRUE() -> TRUE | E85: =COUNTIF(connections!A:A, A85) > 0 -> FALSE | G85: blooddome99
A86: Bloodletter | B86: 2026 | C86: Deckbuilder | D86: FALSE | E86: =COUNTIF(connections!A:A, A86) > 0 -> FALSE | G86: bloodletter | J86: https://store.steampowered.com/app/3493400/BLOODLETTER/
A87: Bloodshed | B87: 2024 | C87: Action | D87: =TRUE() -> TRUE | E87: =COUNTIF(connections!A:A, A87) > 0 -> FALSE | G87: bloodshed | H87: Yes | I87: C:\Users\Owner\Documents\Roguelike Roguelike\Roguelikes\Bloodshed.url | J87: https://store.steampowered.com/app/2747550/Bloodshed/
A88: Bloons TD 6: Rogue Legends | B88: 2025 | C88: Strategy | D88: =FALSE() -> FALSE | E88: =COUNTIF(connections!A:A, A88) > 0 -> FALSE | F88: tower defense | G88: bloons-td-6-rogue-legends
A89: Blue Prince | B89: 2025 | C89: Strategy | D89: =FALSE() -> FALSE | E89: =COUNTIF(connections!A:A, A89) > 0 -> FALSE | G89: blue-prince
A90: Boneraiser Minions | B90: 2022 | C90: Action | D90: =TRUE() -> TRUE | E90: =COUNTIF(connections!A:A, A90) > 0 -> TRUE | F90: undead | G90: boneraiser-minions | H90: Yes | I90: C:\Users\Owner\Documents\Roguelike Roguelike\Roguelikes\Boneraiser Minions.url | J90: https://store.steampowered.com/app/1944570/Boneraiser_Minions/
A91: Book of Demons | B91: 2018 | C91: Deckbuilder | D91: =TRUE() -> TRUE | E91: =COUNTIF(connections!A:A, A91) > 0 -> TRUE | G91: book-of-demons
A92: Bounty of One | B92: 2022 | C92: Action | D92: =TRUE() -> TRUE | E92: =COUNTIF(connections!A:A, A92) > 0 -> TRUE | F92: western | G92: bounty-of-one | H92: Yes | I92: C:\Users\Owner\Documents\Roguelike Roguelike\Roguelikes\Bounty of One.url | J92: https://store.steampowered.com/app/1968730/Bounty_of_One/
A93: Boyfriend Dungeon | B93: 2021 | C93: Action | D93: TRUE | E93: =COUNTIF(connections!A:A, A93) > 0 -> FALSE | G93: boyfriend-dungeon | H93: Yes | I93: C:\Users\Owner\Documents\Roguelike Roguelike\Roguelikes\Boyfriend Dungeon.url | J93: https://store.steampowered.com/app/674930/Boyfriend_Dungeon/
A94: BPM: Bullets Per Minute | B94: 2020 | C94: Action | D94: =TRUE() -> TRUE | E94: =COUNTIF(connections!A:A, A94) > 0 -> FALSE | F94: rhythm | G94: bpm-bullets-per-minute | H94: Yes | I94: C:\Users\Owner\Documents\Roguelike Roguelike\Roguelikes\BPM BULLETS PER MINUTE.url | J94: https://store.steampowered.com/app/1286350/BPM_BULLETS_PER_MINUTE/
A95: Bravery and Greed | B95: 2022 | C95: Action | D95: TRUE | E95: =COUNTIF(connections!A:A, A95) > 0 -> FALSE | G95: bravery-and-greed | H95: Yes | I95: C:\Users\Owner\Documents\Roguelike Roguelike\Roguelikes\Bravery and Greed.url | J95: https://store.steampowered.com/app/943370/Bravery_and_Greed/
A96: Brawl Tactics: Origins | B96: 2023 | C96: Deckbuilder | D96: =TRUE() -> TRUE | E96: =COUNTIF(connections!A:A, A96) > 0 -> FALSE | G96: brawl-tactics-origins | J96: https://store.steampowered.com/app/2451820/Brawl_Tactics_Origins/
A97: Breach Wanderers | B97: 2021 | C97: Deckbuilder | D97: =TRUE() -> TRUE | E97: =COUNTIF(connections!A:A, A97) > 0 -> FALSE | G97: breach-wanderers | H97: Yes | I97: C:\Users\Owner\Documents\Roguelike Roguelike\Roguelikes\Breach Wanderers.url | J97: https://store.steampowered.com/app/1394130/Breach_Wanderers/
A98: Breachway | B98: 2024 | C98: Deckbuilder | D98: =TRUE() -> TRUE | E98: =COUNTIF(connections!A:A, A98) > 0 -> FALSE | F98: space | G98: breachway | H98: Yes | I98: C:\Users\Owner\Documents\Roguelike Roguelike\Roguelikes\Breachway.url | J98: https://store.steampowered.com/app/2118810/Breachway/
A99: Brew | B99: 2025 | C99: Action | D99: =TRUE() -> TRUE | E99: =COUNTIF(connections!A:A, A99) > 0 -> FALSE | G99: brew
A100: Brogue | B100: 2009 | C100: Traditional | D100: =TRUE() -> TRUE | E100: =COUNTIF(connections!A:A, A100) > 0 -> TRUE | G100: brogue | H100: Yes | I100: C:\Users\Owner\Documents\Roguelike Roguelike\Roguelikes\brogue.lnk
...

Sheet connections
A1: Influencer | B1: Influencee | C1: Influencer Time | D1: Dev/Series Relation | E1: Source | F1: Proof | G1: Needs Proof
A2: Hades | B2: [Redacted] | C2: 2019 | E2: look at it | F2: hades---redacted | G2: Yes
A3: Mystery Dungeon 2: Shiren the Wanderer | B3: 100 Rogues | C3: 1995 | E3: https://www.gamedeveloper.com/business/marketing-on-the-app-store-the-cautionary-tale-of-i-100-rogues-i- | F3: mystery_dungeon_2_shiren_the_wanderer---100_rogues | G3: No
A4: Powder | B4: 100 Rogues | C4: 2003 | E4: https://www.gamedeveloper.com/business/marketing-on-the-app-store-the-cautionary-tale-of-i-100-rogues-i- | F4: powder---100_rogues | G4: No
A5: Fights in Tight Spaces | B5: 2 Fights in 2 Tight Spaces | C5: 2021 | D5: Yes | F5: fights_in_tight_spaces---2_fights_in_2_tight_spaces | G5: No
A6: Nova Drift | B6: 20 Minutes Till Dawn | C6: 2019 | E6: https://www.gamebusiness.jp/article/2022/06/15/20252.html | F6: nova_drift---20_minutes_till_dawn | G6: No
A7: Vampire Survivors | B7: 20 Minutes Till Dawn | C7: 2021 | E7: look at it | F7: vampire_survivors---20_minutes_till_dawn | G7: No
A8: Crypt of the NecroDancer | B8: 20XX | C8: 2015 | E8: https://www.reddit.com/r/IAmA/comments/4po4pn/i_am_the_developer_of_20xx_the_megaman_xinspired/ | F8: crypt_of_the_necrodancer---20xx | G8: No
A9: The Binding of Isaac | B9: 20XX | C9: 2011 | E9: https://www.reddit.com/r/IAmA/comments/4po4pn/i_am_the_developer_of_20xx_the_megaman_xinspired/ | F9: the_binding_of_isaac---20xx | G9: No
A10: 20XX | B10: 30XX | C10: 2017 | D10: Yes | F10: 20xx---30xx | G10: No
A11: Realm of the Mad God | B11: 33 Immortals | C11: 2010 | E11: check folder | F11: realm_of_the_mad_god---33_immortals | G11: No
A12: Sundered | B12: 33 Immortals | C12: 2017 | D12: Yes | F12: sundered---33_immortals | G12: No
A13: 868-Hack | B13: 868-Back | C13: 2015 | D13: Yes | F13: 868_hack---868_back | G13: No
A14: Rogue | B14: 868-Hack | C14: 1980 | E14: https://www.gamedeveloper.com/design/how-michael-brough-s-love-of-exploring-a-single-game-mechanic-beget-i-cinco-paus-i- | F14: rogue---868_hack | G14: No
A15: Seraph's Last Stand | B15: 9 Kings | C15: 2022 | D15: Yes | F15: seraph_s_last_stand---9_kings | G15: No
A16: Slay the Spire | B16: 9 Kings | C16: 2017 | E16: https://www.youtube.com/watch?v=9fxnPkfyHuA | F16: slay_the_spire---9_kings | G16: No
A17: Spelunky Classic | B17: 99 Levels to Hell | C17: 2008 | E17: https://youtu.be/wJ2cgBoxsi4 | F17: spelunky_classic-the_binding_of_isaac---99_levels_to_hell | G17: No
A18: The Binding of Isaac | B18: 99 Levels to Hell | C18: 2011 | E18: https://youtu.be/wJ2cgBoxsi4 | F18: spelunky_classic-the_binding_of_isaac---99_levels_to_hell | G18: No
A19: Slay the Spire | B19: A la Card | C19: 2017 | E19: check folder | F19: slay_the_spire---a_la_card | G19: No
A20: The Binding of Isaac | B20: A Robot Named Fight! | C20: 2011 | E20: https://www.reddit.com/r/NintendoSwitch/comments/8jv8rd/im_matt_bitner_sole_developer_of_a_robot_named/#:~:text=I%20left%20my%20old%20job,as%20The%20Binding%20of%20Isaac. | F20: the_binding_of_isaac---a_robot_named_fight | G20: No
A21: FTL | B21: Abandon Ship | C21: 2012 | E21: https://bigbossbattle.com/abandon-ship-interview-fireblade-softwares-gary-burchell/ | F21: ftl---abandon_ship | G21: No
A22: Enter the Gungeon | B22: Abandoned Archive | C22: 2016 | E22: https://www.reddit.com/r/playmygame/comments/sqb852/our_spellcasting_roguelike_abandoned_archive_now/ | F22: enter_the_gungeon---abandoned_archive | G22: No
A23: Wizard of Legend | B23: Abandoned Archive | C23: 2018 | E23: https://www.reddit.com/r/playmygame/comments/sqb852/our_spellcasting_roguelike_abandoned_archive_now/ | F23: wizard_of_legend---abandoned_archive | G23: No
A24: Dead Cells | B24: Absolum | C24: 2018 | E24: https://www.polygon.com/absolum-roguelike-interview-dotemu-guard-crush/ | F24: dead_cells---absolum | G24: No
A25: Gunfire Reborn | B25: Abyssus | C25: 2020 | E25: https://steamcommunity.com/app/1721110/discussions/0/600775708393865281/ | F25: gunfire_reborn---abyssus | G25: No
A26: Nuclear Throne | B26: Abyssus | C26: 2015 | E26: https://steamcommunity.com/app/1721110/discussions/0/600775708393865281/ | F26: nuclear_throne---abyssus | G26: No
A27: Roboquest | B27: Abyssus | C27: 2020 | E27: https://steamcommunity.com/app/1721110/discussions/0/600775708393865281/ | F27: roboquest---abyssus | G27: No
A28: Popup Dungeon | B28: Aces & Adventures | C28: 2020 | D28: Yes | F28: popup_dungeon---aces_adventures | G28: No
A29: Slay the Spire | B29: Aces & Adventures | C29: 2017 | E29: https://creators.spotify.com/pod/show/the-indie-diarist/episodes/Indie-Diary-5-Enrique-Dryere-Triple-B-Titles---Creativity-as-Sacrifice--Secrets-of-Inspiration--DnD-and----Poker-e207m5b | F29: slay_the_spire---aces_adventures | G29: No
A30: Darkest Dungeon | B30: Across the Obelisk | C30: 2015 | E30: duh also check the folder for proof | F30: darkest_dungeon---across_the_obelisk | G30: No
A31: Slay the Spire | B31: Across the Obelisk | C31: 2017 | E31: duh also the devs talk about loving sts in discord | F31: slay_the_spire---across_the_obelisk | G31: Yes
A32: Dead Cells | B32: Aethermancer | C32: 2018 | E32: check folder | F32: dead_cells---aethermancer | G32: No
A33: Enter the Gungeon | B33: AK-xolotl | C33: 2016 | E33: https://www.reddit.com/r/Games/comments/v2kcsr/ama_were_the_team_behind_akxolotl_a_cute_but/ | F33: enter_the_gungeon---ak_xolotl | G33: No
A34: Nuclear Throne | B34: AK-xolotl | C34: 2015 | E34: https://www.reddit.com/r/Games/comments/v2kcsr/ama_were_the_team_behind_akxolotl_a_cute_but/ | F34: nuclear_throne---ak_xolotl | G34: No
A35: Into the Breach | B35: Alina of the Arena | C35: 2018 | E35: https://store.steampowered.com/app/1668690/Alina_of_the_Arena/#:~:text=About%20This%20Game-,ABOUT,and%20'Into%20the%20Breach'. | F35: into_the_breach---alina_of_the_arena | G35: No
A36: Slay the Spire | B36: Alina of the Arena | C36: 2017 | E36: https://store.steampowered.com/app/1668690/Alina_of_the_Arena/#:~:text=About%20This%20Game-,ABOUT,and%20'Into%20the%20Breach'. | F36: slay_the_spire---alina_of_the_arena | G36: No
A37: Dead Cells | B37: An Amazing Wizard | C37: 2018 | E37: https://x.com/AnAmazingWizard/status/1489554155597352962?s=20 | F37: dead_cells---an_amazing_wizard | G37: No
A38: Hades | B38: An Amazing Wizard | C38: 2019 | E38: https://x.com/AnAmazingWizard/status/1489554155597352962?s=20 | F38: hades---an_amazing_wizard | G38: No
A39: The Binding of Isaac | B39: An Amazing Wizard | C39: 2011 | E39: https://x.com/AnAmazingWizard/status/1489554155597352962?s=20 | F39: the_binding_of_isaac---an_amazing_wizard | G39: No
A40: Hack | B40: Ancient Domains of Mystery | C40: 1984 | E40: https://roguebasin.com/index.php/ADOM | F40: hack---ancient_domains_of_mystery | G40: No
... A45: Into the Breach | B45: Anomaly Collapse | C45: 2018 | E45: https://www.facebook.com/groups/132728896890594/posts/2551615688335224/ | F45: into_the_breach---anomaly_collapse | G45: No
A46: Another Farm Roguelike | B46: Another Farm Roguelike: Rebirth | C46: 2022 | D46: Yes | F46: another_farm_roguelike---another_farm_roguelike_rebirth | G46: No
A47: Balatro | B47: Aotenjo: Infinite Hands | C47: 2023 | E47: https://steamcommunity.com/games/3066570/announcements/detail/4356754561281185320 | F47: balatro---aotenjo_infinite_hands | G47: No
A48: Luck be a Landlord | B48: Aotenjo: Infinite Hands | C48: 2021 | E48: https://steamcommunity.com/games/3066570/announcements/detail/4356754561281185320 | F48: luck_be_a_landlord---aotenjo_infinite_hands | G48: No
A49: Monster Train | B49: Aotenjo: Infinite Hands | C49: 2020 | E49: https://steamcommunity.com/games/3066570/announcements/detail/4356754561281185320 | F49: monster_train---aotenjo_infinite_hands | G49: No
A50: Slay the Spire | B50: Aotenjo: Infinite Hands | C50: 2017 | E50: https://steamcommunity.com/games/3066570/announcements/detail/4356754561281185320 | F50: slay_the_spire---aotenjo_infinite_hands | G50: No
A51: Caves of Qud | B51: Approaching Infinity | C51: 2010 | E51: check folder | F51: caves_of_qud---approaching_infinity | G51: No
A52: For The Warp | B52: Arc Seed | C52: 2020 | D52: Yes | F52: for_the_warp---arc_seed | G52: No
A53: Into the Breach | B53: Arc Seed | C53: 2018 | E53: look at it | F53: into_the_breach---arc_seed | G53: Yes
A54: Endgame of Devil | B54: Arcane Trigger | C54: 2023 | D54: Yes | F54: endgame_of_devil---arcane_trigger | G54: No
A55: FTL | B55: Arcanium: Rise of Akhan | C55: 2018 | E55: https://arcanium-rise-of-akhan.xsollasitebuilder.com/ | F55: ftl---arcanium_rise_of_akhan | G55: No
A56: Slay the Spire | B56: Arcanium: Rise of Akhan | C56: 2017 | E56: https://arcanium-rise-of-akhan.xsollasitebuilder.com/ | F56: slay_the_spire---arcanium_rise_of_akhan | G56: No
A57: Dicey Dungeons | B57: Archon Soul | C57: 2019 | E57: https://www.reddit.com/r/WebGames/comments/1m6esqf/archon_soul_its_been_a_year_and_a_half_of_hard/ | F57: dicey_dungeons---archon_soul | G57: No
A58: Slay the Spire | B58: Archon Soul | C58: 2017 | E58: https://www.reddit.com/r/WebGames/comments/1m6esqf/archon_soul_its_been_a_year_and_a_half_of_hard/ | F58: slay_the_spire---archon_soul | G58: No
A59: Vampire Survivors | B59: Archons | C59: 2021 | E59: look at it | F59: vampire_survivors---archons | G59: Yes
A60: Brotato | B60: Arms of God | C60: 2022 | E60: https://steamcommunity.com/app/3100310/discussions/0/735910198043224446/#c735910198043297427 | F60: brotato---arms_of_god | G60: No
A61: Diablo | B61: Arms of God | C61: 1996 | E61: https://steamcommunity.com/app/3100310/discussions/0/735910198042983690/#c758430178052462886 | F61: diablo---arms_of_god | G61: No
A62: Vampire Survivors | B62: Arms of God | C62: 2021 | E62: https://steamcommunity.com/app/3100310/discussions/0/735910198043224446/#c735910198043297427 | F62: vampire_survivors---arms_of_god | G62: No
A63: Vampire Survivors | B63: Army of Ruin | C63: 2021 | E63: check folder | F63: vampire_survivors---army_of_ruin | G63: No
A64: Peglin | B64: Arrogue | C64: 2022 | E64: https://www.reddit.com/r/roguelites/comments/1ic44r5/my_angry_bird_roguelike_is_finally_out_on_steam/ | F64: peglin---arrogue | G64: No
A65: Slay the Spire | B65: Arrogue | C65: 2017 | E65: https://www.reddit.com/r/roguelites/comments/1ic44r5/my_angry_bird_roguelike_is_finally_out_on_steam/ | F65: slay_the_spire---arrogue | G65: No
A66: Darkest Dungeon | B66: As We Descend | C66: 2015 | D66: also mentioned in discord | E66: https://www.reddit.com/r/pcgaming/comments/1kxi8ze/as_we_descend_strategy_roguelike_deckbuilder/ | F66: darkest_dungeon---as_we_descend | G66: No
A67: Slay the Spire | B67: As We Descend | C67: 2017 | E67: check folder | F67: slay_the_spire---as_we_descend | G67: No
A68: Hades | B68: Asgard's Fall: Viking Survivors | C68: 2019 | E68: https://www.reddit.com/r/survivorslikes/comments/1jvtb6m/we_released_asgards_fall_on_steam/ | F68: hades---asgard_s_fall_viking_survivors | G68: No
A69: Vampire Survivors | B69: Asgard's Fall: Viking Survivors | C69: 2021 | E69: look at it | F69: vampire_survivors---asgard_s_fall_viking_survivors | G69: Yes
A70: Enter the Gungeon | B70: Asterogues | C70: 2016 | E70: dev has mentioned playing both isaac and gungeon, and also look at it | F70: enter_the_gungeon---asterogues | G70: Yes
A71: The Binding of Isaac | B71: Asterogues | C71: 2011 | E71: dev has mentioned playing both isaac and gungeon, and also look at it | F71: the_binding_of_isaac---asterogues | G71: Yes
A72: Children of Morta | B72: Astral Ascent | C72: 2019 | E72: https://www.scousegamer88.com/2021/03/31/astral-ascent-hibernian-workshop-interview/ | F72: children_of_morta---astral_ascent | G72: No
A73: Dark Devotion | B73: Astral Ascent | C73: 2019 | D73: Yes | E73: https://www.scousegamer88.com/2021/03/31/astral-ascent-hibernian-workshop-interview/ | F73: dark_devotion---astral_ascent | G73: No
A74: Dead Cells | B74: Astral Ascent | C74: 2018 | E74: https://www.scousegamer88.com/2021/03/31/astral-ascent-hibernian-workshop-interview/ | F74: dead_cells---astral_ascent | G74: No
A75: Hades | B75: Astral Ascent | C75: 2019 | E75: https://www.scousegamer88.com/2021/03/31/astral-ascent-hibernian-workshop-interview/ | F75: hades---astral_ascent | G75: No
A76: Slay the Spire | B76: Astral Ascent | C76: 2017 | E76: https://www.kickstarter.com/projects/hibernian-workshop/astral-ascent#:~:text=Inspired%20by%20rogue%2Dlite%20games,set%20of%20attacks%20and%20spells. | F76: slay_the_spire---astral_ascent | G76: No
A77: Wizard of Legend | B77: Astral Ascent | C77: 2018 | E77: https://www.scousegamer88.com/2021/03/31/astral-ascent-hibernian-workshop-interview/ | F77: wizard_of_legend---astral_ascent | G77: No
A78: Slay the Spire | B78: Astrea: Six-Sided Oracles | C78: 2017 | E78: https://indiecator.org/2022/09/26/astrea-six-sided-oracles-interview/ | F78: slay_the_spire---astrea_six_sided_oracles | G78: No
A79: Brotato | B79: Astro Prospector | C79: 2022 | E79: check folder | F79: brotato---astro_prospector | G79: No
A80: Enter the Gungeon | B80: Astro Prospector | C80: 2016 | E80: check folder | F80: enter_the_gungeon---astro_prospector | G80: No
A81: Magicraft | B81: Astro Prospector | C81: 2023 | E81: check folder | F81: magicraft---astro_prospector | G81: No
A82: Nuclear Throne | B82: Astro Prospector | C82: 2015 | E82: check folder | F82: nuclear_throne---astro_prospector | G82: No
A83: Vampire Survivors | B83: Astro Prospector | C83: 2021 | E83: check folder | F83: vampire_survivors---astro_prospector | G83: No
A84: Fushigi no Gensoukyou | B84: Atai no Gensoukyou | C84: 2010 | D84: Yes | F84: fushigi_no_gensoukyou---atai_no_gensoukyou | G84: No
A85: Dead Cells | B85: Atomic Owl | C85: 2018 | E85: https://x.com/monstertheaterx/status/1819715822203355558?s=20 | F85: dead_cells---atomic_owl | G85: No
A86: Enter the Gungeon | B86: Atomicrops | C86: 2016 | E86: https://www.reddit.com/r/Games/comments/czn9i5/were_the_developers_of_atomicrops_an_action/#:~:text=I%20got%20addicted%20to%20Stardew,simply%20stat%20upgrades%20or%20something). | F86: enter_the_gungeon---atomicrops | G86: No
A87: Nuclear Throne | B87: Atomicrops | C87: 2015 | E87: https://www.reddit.com/r/Games/comments/czn9i5/were_the_developers_of_atomicrops_an_action/#:~:text=I%20got%20addicted%20to%20Stardew,simply%20stat%20upgrades%20or%20something). | F87: nuclear_throne---atomicrops | G87: No
A88: Slay the Spire | B88: Atomicrops | C88: 2017 | E88: https://www.reddit.com/r/Games/comments/czn9i5/were_the_developers_of_atomicrops_an_action/#:~:text=I%20got%20addicted%20to%20Stardew,simply%20stat%20upgrades%20or%20something). | F88: slay_the_spire---atomicrops | G88: No
A89: 100 Rogues | B89: Auro: A Monster-Bumping Adventure | C89: 2010 | D89: Yes | F89: 100_rogues---auro_a_monster_bumping_adventure | G89: No
A90: Torneko's Great Adventure: Mystery Dungeon | B90: Azure Dreams | C90: 1993 | E90: look at it | F90: torneko_s_great_adventure_mystery_dungeon---azure_dreams | G90: Yes
A91: Backpack Hero | B91: Backpack Battles | C91: 2022 | E91: https://www.reddit.com/r/IndieGaming/comments/13vr0mm/comment/jm7alk0/?context=3 | F91: backpack_hero---backpack_battles | G91: No
A92: Super Auto Pets | B92: Backpack Battles | C92: 2021 | E92: check folder | F92: super_auto_pets---backpack_battles | G92: No
A93: Dicey Dungeons | B93: Backpack Hero | C93: 2019 | E93: check folder | F93: dicey_dungeons---backpack_hero | G93: No
A94: Inscryption | B94: Backpack Hero | C94: 2021 | E94: check folder | F94: inscryption---backpack_hero | G94: No
A95: Into the Breach | B95: Backpack Hero | C95: 2018 | E95: https://en.wikipedia.org/wiki/Backpack_Hero#:~:text=Main%20developer%20Jasper%20Cole%20stated,inventory%20as%20an%20additional%20inspiration. | F95: into_the_breach---backpack_hero | G95: No
A96: Luck be a Landlord | B96: Backpack Hero | C96: 2021 | E96: check folder | F96: luck_be_a_landlord---backpack_hero | G96: No
A97: Slay the Spire | B97: Backpack Hero | C97: 2017 | E97: https://en.wikipedia.org/wiki/Backpack_Hero#:~:text=Main%20developer%20Jasper%20Cole%20stated,inventory%20as%20an%20additional%20inspiration. | F97: slay_the_spire---backpack_hero | G97: No
A98: Luck be a Landlord | B98: Balatro | C98: 2021 | E98: https://en.wikipedia.org/wiki/Balatro | F98: luck_be_a_landlord---balatro | G98: No
A99: Slay the Spire | B99: Balatro | C99: 2017 | E99: https://localthunk.com/blog/balatro-timeline-3aarh | F99: slay_the_spire---balatro | G99: No
A100: ToeJam & Earl | B100: Baldi's Basics Plus | C100: 1991 | E100: https://baldis-basics-in-education-and-learning.fandom.com/wiki/Inspiration_and_reference | F100: toejam_earl---baldi_s_basics_plus | G100: No
A101: Deep Rock Galactic: Survivor | B101: Ball x Pit | C101: 2024 | E101: https://www.ign.com/articles/city-of-balls-was-the-original-title-and-somehow-ball-x-pit-got-even-weirder-from-there | F101: deep_rock_galactic_survivor---ball_x_pit | G101: No
... A110: Torneko's Great Adventure: Mystery Dungeon | B110: Baroque | C110: 1993 | E110: https://nervetower.neocities.org/int_yonemitsu_ps | F110: torneko_s_great_adventure_mystery_dungeon---baroque | G110: No
A111: Baroque | B111: Baroque (2007) | C111: 1998 | D111: Yes | F111: baroque---baroque_2007 | G111: No
A112: Oaken Tower | B112: Batomon Showdown | C112: 2026 | E112: check folder | F112: oaken_tower---batomon_showdown | G112: No
...

Sheet characters
A1: Name | B1: Game | C1: Health | D1: Gold | E1: Bash | F1: Dash | G1: Push | H1: Transmute | I1: Scramble | J1: Bombs | K1: Keys | L1: Random | M1: Level Up | N1: Reward | O1: Description | P1: Starting loadout | Q1: File
A2: Antonio Belpaese | B2: Vampire Survivors | C2: 7 | D2: 3 | E2: 1 | F2: 0 | G2: 1 | H2: 0 | I2: 0 | J2: 0 | K2: 0 | L2: 0 | M2: Beat a game while having defeated a vampire | N2: Gain +1 Random Sized Chest | O2: What a wonderful night to hunt beasts! | P2: Whip | Q2: AntonioBelpaese
A3: Erratic Deck | B3: Balatro | C3: 7 | D3: 3 | E3: 0 | F3: 0 | G3: 0 | H3: 0 | I3: 0 | J3: 0 | K3: 0 | L3: 2 | M3: Beat a game while having selected a random starting build | N3: Gain +1 Random Card | O3: All Ranks and Suits in deck are randomized | P3: 1 random joker card | Q3: ErraticDeck
A4: Ironclad | B4: Slay the Spire | C4: 8 | D4: 3 | E4: 2 | F4: 0 | G4: 0 | H4: 0 | I4: 0 | J4: 0 | K4: 0 | L4: 0 | M4: Beat a game while having made a Faustian bargain | N4: Gain +1 Small Chest | O4: The remaining soldier of the Ironclads. Sold his soul to harness demonic energies. | P4: Burning Blood | Q4: Ironclad
A5: Isaac | B5: The Binding of Isaac; The Binding of Isaac: Rebirth | C5: 6 | D5: 3 | E5: 0 | F5: 0 | G5: 0 | H5: 0 | I5: 0 | J5: 1 | K5: 0 | L5: 0 | M5: Beat a game while having used sorrow or self-inflicted pain as a weapon | N5: Gain +1 Small Chest and +1 Scramble | O5: Who am I? | P5: D6 | Q5: Isaac
A6: Manager | B6: Raccoin: Coin Pusher Roguelike | C6: 7 | D6: 3 | E6: 0 | F6: 0 | G6: 2 | H6: 0 | I6: 0 | J6: 0 | K6: 0 | L6: 0 | M6: Beat a game while having collected 3 different types of currency | N6: Gain +1 Push and +1 Gold | O6: Master in using Math coins and earning tickets. | P6: N/A | Q6: Manager
A7: Minä | B7: Noita | C7: 7 | D7: 3 | E7: 0 | F7: 0 | G7: 0 | H7: 2 | I7: 0 | J7: 0 | K7: 0 | L7: 0 | M7: Beat a game while having crafted or combined a spell or weapon | N7: Gain +1 Transmute | O7: Why must you go destroying everything? Why? For glory? For your precious god of gods. Is it really worth all this? Is it? Is it really? | P7: 1 random wand | Q7: Minä
A8: Poe Ratcho | B8: Vampire Survivors | C8: 7 | D8: 3 | E8: 0 | F8: 0 | G8: 2 | H8: 0 | I8: 0 | J8: 0 | K8: 0 | L8: 0 | M8: Beat a game while being stinky | N8: Gain +1 Random Sized Chest | O8: A malodorous hero | P8: Pummarola | Q8: PoeRatcho
A9: Regent | B9: Slay the Spire 2 | C9: 7 | D9: 3 | E9: 0 | F9: 0 | G9: 1 | H9: 1 | I9: 0 | J9: 0 | K9: 0 | L9: 0 | M9: Beat a game while having made a friend | N9: Gain +1 Small Chest | O9: Heir to the Throne of Stars. Wields cosmic powers but his minions do the work. | P9: N/A | Q9: Regent
A10: Rodney | B10: Rogue | C10: 5 | D10: 3 | E10: 0 | F10: 0 | G10: 0 | H10: 0 | I10: 0 | J10: 0 | K10: 0 | L10: 2 | M10: Beat a game without meta progression | N10: Gain +1 Max Health and +1 Loot | O10: Now I abide here, searching endlessly for the precious Amulet... and finding a thousand horrors. | P10: N/A | Q10: Rodney
A11: The Makeshift Sisyphus | B11: Ball x Pit | C11: 7 | D11: 3 | E11: 1 | F11: 0 | G11: 0 | H11: 0 | I11: 0 | J11: 0 | K11: 0 | L11: 0 | M11: Beat a game while having pushed a boulder | N11: Gain +1 Small Chest | O11: A former king, tormented by time | P11: Earthquake | Q11: TheMakeshiftSisyphus
A12: Zagreus | B12: Hades | C12: 7 | D12: 3 | E12: 1 | F12: 1 | G12: 0 | H12: 0 | I12: 0 | J12: 0 | K12: 0 | L12: 0 | M12: Beat a game with the help of a God | N12: Gain +1 Large Chest | O12: ... All right, let's give it another shot. | P12: N/A | Q12: Zagreus
A13: Zoe | B13: Haste | C13: 7 | D13: 3 | E13: 0 | F13: 1 | G13: 1 | H13: 0 | I13: 0 | J13: 0 | K13: 0 | L13: 0 | M13: Perfect a game by beating it without losing | N13: Gain +1 Dash | O13: Express Delivery: Arrives with haste, before the world ends. | P13: N/A | Q13: Zoe

Sheet items
A1: Name | B1: Rating | C1: Type | D1: Description | E1: Effect | F1: Reference | G1: tags | H1: pools | I1: File | J1: Sorting
A2: Alien Baby | B2: Rare | C2: Pickup, Passive | D2: Gain +6 Max Health, but all enemies gain +1 Health | E2: item_acquired: gain_max_hp 6; passive: +1 enemy_health | F2: Brotato | G2: alien | I2: AlienBaby | J2: Health
A3: Anchor | B3: Common | C3: Triggered | D3: At the start of combat, Gain +1 Temporary Shield | E3: game_selected: gain_stat shields 1 | F3: Slay the Spire | G3: sea, ship | I3: Anchor | J3: Defense
A4: Ban Hammer | B4: Uncommon | C4: Pickup | D4: Gain +2 Bashes | E4: item_acquired: gain_stat bash 2 | F4: Yet Another Zombie Survivors | G4: tool, hammer | I4: BanHammer | J4: Stats
A5: Bionic Face Plating | B5: Uncommon | C5: Passive | D5: Gain +3 Speed, but this is destroyed when taking damage | E5: passive_status: speed 3; destroy_on_damage | F5: Mewgenics | G5: cybernetics | I5: BionicFacePlating | J5: Stats
A6: Blood Bag | B6: Event | C6: Pickup | D6: Gain +2 Max Health and +8 Health | E6: item_acquired: gain_max_hp 2; gain_hp 8 | F6: The Binding of Isaac | G6: blood | I6: BloodBag | J6: Health
A7: Blood Bombs | B7: Uncommon | C7: Pickup, Triggered | D7: Gain +1 Bomb. When using a Bomb, Gain +1 Health | E7: item_acquired: gain_stat bombs 1; bomb_used: gain_hp 1 | F7: The Binding of Isaac: Rebirth | G7: bomb, blood | I7: BloodBombs | J7: Bomb
A8: Book of Revelations | B8: Rare | C8: Charged, 3 | D8: Gain +1 Shield | E8: item_used: gain_stat bonus_shields 1 | F8: The Binding of Isaac | G8: book | I8: BookOfRevelations | J8: Defense
A9: Brimstone Bombs | B9: Rare | C9: Pickup, Passive | D9: Gain +1 Bomb. Bombs now apply 1 Stun to all rows in the 4 cardinal directions | E9: item_acquired: gain_stat bombs 1; bomb_cardinal | F9: The Binding of Isaac: Rebirth | G9: bomb | H9: devil_room | I9: BrimstoneBombs | J9: Bomb, Grid
A10: Burning Blood | B10: Starter | C10: Triggered | D10: After beating a game, Gain +1 Health | E10: game_beaten: gain_hp 1 | F10: Slay the Spire | I10: BurningBlood | J10: Health
A11: Caffeine Pill | B11: Common | C11: Passive, Pickup | D11: Gain +1 Speed and +1 Pill | E11: passive_status: speed 1; item_acquired: gain_pill 1 | F11: The Binding of Isaac: Rebirth | G11: drugs, pills | I11: CaffeinePill | J11: Loot, Stats
A12: Calling Bell | B12: Boss | C12: Pickup | D12: Obtain Curse of the Bell and 3 random items — one Common, one Uncommon, one Rare | E12: item_acquired: add_curse curse_of_the_bell, gain_item_per_rarity 3 | F12: Slay the Spire | I12: CallingBell | J12: Special
A13: Candy Bag | B13: Rare | C13: Passive | D13: After Combat ends, Gain +1 Bash, Dash, Push, Transmute or Scramble, but have a 10% chance to spawn a Boss | E13: game_beaten: one_of gain_stat bash 1 | gain_stat dash 1 | gain_stat push 1 | gain_stat transmute 1 | gain_stat scramble 1, 10% chance spawn_boss | F13: Brotato | G13: food, sweets, bag | I13: CandyBag | J13: Stats
A14: Cauldron | B14: Rare | C14: Pickup | D14: Gain +5 Potions | E14: item_acquired: gain_potion 5 | F14: Slay the Spire | G14: pot | H14: shop | I14: Cauldron | J14: Loot
A15: Censer | B15: Uncommon | C15: Passive | D15: Enemies in the 2 leftmost columns take no extra turns | E15: front_column_slow 2 | F15: The Binding of Isaac: Rebirth | G15: holy | H15: angel_room | I15: Censer | J15: Combat
A16: Ceremonial Dagger | B16: Rare | C16: Passive | D16: Whenever an Enemy is defeated, Apply 1 Stun to a random Enemy | E16: enemy_killed: apply_status stun 1 target=random | F16: Risk of Rain | G16: weapon, dagger | I16: CeremonialDagger | J16: Offense
A17: Charm of the Vampire | B17: Uncommon | C17: Triggered, Incremental | D17: When you defeat 3 enemies, Gain +1 Health | E17: enemy_killed: counter key=enemies_defeated every=3 -> gain_hp 1 | F17: The Binding of Isaac | G17: bat, vampire | I17: CharmOfTheVampire | J17: Health
A18: Clover | B18: Uncommon | C18: Passive | D18: Gain +1 Luck | E18: passive: +1 luck | F18: Vampire Survivors | G18: plant | I18: Clover | J18: Stats
A19: Crown | B19: Uncommon | C19: Triggered | D19: When Levelling Up, 50% chance to Level Up an additional time | E19: level_up: 50% | F19: Vampire Survivors | G19: wearable, hat, crown | I19: Crown | J19: Economy
A20: D10 | B20: Common | C20: Charged, 2 | D20: Reroll all non-boss enemies | E20: item_used: reroll_enemies | F20: The Binding of Isaac: Rebirth | G20: dice | I20: D10 | J20: Grid
A21: D6 | B21: Uncommon | C21: Charged, 2 | D21: Gain +1 Scramble | E21: item_used: gain_stat scramble 1 | F21: The Binding of Isaac | G21: dice | I21: D6 | J21: Stats
A22: Deck of Cards | B22: Uncommon | C22: Charged, 2 | D22: Gain +1 Card | E22: item_used: gain_card 1 | F22: The Binding of Isaac | I22: DeckOfCards | J22: Loot
A23: Dragon Fruit | B23: Rare | C23: Triggered | D23: Whenever you obtain any amount of gold, Gain +1 Max Health | E23: gold_gained: gain_max_hp 1 | F23: Slay the Spire 2 | G23: food, fruit | H23: shop | I23: DragonFruit | J23: Economy
A24: Dumb Bell | B24: Uncommon | C24: Passive | D24: When Charging a Weapon, Gain +1 Temporary Strength | E24: weapon_charged: apply_status strength 1 games=1 | F24: Peglin | G24: bell | I24: DumbBell | J24: Stats
A25: Echo Chamber | B25: Rare | C25: Passive | D25: Whenever you use Loot, you also use a copy of the last 3 Loot you used after picking up Echo Chamber | E25: echo_loot 3 | F25: The Binding of Isaac: Rebirth | I25: EchoChamber | J25: Loot
A26: Fanny Pack | B26: Uncommon | C26: Passive | D26: 50% chance to spawn 1 random loot on the grid when losing health | E26: health_lost: 50% chance drop_loot 1 | F26: The Binding of Isaac: Rebirth | G26: wearable, bag | I26: FannyPack | J26: Economy
A27: Fortune Necklace | B27: Common | C27: Triggered | D27: When selecting a game, Gain +1 Gold, but this is destroyed when taking damage | E27: game_selected: gain_gold 1; destroy_on_damage | F27: Mewgenics | G27: wearable, necklace | I27: FortuneNecklace | J27: Economy
A28: Gasoline | B28: Common | C28: Passive | D28: Whenever an Enemy is defeated, Add the Fire Tile Effect to the Tile it died on | E28: death_tile fire | F28: Risk of Rain 2 | G28: fire | I28: Gasoline | J28: Grid
A29: Golden Idol | B29: Event | C29: Passive | D29: All enemies drop +1 Gold | E29: gold_per_enemy: 1 | F29: Slay the Spire | G29: gold | I29: GoldenIdol | J29: Economy
A30: Hollow Heart | B30: Common | C30: Pickup | D30: Gain +4 Empty Max Health | E30: item_acquired: gain_empty_max_hp 4 | F30: Vampire Survivors | G30: heart | I30: HollowHeart | J30: Health
A31: Hot Bombs | B31: Uncommon | C31: Passive | D31: Gain +1 Bomb and Bombs Apply the Fire Tile | E31: item_acquired: gain_stat bombs 1; bomb_tile fire | F31: The Binding of Isaac: Rebirth | G31: bomb, fire | I31: HotBombs | J31: Bomb, Grid
A32: Infusion | B32: Uncommon | C32: Triggered | D32: Every time you defeat an Enemy, Gain +1 Empty Max Health | E32: enemy_killed: gain_empty_max_hp 1 | F32: Risk of Rain 2 | G32: blood | I32: Infusion | J32: Health
A33: IV Bag | B33: Event | C33: Usable, 0 | D33: Lose 1 Health and Gain +1 Gold | E33: item_used: lose_hp 1; gain_gold 1 | F33: The Binding of Isaac | G33: blood | I33: IvBag | J33: Economy
A34: Knight Cap | B34: Common | C34: Passive | D34: After Combat ends, Gain +1 Health if you had remaining Shield | E34: game_beaten if_shields: gain_hp 1 | F34: Peglin | G34: wearable, hat | I34: KnightCap | J34: Health
A35: Landmines | B35: Uncommon | C35: Passive | D35: After Combat ends, Apply the Landmine Unit to a random empty Tile | E35: game_beaten: apply_unit landmine target=random_empty | F35: Brotato | G35: bomb | I35: Landmines | J35: Grid
A36: Latch Key | B36: Common | C36: Pickup, Passive | D36: Gain +1 Key, +1 Shield, and +1 Luck | E36: passive: +1 luck; item_acquired: gain_stat keys 1; gain_stat bonus_shields 1 | F36: The Binding of Isaac: Rebirth | G36: key | I36: LatchKey | J36: Economy
A37: Link Cable | B37: Rare | C37: Passive | D37: All Loot count as adjacent to each other | E37: link_loot | F37: Batomon Showdown | G37: wire | I37: LinkCable | J37: Loot
... A47: Mom's Coin Purse | B47: Common | C47: Pickup | D47: Gain +4 Pills | E47: item_acquired: gain_pill 4 | F47: The Binding of Isaac | G47: mom, bag, drugs, pills | I47: MomsCoinPurse | J47: Loot
A48: Mom's Key | B48: Uncommon | C48: Pickup, Passive | D48: Gain +1 Key, and +1 Base Chest Value | E48: item_acquired: gain_stat keys 1; base_chest_bonus: 1 | F48: The Binding of Isaac: Rebirth | G48: mom, key | H48: shop | I48: MomsKey | J48: Economy
A49: Mysterious Mask | B49: Rare | C49: Pickup | D49: Choose one of 3 Starting Characters and gain their Level Up Condition | E49: item_acquired: mask_choice | F49: Batomon Showdown | G49: wearable, mask | I49: MysteriousMask | J49: Goals
A50: Oddly Smooth Stone | B50: Common | C50: Status | D50: Gain +1 Dexterity | E50: item_acquired: apply_status dexterity 1 | F50: Slay the Spire | G50: stone | I50: OddlySmoothStone | J50: Stats
A51: Old Coin | B51: Rare | C51: Pickup | D51: Gain +6 Gold | E51: item_acquired: gain_gold 6 | F51: Slay the Spire | G51: coin | I51: OldCoin | J51: Economy
A52: Performance Based Health Insurance | B52: Common | C52: Passive | D52: Whenever you Perfect a Game, Gain +2 Health | E52: game_perfected: gain_hp 2 | F52: Haste | I52: PerformanceBasedHealthInsurance | J52: Health
A53: Philosophers Stone | B53: Boss | C53: Passive | D53: Increase the Grid length by 1, but give all spawned enemies +1 Strength | E53: grid_length; spawn_status strength 1 | F53: Slay the Spire | G53: stone | I53: PhilosophersStone | J53: Grid
A54: Piggy Bank | B54: Uncommon | C54: Passive | D54: Whenever you lose Health, Gain +1 Gold | E54: health_lost: gain_gold 1 | F54: The Binding of Isaac: Rebirth | G54: pig, bank | H54: shop | I54: PiggyBank | J54: Economy
A55: Pummarola | B55: Uncommon | C55: Triggered | D55: After beating a game, Gain +1 Health | E55: game_beaten: gain_hp 1 | F55: Vampire Survivors | G55: heart | I55: Pummarola | J55: Health
A56: Red Candle | B56: Common | C56: Charged, 1 | D56: Apply the Fire Tile to any tile within the columns 2 and 3 | E56: item_used: apply_tile fire target=tile cols=2-3 | F56: The Binding of Isaac: Rebirth | G56: fire | H56: shop | I56: RedCandle | J56: Grid
A57: Rejuvenation Rack | B57: Rare | C57: Passive | D57: Double the effect of all Healing | E57: heal_multiplier: 2 | F57: Risk of Rain 2 | I57: RejuvenationRack | J57: Health
A58: Reptile Trinket | B58: Uncommon | C58: Triggered | D58: Whenever you drink or throw a potion, Gain +3 Strength until the end of the next combat | E58: potion_used: apply_status strength 3 games=1 | F58: Slay the Spire 2 | I58: ReptileTrinket | J58: Loot, Stats
A59: Ripple Basin | B59: Uncommon | C59: Triggered | D59: If you lose a run before completing any goals, Gain +1 Temporary Shield | E59: run_lost if_goals=0: gain_stat shields 1 | F59: Slay the Spire 2 | I59: RippleBasin | J59: Combat
A60: Runic Dome | B60: Boss | C60: Passive | D60: Increase the Grid length by 1, but you can no longer see enemies that will spawn | E60: grid_length; hide_spawns | F60: Slay the Spire | I60: RunicDome | J60: Grid
A61: Sacred Bark | B61: Boss | C61: Passive | D61: Double the effect of all Loot consumables (Scrolls, Potions, etc) | E61: loot_multiplier: 2 | F61: Slay the Spire | G61: wood | I61: SacredBark | J61: Special
A62: Salt Shaker | B62: Common | C62: Passive | D62: Whenever you would Gain Max Health, Gain +1 Extra Max Health | E62: stat_gain_bonus: {max_hp: 1} | F62: Peglin | G62: food | I62: SaltShaker | J62: Health
A63: Smelter | B63: Uncommon | C63: Passive, Charged, 3 | D63: Consume a Loot with a passive effect and treat it as an item. Doubles the chances of finding trinkets | E63: charged: charge_cost 3; item_used: smelt; loot_kind_weight: {trinket: 2} | F63: The Binding of Isaac: Rebirth | G63: pot | I63: Smelter | J63: Loot
A64: Snowball | B64: Uncommon | C64: Triggered | D64: When you would Gain +1 Transmute, Gain +1 Transmute | E64: stat_gain_bonus: {transmute: 1} | F64: Brotato | G64: snow | I64: Snowball | J64: Stats
A65: Staff of Flame | B65: Rare | C65: Charged, 2 | D65: Apply +3 Burn to a target enemy | E65: item_used: apply_status burn 3 target=enemy | F65: Mewgenics | G65: magic, fire | I65: StaffOfFlame | J65: Grid
A66: Steam Sale | B66: Event | C66: Passive | D66: Shop prices are 50% off | E66: shop_discount: 50 | F66: The Binding of Isaac: Rebirth | G66: sale | I66: SteamSale | J66: Economy
A67: Sticky Bombs | B67: Uncommon | C67: Pickup, Triggered | D67: Gain +1 Bomb and Bombs Apply the Web Tile | E67: item_acquired: gain_stat bombs 1; bomb_tile web | F67: The Binding of Isaac: Rebirth | G67: bomb, spider | I67: StickyBombs | J67: Bomb
A68: Stigmata | B68: Uncommon | C68: Pickup | D68: Gain +2 Max Health, Gain +2 Health, and +1 Bash | E68: item_acquired: gain_max_hp 2; gain_hp 2; gain_stat bash 1 | F68: The Binding of Isaac | G68: wood | H68: angel_room | I68: Stigmata | J68: Health, Stats
A69: The Book of Sin | B69: Uncommon | C69: Charged, 2 | D69: Gain +1 Gold, +1 Health, +1 Bomb, +1 Key, or 1 random Loot | E69: item_used: one_of gain_gold 1 | gain_hp 1 | gain_stat bombs 1 | gain_stat keys 1 | gain_loot 1 | F69: The Binding of Isaac | G69: book | I69: TheBookOfSin | J69: Economy
A70: The Mark | B70: Uncommon | C70: Pickup, Passive | D70: Gain +1 Bash and +1 Speed | E70: item_acquired: gain_stat bash 1; apply_status speed 1 | F70: The Binding of Isaac | G70: devilish | H70: devil_room | I70: TheMark | J70: Stats
A71: The Necronomicon | B71: Uncommon | C71: Charged, 3 | D71: Apply Stun 1 to all Enemies | E71: item_used: apply_status stun 1 target=all | F71: The Binding of Isaac | G71: book | H71: devil_room | I71: TheNecronomicon | J71: Offense
A72: There's Options | B72: Uncommon | C72: Passive | D72: Increase the chest size dropped from bosses by 1 | E72: boss_chest_bonus: 1 | F72: The Binding of Isaac: Rebirth | H72: shop | I72: TheresOptions | J72: Stats
A73: Ultra Duplicator | B73: Legendary | C73: Passive | D73: Whenever you obtain an item, get an extra copy of it | E73: duplicate_items | F73: Batomon Showdown | I73: UltraDuplicator | J73: Items
A74: Unstable Genome | B74: Uncommon | C74: Triggered | D74: When you beat a game, there's a 33% chance for this item to be destroyed and you may gain 1 of 3 random items | E74: game_beaten: 33% chance random_item_choice 3 destroy_self | F74: Caves of Qud | G74: mutation | I74: UnstableGenome | J74: Economy
A75: Vajra | B75: Common | C75: Status | D75: Gain +1 Strength | E75: item_acquired: apply_status strength 1 | F75: Slay the Spire | I75: Vajra | J75: Stats
A76: Well-Done Steak | B76: Uncommon | C76: Passive | D76: When Charging a Weapon, Gain +1 Health | E76: weapon_charged: gain_hp 1 | F76: Peglin | G76: food, meat | I76: WellDoneSteak | J76: Health
A77: White Beast Statue | B77: Uncommon | C77: Passive | D77: Gain +1 Potion at the end of combat | E77: game_beaten: gain_potion 1 | F77: Slay the Spire | G77: statue | I77: WhiteBeastStatue | J77: Loot
A78: Wooden Nickel | B78: Common | C78: Charged, 1 | D78: 50% chance to Gain +1 Gold | E78: item_used: 50% chance gain_gold 1 | F78: The Binding of Isaac: Rebirth | G78: wood, coin | I78: WoodenNickel | J78: Economy

Sheet enemies
A1: Name | B1: Type | C1: Difficulty | D1: Size | E1: Game | F1: Health | G1: Damage | H1: Goal Type | I1: Goal | J1: Ability | K1: File | L1: Tag | M1: Ticked | N1: Count
A2: Attack Fly | B2: Action | C2: 1-Low | D2: 1x1 | E2: The Binding of Isaac | F2: 1 | G2: 1 | H2: Bounty | I2: Defeat 3 bugs | J2: N/A | K2: AttackFly | L2: bug, fly | M2: any time | N2: 3
A3: Baby Alien | B3: Action | C3: 1-Low | D3: 1x1 | E3: Brotato | F3: 1 | G3: 1 | H3: Bounty | I3: Defeat an enemy that is an alien | J3: N/A | K3: BabyAlien | L3: alien | M3: any time
A4: Bullat | B4: Action | C4: 1-Low | D4: 1x1 | E4: Enter the Gungeon | F4: 1 | G4: 1 | H4: Feat | I4: Shoot down a flying enemy | J4: N/A | K4: Bullat | L4: bat, bullet | M4: any time
A5: Doomvas | B5: Action | C5: 1-Low | D5: 1x1 | E5: Rogue Legacy | F5: 1 | G5: 1 | H5: Feat | I5: Destroy a painting | J5: N/A | K5: Doomvas | L5: art | M5: any time
A6: Flaming Fatty | B6: Action | C6: 1-Low | D6: 1x1 | E6: The Binding of Isaac: Rebirth | F6: 1 | G6: 1 | H6: Feat | I6: Push an enemy into fire | J6: Aftermath (Fire) | K6: FlamingFatty | L6: fire | M6: any time
A7: Keybullet Kin | B7: Action | C7: 1-Low | D7: 1x1 | E7: Enter the Gungeon | F7: 1 | G7: 1 | H7: Fetch | I7: Obtain a key | J7: N/A | K7: KeybulletKin | L7: bullet | M7: any time
A8: Lil Dave | B8: Action | C8: 1-Low | D8: 1x1 | E8: Muck | F8: 1 | G8: 1 | H8: Feat | I8: Destroy a wooden structure | J8: N/A | K8: LilDave | M8: any time
A9: Mysterious Tree | B9: Action | C9: 1-Low | D9: 1x1 | E9: 20 Minutes Till Dawn | F9: 3 | G9: 1 | H9: Feat | I9: Destroy a tree | J9: Immobile | K9: MysteriousTree | L9: plant, tree, wood | M9: any time
A10: Numbskull | B10: Action | C10: 1-Low | D10: 1x1 | E10: Hades | F10: 1 | G10: 1 | H10: Bounty | I10: Defeat an animated body part | J10: N/A | K10: Numbskull | L10: undead, skeleton | M10: any time
A11: Pacer | B11: Action | C11: 1-Low | D11: 1x1 | E11: The Binding of Isaac | F11: 1 | G11: 1 | H11: Bounty | I11: Defeat a headless enemy | J11: N/A | K11: Pacer | M11: any time
A12: Psychic Horf | B12: Action | C12: 1-Low | D12: 1x1 | E12: The Binding of Isaac: Rebirth | F12: 1 | G12: 1 | H12: Feat | I12: Use a homing attack | J12: Ranged (N/A) | K12: PsychicHorf | M12: any time
A13: Skeleton Warrior | B13: Action | C13: 1-Low | D13: 1x1 | E13: Ball x Pit | F13: 1 | G13: 1 | H13: Bounty | I13: Defeat a skeleton with a ball | J13: N/A | K13: SkeletonWarrior | L13: undead, skeleton | M13: any time
A14: Spider | B14: Action | C14: 1-Low | D14: 1x1 | E14: The Binding of Isaac | F14: 1 | G14: 1 | H14: Bounty | I14: Defeat 3 spiders | J14: N/A | K14: Spider | L14: bug, spider | M14: any time | N14: 3
A15: Wisp | B15: Action | C15: 1-Low | D15: 1x1 | E15: Risk of Rain | F15: 1 | G15: 1 | H15: Bounty | I15: Defeat an enemy made of fire | J15: N/A | K15: Wisp | L15: fire | M15: any time
A16: Wringer | B16: Action | C16: 1-Low | D16: 1x1 | E16: Hades | F16: 1 | G16: 1 | H16: Feat | I16: Grab an enemy | J16: N/A | K16: Wringer | L16: undead | M16: any time
A17: Bony | B17: Action | C17: 2-Medium | D17: 1x1 | E17: The Binding of Isaac: Rebirth | F17: 1 | G17: 2 | H17: Bounty | I17: Defeat 5 skeletons | J17: Ranged (3) | K17: Bony | L17: undead, skeleton | M17: any time | N17: 5
A18: Child | B18: Action | C18: 2-Medium | D18: 1x1 | E18: Risk of Rain | F18: 1 | G18: 2 | H18: Bounty | I18: Defeat a child | J18: N/A | K18: Child | L18: alien | M18: any time
A19: Coal Spider | B19: Action | C19: 2-Medium | D19: 1x1 | E19: The Binding of Isaac: Rebirth | F19: 1 | G19: 2 | H19: Feat | I19: Set a rock on fire | J19: N/A | K19: CoalSpider | L19: spider, rock, fire | M19: any time
A20: Flaming Hopper | B20: Action | C20: 2-Medium | D20: 1x1 | E20: The Binding of Isaac | F20: 1 | G20: 2 | H20: Bounty | I20: Defeat an enemy while on fire | J20: Infliction (2, Burn) | K20: FlamingHopper | L20: fire | M20: any time
A21: Fungun | B21: Action | C21: 2-Medium | D21: 1x1 | E21: Enter the Gungeon | F21: 1 | G21: 2 | H21: Feat | I21: Shoot a mushroom | J21: N/A | K21: Fungun | L21: mushroom | M21: any time
A22: King Bullat | B22: Action | C22: 2-Medium | D22: 1x1 | E22: Enter the Gungeon | F22: 1 | G22: 2 | H22: Feat | I22: Shoot down 2 flying enemies | J22: N/A | K22: KingBullat | L22: bat, bullet | M22: any time | N22: 2
A23: Skeletal Brute | B23: Action | C23: 2-Medium | D23: 1x2 | E23: Ball x Pit | F23: 1 | G23: 2 | H23: Bounty | I23: Defeat 2 skeletons with a ball | J23: N/A | K23: SkeletalBrute | L23: undead, skeleton | M23: any time | N23: 2
A24: Bishop | B24: Action | C24: 3-High | D24: 1x1 | E24: The Binding of Isaac: Rebirth | F24: 1 | G24: 3 | H24: Feat | I24: Block damage done to a friendly unit | J24: Bolster (1, Dexterity) | K24: Bishop | M24: any time
A25: Gigantic Vermin | B25: Action | C25: 3-High | D25: 2x2 | E25: Hades | F25: 1 | G25: 3 | H25: Bounty | I25: Defeat a large rodent | J25: N/A | K25: GiganticVermin | L25: rodent, rat | M25: any time
A26: Nemean Chariot | B26: Action | C26: 3-High | D26: 1x1 | E26: Hades | F26: 1 | G26: 3 | H26: Feat | I26: Hit an enemy with a vehicle | J26: Haste (1) | K26: NemeanChariot | M26: any time
A27: Skeletal Bastion | B27: Action | C27: 3-High | D27: 2x3 L 90 CC | E27: Ball x Pit | F27: 1 | G27: 3 | H27: Bounty | I27: Defeat 3 skeletons with a ball | J27: N/A | K27: SkeletalBastion | L27: undead, skeleton | M27: any time | N27: 3
A28: Cultist | B28: Deckbuilder | C28: 1-Low | D28: 1x1 | E28: Slay the Spire | F28: 1 | G28: 1 | H28: Feat | I28: Perform a religious act | J28: Ritual | K28: Cultist | M28: any time
A29: Fungi Beast | B29: Deckbuilder | C29: 1-Low | D29: 1x1 | E29: Slay the Spire | F29: 1 | G29: 1 | H29: Feat | I29: Get infected | J29: N/A | K29: FungiBeast | L29: mushroom | M29: any time
A30: Ice Slime | B30: Deckbuilder | C30: 1-Low | D30: 1x1 | E30: Dungeon Clawler | F30: 1 | G30: 1 | H30: Feat | I30: Freeze an enemy | J30: N/A | K30: IceSlime | L30: slime, ice | M30: any time
A31: Lava Slime | B31: Deckbuilder | C31: 1-Low | D31: 1x1 | E31: Dungeon Clawler | F31: 1 | G31: 1 | H31: Feat | I31: Touch lava | J31: Infliction (1, Burn) | K31: LavaSlime | L31: slime, lava | M31: any time
A32: Punch Construct | B32: Deckbuilder | C32: 1-Low | D32: 1x1 | E32: Slay the Spire 2 | F32: 1 | G32: 1 | H32: Feat | I32: Punch a robot | J32: N/A | K32: PunchConstruct | L32: robot | M32: any time
A33: Shrinker Beetle | B33: Deckbuilder | C33: 1-Low | D33: 1x1 | E33: Slay the Spire 2 | F33: 1 | G33: 1 | H33: Feat | I33: Shrink in size | J33: N/A | K33: ShrinkerBeetle | L33: bug, beetle | M33: any time
A34: Spike Slime (L) | B34: Deckbuilder | C34: 1-Low | D34: 2x2 | E34: Slay the Spire | F34: 1 | G34: 1 | H34: Bounty | I34: Defeat an enemy that splits into another enemy | J34: Split (2, slime tag) | K34: SpikeSlime(L) | L34: slime | M34: any time
A35: Stumpy Stump | B35: Deckbuilder | C35: 1-Low | D35: 1x1 | E35: Peglin | F35: 1 | G35: 1 | H35: Feat | I35: Have a defeated enemy block an attack | J35: N/A | K35: StumpyStump | L35: plant, tree, wood | M35: any time
A36: Shelled Parasite | B36: Deckbuilder | C36: 2-Medium | D36: 1x1 | E36: Slay the Spire | F36: 1 | G36: 2 | H36: Bounty | I36: Defeat an enemy that looks edible | J36: N/A | K36: ShelledParasite | M36: any time
A37: Snecko | B37: Deckbuilder | C37: 2-Medium | D37: 1x1 | E37: Slay the Spire | F37: 1 | G37: 2 | H37: Restriction | I37: Beat a game while having selected a random starting build | J37: N/A | K37: Snecko | M37: game beaten
A38: The Obscura | B38: Deckbuilder | C38: 2-Medium | D38: 1x1 | E38: Slay the Spire 2 | F38: 1 | G38: 2 | H38: Feat | I38: Create an illusion | J38: Illusionist (1, Random Medium) | K38: TheObscura | M38: any time
A39: Chosen | B39: Deckbuilder | C39: 3-High | D39: 1x1 | E39: Slay the Spire | F39: 1 | G39: 3 | H39: Restriction | I39: Beat a game without using magic | J39: Hexer | K39: Chosen | M39: game beaten
A40: Transient | B40: Deckbuilder | C40: 3-High | D40: 2x2 | E40: Slay the Spire | F40: 1 | G40: 3 | H40: Discovery | I40: Witness an enemy kill itself | J40: Tanky (8), Fading (3) | K40: Transient | M40: any time
A41: Carcass | B41: Strategy | C41: 1-Low | D41: 1x1 | E41: Mewgenics | F41: 1 | G41: 1 | H41: Bounty | I41: Destroy an enemy spawner | J41: Nested Spawner (1, fly tag) | K41: Carcass | M41: any time
A42: Cop Bot | B42: Strategy | C42: 1-Low | D42: 1x1 | E42: Mewgenics | F42: 1 | G42: 1 | H42: Feat | I42: Defy an officer of the law | J42: N/A | K42: CopBot | L42: robot, cop | M42: any time
A43: Goblin | B43: Strategy | C43: 1-Low | D43: 1x1 | E43: Gnomes | F43: 1 | G43: 1 | H43: Bounty | I43: Defeat 3 goblins | J43: N/A | K43: Goblin | L43: goblin | M43: any time | N43: 3
A44: Maggot | B44: Strategy | C44: 1-Low | D44: 1x1 | E44: Mewgenics | F44: 1 | G44: 1 | H44: Bounty | I44: Defeat an infested or rotted enemy | J44: N/A | K44: Maggot | L44: fly | M44: any time
A45: Mung | B45: Strategy | C45: 1-Low | D45: 1x1 | E45: Brutal Orchestra | F45: 1 | G45: 1 | H45: Fetch | I45: Obtain 1 fish | J45: N/A | K45: Mung | L45: fish | M45: any time
A46: Atomic Kitten | B46: Strategy | C46: 2-Medium | D46: 1x1 | E46: Mewgenics | F46: 1 | G46: 2 | H46: Bounty | I46: Defeat a radiated enemy | J46: N/A | K46: AtomicKitten | L46: cat, radiation | M46: any time
A47: Caveman Woman | B47: Strategy | C47: 2-Medium | D47: 1x1 | E47: Mewgenics | F47: 1 | G47: 2 | H47: Discovery | I47: Witness a birth | J47: Entry Summon (1, baby tag) | K47: CavemanWoman | M47: any time
A48: Fetus | B48: Strategy | C48: 2-Medium | D48: 1x1 | E48: Mewgenics | F48: 1 | G48: 2 | H48: Fetch | I48: Find a baby | J48: N/A | K48: Fetus | L48: baby | M48: any time
A49: Host | B49: Strategy | C49: 2-Medium | D49: 1x1 | E49: Mewgenics | F49: 1 | G49: 2 | H49: Feat | I49: Reflect a projectile | J49: Ranged (N/A), Immobile | K49: Host | M49: any time
A50: Love Bot | B50: Strategy | C50: 2-Medium | D50: 1x1 | E50: Mewgenics | F50: 1 | G50: 2 | H50: Feat | I50: Use technology to heal yourself | J50: Melee Ally Buff (1, Speed) | K50: LoveBot | L50: robot | M50: any time
A51: Revola | B51: Strategy | C51: 2-Medium | D51: 1x2 | E51: Brutal Orchestra | F51: 1 | G51: 2 | H51: Feat | I51: Body slam an enemy | J51: Defensive Stance | K51: Revola | M51: any time
A52: Robo-Cat | B52: Strategy | C52: 2-Medium | D52: 1x1 | E52: Mewgenics | F52: 1 | G52: 2 | H52: Bounty | I52: Defeat a robot designed to look like an animal | J52: N/A | K52: Robo-Cat | L52: cat, robot | M52: any time
A53: Sharky | B53: Strategy | C53: 2-Medium | D53: 1x1 | E53: Mewgenics | F53: 1 | G53: 2 | H53: Feat | I53: Bleed an enemy to death | J53: Predatory Scent, Infliction(1, Bleed) | K53: Sharky | L53: cat, fish | M53: any time
A54: Spiked Cat | B54: Strategy | C54: 2-Medium | D54: 1x1 | E54: Mewgenics | F54: 1 | G54: 2 | H54: Feat | I54: Break glass | J54: N/A | K54: SpikedCat | L54: cat | M54: any time
A55: Tornado | B55: Strategy | C55: 2-Medium | D55: 1x1 | E55: Forward: Escape the Fold | F55: 1 | G55: 2 | H55: Discovery | I55: Find a Tornado | J55: N/A | K55: Tornado | M55: any time
A56: Giggling Minister | B56: Strategy | C56: 3-High | D56: 1x1 | E56: Brutal Orchestra | F56: 1 | G56: 3 | H56: Discovery | I56: Get something stolen from you | J56: Theft (1, Item), Agile | K56: GigglingMinister | M56: any time
A57: Skeleton Cat | B57: Strategy | C57: 3-High | D57: 1x1 | E57: Mewgenics | F57: 1 | G57: 3 | H57: Bounty | I57: Defeat a skeleton animal | J57: Restless Remains | K57: SkeletonCat | L57: cat, undead, skeleton | M57: any time
A58: Spider Kitten | B58: Strategy | C58: 3-High | D58: 1x1 | E58: Mewgenics | F58: 1 | G58: 3 | H58: Feat | I58: Trap an enemy in place | K58: SpiderKitten | L58: cat, bug, spider | M58: any time
A59: Gatekeeper | B59: Strategy | C59: 4-Insane | D59: 1x1 | E59: Mewgenics | F59: 1 | G59: 4 | H59: Feat | I59: Steal a soul | J59: Drain (2, Max Health), Entry Summon (1, skeleton tag) | K59: Gatekeeper | L59: undead | M59: any time
A60: Stem Cat | B60: Strategy | C60: 4-Insane | D60: 1x1 | E60: Mewgenics | F60: 1 | G60: 4 | H60: Bounty | I60: Defeat an enemy that clones itself | J60: N/A | K60: StemCat | L60: cat | M60: any time
A61: Floating Eye | B61: Traditional | C61: 1-Low | D61: 1x1 | E61: NetHack | F61: 1 | G61: 1 | H61: Restriction | I61: Beat a game without using melee attacks | J61: N/A | K61: FloatingEye | M61: game beaten
A62: Leprechaun | B62: Traditional | C62: 1-Low | D62: 1x1 | E62: NetHack | F62: 1 | G62: 1 | H62: Discovery | I62: Retrieve stolen currency or items | J62: Theft (2, Gold), Agile | K62: Leprechaun | M62: any time
A63: Monkey | B63: Traditional | C63: 1-Low | D63: 1x1 | E63: Crypt of the NecroDancer | F63: 1 | G63: 1 | H63: Bounty | I63: Defeat an enemy that latches on to you | J63: N/A | K63: Monkey | L63: monkey | M63: any time
A64: Rust Monster | B64: Traditional | C64: 2-Medium | D64: 1x1 | E64: NetHack | F64: 1 | G64: 2 | H64: Restriction | I64: Beat a game without using metal armor | J64: Degradation | K64: RustMonster | M64: game beaten
A65: Stalker | B65: Traditional | C65: 2-Medium | D65: 1x1 | E65: NetHack | F65: 1 | G65: 2 | H65: Feat | I65: Become undetectable | J65: Invisibility | K65: Stalker | M65: any time
A66: Chrome Pyramid | B66: Traditional | C66: 3-High | D66: 1x1 | E66: Caves of Qud | F66: 1 | G66: 3 | H66: Feat | I66: Get an achievement 5% or less of players have gotten | J66: N/A | K66: ChromePyramid | L66: robot | M66: any time
A67: Jabberwock | B67: Traditional | C67: 3-High | D67: 1x1 | E67: NetHack | F67: 1 | G67: 3 | H67: Feat | I67: Behead an enemy | J67: N/A | K67: Jabberwock | M67: any time

Sheet bosses
A1: Name | B1: Type | C1: Difficulty | D1: Size | E1: Game | F1: Health | G1: Damage | H1: Goal Type | I1: Goal | J1: Ability | K1: File | L1: Tag | M1: Phases | N1: Ticked | O1: Count
A2: Baby Plum | B2: Action | C2: 1-Low | D2: 2x2 | E2: The Binding of Isaac: Rebirth | F2: 1 | G2: 3 | H2: Bounty | I2: Defeat a boss without using violence | J2: N/A | K2: BabyPlum | N2: any time
A3: Beholster | B3: Action | C3: 1-Low | D3: 2x2 | E3: Enter the Gungeon | F3: 1 | G3: 3 | H3: Fetch | I3: Have 6 Guns at once | J3: Ranged (4) | K3: Beholster | L3: gun | N3: any time
A4: Big Chunk | B4: Action | C4: 1-Low | D4: 2x2 | E4: Muck | F4: 1 | G4: 3 | H4: Bounty | I4: Defeat an enemy made of stone | J4: N/A | K4: BigChunk | L4: rock | N4: any time
A5: Colossus | B5: Action | C5: 1-Low | D5: 2x2 | E5: Risk of Rain | F5: 1 | G5: 3 | H5: Discovery | I5: Witness a living structure | J5: Trample | K5: Colossus | N5: any time
A6: Famine | B6: Action | C6: 1-Low | D6: 1x1 | E6: The Binding of Isaac | F6: 1 | G6: 3 | H6: Restriction | I6: Beat a game without eating any food | J6: Ranged (1) | K6: Famine | N6: game beaten
A7: Khidr | B7: Action | C7: 1-Low | D7: 2x2 | E7: Rogue Legacy | F7: 1 | G7: 3 | H7: Feat | I7: Poke an eye | J7: N/A | K7: Khidr | L7: eye | N7: any time
A8: Mega Fatty | B8: Action | C8: 1-Low | D8: 2x2 | E8: The Binding of Isaac: Rebirth | F8: 1 | G8: 3 | H8: Bounty | I8: Defeat an obese enemy | J8: Ranged (2) | K8: MegaFatty | N8: any time
A9: Megaera | B9: Action | C9: 1-Low | D9: 1x1 | E9: Hades | F9: 1 | G9: 3 | H9: Fetch | I9: Date someone | J9: N/A | K9: Megaera | N9: any time
A10: Steven | B10: Action | C10: 1-Low | D10: 1x1 | E10: The Binding of Isaac | F10: 1 | G10: 3 | H10: Discovery | I10: Be in a time loop | J10: N/A | K10: Steven | N10: any time
A11: The Rainmaker | B11: Action | C11: 1-Low | D11: 1x1 | E11: The Binding of Isaac: Rebirth | F11: 1 | G11: 3 | H11: Feat | I11: Take a shower | J11: N/A | K11: TheRainmaker | N11: any time
A12: Charon | B12: Action | C12: 2-Medium | D12: 2x1 | E12: Hades | F12: 1 | G12: 5 | H12: Fetch | I12: Steal from a shop | J12: N/A | K12: Charon | N12: any time
A13: Mom's Heart | B13: Action | C13: 2-Medium | D13: 1x1 | E13: The Binding of Isaac | F13: 1 | G13: 5 | H13: Feat | I13: Break a Heart | J13: N/A | K13: MomsHeart | N13: any time
A14: Resourceful Rat | B14: Action | C14: 2-Medium | D14: 1x1 | E14: Enter the Gungeon | F14: 1 | G14: 5 | H14: Feat | I14: Beat a mini-game inside of a game | J14: N/A | K14: ResourcefulRat | L14: rat | N14: any time
A15: Royal Phalanx | B15: Action | C15: 2-Medium | D15: 1x1 | E15: Ember Knights | F15: 1 | G15: 5 | H15: Feat | I15: Block an attack with an element | J15: Defensive Stance (2) | K15: RoyalPhalanx | N15: any time
A16: Scylla | B16: Action | C16: 2-Medium | D16: 1x1 | E16: Hades II | F16: 1 | G16: 5 | H16: Feat | I16: Perform a song | J16: N/A | K16: Scylla | N16: any time
A17: Wallmonger | B17: Action | C17: 2-Medium | D17: 2x3 | E17: Enter the Gungeon | F17: 1 | G17: 5 | H17: Feat | I17: Destroy a wall | J17: N/A | K17: Wallmonger | N17: any time
A18: Isaac | B18: Action | C18: 3-High | D18: 1x1 | E18: The Binding of Isaac | F18: 1 | G18: 7 | H18: Bounty | I18: Defeat yourself | J18: N/A | K18: Isaac | N18: any time
A19: Lich | B19: Action | C19: 4-Insane | D19: 1x2 | E19: Enter the Gungeon | F19: 1 | G19: 9 | H19: Bounty | I19: Defeat a magic enemy with a gun | J19: N/A | K19: Lich | L19: undead, skeleton | N19: any time
A20: The Beast | B20: Action | C20: 4-Insane | D20: 3x3 | E20: The Binding of Isaac: Rebirth | F20: 1 | G20: 9 | H20: Bounty | I20: Defeat a true final boss while on the brink of death | J20: Trample | K20: TheBeast | N20: any time
A21: The One Who Waits | B21: Action | C21: 4-Insane | D21: 2x2 | E21: Cult of the Lamb | F21: 1 | G21: 9 | H21: Feat | I21: Enter or Create a religion | J21: N/A | K21: TheOneWhoWaits | N21: any time
A22: Gremlin Nob | B22: Deckbuilder | C22: 1-Low | D22: 1x1 | E22: Slay the Spire | F22: 1 | G22: 3 | H22: Feat | I22: Taunt at someone | J22: N/A | K22: GremlinNob | N22: any time
A23: Lagavulin | B23: Deckbuilder | C23: 1-Low | D23: 2x2 | E23: Slay the Spire | F23: 1 | G23: 3 | H23: Feat | I23: Go to sleep | J23: N/A | K23: Lagavulin | N23: any time
A24: Slime Boss | B24: Deckbuilder | C24: 1-Low | D24: 2x2 | E24: Peglin | F24: 1 | G24: 3 | H24: Feat | I24: Enter an enemy | J24: N/A | K24: SlimeBoss | L24: slime | N24: any time
A25: Vantom | B25: Deckbuilder | C25: 1-Low | D25: 1x1 | E25: Slay the Spire 2 | F25: 1 | G25: 3 | H25: Feat | I25: Use an attack that hits 4+ times | J25: Lacerator | K25: Vantom | N25: any time
A26: The Club | B26: Deckbuilder | C26: 2-Medium | D26: 1x1 | E26: Balatro | F26: 1 | G26: 5 | H26: Restriction | I26: Beat a game without backtracking | J26: N/A | K26: TheClub | N26: game beaten
A27: The Goad | B27: Deckbuilder | C27: 2-Medium | D27: 1x1 | E27: Balatro | F27: 1 | G27: 5 | H27: Restriction | I27: Beat a game without using a weapon | J27: N/A | K27: TheGoad | N27: game beaten
A28: The Head | B28: Deckbuilder | C28: 2-Medium | D28: 1x1 | E28: Balatro | F28: 1 | G28: 5 | H28: Restriction | I28: Beat a game without purposefully healing | J28: N/A | K28: TheHead | N28: game beaten
A29: The Insatiable | B29: Deckbuilder | C29: 2-Medium | D29: 2x2 | E29: Slay the Spire 2 | F29: 1 | G29: 5 | H29: Bounty | I29: Consume an enemy | J29: Ruthless, Devour Whole | K29: TheInsatiable | N29: any time
A30: The Window | B30: Deckbuilder | C30: 2-Medium | D30: 1x1 | E30: Balatro | F30: 1 | G30: 5 | H30: Restriction | I30: Beat a game without spending currency | J30: N/A | K30: TheWindow | N30: game beaten
A31: Cerulean Bell | B31: Deckbuilder | C31: 3-High | D31: 1x1 | E31: Balatro | F31: 1 | G31: 7 | H31: Restriction | I31: Beat a game while only taking the first option offered when taking reward options | J31: N/A | K31: CeruleanBell | N31: game beaten
A32: The Needle | B32: Deckbuilder | C32: 3-High | D32: 1x1 | E32: Balatro | F32: 1 | G32: 7 | H32: Restriction | I32: Beat a game while only using 1 hand | J32: N/A | K32: TheNeedle | N32: game beaten
A33: Time Eater | B33: Deckbuilder | C33: 3-High | D33: 1x1 | E33: Slay the Spire | F33: 1 | G33: 7 | H33: Restriction | I33: Beat the game in 2 hours or less | J33: Bolster (3, Speed) | K33: TimeEater | N33: game beaten
A34: Corrupt Heart | B34: Deckbuilder | C34: 4-Insane | D34: 2x2 | E34: Slay the Spire | F34: 1 | G34: 9 | H34: Feat | I34: Get the true ending on the hardest difficulty possible | J34: Hexer (2) | K34: CorruptHeart | N34: any time
A35: Giant Spider | B35: Strategy | C35: 1-Low | D35: 2x2 | E35: Forward: Escape the Fold | F35: 1 | G35: 3 | H35: Bounty | I35: Defeat a bug larger than you | J35: N/A | K35: GiantSpider | L35: bug, spider | N35: any time
A36: Hickory | B36: Strategy | C36: 1-Low | D36: 1x1 | E36: Brutal Orchestra | F36: 1 | G36: 3 | H36: Feat | I36: Light a liquid on fire | J36: Infliction (1, Burn) | K36: Hickory | L36: fire | N36: any time
A37: Marshmallow | B37: Strategy | C37: 1-Low | D37: 1x1 | E37: Mewgenics | F37: 1 | G37: 3 | H37: Feat | I37: Have an enemy defeat another enemy | J37: N/A | K37: Marshmallow | L37: cat | N37: any time
A38: Mobius | B38: Strategy | C38: 1-Low | D38: 2x2 | E38: Brutal Orchestra | F38: 1 | G38: 3 | H38: Fetch | I38: Obtain a large fish | J38: N/A | K38: Mobius | L38: fish | N38: any time
A39: Morana | B39: Strategy | C39: 1-Low | D39: 1x1 | E39: Mewgenics | F39: 1 | G39: 3 | H39: Feat | I39: Raise the dead | J39: Necromancy (1) | K39: Morana | L39: cat | N39: any time
A40: Trigger Fingers | B40: Strategy | C40: 1-Low | D40: 1x1 | E40: Brutal Orchestra | F40: 1 | G40: 3 | H40: Bounty | I40: Defeat a fascist | J40: N/A | K40: TriggerFingers | N40: any time
A41: Chubs & Nubs | B41: Strategy | C41: 2-Medium | D41: 1x2 | E41: Mewgenics | F41: 1 | G41: 5 | H41: Feat | I41: Eat something smelly | J41: N/A | K41: Chubs&Nubs | L41: dog | N41: any time
A42: Flushmaster | B42: Strategy | C42: 2-Medium | D42: 1x1 | E42: Mewgenics | F42: 1 | G42: 5 | H42: Feat | I42: Flush or get flushed | J42: N/A | K42: Flushmaster | N42: any time
A43: Guillatina | B43: Strategy | C43: 2-Medium | D43: 2x2 | E43: Mewgenics | F43: 1 | G43: 5 | H43: Feat/Feat/Bounty | I43: Eat a living creature/Throw a body part/Defeat a rotten enemy | J43: Trample, Undying (2) | K43: Guillotina, Guillotina2, Guillotina3 | L43: cat | M43: 3 | N43: any time
A44: Lord Bunga | B44: Strategy | C44: 2-Medium | D44: 2x1 | E44: Mewgenics | F44: 1 | G44: 5 | H44: Fetch | I44: Become a cannibal | J44: Ruthless, Devour Whole | K44: LordBunga | N44: any time
A45: Trampy | B45: Strategy | C45: 2-Medium | D45: 1x1 | E45: Mewgenics | F45: 1 | G45: 5 | H45: Feat | I45: Get drunk | J45: N/A | K45: Trampy | L45: cat | N45: any time
A46: The Man in the Moon | B46: Strategy | C46: 3-High | D46: 3x3 | E46: Mewgenics | F46: 1 | G46: 7 | H46: Discovery | I46: Go to a Moon | J46: Trample | K46: TheManInTheMoon | N46: any time
A47: Throbbing King | B47: Strategy | C47: 3-High | D47: 2x2 | E47: Mewgenics | F47: 1 | G47: 7 | H47: Fetch | I47: Steal a body part | J47: Ruthless | K47: ThrobbingKing | N47: any time
A48: The Creator | B48: Strategy | C48: 4-Insane | D48: 2x2 | E48: Mewgenics | F48: 1 | G48: 9 | H48: Bounty | I48: Defeat a God | J48: N/A | K48: TheCreator | L48: god, holy | N48: any time
A49: Banshee | B49: Traditional | C49: 1-Low | D49: 1x1 | E49: Crypt of the NecroDancer | F49: 1 | G49: 3 | H49: Restriction | I49: Beat a game while having muted the game | J49: N/A | K49: Banshee | N49: game beaten
A50: Green Banshee | B50: Traditional | C50: 2-Medium | D50: 1x1 | E50: Crypt of the NecroDancer | F50: 1 | G50: 5 | H50: Restriction | I50: Beat a game while having muted the game | J50: N/A | K50: GreenBanshee | N50: game beaten
A51: Dragon | B51: Traditional | C51: 3-High | D51: 1x2 | E51: Rogue | F51: 1 | G51: 7 | H51: Bounty | I51: Slay a dragon boss | J51: Ranged (2), Fireproof, Infliction (1, Burn) | K51: Dragon | N51: any time

Sheet abilities
A1: Name | B1: Type | C1: Variables | D1: Description | E1: Effect
A2: Aftermath | B2: Death | C2: Tile Effect | D2: On Death, will Add X Tile Effect to the Tile it died on | E2: death: apply_tile Y
A3: Agile | B3: Movement | C3: N/A | D3: Can move diagonally if necessary | E3: passive: move_diagonal
A4: Bolster | B4: Buff | C4: Amount, Status Type | D4: Grants X amount of X Status to all other Enemies and Bosses until death | E4: passive: aura_status Y X
A5: Defensive Stance | B5: Intent | C5: Stacks | D5: Will Gain X Dexterity on it's first turn instead of moving or attacking | E5: first_turn: gain_status dexterity X
A6: Degradation | B6: Attack | C6: Amount | D6: When this Enemy attacks and deals damage, it will Destroy X amount of random obtained Loot | E6: hit: destroy_loot X
A7: Devour Whole | B7: Attack | C7: N/A | D7: When this Enemy attacks and deals damage, the target is eaten and dies, including the plaer | E7: hit: devour
A8: Drain | B8: Attack | C8: Amount, Stats | D8: When this Enemy attacks and deals damage, decrease by X the player's Y(Max Health, Luck, Scramble, Bash, Dash, Transmute) | E8: hit: drain_stat Y X
A9: Entry Summon | B9: Summoner | C9: Amount, Enemy Type | D9: Instead of moving or attacking on it's first turn, it will Summon X amount of Y Enemies to a random adjacent tile | E9: first_turn: summon_adjacent X Y
A10: Fading | B10: Death | C10: Amount | D10: Will die at the end of X amount of combats | E10: spawn: set_fades X
A11: Fireproof | B11: Resistance | C11: N/A | D11: Cannot be Burned | E11: passive: immune burn
A12: Haste | B12: Buff | C12: Stacks | D12: Spawns with X Speed | E12: spawn: gain_status speed X
... A32: Restless Remains | B32: Death | C32: N/A | D32: On Health depletion, will leave a corpse with 1 Max Health that will revive in it's current tile on game completion unless fully defeated | E32: death: leave_corpse 1 revive=game_end

Sheet statuses
A1: Name | B1: Type | C1: Game | D1: On Player | E1: On Player Effect | F1: On Enemy | G1: On Enemy Effect | H1: Combat | I1: Decrease | J1: EnemyOnly | K1: Enemy Combat Effect | L1: Stackable | M1: Image
A2: Burn | B2: Debuff | C2: Brutal Orchestra | D2: Gain "You must beat a game while skipping or trashing X items/upgrades or take 3 Damage." | E2: demand "skip or trash {X} [item/upgrade|items/upgrades]" else -> take_damage 3 | F2: Gains "or instead beat a game while skipping or trashing 4-X items/upgrades" | G2: instead "skip or trash {4-X} [item/upgrade|items/upgrades]" | H2: Half Damage dealt | I2: On Completion | J2: Yes | K2: damage_dealt x0.5 | L2: Max: 3 | M2: Burn
A3: Dexterity | B3: Buff | C3: Slay the Spire | D3: Gain "if X or all bosses were beaten without getting hit when beating a game, Gain a [chest reward]" | E3: goal "{X} or all bosses were beaten without getting hit" -> gain_chest reward {X} | F3: Gains "and you must beat X or all bosses without getting hit in the run you complete the goal in" | G3: clause "you must beat {X} or all bosses without getting hit" | H3: Gain +X Shields | I3: N/A | J3: Yes | K3: shield +{X} | L3: Intensity | M3: Dexterity
A4: Marked | B4: Debuff | C4: Mewgenics | D4: Gain "You must beat a game while getting X achievements or take 3 Damage." | E4: demand "get {X} [achievement|achievements]" else -> take_damage 3 | F4: Gains "and if you get X achievements in the run you complete the goal in, Gain a [chest reward]" | G4: bonus "you get {X} [achievement|achievements]" decay -> gain_chest reward {X} | H4: Damage taken increased by x2. Ignores shields. | I4: On Completion | J4: No | K4: damage_taken x2; pierce_shields | L4: Intensity | M4: Marked
A5: Speed | B5: Buff | C5: Mewgenics | D5: Gain "If beaten in 1+(1/2)^(X-2) hours or less, Gain a [chest reward] and 1 Dash" | E5: goal "beaten in {1+(1/2)^(X-2):hours} or less" -> gain_chest reward {X}; gain_stat dash 1 | F5: Gains "and the game must be beaten in 1+(1/2)^(X-2) hours or less" — on a goal you can do any time, "and you must do it within 1+(1/2)^(X-2) hours of starting the game" | G5: clause "the game must be beaten in {1+(1/2)^(X-2):hours} or less" any_time "you must do it within {1+(1/2)^(X-2):hours} of starting the game" | H5: Increase tile movement by X | I5: N/A | J5: Yes | K5: tile_move +{X} | L5: Intensity | M5: Speed
A6: Strength | B6: Buff | C6: Slay the Spire | D6: Gain "If beaten while the difficulty is increased X times or as much as possible, Gain a [chest reward] and 1 Bash" | E6: goal "the difficulty is increased {X} [time|times] or as much as possible" -> gain_chest reward {X}; gain_stat bash 1 | F6: Gains "and the difficulty must be increased X times or as much as possible in the run you complete the goal in" | G6: clause "the difficulty must be increased {X} [time|times] or as much as possible" | H6: Increase Damage Dealt by X | I6: N/A | J6: Yes | K6: damage_dealt +{X} | L6: Intensity | M6: Strength
A7: Bleed | B7: Debuff | C7: Mewgenics | D7: Gain "You must beat a game while not healing intentionally or take 3 Damage. This lasts for X games." | E7: demand "not heal intentionally" else -> take_damage 3 | F7: Gains "and if you didn't intentionally heal in the game you beat it in, Gain a [chest reward]" — on a goal you can do any time, "before clearing it" | G7: bonus "you didn't intentionally heal" any_time "you didn't intentionally heal before clearing it" -> gain_chest reward {X} | H7: 50% chance to take 1 Damage when attacking | I7: On Trigger | J7: Yes | K7: recoil +1 chance=50 | L7: Intensity | M7: Bleed
A8: Stun | B8: Debuff | C8: Slay the Spire | H8: Skip their turn | I8: Each Turn | J8: Yes | K8: skip_turn | L8: Intensity | M8: Stun

Sheet events
A1: Event | B1: Game | C1: Tier | D1: Where | E1: Requirement | F1: Trigger | G1: Rarity | H1: Image | I1: Prompt | J1: Opens With | K1: Goal Met | L1: Goal Missed | M1: Chance Won | N1: Chance Lost | O1: Choice 1 | P1: Repeat 1 | Q1: Result 1 | R1: Effect 1 | S1: Choice 2 | T1: Repeat 2 | U1: Result 2 | V1: Effect 2 | W1: Choice 3 | X1: Repeat 3 | Y1: Result 3 | Z1: Effect 3 | AA1: Choice 4 | AB1: Repeat 4 | AC1: Result 4 | AD1: Effect 4 | AE1: Choice 5 | AF1: Repeat 5 | AG1: Result 5 | AH1: Effect 5 | AI1: Choice 6 | AJ1: Repeat 6 | AK1: Result 6 | AL1: Effect 6
A2: Abyssal Baths | B2: Slay the Spire 2 | C2: All | F2: After | G2: Common | H2: AbyssalBaths | I2: You discover a secluded chamber. Steam rises from bubbling pools of hot liquid that shifts colors with hypnotic rhythm. Barnacled growths hang from the ceiling, dripping viscous fluid that hisses and writhes when it touches the surface. The air feels heavy, laden with salt and something unmistakably organic. As you approach the edge of the largest pool, the liquid ripples. The waters bubble more intensely as if anticipating your entry. | O2: Immerse | P2: Stay | Q2: The liquid burns against your skin, simultaneously freezing and scalding. Beneath the surface, something brushes against your legs—tendrils? Currents with purpose? But when the pain subsides, you feel... denser somehow. More substantial. | R2: gain_max_hp 1; lose_hp 2 | S2: Linger | T2: Again | U2: The temperature keeps rising! How long can you endure before the steam cooks you from within? || It keeps getting hotter! The pool's bubbling sounds like laughter. IT'S SO HOT! || You wonder if this is what it's like to live in the Village of Demons? You have bathed so long you have lost track of time and your mind... It's nice in here. Really fantastic. || If you bathe any longer you will die. | V2: needs Immerse > 0; gain_max_hp 1; lose_hp {3+X} | W2: Abstain | Y2: You decline the temptation of the waters, instead gathering crystalline salts that have formed along the edges. As you apply them to your skin, the pools churn and froth agitatedly. | Z2: needs Immerse = 0; gain_hp 3 | AA2: Exit Baths | AC2: The heat finally gets to you, and you hop out of the bath. | AD2: needs Immerse > 0; nothing
A3: Arcade Room | B3: The Binding of Isaac | C3: All | E3: gold>=1 | F3: After | G3: Common | H3: ArcadeRoom | O3: Enter | P3: Stay | R3: lose_gold 1; spawn_object tag=arcade 2-3 | S3: Leave | V3: nothing
A4: Battleworn Dummy | B4: Slay the Spire 2 | C4: All | F4: After | G4: Common | H4: BattlewornDummy | I4: As you approach, it begins to rumble and fizzle and lights up brilliantly! "BZZZT! TIME TO TRAIN!!! YOU HAVE 3 TURNS TO DEFEAT ME! CHOOSE A SETTING OR FACE LETHAL HUMILIATION." | K4: "YOU PASS THE TRAINING! YOU ARE NOW EQUIPPED TO DEFEND THIS FACTORY AGAINST INTRUDERS!! BE SURE TO HYDRATE AFTER TRAINING SESSIONS!" | L4: "YOU ARE WEAK!! HUMILIATION HAS BEEN ADMINISTERED!" The dummy is silent for a moment and— "Choose a lower setting next time." | O4: Setting 1 | R4: add_goal "beat a game in 5 attempts or fewer" for 3 games -> gain_potion 1 | S4: Setting 2 | V4: add_goal "beat a game in 3 attempts or fewer" for 3 games -> gain_chest small 1 | W4: Setting 3 | Z4: add_goal "beat a game in 1 attempt" for 3 games -> gain_chest large 1
A5: Golden Idol | B5: Slay the Spire | C5: All | F5: After | G5: Common | H5: GoldenIdol | I5: You come across an inconspicuous pedestal with a shining gold idol sitting peacefully atop. It looks incredibly valuable. You sure don't see any traps nearby. | O5: Take | P5: Stay | Q5: As you grab the Idol and stow it away, a giant boulder smashes through the ceiling into the ground next to you. You realize that the floor is slanted downwards as the boulder starts to roll towards you. | R5: gain_item golden_idol | S5: Leave | U5: If there was ever an obvious trap, this would be it. You decide not to interfere with objects placed upon pedestals. | V5: needs Take = 0; nothing | W5: Outrun | Y5: RUUUUUUUUUUN! You barely leap into a side passageway as the boulder rushes by. Unfortunately it feels like you sprained something however. | Z5: needs Take > 0; lose_hp {max(1,round(0.25*MAX_HP))} | AA5: Smash | AC5: You throw yourself at the boulder with everything you have. When the dust clears, you can make a safe way out. | AD5: needs Take > 0; add_curse injury | AE5: Hide | AG5: SQUISH! The boulder flattens you a little as it passes by, but otherwise you can get out of here. | AH5: needs Take > 0; lose_max_hp {max(1,round(0.08*MAX_HP))}
A6: Golden Monkey | B6: Tiny Rogues | C6: All | F6: After | G6: Common | H6: GoldenMonkey | O6: Touch the Golden Monkey | R6: gain_stat luck 1; add_curse random | S6: Leave | V6: nothing
A7: Jungle Maze Adventure | B7: Slay the Spire 2 | C7: All | F7: After | G7: Common | H7: JungleMazeAdventure | I7: In a clearing, you run into a Ragtag Group of Adventurers looking down and gesturing at a gigantic maze. They offer to join forces with you in an Epic Quest to loot the riches of this maze. As an experienced adventurer yourself, it's clear this maze is filled with deadly traps and guardians. It would be easier if you work together, but then you would have to split the loot. | O7: Solo Quest | Q7: Feeling misanthropic, you wordlessly walk past their now-frowning faces. One of them even shakes their fist at you. The maze is not welcoming. You fall into a spike trap, you are struck by a massive log with spikes, and feisty creatures with spiky clubs fight you along the entire journey. You are sick of spikes, and consider teamwork for the next adventure. | R7: gain_gold 3; lose_hp 2 | S7: Join Forces | U7: Everyone's face immediately lights up, including your own! One of the adventurers turns out to be a bard! You merrily waltz into the maze as Aquid the squid wizard effortlessly disarms traps, while you and the Grathorian fighter take out the spiky club-wielding guards with ease. This was the most joyous adventure of your life and you've made some truly Great Memories. | V7: gain_gold 1
A8: Morphic Grove | B8: Slay the Spire 2 | C8: All | E8: gold >=3 | F8: After | G8: Common | H8: MorphicGrove | I8: You enter a grove of crystalline trees, and they begin to quiver excitedly! A chorus of hellos and welcomes bombard you as a group of Morphics burst forth from trees. One of the Morphics is fidgeting in the corner, clearly not as sociable as the others. Approach the group or the loner? | O8: Group | Q8: You greet the chittering Morphics and they embrace you into their crystally arms. They share their combined knowledge and inject you with Morphic Magic, changing your nature... Such lovely creatures, these Morphics. One of them stole your gold. | R8: gain_stat transmute 2; lose_gold all | S8: Loner | U8: You reach out a hand to the lone Morphic, sympathizing with its nature. It gifts you a tiny crystal fruit, and you consume it, as is custom. The fruit clarifies your mind and purpose. You give thanks, then make your way onwards. | V8: gain_max_hp 1
A9: Potion Lab | B9: Tiny Rogues | C9: All | F9: After | G9: Rare | H9: PotionLab | J9: offer_loot potion 3 | O9: Leave | R9: nothing
A10: Punch Off | B10: Slay the Spire 2 | C10: All | E10: games >= 6 | F10: After | G10: Common | H10: PunchOff | I10: Two Punch Constructs are duking it out and you see some treasure in between them... Should you try to nab it? | O10: Nab | Q10: You successfully nab the relic! ...or so you thought. A right-hook clocks you in the face. | R10: add_curse injury; gain_chest small 1 | S10: I Can Take Them | U10: The Constructs turn to you menacingly! | V10: spawn_enemy tag=robot 1; play_game tag=mecha -> gain_loot 1; gain_chest small 2
A11: Ranwid the Elder | B11: Slay the Spire 2 | C11: All | E11: gold>=2 and potions>=1 and relics>=1 | F11: After | G11: Common | H11: RanwidTheElder | I11: You are approached by the oldest person you have ever seen. “We meet once more... it's me, Ranwid!” You do not know this man. | O11: Give 2 Gold | Q11: “Mag.. nificent...” Ranwid mumbles while chewing the gold. | R11: needs gold 2; lose_gold 2; gain_random_item 1 | S11: Give <potion> | U11: “Exquisite...” Glup glup glup. He downs the <potion> in one go. | V11: lose_potion; gain_random_item 1 | W11: Give <relic> | Y11: “Exemplary...” Ranwid observes the relic studiously for several minutes... Then eats the <relic>. | Z11: lose_relic; gain_random_item 2
A12: Relic Trader | B12: Slay the Spire 2 | C12: All | E12: relics >= 5 | F12: After | G12: Common | H12: RelicTrader | I12: You turn a corner and suddenly, a shadowy figure is just standing there. He pivots to face you. “Welcome! What're ya trading?” The figure inquires as he flares open his cloak to reveal a slew of suspicious wares. | O12: Take the Top One | Q12: “Hehehe Heh... Thank you!” | R12: trade_relic 1 | S12: Take the Middle One | U12: “Hehehe Heh... Thank you!” | V12: trade_relic 2 | W12: Take the Bottom One | Y12: “Hehehe Heh... Thank you!” | Z12: trade_relic 3
A13: Scrap Ooze | B13: Slay the Spire | C13: All | F13: After | G13: Common | H13: ScrapOoze | I13: As you walk into the room you hear a gurgling and the grinding of metals. Before you is a slime-like creature that ate too much scrap for its own good. From the center of the creature you see glints of strange light, perhaps something magical? It looks like you can get some treasure if you just reach inside its... opening. However, the acid and sharp objects may hurt. | M13: Success! After rummaging through the metal and burning acid, you finally grab hold of a relic and yank it out. You pull your way out of the ooze damaged but rewarded. | N13: Ouch! All you find is corroded metal and a bit of burning pain. However, you're still convinced there's a relic... | O13: Reach Inside | P13: Stay | R13: lose_hp 1; chance 25% -> gain_chest small 1 | S13: Deeper | T13: Again | V13: needs Reach Inside > 0; lose_hp {2+X}; chance {35+10*X}% -> gain_chest small 1 | W13: Leave | Y13: You decide to leave the area. The slime pays no attention, content with its meal. | Z13: nothing
A14: The Woman in Blue | B14: Slay the Spire | C14: All | E14: gold>=3 | F14: After | G14: Common | H14: TheWomanInBlue | I14: From the darkness, an arm pulls you into a small shop. As your eyes adjust, you see a pale woman in sharp clothes gesturing towards a wall of potions. Pale Woman: “Buy a potion. Now!” she states. | O14: Buy 1 Potion | Q14: Pale Woman: “Good. Now leave.” You exit the shop cautiously. | R14: needs gold 1; lose_gold 1; gain_potion 1 | S14: Buy 2 Potions | U14: Pale Woman: “Good. Now leave.” You exit the shop cautiously. | V14: needs gold 2; lose_gold 2; gain_potion 2 | W14: Buy 3 Potions | Y14: Pale Woman: “Good. Now leave.” You exit the shop cautiously. | Z14: needs gold 3; lose_gold 3; gain_potion 3 | AA14: Leave | AC14: WHAM. Her gloved fist collides with your face, nearly knocking you off your feet. Pale Woman: “Get out before I litter the floor with your guts.” You take her word and exit with your guts still safely in your body. | AD14: nothing
A15: Unrest Site | B15: Slay the Spire 2 | C15: All | E15: hp <= 70% | F15: After | G15: Common | H15: UnrestSite | I15: You find a secluded Rest Site and start a fire to get some rest. Once the fire is started, it begins to swell, reaching not upwards but sideways towards a grove of oil-seeping trees. | O15: Rest Anyways | Q15: All this adventuring has left you exhausted, and despite the oddities, you decide to sleep. You toss and turn as the fire roars and crackles through the night. The disgusting trees give off a wretched scent from their pitch-black sap. | R15: heal_full; add_curse poor_sleep | S15: Kill the Trees | U15: These trees are clearly malicious so you decide to get rid of them. Days later, you're covered in ash and oily goop. A massive flock of little byrd spirits rise from the slain trees and drop a small box at your feet. "Thank you for freeing us from those trees... cheep cheep!" | V15: lose_max_hp 2; gain_chest small 1
A16: We Meet Again! | B16: Slay the Spire | C16: All | E16: gold>=2 | F16: After | G16: Common | H16: WeMeetAgain | I16: “We meet again!” A cheery disheveled fellow approaches you gleefully. You do not know this man. “It's me, Ranwid! Have any goods for me today? The usual? A fella like me can't make it alone, you know?” You eye him suspiciously and consider your options... | O16: Give <potion> | Q16: Ranwid: “Exquisite! Was feeling parched.” Glup glup glup. He downs the potion in one go and lets out a satisfied burp. He rummages around his various pockets... Ranwid: “Here, look what I've got for you today! Take it take it!” | R16: lose_potion; gain_random_item 1 | S16: Give 2 Gold | U16: Ranwid: “Magnificent! This will be quite handy if I run into those mask wearing hoodlums again.” He rummages around his various pockets... Ranwid: “Here, look what I've got for you today! Take it take it!” | V16: needs gold 2; lose_gold 2; gain_random_item 1 | W16: Give <card> | Y16: Ranwid: “Exemplary! I shall study this further in my chambers.” He rummages around his various pockets... Ranwid: “Here, look what I've got for you today! Take it take it!” | Z16: lose_card uncommon+; gain_random_item 1 | AA16: Attack | AC16: Ranwid: “Aaaaagghh!! What a jerk you are sometimes!” He runs away. | AD16: nothing
A17: Whispering Hollow | B17: Slay the Spire 2 | C17: All | E17: gold >=1 | F17: After | G17: Common | H17: WhisperingHollow | I17: Making your way through a hollow of dead trees you happen upon a single bone-white tree. Clay baubles hang off its branches, which curve inward like protective ribs. Such a creepy tree. It whispers. ...make exchange..... | O17: Exchange Gold | Q17: You scatter some gold at the base of the tree and two of the clay vessels drop to the floor soundlessly. They break open, and contain perfectly intact potions within. You nab the potions and flee. | R17: lose_gold 1; gain_loot 2 | S17: Hug the Tree | U17: The whispering compels you to give it gold but you resist and give the tree a big hug instead! It thrashes about, scratching you with its branches, but eventually calms down. The tree-hugging experience transforms you. ...make hug.....? | V17: lose_hp 1; gain_stat transmute 1

Sheet cards
A1: Name | B1: Rarity | C1: Type | D1: Description | E1: Effect | F1: Tags | G1: Game | H1: Image | I1: Icon Image
A2: ? Card | B2: Uncommon | C2: Usable | D2: Copy the effect of a selected Usable Item in your inventory | E2: copy_item | G2: The Binding of Isaac: Rebirth | H2: QuestionMarkCard | I2: Isaac_Playing_Cards
A3: 0 - The Fool | B3: Uncommon | C3: Usable | D3: Teleport to the Starting Game | E3: teleport_start | F3: tarot | G3: The Binding of Isaac | H3: 0TheFool | I3: Isaac_Major_Arcana
A4: 2 of Clubs | B4: Rare | C4: Usable | D4: Double your Bombs, if you have no Bombs then Gain +2 | E4: double_stat bombs floor=2 | F4: playing_card | G4: The Binding of Isaac | H4: 2OfClubs | I4: Isaac_Playing_Cards
A5: 2 of Diamonds | B5: Rare | C5: Usable | D5: Double your Gold, if you have no Gold Gain +2 Gold | E5: double_stat gold floor=2 | F5: playing_card | G5: The Binding of Isaac | H5: 2OfDiamonds | I5: Isaac_Playing_Cards
A6: 2 of Hearts | B6: Rare | C6: Usable | D6: Double your Health | E6: double_stat hp | F6: playing_card | G6: The Binding of Isaac | H6: 2OfHearts | I6: Isaac_Playing_Cards
A7: 2 of Spades | B7: Rare | C7: Usable | D7: Double your Keys, if you have no Keys then Gain +2 | E7: double_stat keys floor=2 | F7: playing_card | G7: The Binding of Isaac | H7: 2OfSpades | I7: Isaac_Playing_Cards
A8: After Image | B8: Rare | C8: Passive | D8: Whenever you use a Card, Gain +1 Temporary Shield | E8: card_used: gain_stat shields 1 | F8: silent | G8: Slay the Spire | H8: AfterImage | I8: Slay_The_Spire_Silent_Rare
A9: Alchemize | B9: Rare | C9: Usable | D9: Gain +1 Random Potion and Identify it | E9: gain_loot potion 1 identify | F9: silent | G9: Slay the Spire | H9: Alchemize | I9: Slay_The_Spire_Silent_Rare
A10: Ancient Recall | B10: Rare | C10: Usable | D10: Gain +3 Random Cards | E10: gain_loot card 3 | G10: The Binding of Isaac: Rebirth | H10: AncientRecall | I10: Isaac_MTG_Cards
A11: Barricade | B11: Rare | C11: Passive | D11: When a game resolves, unspent Temporary Shields become Shields | E11: bank_shields | F11: ironclad | G11: Slay the Spire | H11: Barricade | I11: Slay_the_Spire_Ironclad_Rare
A12: Bloodletting | B12: Uncommon | C12: Usable | D12: Lose 2 Health and Give 4 Charges to a Chargeable Item or Loot | E12: lose_hp 2; charge_pick 4 | F12: ironclad | G12: Slay the Spire | H12: Bloodletting | I12: Slay_The_Spire_Ironclad_Uncommon
A13: Blueprint | B13: Rare | C13: Passive | D13: Copy the effect of the loot to the right of this if possible | E13: copy_right | F13: joker | G13: Balatro | H13: Blueprint | I13: Balatro_Playing_Cards
A14: Bullseye | B14: Uncommon | C14: Usable | D14: Apply 1 Stun and 1 Marked to an Enemy | E14: stun 1; apply_status marked 1 | F14: defect, attack | G14: Slay the Spire | H14: Bullseye | I14: Slay_The_Spire_Defect_Uncommon
A15: Chaos the Clown | B15: Common | C15: Passive | D15: Whenever you enter a shop, Gain +1 Scramble | E15: shop_entered: gain_stat scramble 1 | F15: joker | G15: Balatro | H15: ChaosTheClown | I15: Balatro_Playing_Cards
A16: Cleave | B16: Common | C16: Usable | D16: Apply Stun 1 to each enemy in a row | E16: stun 1 area=row | F16: ironclad, attack | G16: Slay the Spire | H16: Cleave | I16: Slay_The_Spire_Ironclad_Common
A17: Echo Form | B17: Rare | C17: Passive | D17: The first loot you use each game plays an additional copy | E17: echo_first_loot 1 | F17: defect | G17: Slay the Spire | H17: EchoForm | I17: Slay_the_Spire_Defect_Rare
A18: Exhume | B18: Rare | C18: Usable | D18: Put a destroyed Loot back into your inventory | E18: exhume | F18: ironclad | G18: Slay the Spire | H18: Exhume | I18: Slay_The_Spire_Ironclad_Rare
A19: Fiend Fire | B19: Rare | C19: Usable | D19: Destroy all other loot in this row and Apply Stun 1 to an Enemy for each loot destroyed | E19: destroy_row; stun 1 per=destroyed | F19: ironclad, attack | G19: Slay the Spire | H19: FiendFire | I19: Slay_The_Spire_Ironclad_Rare
A20: Finisher | B20: Uncommon | C20: Usable | D20: Apply Stun 1 for each other Card used during this game | E20: stun 1 per=cards_used | F20: silent, attack | G20: Slay the Spire | H20: Finisher | I20: Slay_The_Spire_Silent_Uncommon
A21: IV - The Emperor | B21: Common | C21: Usable | D21: Spawn a random Boss from the current Game Type and Difficulty Tier | E21: spawn_boss | F21: tarot | G21: The Binding of Isaac | H21: IVTheEmperor | I21: Isaac_Major_Arcana
A22: IX - The Hermit | B22: Uncommon | C22: Usable | D22: Teleport to the nearest Shop | E22: teleport_shop | F22: tarot | G22: The Binding of Isaac | H22: IXTheHermit | I22: Isaac_Major_Arcana
... A38: XIV - Temperance | B38: Common | C38: Usable | D38: Spawn a Blood Donation Machine | E38: spawn_object blood_donation_machine | F38: tarot | G38: The Binding of Isaac | H38: XIVTemperance | I38: Isaac_Major_Arcana

Sheet scrolls
A1: Scrolls | B1: Game | C1: Preference | D1: Rarity | E1: Description | F1: Effect | G1: Tags | H1: File | I1: Notes | K1: Random Scroll Name | L1: Game | N1: Random Scroll Part | O1: Game
A2: Scroll of Aggravate Monsters | B2: Rogue | C2: Negative | D2: Common | E2: All current enemies Gain +1 Strength | F2: apply_status strength 1 all | K2: ANDOVA BEGARIN | L2: NetHack | N2: ah | O2: Rogue
A3: Scroll of Amnesia | B3: Hack | C3: Negative | D3: Uncommon | E3: Forget 1 random Identified Loot. | F3: forget loot 1 | H3: Amnesia | K3: DAIYEN FOOELS | L3: NetHack | N3: arek | O3: Rogue
A4: Scroll of Create Monster | B4: Rogue | C4: Negative | D4: Uncommon | E4: Spawn a Random Enemy with the current Difficulty | F4: spawn_enemy current | K4: DUAM XNAHT | L4: NetHack | N4: bahl | O4: Rogue
A5: Scroll of Identify | B5: Rogue | C5: Positive | D5: Common | E5: Choose 1 Loot to Identify. | F5: identify_loot choose 1 | H5: Identify | I5: Not rolled with the other scrolls: 10% of every loot drop is this one instead. | K5: ELAM EBOW | L5: NetHack | N5: bar | O5: Rogue
A6: Scroll of Scare Monster | B6: Rogue | C6: Positive | D6: Uncommon | E6: Apply +1 Stun to a target Enemy | F6: stun_enemies choose 1 | K6: ELBIB YLOH | L6: NetHack | N6: barf | O6: Rogue
A7: Scroll of Teleportation | B7: Rogue | C7: Neutral | D7: Common | E7: Teleport to a Random Space with roughly the same distance from the Amulet Game. (+ or - 2) | F7: teleport same 2 | H7: Teleportation | K7: FOOBIE BLETCH | L7: NetHack | N7: behil | O7: Rogue
A8: Scroll of Fire | B8: Hack | C8: Negative | D8: Uncommon | E8: Gain +3 Burn, Apply the Fire Tile and +3 Burn to all everything in the first column | F8: apply_status burn 3 player; apply_tile fire front; apply_status burn 3 front | G8: heat | K8: GARVEN DEH | L8: NetHack | N8: blech | O8: Rogue
A9: Scroll of Remove Curse | B9: Rogue | C9: Positive | D9: Rare | E9: Remove 1 target Curse | F9: remove_curse choose 1 | K9: HACKEM MUCHE | L9: NetHack | N9: blorp | O9: Rogue
A10: Scroll of Enchant Weapon | B10: Rogue | C10: Positive | D10: Uncommon | E10: A random Weapon Gains +1 Stun | F10: enchant_weapon random 1 | H10: EnchantWeapon | K10: JUYED AWK YACC | L10: NetHack | N10: bloto | O10: Rogue
K11: KERNOD WEL | L11: NetHack | N11: caca | O11: Rogue
K12: KIRJE | L12: NetHack | N12: coph | O12: Rogue
K13: LEP GEX VEN ZEA | L13: NetHack | N13: druhl | O13: Rogue
K14: NR 9 | L14: NetHack | N14: erp | O14: Rogue
K15: PRATYAVAYAH | L15: NetHack | N15: festr | O15: Rogue
K16: PRIRUTSENIE | L16: NetHack | N16: flem | O16: Rogue
K17: READ ME | L17: NetHack | N17: foo | O17: Rogue
K18: TEMOV | L18: NetHack | N18: grit | O18: Rogue
K19: THARR | L19: NetHack | N19: ichi | O19: Rogue
K20: VE FORBRYDERNE | L20: NetHack | N20: ighr | O20: Rogue
K21: VELOX NEB | L21: NetHack | N21: iky | O21: Rogue
K22: VENZAR BORGAVVE | L22: NetHack | N22: kini | O22: Rogue
... K37: TIDDER ROF | L37: WazHack | N37: tims | O37: Rogue
N38: yuky | O38: Rogue
N39: zep | O39: Rogue
N40: zihr | O40: Rogue

Sheet pills
A1: Name | B1: Preference | C1: Description | D1: Effect | E1: Horse Description | F1: Horse Effect | G1: Notes
A2: 48 Hour Energy | B2: Positive | C2: Gain +3 Charges for random Chargeable Items and Loot | D2: charge random 3 | E2: Fully Charge 3 Random Chargeable Items and Loot | F2: charge random 3 full
A3: Amnesia | B3: Negative | C3: Gain a Random Curse and Forget 1 random Identified Loot | D3: add_curse random; forget loot 1 | E3: Gain a Random Curse and Forget all Identified loot | F3: add_curse random; forget loot all
A4: Bad Trip | B4: Negative | C4: Lose -2 Health | D4: lose_hp 2 lethal=heal_full | E4: Lose -4 Health | F4: lose_hp 4 lethal=heal_full | G4: When a Bad Trip pill when it would kill you, it becomes Full Health
A5: Balls of Steel | B5: Positive | C5: Gain +2 Shields | D5: gain_stat bonus_shields 2 | E5: Gain +4 Shields | F5: gain_stat bonus_shields 4
A6: Full Health | B6: Positive | C6: Heal to full health | D6: heal_full | E6: Heal to full health and Gain +3 Shields | F6: heal_full; gain_stat bonus_shields 3
A7: Health Down | B7: Negative | C7: Lose -2 Max Health | D7: lose_max_hp 2 | E7: Lose -4 Max Health | F7: lose_max_hp 4
A8: Health Up | B8: Positive | C8: Gain +2 Max Health | D8: gain_max_hp 2 | E8: Gain +4 Max Health | F8: gain_max_hp 4
A9: Luck Down | B9: Negative | C9: Lose -1 Luck | D9: lose_stat luck 1 | E9: Lose -2 Luck | F9: lose_stat luck 2
A10: Luck Up | B10: Positive | C10: Gain +1 Luck | D10: gain_stat luck 1 | E10: Gain +2 Luck | F10: gain_stat luck 2
A11: Telepills | B11: Neutral | C11: Teleport to a Random Space with roughly the same distance from the Amulet Game. (+ or - 2) | D11: teleport same 2 | E11: Teleport to a Random Space with a 1-3 distance from the Amulet Game | F11: teleport amulet 1 3

Sheet potions
A1: Name | B1: Rarity | C1: Preference | D1: On Player | E1: On Player Effect | F1: On Tile | G1: On Tile Effect | H1: Tags | I1: Reference | J1: File
A2: Fire Potion | B2: Common | C2: Negative | D2: Gain +3 Burn | E2: apply_status burn 3 player | F2: Apply the Fire tile and Apply +3 Burn to everything in a 3x3 area centered on this tile | G2: apply_tile fire area=3x3; apply_status burn 3 area=3x3 | H2: heat | I2: Slay the Spire | J2: FirePotion
A3: Block Potion | B3: Common | C3: Positive | D3: Gain +2 Shields | E3: gain_stat bonus_shields 2 | F3: Apply 2 Sheilds | G3: grant_shield 2 area=cell | I3: Slay the Spire | J3: BlockPotion
A4: Speed Potion | B4: Common | C4: Positive | D4: Gain +5 Dexterity until the end of the next combat | E4: apply_status dexterity 5 player games=1 | F4: Apply +5 Dexterity until the end of the next combat | G4: apply_status dexterity 5 area=cell games=1 | I4: Slay the Spire | J4: SpeedPotion
A5: Flex Potion | B5: Common | C5: Positive | D5: Gain +5 Strength until the end of the next combat | E5: apply_status strength 5 player games=1 | F5: Apply +5 Strength until the end of the next combat | G5: apply_status strength 5 area=cell games=1 | I5: Slay the Spire | J5: FlexPotion
A6: Fruit Juice | B6: Rare | C6: Positive | D6: Gain +2 Max Health | E6: gain_max_hp 2 | F6: Apply +2 Max Health | G6: grant_max_health 2 area=cell | I6: Slay the Spire | J6: FruitJuice
A7: Dexterity Potion | B7: Common | C7: Positive | D7: Gain +2 Dexterity until the end of the next combat | E7: apply_status dexterity 2 player games=1 | F7: Apply +1 Dexterity until the end of the next combat | G7: apply_status dexterity 1 area=cell games=1 | I7: Slay the Spire | J7: DexterityPotion
A8: Strength Potion | B8: Common | C8: Positive | D8: Gain +2 Strength until the end of the next combat | E8: apply_status strength 2 player games=1 | F8: Apply +1 Strength until the end of the next combat | G8: apply_status strength 1 area=cell games=1 | I8: Slay the Spire | J8: StrengthPotion
A9: Explosive Ampoule | B9: Common | C9: Negative | D9: Take 3 Damage | E9: take_damage 3 | F9: Deal 1 Damage everything on this tile and it's row | G9: deal_damage 1 area=row | I9: Slay the Spire | J9: ExplosiveAmpoule
A10: Fysh Oil | B10: Uncommon | C10: Positive | D10: Gain +1 Strength and +1 Dexterity until the end of the next combat | E10: apply_status strength 1 player games=1; apply_status dexterity 1 player games=1 | F10: Apply +1 Strength and +1 Dexterity until the end of the next combat | G10: apply_status strength 1 area=cell games=1; apply_status dexterity 1 area=cell games=1 | I10: Slay the Spire 2 | J10: FyshOil
A11: Potion of Healing | B11: Common | C11: Positive | D11: Gain +2 Health | E11: gain_hp 2 | F11: Apply +2 Health | G11: grant_health 2 area=cell | I11: Rogue | J11: N/A
A12: Potion of Raise Level | B12: Rare | C12: Positive | D12: Gain +1 Level | E12: gain_level 1 | F12: N/A | G12: none | I12: Rogue | J12: N/A
A13: Potion of Extra Healing | B13: Rare | C13: Positive | D13: Gain +5 Health | E13: gain_hp 5 | F13: Apply +5 Health | G13: grant_health 5 area=cell | I13: Rogue | J13: N/A
A14: Potion of Haste Self | B14: Uncommon | C14: Positive | D14: Gain +2 Speed until the end of the next combat | E14: apply_status speed 2 player games=1 | F14: Apply +2 Speed until the end of the next combat | G14: apply_status speed 2 area=cell games=1 | I14: Rogue | J14: N/A
... A16: Potion of Uselessness | B16: Uncommon | C16: Neutral | D16: Do nothing | E16: none | F16: Do nothing | G16: none | I16: Ancient Domains of Mystery | J16: N/A

Sheet wands
A1: Name | B1: Rarity | C1: Game | D1: Preference | E1: Aim | F1: Charges | G1: Description | H1: Effect | I1: Tags | J1: File
A2: Wand of Cancellation | B2: Uncommon | C2: Rogue | D2: Positive | E2: Ray, Bounce 1 | F2: 2 | G2: Target Unit loses it's ability | H2: cancel_abilities | J2: N/A
A3: Wand of Create Monster | B3: Rare | C3: NetHack | D3: Negative | E3: Non-Directional | F3: 4 | G3: Spawn 1 Random Enemy to the Board | H3: spawn_enemy current | J3: N/A
A4: Wand of Death | B4: Legendary | C4: NetHack | D4: Positive | E4: Ray, Bounce 1 | F4: 1 | G4: Target Unit is instantly killed | H4: kill | J4: N/A
A5: Wand of Fire | B5: Rare | C5: Rogue | D5: Positive | E5: Ray, Bounce 1 | F5: 3 | G5: Apply +3 Burn to any Unit on target Tile and apply the Fire Tile to this Tile | H5: apply_status burn 3 target=enemy; apply_tile fire | I5: Heat | J5: N/A
A6: Wand of Haste Monster | B6: Common | C6: Rogue | D6: Negative | E6: Ray, Bounce 1 | F6: 3 | G6: Target Unit Gains +1 Speed | H6: apply_status speed 1 target=enemy | J6: N/A
A7: Wand of Invisibility | B7: Common | C7: Rogue | D7: Negative | E7: Ray, Bounce 1 | F7: 3 | G7: Target Unit becomes invisible | H7: grant_ability invisibility | J7: N/A
A8: Wand of Magic Missile | B8: Common | C8: Rogue | D8: Positive | E8: Ray, Bounce 1 | F8: 2 | G8: Target Unit takes 1 Damage | H8: deal_damage 1 | J8: N/A
A9: Wand of Nothing | B9: Common | C9: Rogue | D9: Neutral | E9: Random | F9: 4 | G9: Do nothing | H9: nothing | J9: N/A
A10: Wand of Plenty | B10: Uncommon | C10: Brogue | D10: Neutral | E10: Ray, Bounce 1 | F10: 2 | G10: Target Unit is split into two of the same Units with half Max Health if possible | H10: split | J10: N/A
A11: Wand of Polymorph | B11: Rare | C11: Rogue | D11: Positive | E11: Ray, Bounce 1 | F11: 3 | G11: Target Unit becomes a random Enemy of the same difficulty | H11: polymorph | J11: N/A
A12: Wand of Teleportation | B12: Rare | C12: Rogue | D12: Positive | E12: Ray, Bounce 1 | F12: 3 | G12: Target Unit is transported to a random Tile | H12: teleport | J12: N/A
A13: Wand of Wishing | B13: Legendary | C13: NetHack | D13: Positive | E13: Non-Directional | F13: 1 | G13: Obtain any one item in the game | H13: obtain_item any | J13: N/A

Sheet trinkets
A1: Name | B1: Rarity | C1: Size | D1: Type | E1: Description | F1: Effect | G1: Tag | H1: Game | I1: Image
A2: Bag Lunch | B2: Common | C2: 1x1 | D2: Passive | E2: 5% on losing Health to lose this and Gain + 1 Lunch | F2: health_lost: 5% chance break_into lunch | G2: food, bag | H2: The Binding of Isaac: Rebirth | I2: BagLunch
A3: Bloody Penny | B3: Common | C3: 1x1 | D3: Passive | E3: 25% chance to Gain +1 Health when gaining Gold | F3: gold_gained: 25% chance gain_hp 1 | G3: coin, blood | H3: The Binding of Isaac | I3: BloodyPenny
A4: Broccoli | B4: Uncommon | C4: 2x1 | D4: Charged | E4: Whenever you defeat an enemy, Gain +1 Charge. On 6 Charges, Gain +2 Luck | F4: enemy_killed charges=6: gain_stat luck 2 | G4: food, vegetable | H4: Backpack Battles | I4: Broccoli
A5: Burnt Penny | B5: Uncommon | C5: 1x1 | D5: Passive | E5: 25% chance to Gain +1 Bomb when gaining Gold | F5: gold_gained: 25% chance gain_stat bombs 1 | G5: coin | H5: The Binding of Isaac | I5: BurntPenny
A6: Carrot | B6: Uncommon | C6: 1x2 | D6: Charged | E6: Whenever you defeat an enemy, Gain +1 Charge. On 3 Charges, Lose 1 Random Debuff | F6: enemy_killed charges=3: remove_random_debuff 1 | G6: food, vegetable | H6: Backpack Battles | I6: Carrot
A7: Charged Penny | B7: Uncommon | C7: 1x1 | D7: Passive | E7: 16% chance to Gain +1 Charge to a random Chargeable Item or Loot when gaining Gold | F7: gold_gained: 16% chance charge_random 1 | G7: coin | H7: The Binding of Isaac: Rebirth | I7: ChargedPenny
A8: Cheese | B8: Rare | C8: 1x2 | D8: Charged | E8: Whenever you defeat an enemy, Gain +1 Charge. On 4 Charges, Gain +5 Empty Max Health and Gain +1 Random Buff | F8: enemy_killed charges=4: gain_empty_max_hp 5; gain_random_buff 1 | G8: food, dairy | H8: Backpack Battles | I8: Cheese
A9: Counterfeit Penny | B9: Rare | C9: 1x1 | D9: Passive | E9: 50% chance to Gain +1 Gold when gaining Gold | F9: gold_gained: 50% chance gain_gold 1 | G9: coin | H9: The Binding of Isaac | I9: CounterfeitPenny
A10: Cupcake | B10: Rare | C10: 1x1 | D10: Charged | E10: Whenever you defeat an enemy, Gain +1 Charge. On 6 Charges, Gain +5 Health and Gain +1 Buff to the one you have the most of | F10: enemy_killed charges=6: gain_hp 5; gain_top_buff 1 | G10: food, sweets | H10: Backpack Battles | I10: Cupcake
A11: Duplicator | B11: Rare | C11: 1x1 | D11: Passive | E11: Adjacent Weapons trigger an extra time | F11: weapon_retrigger +1 dirs=adjacent | G11: ring | H11: Vampire Survivors | I11: Duplicator
A12: Endless Nameless | B12: Uncommon | C12: 1x1 | D12: Passive | E12: Whenever you use a loot, 25% chance to spawn a duplicate of that loot on the board | F12: loot_used: 25% chance drop_copy | H12: The Binding of Isaac: Rebirth | I12: EndlessNameless
A13: Flat Penny | B13: Uncommon | C13: 1x1 | D13: Passive | E13: 25% chance to Gain +1 Key when gaining Gold | F13: gold_gained: 25% chance gain_stat keys 1 | G13: coin | H13: The Binding of Isaac | I13: FlatPenny
A14: Garlic | B14: Common | C14: 2x1 | D14: Charged | E14: Whenever you defeat an enemy, Gain +1 Charge. On 4 Charges, Gain +3 Temporary Shield | F14: enemy_killed charges=4: gain_stat shields 3 | G14: food, vegetable, garlic | H14: Backpack Battles | I14: Garlic
A15: Gecko Gi | B15: Rare | C15: 2x2 | D15: Passive | E15: Burn does not deal damage to the Player | F15: harmless_status burn | G15: wearable, torso | H15: Backpack Hero | I15: GeckoGi
A16: Goat Hoof | B16: Common | C16: 1x1 | D16: Passive | E16: Gain +1 Speed | F16: passive_status: speed 1 | H16: The Binding of Isaac | I16: GoatHoof
A17: Hairpin | B17: Common | C17: 1x1 | D17: Passive | E17: Fully Charge a random Chargeable Item or Loot when a Boss spawns | F17: boss_spawned: charge_random full | H17: The Binding of Isaac: Rebirth | I17: Hairpin
A18: Isaac's Fork | B18: Common | C18: 1x1 | D18: Passive | E18: 25% chance to Gain +1 Health when Completing a Game | F18: game_won: 25% chance gain_hp 1 | H18: The Binding of Isaac | I18: IsaacsFork
A19: Lucky Toe | B19: Uncommon | C19: 1x1 | D19: Passive | E19: Gain +1 Luck | F19: passive: +1 luck | H19: The Binding of Isaac | I19: LuckyToe
A20: Swallowed Penny | B20: Uncommon | C20: 1x1 | D20: Passive | E20: Gain +1 Gold when losing Health | F20: health_lost: gain_gold 1 | G20: coin | H20: The Binding of Isaac: Rebirth | I20: SwallowedPenny
A21: Whetstone | B21: Common | C21: 1x1 | D21: Passive | E21: Weapons above and below Gain +1 Stun | F21: weapon_stun +1 dirs=up,down | G21: stone, whetstone | H21: Backpack Battles | I21: Whetstone
A22: Wish Bone | B22: Common | C22: 1x1 | D22: Passive | E22: 5% on losing Health to lose this and Gain + 1 Random Item | F22: health_lost: 5% chance break_into random_item | G22: bone | H22: The Binding of Isaac: Rebirth | I22: WishBone
A23: Wooden Cross | B23: Rare | C23: 1x1 | D23: Passive | E23: At the start of combat, Gain +1 Temporary Shield | F23: game_selected: gain_stat shields 1 | G23: wood | H23: The Binding of Isaac: Rebirth | I23: WoodenCross

Sheet weapons
A1: Name | B1: Rarity | C1: Size | D1: Aim | E1: Area | F1: Effect | G1: Type | H1: Passive | I1: Passive Effect | J1: Goal | K1: Charge | L1: Tag | M1: Game | N1: Image
A2: Bloody Tear | B2: Rare | C2: 2x2 | D2: front | E2: 4x1 | F2: stun 2 | G2: Melee | H2: Gain +1 Health for each enemy hit | I2: weapon_hit if_self: gain_hp 1 | J2: Defeat a vampire | K2: 3 | L2: blood | M2: Vampire Survivors | N2: BloodyTear
A3: Hero Longsword | B3: Rare | C3: 3x1 | D3: front | E3: 3x2 | F3: stun 2, push right 1 | G3: Melee | H3: Every Weapon adjacent to this Gains +2 Stun | I3: weapon_stun +2 dirs=adjacent | J3: Be a hero | K3: 3 | M3: Backpack Battles | N3: HeroLongsword
A4: Hero Sword | B4: Uncommon | C4: 2x1 | D4: front | E4: 2x1 | F4: stun 1 | G4: Melee | H4: Every Weapon adjacent to this Gains +1 Stun | I4: weapon_stun +1 dirs=adjacent | J4: Be a hero | K4: 3 | M4: Backpack Battles | N4: HeroSword
A5: King Bomber | B5: Rare | C5: 1x2 | D5: any | E5: plus | F5: stun 2 | G5: Ranged | H5: Gain +1 Gold for each enemy Stunned with this weapon | I5: weapon_stunned if_self: gain_gold 1 | J5: Explode an enemy with a cannon ball | K5: 3 | M5: Enter the Gungeon | N5: KingBomber
A6: Lightning Ring | B6: Uncommon | C6: 1x1 | D6: random | E6: 1x1 | F6: stun 1 | G6: Ranged | H6: Gains +1 Replay after each use (Max 4 times) | I6: replay_on_use +1 max=4 | J6: Defeat an enemy with a lightning bolt | K6: 3 | L6: ring, lightning | M6: Vampire Survivors | N6: LightningRing
A7: Lil' Bomber | B7: Common | C7: 1x2 | D7: any | E7: plus | F7: stun 1 | G7: Ranged | H7: N/A | J7: Explode an enemy with a cannon ball | K7: 3 | M7: Enter the Gungeon | N7: LilBomber
A8: Stankus' Toothpick | B8: Rare | C8: 2x1 | D8: front | E8: 2x1 | F8: stun 1 | G8: Melee | H8: Every 2 Food adjacent to this weapon gives this +1 Stun | I8: stun_per_food +1 per=2 | J8: Attack an enemy with food | K8: 3 | M8: Backpack Battles | N8: StankusToothpick
A9: Thunder Loop | B9: Rare | C9: 1x1 | D9: random | E9: plus | F9: stun 1 | G9: Ranged | H9: Gains +1 Replay after each use (Max 4 times) | I9: replay_on_use +1 max=4 | J9: Defeat an enemy with a lightning bolt | K9: 3 | L9: ring, lightning | M9: Vampire Survivors | N9: ThunderLoop
A10: Whip | B10: Common | C10: 2x2 | D10: front | E10: 3x1 | F10: stun 1 | G10: Melee | H10: N/A | J10: Defeat a vampire | K10: 3 | M10: Vampire Survivors | N10: Whip
A11: Wooden Sword | B11: Common | C11: 2x1 | D11: front | E11: 2x1 | F11: stun 1 | G11: Melee | H11: N/A | J11: Defeat an enemy with wooden gear on | K11: 3 | L11: wood | M11: Backpack Battles | N11: WoodenSword
A12: Earthquake | B12: Common | C12: 2x2 | D12: ray | E12: 3x3 | F12: stun 1, bounce 1 | G12: Ranged | H12: N/A | J12: Attack an enemy with a spherical rock | K12: 3 | L12: rock, ball | M12: Ball x Pit | N12: Earthquake

Sheet evolutions
A1: Name | B1: Requirement 1 | C1: Requirement 2 | D1: Outcome
A2: Hero Longsword | B2: Hero Sword | C2: Any 2 Items or Trinkets with "whetstone" | D2: Consume All
A3: Hero Sword | B3: Wooden Sword | C3: Any Item or Trinket with "whetstone" | D3: Consume All
A4: King Bomber | B4: Lil' Bomber | C4: Any Item or Trinket with "crown" | D4: Consume None
A5: Stankus' Toothpick | B5: Hero Sword | C5: Any Item or Trinket with "garlic" | D5: Consume All
A6: Thunder Loop | B6: Lightning Ring | C6: Duplicator | D6: Consume None
A7: Bloody Tear | B7: Whip | C7: Any Item or Trinket with "heart" | D7: Consume None

Sheet bags
A1: Name | B1: Rarity | C1: Size | D1: Description | E1: Effect | F1: Game | G1: Image
A2: Fanny Pack | B2: Common | C2: 1x2 | D2: When Loot inside this bag would Gain +1 Charge, it has a +10% chance to Gain +1 Charge | E2: charge_bonus 10% | F2: Backpack Battles | G2: FannyPack
A3: Holdall | B3: Rare | C3: 2x3 | D3: At the start of combat, Gain +1 Temporary Shield for every 2 Unidentified Loot in this bag | E3: game_selected: gain_stat shields 1 per=2 of=unidentified_in_bag | F3: Backpack Battles | G3: Holdall
A4: Leather Bag | B4: Common | C4: 2x2 | D4: N/A | E4: N/A | F4: Backpack Battles | G4: LeatherBag
A5: Potion Belt | B5: Rare | C5: 4x1 | D5: The first time a potion is consumed while inside this bag, Gain +1 Random Buff. Every 4 Potions consumed in this bag removes a random Debuff on the player. | E5: loot_used if_loot=potion if_in_bag once_per_game: gain_random_buff 1; loot_used if_loot=potion if_in_bag every=4: remove_random_debuff 1 | F5: Backpack Battles | G5: PotionBelt
A6: Protective Purse | B6: Uncommon | C6: 1x1 | D6: At the start of combat, Gain +1 Temporary Shield | E6: game_selected: gain_stat shields 1 | F6: Backpack Battles | G6: ProtectivePurse

Sheet objects
A1: Name | B1: Game | C1: Tag | D1: Image | E1: Rarity | F1: Limit | G1: Unique | H1: Where | I1: Requirement | J1: Trigger | K1: Prompt | L1: Chance Won | M1: Chance Lost | N1: Choice 1 | O1: Repeat 1 | P1: Result 1 | Q1: Effect 1 | R1: Choice 2 | S1: Repeat 2 | T1: Result 2 | U1: Effect 2 | V1: Choice 3 | W1: Repeat 3 | X1: Result 3 | Y1: Effect 3 | Z1: Choice 4 | AA1: Repeat 4 | AB1: Result 4 | AC1: Effect 4 | AD1: Choice 5 | AE1: Repeat 5 | AF1: Result 5 | AG1: Effect 5 | AH1: Choice 6 | AI1: Repeat 6 | AJ1: Result 6 | AK1: Effect 6
A2: Blood Donation Machine | B2: The Binding of Isaac | C2: arcade | D2: BloodDonationMachine | E2: Common | L2: The machine exploded, and {ITEM} appeared. | N2: Give Blood | O2: Again | Q2: lose_hp 1; chance 6.7% -> gain_item_of blood_bag|iv_bag; destroy_object else gain_gold 1 | R2: Bomb | U2: needs bombs 1; spend_bomb 1; gain_pickups 2-4 hp|gold; destroy_object
A3: Donation Machine | B3: The Binding of Isaac: Rebirth | C3: arcade | D3: DonationMachine | E3: Common | G3: Yes | N3: Give Gold | O3: Again | Q3: needs gold 1; needs not_jammed; needs bank_space; donate_gold 1; roll 5% gain_stat luck 1; roll {1+X}% jam_object | R3: Bomb | U3: needs bombs 1; spend_bomb 1; bank_payout 2-5; destroy_object run

Sheet curses
A1: Curse | B1: Game | C1: Condition | D1: Penalty | E1: Timer | F1: Image
A2: Curse of the Bell | B2: Slay the Spire | C2: you don't ring a bell | D2: spawn_enemy | E2: N/A | F2: CurseOfTheBell
A3: Injury | B3: Slay the Spire 2 | C3: you go below half health | D3: spawn_enemy | E3: 3 | F3: Injury
A4: Poor Sleep | B4: Slay the Spire 2 | C4: you use a rest site to replenish health | D4: spawn_enemy | E4: 3 | F4: PoorSleep

Sheet tiles
A1: Name | B1: Description | C1: Effect | D1: Interactions | E1: Decay | F1: Img
A2: Fire | B2: Apply +1 Burn to enemies who enter or start their turn on this tile | C2: enemy_enters: apply_status burn 1; enemy_turn_start: apply_status burn 1 | E2: 3 Games | F2: Fire
A3: Web | B3: Apply +1 Stun to enemies who enter or start their turn on this tile | C3: enemy_enters: apply_status stun 1; enemy_turn_start: apply_status stun 1 | E3: Until Triggered | F3: Web

Sheet units
A1: Name | B1: Type | C1: Description | D1: Effect | E1: Interactions | F1: On Destruction | G1: Health | H1: Tag | I1: Img
A2: Landmine | B2: Inanimate | C2: On contact with an enemy, or when it takes damage, destroy itself, explode, and trigger your bomb effects | D2: enemy_enters: detonate; damaged: detonate | E2: tile fire: detonate_unit; remove_tile | G2: 1 | I2: Landmine
A3: Poop | B3: Inanimate | C3: Will block the enemy's path and can be damaged by both player and enemy. May drop loot or spawn an Enemy | D3: block | F3: 50% Random Loot, 50% Random fly tagged Enemy | G3: 3 | H3: poop | I3: Poop
A4: Golden Poop | B4: Inanimate | C4: Will block the enemy's path and can be damaged by both player and enemy. May drop gold or Counterfeit Penny | D4: block | F4: 50% 2 Gold, 30% 3 Gold, 10% 4 Gold, 5% 5 Gold, 5% Counterfeit Penny | G4: 5 | H4: poop | I4: GoldenPoop
A5: Rainbow Poop | B5: Inanimate | C5: Will block the enemy's path and can be damaged by both player and enemy. Heals the Player when destroyed | D5: block | F5: Gain +3 Health | G5: 3 | H5: poop | I5: RainbowPoop

Sheet goals
A1: Goal | B1: Type | C1: Difficulty | D1: Owner Sheet | E1: Owner | F1: Owner Detail | G1: Relation | H1: Ticked | I1: Count | J1: Tags
A2: Attack an enemy with a spherical rock | B2: Feat | D2: weapon | E2: Earthquake | G2: has | H2: any time
A3: Be in a time loop | B3: Discovery | C3: 1-Low | D3: boss | E3: Steven | G3: has | H3: any time
A4: Beat a game while having pushed a boulder | D4: character | E4: The Makeshift Sisyphus | G4: has | H4: game beaten
A5: Beat a game without meta progression | D5: character | E5: Rodney | G5: has | H5: game beaten
A6: Beat a mini-game inside of a game | B6: Feat | C6: 2-Medium | D6: boss | E6: Resourceful Rat | G6: has | H6: any time
A7: beat a game while not healing intentionally | D7: status | E7: Bleed | F7: on player | G7: modifies | H7: game beaten
A8: beat a game while skipping or trashing X items/upgrades | D8: status | E8: Burn | F8: on player | G8: modifies | H8: game beaten
A9: Beat the game in 2 hours or less | B9: Restriction | C9: 3-High | D9: boss | E9: Time Eater | G9: has | H9: game beaten
A10: beat a game while getting X achievements | D10: status | E10: Marked | F10: on player | G10: modifies | H10: game beaten
A11: Become a cannibal | B11: Fetch | C11: 2-Medium | D11: boss | E11: Lord Bunga | G11: has | H11: any time
A12: Become undetectable | B12: Feat | C12: 2-Medium | D12: enemy | E12: Stalker | G12: has | H12: any time
A13: Behead an enemy | B13: Feat | C13: 3-High | D13: enemy | E13: Jabberwock | G13: has | H13: any time
A14: Bleed an enemy to death | B14: Feat | C14: 2-Medium | D14: enemy | E14: Sharky | G14: has | H14: any time
A15: Block an attack with an element | B15: Feat | C15: 2-Medium | D15: boss | E15: Royal Phalanx | G15: has | H15: any time
A16: Block damage done to a friendly unit | B16: Feat | C16: 3-High | D16: enemy | E16: Bishop | G16: has | H16: any time
A17: Body slam an enemy | B17: Feat | C17: 2-Medium | D17: enemy | E17: Revola | G17: has | H17: any time
A18: Break a Heart | B18: Feat | C18: 2-Medium | D18: boss | E18: Mom's Heart | G18: has | H18: any time
A19: Break glass | B19: Feat | C19: 2-Medium | D19: enemy | E19: Spiked Cat | G19: has | H19: any time
A20: Beat a game while having collected 3 different types of currency | D20: character | E20: Manager | G20: has | H20: game beaten
A21: Consume an enemy | B21: Bounty | C21: 2-Medium | D21: boss | E21: The Insatiable | G21: has | H21: any time
A22: Beat a game while having crafted or combined a spell or weapon | D22: character | E22: Minä | G22: has | H22: game beaten
A23: Create an illusion | B23: Feat | C23: 2-Medium | D23: enemy | E23: The Obscura | G23: has | H23: any time
A24: Date someone | B24: Fetch | C24: 1-Low | D24: boss | E24: Megaera | G24: has | H24: any time
A25: Defeat 3 bugs | B25: Bounty | C25: 1-Low | D25: enemy | E25: Attack Fly | G25: has | H25: any time | I25: 3
A26: Defeat 3 goblins | B26: Bounty | C26: 1-Low | D26: enemy | E26: Goblin | G26: has | H26: any time | I26: 3
A27: Defeat 5 skeletons | B27: Bounty | C27: 2-Medium | D27: enemy | E27: Bony | G27: has | H27: any time | I27: 5
A28: Defeat 3 spiders | B28: Bounty | C28: 1-Low | D28: enemy | E28: Spider | G28: has | H28: any time | I28: 3
A29: Defeat a boss without using violence | B29: Bounty | C29: 1-Low | D29: boss | E29: Baby Plum | G29: has | H29: any time
A30: Defeat a bug larger than you | B30: Bounty | C30: 1-Low | D30: boss | E30: Giant Spider | G30: has | H30: any time
A31: Defeat a child | B31: Bounty | C31: 2-Medium | D31: enemy | E31: Child | G31: has | H31: any time
A32: Defeat a fascist | B32: Bounty | C32: 1-Low | D32: boss | E32: Trigger Fingers | G32: has | H32: any time
A33: Defeat a headless enemy | B33: Bounty | C33: 1-Low | D33: enemy | E33: Pacer | G33: has | H33: any time
A34: Defeat a large rodent | B34: Bounty | C34: 3-High | D34: enemy | E34: Gigantic Vermin | G34: has | H34: any time
A35: Defeat a magic enemy with a gun | B35: Bounty | C35: 4-Insane | D35: boss | E35: Lich | G35: has | H35: any time
A36: Defeat a radiated enemy | B36: Bounty | C36: 2-Medium | D36: enemy | E36: Atomic Kitten | G36: has | H36: any time
A37: Defeat a robot designed to look like an animal | B37: Bounty | C37: 2-Medium | D37: enemy | E37: Robo-Cat | G37: has | H37: any time
A38: Defeat a rotten enemy | B38: Bounty | C38: 2-Medium | D38: boss | E38: Guillatina | F38: phase 3 of 3 | G38: has | H38: any time
A39: Defeat a skeleton animal | B39: Bounty | C39: 3-High | D39: enemy | E39: Skeleton Cat | G39: has | H39: any time
A40: Defeat a skeleton with a ball | B40: Bounty | C40: 1-Low | D40: enemy | E40: Skeleton Warrior | G40: has | H40: any time
A41: Defeat 2 skeletons with a ball | B41: Bounty | C41: 2-Medium | D41: enemy | E41: Skeletal Brute | G41: has | H41: any time | I41: 2
A42: Defeat 3 skeletons with a ball | B42: Bounty | C42: 3-High | D42: enemy | E42: Skeletal Bastion | G42: has | H42: any time | I42: 3
A43: Defeat a true final boss while on the brink of death | B43: Bounty | C43: 4-Insane | D43: boss | E43: The Beast | G43: has | H43: any time
A44: Defeat an animated body part | B44: Bounty | C44: 1-Low | D44: enemy | E44: Numbskull | G44: has | H44: any time
A45: Defeat an enemy made of fire | B45: Bounty | C45: 1-Low | D45: enemy | E45: Wisp | G45: has | H45: any time
A46: Defeat an enemy made of stone | B46: Bounty | C46: 1-Low | D46: boss | E46: Big Chunk | G46: has | H46: any time
A47: Defeat an enemy that clones itself | B47: Bounty | C47: 4-Insane | D47: enemy | E47: Stem Cat | G47: has | H47: any time
A48: Defeat an enemy that is an alien | B48: Bounty | C48: 1-Low | D48: enemy | E48: Baby Alien | G48: has | H48: any time
A49: Defeat an enemy that latches on to you | B49: Bounty | C49: 1-Low | D49: enemy | E49: Monkey | G49: has | H49: any time
A50: Defeat an enemy that looks edible | B50: Bounty | C50: 2-Medium | D50: enemy | E50: Shelled Parasite | G50: has | H50: any time
A51: Defeat an enemy that splits into another enemy | B51: Bounty | C51: 1-Low | D51: enemy | E51: Spike Slime (L) | G51: has | H51: any time
A52: Defeat an enemy while on fire | B52: Bounty | C52: 2-Medium | D52: enemy | E52: Flaming Hopper | G52: has | H52: any time
A53: Defeat an infested or rotted enemy | B53: Bounty | C53: 1-Low | D53: enemy | E53: Maggot | G53: has | H53: any time
A54: Defeat an obese enemy | B54: Bounty | C54: 1-Low | D54: boss | E54: Mega Fatty | G54: has | H54: any time
... A69: Beat a game without eating any food | B69: Restriction | C69: 1-Low | D69: boss | E69: Famine | G69: has | H69: game beaten
A70: Eat a living creature | B70: Feat | C70: 2-Medium | D70: boss | E70: Guillatina | F70: phase 1 of 3 | G70: has | H70: any time
A71: Eat something smelly | B71: Feat | C71: 2-Medium | D71: boss | E71: Chubs & Nubs | G71: has | H71: any time
A72: Enter an enemy | B72: Feat | C72: 1-Low | D72: boss | E72: Slime Boss | G72: has | H72: any time
A73: Enter or Create a religion | B73: Feat | C73: 4-Insane | D73: boss | E73: The One Who Waits | G73: has | H73: any time
A74: Find a baby | B74: Fetch | C74: 2-Medium | D74: enemy | E74: Fetus | G74: has | H74: any time
A75: Find a Tornado | B75: Discovery | C75: 2-Medium | D75: enemy | E75: Tornado | G75: has | H75: any time
A76: Flush or get flushed | B76: Feat | C76: 2-Medium | D76: boss | E76: Flushmaster | G76: has | H76: any time
A77: Freeze an enemy | B77: Feat | C77: 1-Low | D77: enemy | E77: Ice Slime | G77: has | H77: any time
A78: Get an achievement 5% or less of players have gotten | B78: Feat | C78: 3-High | D78: enemy | E78: Chrome Pyramid | G78: has | H78: any time
A79: Get drunk | B79: Feat | C79: 2-Medium | D79: boss | E79: Trampy | G79: has | H79: any time
A80: Beat a game with the help of a God | D80: character | E80: Zagreus | G80: has | H80: game beaten
A81: Get infected | B81: Feat | C81: 1-Low | D81: enemy | E81: Fungi Beast | G81: has | H81: any time
A82: Get something stolen from you | B82: Discovery | C82: 3-High | D82: enemy | E82: Giggling Minister | G82: has | H82: any time
A83: Get the true ending on the hardest difficulty possible | B83: Feat | C83: 4-Insane | D83: boss | E83: Corrupt Heart | G83: has | H83: any time
A84: Go to a Moon | B84: Discovery | C84: 3-High | D84: boss | E84: The Man in the Moon | G84: has | H84: any time
A85: Go to sleep | B85: Feat | C85: 1-Low | D85: boss | E85: Lagavulin | G85: has | H85: any time
A86: Grab an enemy | B86: Feat | C86: 1-Low | D86: enemy | E86: Wringer | G86: has | H86: any time
A87: Have an enemy defeat another enemy | B87: Feat | C87: 1-Low | D87: boss | E87: Marshmallow | G87: has | H87: any time
A88: Hit an enemy with a vehicle | B88: Feat | C88: 3-High | D88: enemy | E88: Nemean Chariot | G88: has | H88: any time
A89: If beaten in 1+(1/2)^(X-2) hours or less | D89: status | E89: Speed | F89: on player | G89: modifies | H89: game beaten
A90: If beaten while the difficulty is increased X times or as much as possible | D90: status | E90: Strength | F90: on player | G90: modifies | H90: game beaten
A91: if X or all bosses were beaten without getting hit when beating a game | D91: status | E91: Dexterity | F91: on player | G91: modifies | H91: game beaten
A92: Defeat a God | B92: Bounty | C92: 4-Insane | D92: boss | E92: The Creator | G92: has | H92: any time
A93: Beat a game while having defeated a vampire | D93: character | E93: Antonio Belpaese | G93: has | H93: game beaten
A94: Light a liquid on fire | B94: Feat | C94: 1-Low | D94: boss | E94: Hickory | G94: has | H94: any time
A95: Beat a game while having made a Faustian bargain | D95: character | E95: Ironclad | G95: has | H95: game beaten
A96: Beat a game while having made a friend | D96: character | E96: Regent | G96: has | H96: game beaten
A97: Beat a game while having muted the game | B97: Restriction | C97: 1-Low | D97: boss | E97: Banshee | G97: has | H97: game beaten
A98: Beat a game while having muted the game | B98: Restriction | C98: 2-Medium | D98: boss | E98: Green Banshee | G98: has | H98: game beaten
A99: Obtain 1 fish | B99: Fetch | C99: 1-Low | D99: enemy | E99: Mung | G99: has | H99: any time
A100: Obtain a key | B100: Fetch | C100: 1-Low | D100: enemy | E100: Keybullet Kin | G100: has | H100: any time
A101: Have 6 Guns at once | B101: Fetch | C101: 1-Low | D101: boss | E101: Beholster | G101: has | H101: any time
A102: Obtain a large fish | B102: Fetch | C102: 1-Low | D102: boss | E102: Mobius | G102: has | H102: any time
A103: Beat a game while only using 1 hand | B103: Restriction | C103: 3-High | D103: boss | E103: The Needle | G103: has | H103: game beaten
A104: Perfect a game by beating it without losing | D104: character | E104: Zoe | G104: has | H104: game beaten
A105: Perform a religious act | B105: Feat | C105: 1-Low | D105: enemy | E105: Cultist | G105: has | H105: any time
A106: Perform a song | B106: Feat | C106: 2-Medium | D106: boss | E106: Scylla | G106: has | H106: any time
A107: Poke an eye | B107: Feat | C107: 1-Low | D107: boss | E107: Khidr | G107: has | H107: any time
A108: Punch a robot | B108: Feat | C108: 1-Low | D108: enemy | E108: Punch Construct | G108: has | H108: any time
A109: Push an enemy into fire | B109: Feat | C109: 1-Low | D109: enemy | E109: Flaming Fatty | G109: has | H109: any time
A110: Raise the dead | B110: Feat | C110: 1-Low | D110: boss | E110: Morana | G110: has | H110: any time
A111: Beat a game while having selected a random starting build | D111: character | E111: Erratic Deck | G111: has | H111: game beaten
A112: Reflect a projectile | B112: Feat | C112: 2-Medium | D112: enemy | E112: Host | G112: has | H112: any time
A113: Retrieve stolen currency or items | B113: Discovery | C113: 1-Low | D113: enemy | E113: Leprechaun | G113: has | H113: any time
A114: Set a rock on fire | B114: Feat | C114: 2-Medium | D114: enemy | E114: Coal Spider | G114: has | H114: any time
...

Sheet shopkeepers
A1: Name | B1: Game | C1: Description | D1: Image | E1: Pool | F1: Loot Kinds | G1: Currency | H1: Sale | I1: Effect | J1: Item Slots | K1: Loot Slots | L1: Rarity | M1: Boss | N1: Loot Tag | O1: Pack Slots
A2: Charon | B2: Hades | D2: Charon | I2: steal 3, beaten_sale 20 | J2: 3 | K2: 0 | M2: Charon
A3: Jimbo | B3: Balatro | D3: Jimbo | F3: card | J3: 1 | K3: 2 | N3: joker | O3: 2
A4: Shopkeeper (Isaac) | B4: The Binding of Isaac: Rebirth | D4: Shopkeeper(Isaac) | I4: bombable, donation_shelf
A5: Shopkeeper Furcifer | B5: Backpack Battles | D5: ShopkeeperFurcifer | H5: 10% half | I5: gold_reroll | J5: 0 | K5: 5

Sheet radio
A1: Name | B1: Artist | C1: Album | D1: Year | E1: Game | F1: File | G1: Tags
A2: No Escape | B2: Darren Korb | C2: Hades: Original Soundtrack | D2: 2020 | E2: Hades | F2: Hades/01. No Escape.mp3 | G2: menu
A3: The Year Is... | B3: Cityfires | C3: 20XX Soundtrack | D3: 2017 | E3: 20XX | F3: 20XX/01 The Year Is....mp3
A4: 20XX | B4: Cityfires | C4: 20XX Soundtrack | D4: 2017 | E4: 20XX | F4: 20XX/02 20XX.mp3 | G4: menu
A5: Get Ready! | B5: Cityfires | C5: 20XX Soundtrack | D5: 2017 | E5: 20XX | F5: 20XX/03 Get Ready!.mp3
A6: Firestorm | B6: Cityfires | C6: 20XX Soundtrack | D6: 2017 | E6: 20XX | F6: 20XX/04 Firestorm.mp3
A7: Identity Crisis | B7: Cityfires | C7: 20XX Soundtrack | D7: 2017 | E7: 20XX | F7: 20XX/05 Identity Crisis.mp3
A8: Permission Denied | B8: Cityfires | C8: 20XX Soundtrack | D8: 2017 | E8: 20XX | F8: 20XX/06 Permission Denied.mp3
A9: Second Strike | B9: Cityfires | C9: 20XX Soundtrack | D9: 2017 | E9: 20XX | F9: 20XX/07 Second Strike.mp3
A10: Permafrost | B10: Cityfires | C10: 20XX Soundtrack | D10: 2017 | E10: 20XX | F10: 20XX/08 Permafrost.mp3
A11: Pseudocode | B11: Cityfires | C11: 20XX Soundtrack | D11: 2017 | E11: 20XX | F11: 20XX/09 Pseudocode.mp3
A12: Another Chance 1 | B12: Cityfires | C12: 20XX Soundtrack | D12: 2017 | E12: 20XX | F12: 20XX/10 Another Chance 1.mp3
A13: Apex | B13: Cityfires | C13: 20XX Soundtrack | D13: 2017 | E13: 20XX | F13: 20XX/11 Apex.mp3
A14: Another Chance 2 | B14: Cityfires | C14: 20XX Soundtrack | D14: 2017 | E14: 20XX | F14: 20XX/12 Another Chance 2.mp3
A15: Spark Engine | B15: Cityfires | C15: 20XX Soundtrack | D15: 2017 | E15: 20XX | F15: 20XX/13 Spark Engine.mp3
A16: Endless Echo | B16: Cityfires | C16: 20XX Soundtrack | D16: 2017 | E16: 20XX | F16: 20XX/14 Endless Echo.mp3
... A19: Reboot | B19: Cityfires | C19: 20XX Soundtrack | D19: 2017 | E19: 20XX | F19: 20XX/17 Reboot.mp3
A20: Main Theme | B20: LouisF | C20: Balatro (Original Game Soundtrack) | D20: 2023 | E20: Balatro | F20: Balatro/01. Main Theme.mp3 | G20: menu
A21: Shop Theme | B21: LouisF | C21: Balatro (Original Game Soundtrack) | D21: 2023 | E21: Balatro | F21: Balatro/02. Shop Theme.mp3
A22: Arcana Theme | B22: LouisF | C22: Balatro (Original Game Soundtrack) | D22: 2023 | E22: Balatro | F22: Balatro/03. Arcana Theme.mp3
A23: Celestial Theme | B23: LouisF | C23: Balatro (Original Game Soundtrack) | D23: 2023 | E23: Balatro | F23: Balatro/04. Celestial Theme.mp3
A24: Boss Theme | B24: LouisF | C24: Balatro (Original Game Soundtrack) | D24: 2023 | E24: Balatro | F24: Balatro/05. Boss Theme.mp3
A25: Ballbylon Has Fallen | B25: Amos Roddy | C25: BALL x PIT (Original Soundtrack) | D25: 2025 | E25: Ball x Pit | F25: Ball x Pit/01. Ballbylon Has Fallen.mp3 | G25: menu
A26: Bone x Yard | B26: Amos Roddy | C26: BALL x PIT (Original Soundtrack) | D26: 2025 | E26: Ball x Pit | F26: Ball x Pit/02. Bone x Yard.mp3
A27: The Skeleton King | B27: Amos Roddy | C27: BALL x PIT (Original Soundtrack) | D27: 2025 | E27: Ball x Pit | F27: Ball x Pit/03. The Skeleton King.mp3
A28: Bountiful Harvest | B28: Amos Roddy | C28: BALL x PIT (Original Soundtrack) | D28: 2025 | E28: Ball x Pit | F28: Ball x Pit/04. Bountiful Harvest.mp3
A29: Snowy x Shores | B29: Amos Roddy | C29: BALL x PIT (Original Soundtrack) | D29: 2025 | E29: Ball x Pit | F29: Ball x Pit/05. Snowy x Shores.mp3
A30: The Yeti Queen | B30: Amos Roddy | C30: BALL x PIT (Original Soundtrack) | D30: 2025 | E30: Ball x Pit | F30: Ball x Pit/06. The Yeti Queen.mp3
A31: Liminal x Desert | B31: Amos Roddy | C31: BALL x PIT (Original Soundtrack) | D31: 2025 | E31: Ball x Pit | F31: Ball x Pit/07. Liminal x Desert.mp3
A32: The Twisted Serpent | B32: Amos Roddy | C32: BALL x PIT (Original Soundtrack) | D32: 2025 | E32: Ball x Pit | F32: Ball x Pit/08. The Twisted Serpent.mp3
A33: A Pit Remains | B33: Amos Roddy | C33: BALL x PIT (Original Soundtrack) | D33: 2025 | E33: Ball x Pit | F33: Ball x Pit/09. A Pit Remains.mp3
A34: Fungal x Forest | B34: Amos Roddy | C34: BALL x PIT (Original Soundtrack) | D34: 2025 | E34: Ball x Pit | F34: Ball x Pit/10. Fungal x Forest.mp3
A35: The Shroom Swarm | B35: Amos Roddy | C35: BALL x PIT (Original Soundtrack) | D35: 2025 | E35: Ball x Pit | F35: Ball x Pit/11. The Shroom Swarm.mp3
A36: Gory x Grasslands | B36: Amos Roddy | C36: BALL x PIT (Original Soundtrack) | D36: 2025 | E36: Ball x Pit | F36: Ball x Pit/12. Gory x Grasslands.mp3
A37: The Sabertooth | B37: Amos Roddy | C37: BALL x PIT (Original Soundtrack) | D37: 2025 | E37: Ball x Pit | F37: Ball x Pit/13. The Sabertooth.mp3
... A46: Scroll of Names | B46: Amos Roddy | C46: BALL x PIT (Original Soundtrack) | D46: 2025 | E46: Ball x Pit | F46: Ball x Pit/22. Scroll of Names.mp3
A47: Liquid Glass | B47: Adonai | C47: Brotato Soundtrack | D47: 2024 | E47: Brotato | F47: Brotato/1-01 - Liquid Glass.mp3 | G47: menu
A48: Phase Break | B48: Adonai | C48: Brotato Soundtrack | D48: 2024 | E48: Brotato | F48: Brotato/1-02 - Phase Break.mp3
A49: Turbine Kick | B49: Adonai ft. Rez | C49: Brotato Soundtrack | D49: 2024 | E49: Brotato | F49: Brotato/1-03 - Turbine Kick.mp3
A50: Wubs of the Deep | B50: Adonai ft. Rez | C50: Brotato Soundtrack | D50: 2024 | E50: Brotato | F50: Brotato/1-04 - Wubs of the Deep.mp3
A51: Hyperspace | B51: Adonai ft. Subkey | C51: Brotato Soundtrack | D51: 2024 | E51: Brotato | F51: Brotato/1-05 - Hyperspace.mp3
A52: Currents | B52: Adonai | C52: Brotato Soundtrack | D52: 2024 | E52: Brotato | F52: Brotato/2-01 - Currents.mp3
A53: Kora | B53: Adonai | C53: Brotato Soundtrack | D53: 2024 | E53: Brotato | F53: Brotato/2-02 - Kora.mp3
A54: Shipwrecked | B54: Adonai | C54: Brotato Soundtrack | D54: 2024 | E54: Brotato | F54: Brotato/2-03 - Shipwrecked.mp3
A55: Covert Sub | B55: Adonai ft. Rez | C55: Brotato Soundtrack | D55: 2024 | E55: Brotato | F55: Brotato/2-04 - Covert Sub.mp3
A56: Thalassophobia | B56: Adonai ft. Rez | C56: Brotato Soundtrack | D56: 2024 | E56: Brotato | F56: Brotato/2-05 - Thalassophobia.mp3
A57: Sonar | B57: Adonai ft. Subkey | C57: Brotato Soundtrack | D57: 2024 | E57: Brotato | F57: Brotato/2-06 - Sonar.mp3
A58: Dreams of Purgatory | B58: Publio Delgado | C58: Brutal Orchestra Soundtrack | D58: 2022 | E58: Brutal Orchestra | F58: Brutal Orchestra/01 Dreams of Purgatory.mp3 | G58: menu
A59: Give a Man a Fish | B59: Publio Delgado | C59: Brutal Orchestra Soundtrack | D59: 2022 | E59: Brutal Orchestra | F59: Brutal Orchestra/02 Give a Man a Fish.mp3
A60: Teach a Fish to Man | B60: Publio Delgado | C60: Brutal Orchestra Soundtrack | D60: 2022 | E60: Brutal Orchestra | F60: Brutal Orchestra/03 Teach a Fish to Man.mp3
A61: Estupido Pez Sexy | B61: Publio Delgado | C61: Brutal Orchestra Soundtrack | D61: 2022 | E61: Brutal Orchestra | F61: Brutal Orchestra/04 Estupido Pez Sexy.mp3
A62: Primary Colours | B62: Publio Delgado | C62: Brutal Orchestra Soundtrack | D62: 2022 | E62: Brutal Orchestra | F62: Brutal Orchestra/05 Primary Colours.mp3
A63: Amphibious Army | B63: Publio Delgado | C63: Brutal Orchestra Soundtrack | D63: 2022 | E63: Brutal Orchestra | F63: Brutal Orchestra/06 Amphibious Army.mp3
A64: Swallowing the Sea | B64: Publio Delgado | C64: Brutal Orchestra Soundtrack | D64: 2022 | E64: Brutal Orchestra | F64: Brutal Orchestra/07 Swallowing the Sea.mp3
A65: The Far Shore | B65: Publio Delgado | C65: Brutal Orchestra Soundtrack | D65: 2022 | E65: Brutal Orchestra | F65: Brutal Orchestra/08 The Far Shore.mp3
A66: Muscle Memory | B66: Publio Delgado | C66: Brutal Orchestra Soundtrack | D66: 2022 | E66: Brutal Orchestra | F66: Brutal Orchestra/09 Muscle Memory.mp3
A67: Burning Passion | B67: Publio Delgado | C67: Brutal Orchestra Soundtrack | D67: 2022 | E67: Brutal Orchestra | F67: Brutal Orchestra/10 Burning Passion.mp3
A68: To See Her Again | B68: Publio Delgado | C68: Brutal Orchestra Soundtrack | D68: 2022 | E68: Brutal Orchestra | F68: Brutal Orchestra/11 To See Her Again.mp3
A69: The Other Escape | B69: Publio Delgado | C69: Brutal Orchestra Soundtrack | D69: 2022 | E69: Brutal Orchestra | F69: Brutal Orchestra/12 The Other Escape.mp3
A70: Bosch's Butt Song | B70: Publio Delgado | C70: Brutal Orchestra Soundtrack | D70: 2022 | E70: Brutal Orchestra | F70: Brutal Orchestra/13 Bosch's Butt Song.mp3
... A98: Zanguango | B98: Publio Delgado | C98: Brutal Orchestra Soundtrack | D98: 2022 | E98: Brutal Orchestra | F98: Brutal Orchestra/41 Zanguango.mp3
A99: Overworld | B99: Craig Hamilton | C99: Caves of Qud OST | D99: 2024 | E99: Caves of Qud | F99: Caves of Qud/01. Overworld.mp3 | G99: menu
A100: Pilgrim's Path | B100: Craig Hamilton | C100: Caves of Qud OST | D100: 2024 | E100: Caves of Qud | F100: Caves of Qud/02. Pilgrim's Path.mp3
A101: Mehmet's Morning | B101: Craig Hamilton | C101: Caves of Qud OST | D101: 2024 | E101: Caves of Qud | F101: Caves of Qud/03. Mehmet's Morning.mp3
A102: Moghra'yi Remembrance Circle | B102: Craig Hamilton | C102: Caves of Qud OST | D102: 2024 | E102: Caves of Qud | F102: Caves of Qud/04. Moghra'yi Remembrance Circle.mp3
A103: Mehmet's Book on Strings | B103: Craig Hamilton | C103: Caves of Qud OST | D103: 2024 | E103: Caves of Qud | F103: Caves of Qud/05. Mehmet's Book on Strings.mp3
A104: 3rd Spore Phase | B104: Craig Hamilton | C104: Caves of Qud OST | D104: 2024 | E104: Caves of Qud | F104: Caves of Qud/06. 3rd Spore Phase.mp3
A105: Bey Lah Heritage II | B105: Craig Hamilton | C105: Caves of Qud OST | D105: 2024 | E105: Caves of Qud | F105: Caves of Qud/07. Bey Lah Heritage II.mp3
A106: Stoic Porridge | B106: Craig Hamilton | C106: Caves of Qud OST | D106: 2024 | E106: Caves of Qud | F106: Caves of Qud/08. Stoic Porridge.mp3
A107: Golgotha | B107: Craig Hamilton | C107: Caves of Qud OST | D107: 2024 | E107: Caves of Qud | F107: Caves of Qud/09. Golgotha.mp3
A108: Deeper Eaters | B108: Craig Hamilton | C108: Caves of Qud OST | D108: 2024 | E108: Caves of Qud | F108: Caves of Qud/10. Deeper Eaters.mp3
A109: of Chrome, and How (Sultan's Song) | B109: Craig Hamilton | C109: Caves of Qud OST | D109: 2024 | E109: Caves of Qud | F109: Caves of Qud/11. of Chrome, and How (Sultan's Song).mp3
A110: Lazarus | B110: Craig Hamilton | C110: Caves of Qud OST | D110: 2024 | E110: Caves of Qud | F110: Caves of Qud/12. Lazarus.mp3
A111: Barathrum's Study | B111: Craig Hamilton | C111: Caves of Qud OST | D111: 2024 | E111: Caves of Qud | F111: Caves of Qud/13. Barathrum's Study.mp3
... A130: Live and Drink | B130: Craig Hamilton | C130: Caves of Qud OST | D130: 2024 | E130: Caves of Qud | F130: Caves of Qud/32. Live and Drink.mp3
A131: Tombtorial (Tutorial) | B131: Danny Baranowsky | C131: Crypt of the Necrodancer OST | D131: 2014 | E131: Crypt of the NecroDancer | F131: Crypt of the NecroDancer/01. Tombtorial (Tutorial).mp3 | G131: menu
A132: Watch Your Step (Training) | B132: Danny Baranowsky | C132: Crypt of the Necrodancer OST | D132: 2014 | E132: Crypt of the NecroDancer | F132: Crypt of the NecroDancer/02. Watch Your Step (Training).mp3
A133: Disco Descent (1-1) | B133: Danny Baranowsky | C133: Crypt of the Necrodancer OST | D133: 2014 | E133: Crypt of the NecroDancer | F133: Crypt of the NecroDancer/03. Disco Descent (1-1).mp3
A134: Crypteque (1-2) | B134: Danny Baranowsky | C134: Crypt of the Necrodancer OST | D134: 2014 | E134: Crypt of the NecroDancer | F134: Crypt of the NecroDancer/04. Crypteque (1-2).mp3
A135: Mausoleum Mash (1-3) | B135: Danny Baranowsky | C135: Crypt of the Necrodancer OST | D135: 2014 | E135: Crypt of the NecroDancer | F135: Crypt of the NecroDancer/05. Mausoleum Mash (1-3).mp3
A136: Konga Conga Kappa (King Conga) | B136: Danny Baranowsky | C136: Crypt of the Necrodancer OST | D136: 2014 | E136: Crypt of the NecroDancer | F136: Crypt of the NecroDancer/06. Konga Conga Kappa (King Conga).mp3
A137: Fungal Funk (2-1) | B137: Danny Baranowsky | C137: Crypt of the Necrodancer OST | D137: 2014 | E137: Crypt of the NecroDancer | F137: Crypt of the NecroDancer/07. Fungal Funk (2-1).mp3
A138: Grave Throbbing (2-2) | B138: Danny Baranowsky | C138: Crypt of the Necrodancer OST | D138: 2014 | E138: Crypt of the NecroDancer | F138: Crypt of the NecroDancer/08. Grave Throbbing (2-2).mp3
A139: Portabellohead (2-3) | B139: Danny Baranowsky | C139: Crypt of the Necrodancer OST | D139: 2014 | E139: Crypt of the NecroDancer | F139: Crypt of the NecroDancer/09. Portabellohead (2-3).mp3
A140: Metalmancy (Death Metal feat. FamilyJules7x) | B140: Danny Baranowsky | C140: Crypt of the Necrodancer OST | D140: 2014 | E140: Crypt of the NecroDancer | F140: Crypt of the NecroDancer/10. Metalmancy (Death Metal feat. FamilyJules7x).mp3
A141: Stone Cold (3-1 Cold) | B141: Danny Baranowsky | C141: Crypt of the Necrodancer OST | D141: 2014 | E141: Crypt of the NecroDancer | F141: Crypt of the NecroDancer/11. Stone Cold (3-1 Cold).mp3
A142: Igneous Rock (3-1 Hot feat. FamilyJules7x) | B142: Danny Baranowsky | C142: Crypt of the Necrodancer OST | D142: 2014 | E142: Crypt of the NecroDancer | F142: Crypt of the NecroDancer/12. Igneous Rock (3-1 Hot feat. FamilyJules7x).mp3
A143: Dance of the Decorous (3-2 Cold) | B143: Danny Baranowsky | C143: Crypt of the Necrodancer OST | D143: 2014 | E143: Crypt of the NecroDancer | F143: Crypt of the NecroDancer/13. Dance of the Decorous (3-2 Cold).mp3
... A157: Vamplified (Conductor Fight) | B157: Danny Baranowsky | C157: Crypt of the Necrodancer OST | D157: 2014 | E157: Crypt of the NecroDancer | F157: Crypt of the NecroDancer/27. Vamplified (Conductor Fight).mp3
A158: Praise the Lamb | B158: River Boy | C158: Cult of the Lamb Original Soundtrack | D158: 2022 | E158: Cult of the Lamb | F158: Cult of the Lamb/01. Praise the Lamb.mp3 | G158: menu
A159: Start a Cult | B159: River Boy | C159: Cult of the Lamb Original Soundtrack | D159: 2022 | E159: Cult of the Lamb | F159: Cult of the Lamb/02. Start a Cult.mp3
A160: Temple | B160: River Boy | C160: Cult of the Lamb Original Soundtrack | D160: 2022 | E160: Cult of the Lamb | F160: Cult of the Lamb/03. Temple.mp3
A161: Work and Worship | B161: River Boy | C161: Cult of the Lamb Original Soundtrack | D161: 2022 | E161: Cult of the Lamb | F161: Cult of the Lamb/04. Work and Worship.mp3
A162: Faith Up | B162: River Boy | C162: Cult of the Lamb Original Soundtrack | D162: 2022 | E162: Cult of the Lamb | F162: Cult of the Lamb/05. Faith Up.mp3
A163: Sacrifice | B163: River Boy | C163: Cult of the Lamb Original Soundtrack | D163: 2022 | E163: Cult of the Lamb | F163: Cult of the Lamb/06. Sacrifice.mp3
A164: Saviour | B164: River Boy | C164: Cult of the Lamb Original Soundtrack | D164: 2022 | E164: Cult of the Lamb | F164: Cult of the Lamb/07. Saviour.mp3
A165: Darkwood | B165: River Boy | C165: Cult of the Lamb Original Soundtrack | D165: 2022 | E165: Cult of the Lamb | F165: Cult of the Lamb/08. Darkwood.mp3
A166: Amdusias | B166: River Boy | C166: Cult of the Lamb Original Soundtrack | D166: 2022 | E166: Cult of the Lamb | F166: Cult of the Lamb/09. Amdusias.mp3
A167: Leshy | B167: River Boy | C167: Cult of the Lamb Original Soundtrack | D167: 2022 | E167: Cult of the Lamb | F167: Cult of the Lamb/10. Leshy.mp3
A168: Knucklebones | B168: River Boy | C168: Cult of the Lamb Original Soundtrack | D168: 2022 | E168: Cult of the Lamb | F168: Cult of the Lamb/11. Knucklebones.mp3
...

Sheet locations
A1: Name | B1: Game | C1: Difficulty | D1: Description | E1: Effect | F1: Tag Type | G1: Tag % Up | H1: Img | K1: Column3
A2: Burning Basement | B2: The Binding of Isaac: Rebirth | C2: 1-Low | D2: When entered, spawn 1 random fire tagged Enemy and 2 fire tiles on random tiles | E2: arrive: spawn_enemy fire 1; place_tile fire 2 | F2: fire | G2: 0.2 | H2: BurningBasement
A3: Dross | B3: The Binding of Isaac: Rebirth | C3: 1-Low | D3: When entered, spawn 2 random poop tagged objects on random tiles. There is an 80% chance it is the normal Poop. | E3: arrive: place_unit poop 2 favour=poop:80 | F3: poop, stinky | G3: 0.2 | H3: Dross
A4: The Hive | B4: Slay the Spire 2 | C4: 2-Medium | D4: When entered, spawn 2 random bug tagged Enemies | E4: arrive: spawn_enemy bug 2 | F4: bug | G4: 0.3 | H4: TheHive
A5: Dark Room | B5: The Binding of Isaac: Rebirth | C5: 3-High | D5: Damage taken here is doubled. When entered, Lose 2 Max Health to Gain +1 Devilish Small Chest up to 4 times | E5: while: damage_taken_mult 2; action 4: lose_max_hp 2 => gain_chest small devilish | F5: devilish | G5: 0.2 | H5: DarkRoom
A6: The Chest | B6: The Binding of Isaac | C6: 3-High | D6: Damage taken here is doubled. When entered, Use a key to Gain +1 Small Chest up to 4 times | E6: while: damage_taken_mult 2; action 4: spend keys 1 => gain_chest small | H6: TheChest
A7: The Void | B7: The Binding of Isaac: Rebirth | C7: 4-Insane | D7: 1 Random Game in the Game Choice Select will be a Random Game Rift | E7: while: offering_rift 1 | H7: TheVoid

Sheet Map Analysis
A1: Influence Graph — live analysis
A2: Every figure is a formula over the games and connections sheets. Add a row to either and these update on open.
A4: Measure | B4: Value | C4: What it means | E4: Degree | F4: Games | G4: Owned | H4: On the map | I4: Genre | J4: Games | K4: Owned | L4: Owned % | N4: Rank | O4: Game | P4: Degree | R4: Rank | S4: Game you own | T4: Degree | V4: Year | W4: Games | X4: Owned | Y4: Connections | AA4: Edge span | AB4: Connections | AD4: Rank | AE4: Game to buy | AF4: Owned games it joins | AH4: Rank | AI4: Hub on the map | AJ4: Map degree
A5: Games | B5: =SUMPRODUCT(--('Map Calc'!$A$2:$A$1500<>"")) | C5: Nodes in the graph | E5: 0 | F5: =COUNTIFS('Map Calc'!$D$2:$D$1500,0) | G5: =COUNTIFS('Map Calc'!$D$2:$D$1500,0,'Map Calc'!$P$2:$P$1500,"Yes") | H5: =COUNTIFS('Map Calc'!$AI$2:$AI$1500,0) | I5: Action | J5: =COUNTIF('Map Calc'!$C$2:$C$1500,$I5) | K5: =COUNTIFS('Map Calc'!$C$2:$C$1500,$I5,'Map Calc'!$P$2:$P$1500,"Yes") | L5: =IF($J5=0,0,$K5/$J5) -> 0.6547619 | N5: 1 | O5: =IFERROR(INDEX('Map Calc'!$A$2:$A$1500,MATCH(LARGE('Map Calc'!$O$2:$O$1500,1),'Map Calc'!$O$2:$O$1500,0)),"") | P5: =IFERROR(INDEX('Map Calc'!$D$2:$D$1500,MATCH(LARGE('Map Calc'!$O$2:$O$1500,1),'Map Calc'!$O$2:$O$1500,0)),"") | R5: 1 | S5: =IFERROR(INDEX('Map Calc'!$A$2:$A$1500,MATCH(LARGE('Map Calc'!$Q$2:$Q$1500,1),'Map Calc'!$Q$2:$Q$1500,0)),"") | T5: =IFERROR(INDEX('Map Calc'!$D$2:$D$1500,MATCH(LARGE('Map Calc'!$Q$2:$Q$1500,1),'Map Calc'!$Q$2:$Q$1500,0)),"") | V5: 1978 | W5: =COUNTIF('Map Calc'!$B$2:$B$1500,$V5) | X5: =COUNTIFS('Map Calc'!$B$2:$B$1500,$V5,'Map Calc'!$P$2:$P$1500,"Yes") | Y5: =COUNTIF('Map Calc'!$T$2:$T$2500,$V5) | AA5: 0 | AB5: =COUNTIF('Map Calc'!$V$2:$V$2500,$AA5) | AD5: 1 | AE5: =IFERROR(INDEX('Map Calc'!$A$2:$A$1500,MATCH(LARGE('Map Calc'!$AK$2:$AK$1500,1),'Map Calc'!$AK$2:$AK$1500,0)),"") | AF5: =IFERROR(INDEX('Map Calc'!$AG$2:$AG$1500,MATCH(LARGE('Map Calc'!$AK$2:$AK$1500,1),'Map Calc'!$AK$2:$AK$1500,0)),"") | AH5: 1 | AI5: =IFERROR(INDEX('Map Calc'!$A$2:$A$1500,MATCH(LARGE('Map Calc'!$AJ$2:$AJ$1500,1),'Map Calc'!$AJ$2:$AJ$1500,0)),"") | AJ5: =IFERROR(INDEX('Map Calc'!$AI$2:$AI$1500,MATCH(LARGE('Map Calc'!$AJ$2:$AJ$1500,1),'Map Calc'!$AJ$2:$AJ$1500,0)),"")
A6: Games owned | B6: =COUNTIF('Map Calc'!$P$2:$P$1500,"Yes") | C6: Marked Owned — the catalog a default run draws from | E6: 1 | F6: =COUNTIFS('Map Calc'!$D$2:$D$1500,1) | G6: =COUNTIFS('Map Calc'!$D$2:$D$1500,1,'Map Calc'!$P$2:$P$1500,"Yes") | H6: =COUNTIFS('Map Calc'!$AI$2:$AI$1500,1) | I6: Strategy | J6: =COUNTIF('Map Calc'!$C$2:$C$1500,$I6) | K6: =COUNTIFS('Map Calc'!$C$2:$C$1500,$I6,'Map Calc'!$P$2:$P$1500,"Yes") | L6: =IF($J6=0,0,$K6/$J6) -> 0.63905325 | N6: 2 | O6: =IFERROR(INDEX('Map Calc'!$A$2:$A$1500,MATCH(LARGE('Map Calc'!$O$2:$O$1500,2),'Map Calc'!$O$2:$O$1500,0)),"") | P6: =IFERROR(INDEX('Map Calc'!$D$2:$D$1500,MATCH(LARGE('Map Calc'!$O$2:$O$1500,2),'Map Calc'!$O$2:$O$1500,0)),"") | R6: 2 | S6: =IFERROR(INDEX('Map Calc'!$A$2:$A$1500,MATCH(LARGE('Map Calc'!$Q$2:$Q$1500,2),'Map Calc'!$Q$2:$Q$1500,0)),"") | T6: =IFERROR(INDEX('Map Calc'!$D$2:$D$1500,MATCH(LARGE('Map Calc'!$Q$2:$Q$1500,2),'Map Calc'!$Q$2:$Q$1500,0)),"") | V6: 1979 | W6: =COUNTIF('Map Calc'!$B$2:$B$1500,$V6) | X6: =COUNTIFS('Map Calc'!$B$2:$B$1500,$V6,'Map Calc'!$P$2:$P$1500,"Yes") | Y6: =COUNTIF('Map Calc'!$T$2:$T$2500,$V6) | AA6: 1 | AB6: =COUNTIF('Map Calc'!$V$2:$V$2500,$AA6) | AD6: 2 | AE6: =IFERROR(INDEX('Map Calc'!$A$2:$A$1500,MATCH(LARGE('Map Calc'!$AK$2:$AK$1500,2),'Map Calc'!$AK$2:$AK$1500,0)),"") | AF6: =IFERROR(INDEX('Map Calc'!$AG$2:$AG$1500,MATCH(LARGE('Map Calc'!$AK$2:$AK$1500,2),'Map Calc'!$AK$2:$AK$1500,0)),"") | AH6: 2 | AI6: =IFERROR(INDEX('Map Calc'!$A$2:$A$1500,MATCH(LARGE('Map Calc'!$AJ$2:$AJ$1500,2),'Map Calc'!$AJ$2:$AJ$1500,0)),"") | AJ6: =IFERROR(INDEX('Map Calc'!$AI$2:$AI$1500,MATCH(LARGE('Map Calc'!$AJ$2:$AJ$1500,2),'Map Calc'!$AJ$2:$AJ$1500,0)),"")
A7: Owned share | B7: =IF(B5=0,0,B6/B5) | C7: How much of the sheet a run can actually be sent to | E7: 2 | F7: =COUNTIFS('Map Calc'!$D$2:$D$1500,2) | G7: =COUNTIFS('Map Calc'!$D$2:$D$1500,2,'Map Calc'!$P$2:$P$1500,"Yes") | H7: =COUNTIFS('Map Calc'!$AI$2:$AI$1500,2) | I7: Deckbuilder | J7: =COUNTIF('Map Calc'!$C$2:$C$1500,$I7) | K7: =COUNTIFS('Map Calc'!$C$2:$C$1500,$I7,'Map Calc'!$P$2:$P$1500,"Yes") | L7: =IF($J7=0,0,$K7/$J7) -> 0.52040816 | N7: 3 | O7: =IFERROR(INDEX('Map Calc'!$A$2:$A$1500,MATCH(LARGE('Map Calc'!$O$2:$O$1500,3),'Map Calc'!$O$2:$O$1500,0)),"") | P7: =IFERROR(INDEX('Map Calc'!$D$2:$D$1500,MATCH(LARGE('Map Calc'!$O$2:$O$1500,3),'Map Calc'!$O$2:$O$1500,0)),"") | R7: 3 | S7: =IFERROR(INDEX('Map Calc'!$A$2:$A$1500,MATCH(LARGE('Map Calc'!$Q$2:$Q$1500,3),'Map Calc'!$Q$2:$Q$1500,0)),"") | T7: =IFERROR(INDEX('Map Calc'!$D$2:$D$1500,MATCH(LARGE('Map Calc'!$Q$2:$Q$1500,3),'Map Calc'!$Q$2:$Q$1500,0)),"") | V7: 1980 | W7: =COUNTIF('Map Calc'!$B$2:$B$1500,$V7) | X7: =COUNTIFS('Map Calc'!$B$2:$B$1500,$V7,'Map Calc'!$P$2:$P$1500,"Yes") | Y7: =COUNTIF('Map Calc'!$T$2:$T$2500,$V7) | AA7: 2 | AB7: =COUNTIF('Map Calc'!$V$2:$V$2500,$AA7) | AD7: 3 | AE7: =IFERROR(INDEX('Map Calc'!$A$2:$A$1500,MATCH(LARGE('Map Calc'!$AK$2:$AK$1500,3),'Map Calc'!$AK$2:$AK$1500,0)),"") | AF7: =IFERROR(INDEX('Map Calc'!$AG$2:$AG$1500,MATCH(LARGE('Map Calc'!$AK$2:$AK$1500,3),'Map Calc'!$AK$2:$AK$1500,0)),"") | AH7: 3 | AI7: =IFERROR(INDEX('Map Calc'!$A$2:$A$1500,MATCH(LARGE('Map Calc'!$AJ$2:$AJ$1500,3),'Map Calc'!$AJ$2:$AJ$1500,0)),"") | AJ7: =IFERROR(INDEX('Map Calc'!$AI$2:$AI$1500,MATCH(LARGE('Map Calc'!$AJ$2:$AJ$1500,3),'Map Calc'!$AJ$2:$AJ$1500,0)),"")
A8: Connections | B8: =SUMPRODUCT(--('Map Calc'!$W$2:$W$2500<>"")) | C8: Authored influence edges | E8: 3 | F8: =COUNTIFS('Map Calc'!$D$2:$D$1500,3) | G8: =COUNTIFS('Map Calc'!$D$2:$D$1500,3,'Map Calc'!$P$2:$P$1500,"Yes") | H8: =COUNTIFS('Map Calc'!$AI$2:$AI$1500,3) | I8: Traditional | J8: =COUNTIF('Map Calc'!$C$2:$C$1500,$I8) | K8: =COUNTIFS('Map Calc'!$C$2:$C$1500,$I8,'Map Calc'!$P$2:$P$1500,"Yes") | L8: =IF($J8=0,0,$K8/$J8) -> 0.64880952 | N8: 4 | O8: =IFERROR(INDEX('Map Calc'!$A$2:$A$1500,MATCH(LARGE('Map Calc'!$O$2:$O$1500,4),'Map Calc'!$O$2:$O$1500,0)),"") | P8: =IFERROR(INDEX('Map Calc'!$D$2:$D$1500,MATCH(LARGE('Map Calc'!$O$2:$O$1500,4),'Map Calc'!$O$2:$O$1500,0)),"") | R8: 4 | S8: =IFERROR(INDEX('Map Calc'!$A$2:$A$1500,MATCH(LARGE('Map Calc'!$Q$2:$Q$1500,4),'Map Calc'!$Q$2:$Q$1500,0)),"") | T8: =IFERROR(INDEX('Map Calc'!$D$2:$D$1500,MATCH(LARGE('Map Calc'!$Q$2:$Q$1500,4),'Map Calc'!$Q$2:$Q$1500,0)),"") | V8: 1981 | W8: =COUNTIF('Map Calc'!$B$2:$B$1500,$V8) | X8: =COUNTIFS('Map Calc'!$B$2:$B$1500,$V8,'Map Calc'!$P$2:$P$1500,"Yes") | Y8: =COUNTIF('Map Calc'!$T$2:$T$2500,$V8) | AA8: 3 | AB8: =COUNTIF('Map Calc'!$V$2:$V$2500,$AA8) | AD8: 4 | AE8: =IFERROR(INDEX('Map Calc'!$A$2:$A$1500,MATCH(LARGE('Map Calc'!$AK$2:$AK$1500,4),'Map Calc'!$AK$2:$AK$1500,0)),"") | AF8: =IFERROR(INDEX('Map Calc'!$AG$2:$AG$1500,MATCH(LARGE('Map Calc'!$AK$2:$AK$1500,4),'Map Calc'!$AK$2:$AK$1500,0)),"") | AH8: 4 | AI8: =IFERROR(INDEX('Map Calc'!$A$2:$A$1500,MATCH(LARGE('Map Calc'!$AJ$2:$AJ$1500,4),'Map Calc'!$AJ$2:$AJ$1500,0)),"") | AJ8: =IFERROR(INDEX('Map Calc'!$AI$2:$AI$1500,MATCH(LARGE('Map Calc'!$AJ$2:$AJ$1500,4),'Map Calc'!$AJ$2:$AJ$1500,0)),"")
A9: Average degree | B9: =IF(B5=0,0,2*B8/B5) | C9: Connections per game — under 3 means a sparse graph | E9: 4 | F9: =COUNTIFS('Map Calc'!$D$2:$D$1500,4) | G9: =COUNTIFS('Map Calc'!$D$2:$D$1500,4,'Map Calc'!$P$2:$P$1500,"Yes") | H9: =COUNTIFS('Map Calc'!$AI$2:$AI$1500,4) | I9: All | J9: =SUM(J5:J8) -> 953 | K9: =SUM(K5:K8) -> 594 | L9: =IF($J9=0,0,$K9/$J9) -> 0.62329486 | N9: 5 | O9: =IFERROR(INDEX('Map Calc'!$A$2:$A$1500,MATCH(LARGE('Map Calc'!$O$2:$O$1500,5),'Map Calc'!$O$2:$O$1500,0)),"") | P9: =IFERROR(INDEX('Map Calc'!$D$2:$D$1500,MATCH(LARGE('Map Calc'!$O$2:$O$1500,5),'Map Calc'!$O$2:$O$1500,0)),"") | R9: 5 | S9: =IFERROR(INDEX('Map Calc'!$A$2:$A$1500,MATCH(LARGE('Map Calc'!$Q$2:$Q$1500,5),'Map Calc'!$Q$2:$Q$1500,0)),"") | T9: =IFERROR(INDEX('Map Calc'!$D$2:$D$1500,MATCH(LARGE('Map Calc'!$Q$2:$Q$1500,5),'Map Calc'!$Q$2:$Q$1500,0)),"") | V9: 1982 | W9: =COUNTIF('Map Calc'!$B$2:$B$1500,$V9) | X9: =COUNTIFS('Map Calc'!$B$2:$B$1500,$V9,'Map Calc'!$P$2:$P$1500,"Yes") | Y9: =COUNTIF('Map Calc'!$T$2:$T$2500,$V9) | AA9: 4 | AB9: =COUNTIF('Map Calc'!$V$2:$V$2500,$AA9) | AD9: 5 | AE9: =IFERROR(INDEX('Map Calc'!$A$2:$A$1500,MATCH(LARGE('Map Calc'!$AK$2:$AK$1500,5),'Map Calc'!$AK$2:$AK$1500,0)),"") | AF9: =IFERROR(INDEX('Map Calc'!$AG$2:$AG$1500,MATCH(LARGE('Map Calc'!$AK$2:$AK$1500,5),'Map Calc'!$AK$2:$AK$1500,0)),"") | AH9: 5 | AI9: =IFERROR(INDEX('Map Calc'!$A$2:$A$1500,MATCH(LARGE('Map Calc'!$AJ$2:$AJ$1500,5),'Map Calc'!$AJ$2:$AJ$1500,0)),"") | AJ9: =IFERROR(INDEX('Map Calc'!$AI$2:$AI$1500,MATCH(LARGE('Map Calc'!$AJ$2:$AJ$1500,5),'Map Calc'!$AJ$2:$AJ$1500,0)),"")
A10: Average degree (owned) | B10: =IFERROR(SUMIFS('Map Calc'!$D$2:$D$1500,'Map Calc'!$P$2:$P$1500,"Yes")/B6,0) | C10: Over the owned games, but still counting their links to games you don't own | E10: 5 | F10: =COUNTIFS('Map Calc'!$D$2:$D$1500,5) | G10: =COUNTIFS('Map Calc'!$D$2:$D$1500,5,'Map Calc'!$P$2:$P$1500,"Yes") | H10: =COUNTIFS('Map Calc'!$AI$2:$AI$1500,5) | N10: 6 | O10: =IFERROR(INDEX('Map Calc'!$A$2:$A$1500,MATCH(LARGE('Map Calc'!$O$2:$O$1500,6),'Map Calc'!$O$2:$O$1500,0)),"") | P10: =IFERROR(INDEX('Map Calc'!$D$2:$D$1500,MATCH(LARGE('Map Calc'!$O$2:$O$1500,6),'Map Calc'!$O$2:$O$1500,0)),"") | R10: 6 | S10: =IFERROR(INDEX('Map Calc'!$A$2:$A$1500,MATCH(LARGE('Map Calc'!$Q$2:$Q$1500,6),'Map Calc'!$Q$2:$Q$1500,0)),"") | T10: =IFERROR(INDEX('Map Calc'!$D$2:$D$1500,MATCH(LARGE('Map Calc'!$Q$2:$Q$1500,6),'Map Calc'!$Q$2:$Q$1500,0)),"") | V10: 1983 | W10: =COUNTIF('Map Calc'!$B$2:$B$1500,$V10) | X10: =COUNTIFS('Map Calc'!$B$2:$B$1500,$V10,'Map Calc'!$P$2:$P$1500,"Yes") | Y10: =COUNTIF('Map Calc'!$T$2:$T$2500,$V10) | AA10: 5 | AB10: =COUNTIF('Map Calc'!$V$2:$V$2500,$AA10) | AD10: 6 | AE10: =IFERROR(INDEX('Map Calc'!$A$2:$A$1500,MATCH(LARGE('Map Calc'!$AK$2:$AK$1500,6),'Map Calc'!$AK$2:$AK$1500,0)),"") | AF10: =IFERROR(INDEX('Map Calc'!$AG$2:$AG$1500,MATCH(LARGE('Map Calc'!$AK$2:$AK$1500,6),'Map Calc'!$AK$2:$AK$1500,0)),"") | AH10: 6 | AI10: =IFERROR(INDEX('Map Calc'!$A$2:$A$1500,MATCH(LARGE('Map Calc'!$AJ$2:$AJ$1500,6),'Map Calc'!$AJ$2:$AJ$1500,0)),"") | AJ10: =IFERROR(INDEX('Map Calc'!$AI$2:$AI$1500,MATCH(LARGE('Map Calc'!$AJ$2:$AJ$1500,6),'Map Calc'!$AJ$2:$AJ$1500,0)),"")
A11: Median degree | B11: =MEDIAN('Map Calc'!$D$2:$D$1500) | C11: Half of all games sit at or below this | E11: 6-9 | F11: =COUNTIFS('Map Calc'!$D$2:$D$1500,">=6",'Map Calc'!$D$2:$D$1500,"<=9") | G11: =COUNTIFS('Map Calc'!$D$2:$D$1500,">=6",'Map Calc'!$D$2:$D$1500,"<=9",'Map Calc'!$P$2:$P$1500,"Yes") | H11: =COUNTIFS('Map Calc'!$AI$2:$AI$1500,">=6",'Map Calc'!$AI$2:$AI$1500,"<=9") | N11: 7 | O11: =IFERROR(INDEX('Map Calc'!$A$2:$A$1500,MATCH(LARGE('Map Calc'!$O$2:$O$1500,7),'Map Calc'!$O$2:$O$1500,0)),"") | P11: =IFERROR(INDEX('Map Calc'!$D$2:$D$1500,MATCH(LARGE('Map Calc'!$O$2:$O$1500,7),'Map Calc'!$O$2:$O$1500,0)),"") | R11: 7 | S11: =IFERROR(INDEX('Map Calc'!$A$2:$A$1500,MATCH(LARGE('Map Calc'!$Q$2:$Q$1500,7),'Map Calc'!$Q$2:$Q$1500,0)),"") | T11: =IFERROR(INDEX('Map Calc'!$D$2:$D$1500,MATCH(LARGE('Map Calc'!$Q$2:$Q$1500,7),'Map Calc'!$Q$2:$Q$1500,0)),"") | V11: 1984 | W11: =COUNTIF('Map Calc'!$B$2:$B$1500,$V11) | X11: =COUNTIFS('Map Calc'!$B$2:$B$1500,$V11,'Map Calc'!$P$2:$P$1500,"Yes") | Y11: =COUNTIF('Map Calc'!$T$2:$T$2500,$V11) | AA11: 6 | AB11: =COUNTIF('Map Calc'!$V$2:$V$2500,$AA11) | AD11: 7 | AE11: =IFERROR(INDEX('Map Calc'!$A$2:$A$1500,MATCH(LARGE('Map Calc'!$AK$2:$AK$1500,7),'Map Calc'!$AK$2:$AK$1500,0)),"") | AF11: =IFERROR(INDEX('Map Calc'!$AG$2:$AG$1500,MATCH(LARGE('Map Calc'!$AK$2:$AK$1500,7),'Map Calc'!$AK$2:$AK$1500,0)),"") | AH11: 7 | AI11: =IFERROR(INDEX('Map Calc'!$A$2:$A$1500,MATCH(LARGE('Map Calc'!$AJ$2:$AJ$1500,7),'Map Calc'!$AJ$2:$AJ$1500,0)),"") | AJ11: =IFERROR(INDEX('Map Calc'!$AI$2:$AI$1500,MATCH(LARGE('Map Calc'!$AJ$2:$AJ$1500,7),'Map Calc'!$AJ$2:$AJ$1500,0)),"")
A12: Largest hub | B12: =MAX('Map Calc'!$D$2:$D$1500) | C12: Degree of the single most connected game | E12: 10-24 | F12: =COUNTIFS('Map Calc'!$D$2:$D$1500,">=10",'Map Calc'!$D$2:$D$1500,"<=24") | G12: =COUNTIFS('Map Calc'!$D$2:$D$1500,">=10",'Map Calc'!$D$2:$D$1500,"<=24",'Map Calc'!$P$2:$P$1500,"Yes") | H12: =COUNTIFS('Map Calc'!$AI$2:$AI$1500,">=10",'Map Calc'!$AI$2:$AI$1500,"<=24") | N12: 8 | O12: =IFERROR(INDEX('Map Calc'!$A$2:$A$1500,MATCH(LARGE('Map Calc'!$O$2:$O$1500,8),'Map Calc'!$O$2:$O$1500,0)),"") | P12: =IFERROR(INDEX('Map Calc'!$D$2:$D$1500,MATCH(LARGE('Map Calc'!$O$2:$O$1500,8),'Map Calc'!$O$2:$O$1500,0)),"") | R12: 8 | S12: =IFERROR(INDEX('Map Calc'!$A$2:$A$1500,MATCH(LARGE('Map Calc'!$Q$2:$Q$1500,8),'Map Calc'!$Q$2:$Q$1500,0)),"") | T12: =IFERROR(INDEX('Map Calc'!$D$2:$D$1500,MATCH(LARGE('Map Calc'!$Q$2:$Q$1500,8),'Map Calc'!$Q$2:$Q$1500,0)),"") | V12: 1985 | W12: =COUNTIF('Map Calc'!$B$2:$B$1500,$V12) | X12: =COUNTIFS('Map Calc'!$B$2:$B$1500,$V12,'Map Calc'!$P$2:$P$1500,"Yes") | Y12: =COUNTIF('Map Calc'!$T$2:$T$2500,$V12) | AA12: 7 | AB12: =COUNTIF('Map Calc'!$V$2:$V$2500,$AA12) | AD12: 8 | AE12: =IFERROR(INDEX('Map Calc'!$A$2:$A$1500,MATCH(LARGE('Map Calc'!$AK$2:$AK$1500,8),'Map Calc'!$AK$2:$AK$1500,0)),"") | AF12: =IFERROR(INDEX('Map Calc'!$AG$2:$AG$1500,MATCH(LARGE('Map Calc'!$AK$2:$AK$1500,8),'Map Calc'!$AK$2:$AK$1500,0)),"") | AH12: 8 | AI12: =IFERROR(INDEX('Map Calc'!$A$2:$A$1500,MATCH(LARGE('Map Calc'!$AJ$2:$AJ$1500,8),'Map Calc'!$AJ$2:$AJ$1500,0)),"") | AJ12: =IFERROR(INDEX('Map Calc'!$AI$2:$AI$1500,MATCH(LARGE('Map Calc'!$AJ$2:$AJ$1500,8),'Map Calc'!$AJ$2:$AJ$1500,0)),"")
A13: Leaves (degree 1) | B13: =COUNTIF('Map Calc'!$D$2:$D$1500,1) | C13: Dead ends — one way in, the same way out | E13: 25+ | F13: =COUNTIFS('Map Calc'!$D$2:$D$1500,">=25") | G13: =COUNTIFS('Map Calc'!$D$2:$D$1500,">=25",'Map Calc'!$P$2:$P$1500,"Yes") | H13: =COUNTIFS('Map Calc'!$AI$2:$AI$1500,">=25") | N13: 9 | O13: =IFERROR(INDEX('Map Calc'!$A$2:$A$1500,MATCH(LARGE('Map Calc'!$O$2:$O$1500,9),'Map Calc'!$O$2:$O$1500,0)),"") | P13: =IFERROR(INDEX('Map Calc'!$D$2:$D$1500,MATCH(LARGE('Map Calc'!$O$2:$O$1500,9),'Map Calc'!$O$2:$O$1500,0)),"") | R13: 9 | S13: =IFERROR(INDEX('Map Calc'!$A$2:$A$1500,MATCH(LARGE('Map Calc'!$Q$2:$Q$1500,9),'Map Calc'!$Q$2:$Q$1500,0)),"") | T13: =IFERROR(INDEX('Map Calc'!$D$2:$D$1500,MATCH(LARGE('Map Calc'!$Q$2:$Q$1500,9),'Map Calc'!$Q$2:$Q$1500,0)),"") | V13: 1986 | W13: =COUNTIF('Map Calc'!$B$2:$B$1500,$V13) | X13: =COUNTIFS('Map Calc'!$B$2:$B$1500,$V13,'Map Calc'!$P$2:$P$1500,"Yes") | Y13: =COUNTIF('Map Calc'!$T$2:$T$2500,$V13) | AA13: 8 | AB13: =COUNTIF('Map Calc'!$V$2:$V$2500,$AA13) | AD13: 9 | AE13: =IFERROR(INDEX('Map Calc'!$A$2:$A$1500,MATCH(LARGE('Map Calc'!$AK$2:$AK$1500,9),'Map Calc'!$AK$2:$AK$1500,0)),"") | AF13: =IFERROR(INDEX('Map Calc'!$AG$2:$AG$1500,MATCH(LARGE('Map Calc'!$AK$2:$AK$1500,9),'Map Calc'!$AK$2:$AK$1500,0)),"") | AH13: 9 | AI13: =IFERROR(INDEX('Map Calc'!$A$2:$A$1500,MATCH(LARGE('Map Calc'!$AJ$2:$AJ$1500,9),'Map Calc'!$AJ$2:$AJ$1500,0)),"") | AJ13: =IFERROR(INDEX('Map Calc'!$AI$2:$AI$1500,MATCH(LARGE('Map Calc'!$AJ$2:$AJ$1500,9),'Map Calc'!$AJ$2:$AJ$1500,0)),"")
A14: Isolated (degree 0) | B14: =COUNTIF('Map Calc'!$D$2:$D$1500,0) | C14: No connection at all; only a rift or Transmute ever puts one in a run | N14: 10 | O14: =IFERROR(INDEX('Map Calc'!$A$2:$A$1500,MATCH(LARGE('Map Calc'!$O$2:$O$1500,10),'Map Calc'!$O$2:$O$1500,0)),"") | P14: =IFERROR(INDEX('Map Calc'!$D$2:$D$1500,MATCH(LARGE('Map Calc'!$O$2:$O$1500,10),'Map Calc'!$O$2:$O$1500,0)),"") | R14: 10 | S14: =IFERROR(INDEX('Map Calc'!$A$2:$A$1500,MATCH(LARGE('Map Calc'!$Q$2:$Q$1500,10),'Map Calc'!$Q$2:$Q$1500,0)),"") | T14: =IFERROR(INDEX('Map Calc'!$D$2:$D$1500,MATCH(LARGE('Map Calc'!$Q$2:$Q$1500,10),'Map Calc'!$Q$2:$Q$1500,0)),"") | V14: 1987 | W14: =COUNTIF('Map Calc'!$B$2:$B$1500,$V14) | X14: =COUNTIFS('Map Calc'!$B$2:$B$1500,$V14,'Map Calc'!$P$2:$P$1500,"Yes") | Y14: =COUNTIF('Map Calc'!$T$2:$T$2500,$V14) | AA14: 9 | AB14: =COUNTIF('Map Calc'!$V$2:$V$2500,$AA14) | AD14: 10 | AE14: =IFERROR(INDEX('Map Calc'!$A$2:$A$1500,MATCH(LARGE('Map Calc'!$AK$2:$AK$1500,10),'Map Calc'!$AK$2:$AK$1500,0)),"") | AF14: =IFERROR(INDEX('Map Calc'!$AG$2:$AG$1500,MATCH(LARGE('Map Calc'!$AK$2:$AK$1500,10),'Map Calc'!$AK$2:$AK$1500,0)),"") | AH14: 10 | AI14: =IFERROR(INDEX('Map Calc'!$A$2:$A$1500,MATCH(LARGE('Map Calc'!$AJ$2:$AJ$1500,10),'Map Calc'!$AJ$2:$AJ$1500,0)),"") | AJ14: =IFERROR(INDEX('Map Calc'!$AI$2:$AI$1500,MATCH(LARGE('Map Calc'!$AJ$2:$AJ$1500,10),'Map Calc'!$AJ$2:$AJ$1500,0)),"")
A15: Leaves + isolated | B15: =B13+B14 | C15: Share of the map that carries no routing information | N15: 11 | O15: =IFERROR(INDEX('Map Calc'!$A$2:$A$1500,MATCH(LARGE('Map Calc'!$O$2:$O$1500,11),'Map Calc'!$O$2:$O$1500,0)),"") | P15: =IFERROR(INDEX('Map Calc'!$D$2:$D$1500,MATCH(LARGE('Map Calc'!$O$2:$O$1500,11),'Map Calc'!$O$2:$O$1500,0)),"") | R15: 11 | S15: =IFERROR(INDEX('Map Calc'!$A$2:$A$1500,MATCH(LARGE('Map Calc'!$Q$2:$Q$1500,11),'Map Calc'!$Q$2:$Q$1500,0)),"") | T15: =IFERROR(INDEX('Map Calc'!$D$2:$D$1500,MATCH(LARGE('Map Calc'!$Q$2:$Q$1500,11),'Map Calc'!$Q$2:$Q$1500,0)),"") | V15: 1988 | W15: =COUNTIF('Map Calc'!$B$2:$B$1500,$V15) | X15: =COUNTIFS('Map Calc'!$B$2:$B$1500,$V15,'Map Calc'!$P$2:$P$1500,"Yes") | Y15: =COUNTIF('Map Calc'!$T$2:$T$2500,$V15) | AA15: 10 | AB15: =COUNTIF('Map Calc'!$V$2:$V$2500,$AA15) | AD15: 11 | AE15: =IFERROR(INDEX('Map Calc'!$A$2:$A$1500,MATCH(LARGE('Map Calc'!$AK$2:$AK$1500,11),'Map Calc'!$AK$2:$AK$1500,0)),"") | AF15: =IFERROR(INDEX('Map Calc'!$AG$2:$AG$1500,MATCH(LARGE('Map Calc'!$AK$2:$AK$1500,11),'Map Calc'!$AK$2:$AK$1500,0)),"") | AH15: 11 | AI15: =IFERROR(INDEX('Map Calc'!$A$2:$A$1500,MATCH(LARGE('Map Calc'!$AJ$2:$AJ$1500,11),'Map Calc'!$AJ$2:$AJ$1500,0)),"") | AJ15: =IFERROR(INDEX('Map Calc'!$AI$2:$AI$1500,MATCH(LARGE('Map Calc'!$AJ$2:$AJ$1500,11),'Map Calc'!$AJ$2:$AJ$1500,0)),"")
A16: Owned & routable | B16: =COUNTIFS('Map Calc'!$P$2:$P$1500,"Yes",'Map Calc'!$D$2:$D$1500,">1") | C16: Owned games with more than one way out — real junctions on a route | N16: 12 | O16: =IFERROR(INDEX('Map Calc'!$A$2:$A$1500,MATCH(LARGE('Map Calc'!$O$2:$O$1500,12),'Map Calc'!$O$2:$O$1500,0)),"") | P16: =IFERROR(INDEX('Map Calc'!$D$2:$D$1500,MATCH(LARGE('Map Calc'!$O$2:$O$1500,12),'Map Calc'!$O$2:$O$1500,0)),"") | R16: 12 | S16: =IFERROR(INDEX('Map Calc'!$A$2:$A$1500,MATCH(LARGE('Map Calc'!$Q$2:$Q$1500,12),'Map Calc'!$Q$2:$Q$1500,0)),"") | T16: =IFERROR(INDEX('Map Calc'!$D$2:$D$1500,MATCH(LARGE('Map Calc'!$Q$2:$Q$1500,12),'Map Calc'!$Q$2:$Q$1500,0)),"") | V16: 1989 | W16: =COUNTIF('Map Calc'!$B$2:$B$1500,$V16) | X16: =COUNTIFS('Map Calc'!$B$2:$B$1500,$V16,'Map Calc'!$P$2:$P$1500,"Yes") | Y16: =COUNTIF('Map Calc'!$T$2:$T$2500,$V16) | AA16: 11-20 | AB16: =COUNTIFS('Map Calc'!$V$2:$V$2500,">=11",'Map Calc'!$V$2:$V$2500,"<=20") | AD16: 12 | AE16: =IFERROR(INDEX('Map Calc'!$A$2:$A$1500,MATCH(LARGE('Map Calc'!$AK$2:$AK$1500,12),'Map Calc'!$AK$2:$AK$1500,0)),"") | AF16: =IFERROR(INDEX('Map Calc'!$AG$2:$AG$1500,MATCH(LARGE('Map Calc'!$AK$2:$AK$1500,12),'Map Calc'!$AK$2:$AK$1500,0)),"") | AH16: 12 | AI16: =IFERROR(INDEX('Map Calc'!$A$2:$A$1500,MATCH(LARGE('Map Calc'!$AJ$2:$AJ$1500,12),'Map Calc'!$AJ$2:$AJ$1500,0)),"") | AJ16: =IFERROR(INDEX('Map Calc'!$AI$2:$AI$1500,MATCH(LARGE('Map Calc'!$AJ$2:$AJ$1500,12),'Map Calc'!$AJ$2:$AJ$1500,0)),"")
A17: Owned dead ends | B17: =COUNTIFS('Map Calc'!$P$2:$P$1500,"Yes",'Map Calc'!$D$2:$D$1500,"<=1") | C17: Owned games the run can only reach and turn around in | N17: 13 | O17: =IFERROR(INDEX('Map Calc'!$A$2:$A$1500,MATCH(LARGE('Map Calc'!$O$2:$O$1500,13),'Map Calc'!$O$2:$O$1500,0)),"") | P17: =IFERROR(INDEX('Map Calc'!$D$2:$D$1500,MATCH(LARGE('Map Calc'!$O$2:$O$1500,13),'Map Calc'!$O$2:$O$1500,0)),"") | R17: 13 | S17: =IFERROR(INDEX('Map Calc'!$A$2:$A$1500,MATCH(LARGE('Map Calc'!$Q$2:$Q$1500,13),'Map Calc'!$Q$2:$Q$1500,0)),"") | T17: =IFERROR(INDEX('Map Calc'!$D$2:$D$1500,MATCH(LARGE('Map Calc'!$Q$2:$Q$1500,13),'Map Calc'!$Q$2:$Q$1500,0)),"") | V17: 1990 | W17: =COUNTIF('Map Calc'!$B$2:$B$1500,$V17) | X17: =COUNTIFS('Map Calc'!$B$2:$B$1500,$V17,'Map Calc'!$P$2:$P$1500,"Yes") | Y17: =COUNTIF('Map Calc'!$T$2:$T$2500,$V17) | AA17: 21+ | AB17: =COUNTIF('Map Calc'!$V$2:$V$2500,">=21") | AD17: 13 | AE17: =IFERROR(INDEX('Map Calc'!$A$2:$A$1500,MATCH(LARGE('Map Calc'!$AK$2:$AK$1500,13),'Map Calc'!$AK$2:$AK$1500,0)),"") | AF17: =IFERROR(INDEX('Map Calc'!$AG$2:$AG$1500,MATCH(LARGE('Map Calc'!$AK$2:$AK$1500,13),'Map Calc'!$AK$2:$AK$1500,0)),"") | AH17: 13 | AI17: =IFERROR(INDEX('Map Calc'!$A$2:$A$1500,MATCH(LARGE('Map Calc'!$AJ$2:$AJ$1500,13),'Map Calc'!$AJ$2:$AJ$1500,0)),"") | AJ17: =IFERROR(INDEX('Map Calc'!$AI$2:$AI$1500,MATCH(LARGE('Map Calc'!$AJ$2:$AJ$1500,13),'Map Calc'!$AJ$2:$AJ$1500,0)),"")
A18: Backward in time | B18: =SUMPRODUCT(('Map Calc'!$V$2:$V$2500<>"")*('Map Calc'!$V$2:$V$2500<0)) | C18: MUST BE 0 — an influence cannot point at an older game | N18: 14 | O18: =IFERROR(INDEX('Map Calc'!$A$2:$A$1500,MATCH(LARGE('Map Calc'!$O$2:$O$1500,14),'Map Calc'!$O$2:$O$1500,0)),"") | P18: =IFERROR(INDEX('Map Calc'!$D$2:$D$1500,MATCH(LARGE('Map Calc'!$O$2:$O$1500,14),'Map Calc'!$O$2:$O$1500,0)),"") | R18: 14 | S18: =IFERROR(INDEX('Map Calc'!$A$2:$A$1500,MATCH(LARGE('Map Calc'!$Q$2:$Q$1500,14),'Map Calc'!$Q$2:$Q$1500,0)),"") | T18: =IFERROR(INDEX('Map Calc'!$D$2:$D$1500,MATCH(LARGE('Map Calc'!$Q$2:$Q$1500,14),'Map Calc'!$Q$2:$Q$1500,0)),"") | V18: 1991 | W18: =COUNTIF('Map Calc'!$B$2:$B$1500,$V18) | X18: =COUNTIFS('Map Calc'!$B$2:$B$1500,$V18,'Map Calc'!$P$2:$P$1500,"Yes") | Y18: =COUNTIF('Map Calc'!$T$2:$T$2500,$V18) | AD18: 14 | AE18: =IFERROR(INDEX('Map Calc'!$A$2:$A$1500,MATCH(LARGE('Map Calc'!$AK$2:$AK$1500,14),'Map Calc'!$AK$2:$AK$1500,0)),"") | AF18: =IFERROR(INDEX('Map Calc'!$AG$2:$AG$1500,MATCH(LARGE('Map Calc'!$AK$2:$AK$1500,14),'Map Calc'!$AK$2:$AK$1500,0)),"") | AH18: 14 | AI18: =IFERROR(INDEX('Map Calc'!$A$2:$A$1500,MATCH(LARGE('Map Calc'!$AJ$2:$AJ$1500,14),'Map Calc'!$AJ$2:$AJ$1500,0)),"") | AJ18: =IFERROR(INDEX('Map Calc'!$AI$2:$AI$1500,MATCH(LARGE('Map Calc'!$AJ$2:$AJ$1500,14),'Map Calc'!$AJ$2:$AJ$1500,0)),"")
A19: Same year | B19: =SUMPRODUCT(('Map Calc'!$V$2:$V$2500<>"")*('Map Calc'!$V$2:$V$2500=0)) | C19: Legal: a demo influencing something shipped the same year | N19: 15 | O19: =IFERROR(INDEX('Map Calc'!$A$2:$A$1500,MATCH(LARGE('Map Calc'!$O$2:$O$1500,15),'Map Calc'!$O$2:$O$1500,0)),"") | P19: =IFERROR(INDEX('Map Calc'!$D$2:$D$1500,MATCH(LARGE('Map Calc'!$O$2:$O$1500,15),'Map Calc'!$O$2:$O$1500,0)),"") | R19: 15 | S19: =IFERROR(INDEX('Map Calc'!$A$2:$A$1500,MATCH(LARGE('Map Calc'!$Q$2:$Q$1500,15),'Map Calc'!$Q$2:$Q$1500,0)),"") | T19: =IFERROR(INDEX('Map Calc'!$D$2:$D$1500,MATCH(LARGE('Map Calc'!$Q$2:$Q$1500,15),'Map Calc'!$Q$2:$Q$1500,0)),"") | V19: 1992 | W19: =COUNTIF('Map Calc'!$B$2:$B$1500,$V19) | X19: =COUNTIFS('Map Calc'!$B$2:$B$1500,$V19,'Map Calc'!$P$2:$P$1500,"Yes") | Y19: =COUNTIF('Map Calc'!$T$2:$T$2500,$V19) | AD19: 15 | AE19: =IFERROR(INDEX('Map Calc'!$A$2:$A$1500,MATCH(LARGE('Map Calc'!$AK$2:$AK$1500,15),'Map Calc'!$AK$2:$AK$1500,0)),"") | AF19: =IFERROR(INDEX('Map Calc'!$AG$2:$AG$1500,MATCH(LARGE('Map Calc'!$AK$2:$AK$1500,15),'Map Calc'!$AK$2:$AK$1500,0)),"") | AH19: 15 | AI19: =IFERROR(INDEX('Map Calc'!$A$2:$A$1500,MATCH(LARGE('Map Calc'!$AJ$2:$AJ$1500,15),'Map Calc'!$AJ$2:$AJ$1500,0)),"") | AJ19: =IFERROR(INDEX('Map Calc'!$AI$2:$AI$1500,MATCH(LARGE('Map Calc'!$AJ$2:$AJ$1500,15),'Map Calc'!$AJ$2:$AJ$1500,0)),"")
A20: Median edge span | B20: =MEDIAN('Map Calc'!$V$2:$V$2500) | C20: Years between an influencer and what it influenced | N20: 16 | O20: =IFERROR(INDEX('Map Calc'!$A$2:$A$1500,MATCH(LARGE('Map Calc'!$O$2:$O$1500,16),'Map Calc'!$O$2:$O$1500,0)),"") | P20: =IFERROR(INDEX('Map Calc'!$D$2:$D$1500,MATCH(LARGE('Map Calc'!$O$2:$O$1500,16),'Map Calc'!$O$2:$O$1500,0)),"") | R20: 16 | S20: =IFERROR(INDEX('Map Calc'!$A$2:$A$1500,MATCH(LARGE('Map Calc'!$Q$2:$Q$1500,16),'Map Calc'!$Q$2:$Q$1500,0)),"") | T20: =IFERROR(INDEX('Map Calc'!$D$2:$D$1500,MATCH(LARGE('Map Calc'!$Q$2:$Q$1500,16),'Map Calc'!$Q$2:$Q$1500,0)),"") | V20: 1993 | W20: =COUNTIF('Map Calc'!$B$2:$B$1500,$V20) | X20: =COUNTIFS('Map Calc'!$B$2:$B$1500,$V20,'Map Calc'!$P$2:$P$1500,"Yes") | Y20: =COUNTIF('Map Calc'!$T$2:$T$2500,$V20) | AD20: 16 | AE20: =IFERROR(INDEX('Map Calc'!$A$2:$A$1500,MATCH(LARGE('Map Calc'!$AK$2:$AK$1500,16),'Map Calc'!$AK$2:$AK$1500,0)),"") | AF20: =IFERROR(INDEX('Map Calc'!$AG$2:$AG$1500,MATCH(LARGE('Map Calc'!$AK$2:$AK$1500,16),'Map Calc'!$AK$2:$AK$1500,0)),"") | AH20: 16 | AI20: =IFERROR(INDEX('Map Calc'!$A$2:$A$1500,MATCH(LARGE('Map Calc'!$AJ$2:$AJ$1500,16),'Map Calc'!$AJ$2:$AJ$1500,0)),"") | AJ20: =IFERROR(INDEX('Map Calc'!$AI$2:$AI$1500,MATCH(LARGE('Map Calc'!$AJ$2:$AJ$1500,16),'Map Calc'!$AJ$2:$AJ$1500,0)),"")
A21: Dev/Series flagged | B21: =COUNTIF(connections!$D:$D,"Yes") | C21: Sequel / same-devs links, distinct from plain influence | N21: 17 | O21: =IFERROR(INDEX('Map Calc'!$A$2:$A$1500,MATCH(LARGE('Map Calc'!$O$2:$O$1500,17),'Map Calc'!$O$2:$O$1500,0)),"") | P21: =IFERROR(INDEX('Map Calc'!$D$2:$D$1500,MATCH(LARGE('Map Calc'!$O$2:$O$1500,17),'Map Calc'!$O$2:$O$1500,0)),"") | R21: 17 | S21: =IFERROR(INDEX('Map Calc'!$A$2:$A$1500,MATCH(LARGE('Map Calc'!$Q$2:$Q$1500,17),'Map Calc'!$Q$2:$Q$1500,0)),"") | T21: =IFERROR(INDEX('Map Calc'!$D$2:$D$1500,MATCH(LARGE('Map Calc'!$Q$2:$Q$1500,17),'Map Calc'!$Q$2:$Q$1500,0)),"") | V21: 1994 | W21: =COUNTIF('Map Calc'!$B$2:$B$1500,$V21) | X21: =COUNTIFS('Map Calc'!$B$2:$B$1500,$V21,'Map Calc'!$P$2:$P$1500,"Yes") | Y21: =COUNTIF('Map Calc'!$T$2:$T$2500,$V21) | AD21: 17 | AE21: =IFERROR(INDEX('Map Calc'!$A$2:$A$1500,MATCH(LARGE('Map Calc'!$AK$2:$AK$1500,17),'Map Calc'!$AK$2:$AK$1500,0)),"") | AF21: =IFERROR(INDEX('Map Calc'!$AG$2:$AG$1500,MATCH(LARGE('Map Calc'!$AK$2:$AK$1500,17),'Map Calc'!$AK$2:$AK$1500,0)),"") | AH21: 17 | AI21: =IFERROR(INDEX('Map Calc'!$A$2:$A$1500,MATCH(LARGE('Map Calc'!$AJ$2:$AJ$1500,17),'Map Calc'!$AJ$2:$AJ$1500,0)),"") | AJ21: =IFERROR(INDEX('Map Calc'!$AI$2:$AI$1500,MATCH(LARGE('Map Calc'!$AJ$2:$AJ$1500,17),'Map Calc'!$AJ$2:$AJ$1500,0)),"")
A22: With a source | B22: =COUNTA(connections!$E:$E)-COUNTA(connections!$E$1) | C22: Connections carrying a URL or note as evidence | N22: 18 | O22: =IFERROR(INDEX('Map Calc'!$A$2:$A$1500,MATCH(LARGE('Map Calc'!$O$2:$O$1500,18),'Map Calc'!$O$2:$O$1500,0)),"") | P22: =IFERROR(INDEX('Map Calc'!$D$2:$D$1500,MATCH(LARGE('Map Calc'!$O$2:$O$1500,18),'Map Calc'!$O$2:$O$1500,0)),"") | R22: 18 | S22: =IFERROR(INDEX('Map Calc'!$A$2:$A$1500,MATCH(LARGE('Map Calc'!$Q$2:$Q$1500,18),'Map Calc'!$Q$2:$Q$1500,0)),"") | T22: =IFERROR(INDEX('Map Calc'!$D$2:$D$1500,MATCH(LARGE('Map Calc'!$Q$2:$Q$1500,18),'Map Calc'!$Q$2:$Q$1500,0)),"") | V22: 1995 | W22: =COUNTIF('Map Calc'!$B$2:$B$1500,$V22) | X22: =COUNTIFS('Map Calc'!$B$2:$B$1500,$V22,'Map Calc'!$P$2:$P$1500,"Yes") | Y22: =COUNTIF('Map Calc'!$T$2:$T$2500,$V22) | AD22: 18 | AE22: =IFERROR(INDEX('Map Calc'!$A$2:$A$1500,MATCH(LARGE('Map Calc'!$AK$2:$AK$1500,18),'Map Calc'!$AK$2:$AK$1500,0)),"") | AF22: =IFERROR(INDEX('Map Calc'!$AG$2:$AG$1500,MATCH(LARGE('Map Calc'!$AK$2:$AK$1500,18),'Map Calc'!$AK$2:$AK$1500,0)),"") | AH22: 18 | AI22: =IFERROR(INDEX('Map Calc'!$A$2:$A$1500,MATCH(LARGE('Map Calc'!$AJ$2:$AJ$1500,18),'Map Calc'!$AJ$2:$AJ$1500,0)),"") | AJ22: =IFERROR(INDEX('Map Calc'!$AI$2:$AI$1500,MATCH(LARGE('Map Calc'!$AJ$2:$AJ$1500,18),'Map Calc'!$AJ$2:$AJ$1500,0)),"")
A23: Owned, no Steam page | B23: =COUNTIFS('Map Calc'!$P$2:$P$1500,"Yes",'Map Calc'!$AL$2:$AL$1500,"") | C23: Owned rows with nothing to link to — a gap in the sheet, not the graph | N23: 19 | O23: =IFERROR(INDEX('Map Calc'!$A$2:$A$1500,MATCH(LARGE('Map Calc'!$O$2:$O$1500,19),'Map Calc'!$O$2:$O$1500,0)),"") | P23: =IFERROR(INDEX('Map Calc'!$D$2:$D$1500,MATCH(LARGE('Map Calc'!$O$2:$O$1500,19),'Map Calc'!$O$2:$O$1500,0)),"") | R23: 19 | S23: =IFERROR(INDEX('Map Calc'!$A$2:$A$1500,MATCH(LARGE('Map Calc'!$Q$2:$Q$1500,19),'Map Calc'!$Q$2:$Q$1500,0)),"") | T23: =IFERROR(INDEX('Map Calc'!$D$2:$D$1500,MATCH(LARGE('Map Calc'!$Q$2:$Q$1500,19),'Map Calc'!$Q$2:$Q$1500,0)),"") | V23: 1996 | W23: =COUNTIF('Map Calc'!$B$2:$B$1500,$V23) | X23: =COUNTIFS('Map Calc'!$B$2:$B$1500,$V23,'Map Calc'!$P$2:$P$1500,"Yes") | Y23: =COUNTIF('Map Calc'!$T$2:$T$2500,$V23) | AD23: 19 | AE23: =IFERROR(INDEX('Map Calc'!$A$2:$A$1500,MATCH(LARGE('Map Calc'!$AK$2:$AK$1500,19),'Map Calc'!$AK$2:$AK$1500,0)),"") | AF23: =IFERROR(INDEX('Map Calc'!$AG$2:$AG$1500,MATCH(LARGE('Map Calc'!$AK$2:$AK$1500,19),'Map Calc'!$AK$2:$AK$1500,0)),"") | AH23: 19 | AI23: =IFERROR(INDEX('Map Calc'!$A$2:$A$1500,MATCH(LARGE('Map Calc'!$AJ$2:$AJ$1500,19),'Map Calc'!$AJ$2:$AJ$1500,0)),"") | AJ23: =IFERROR(INDEX('Map Calc'!$AI$2:$AI$1500,MATCH(LARGE('Map Calc'!$AJ$2:$AJ$1500,19),'Map Calc'!$AJ$2:$AJ$1500,0)),"")
A24: On the map | B24: Value | C24: What it means | N24: 20 | O24: =IFERROR(INDEX('Map Calc'!$A$2:$A$1500,MATCH(LARGE('Map Calc'!$O$2:$O$1500,20),'Map Calc'!$O$2:$O$1500,0)),"") | P24: =IFERROR(INDEX('Map Calc'!$D$2:$D$1500,MATCH(LARGE('Map Calc'!$O$2:$O$1500,20),'Map Calc'!$O$2:$O$1500,0)),"") | R24: 20 | S24: =IFERROR(INDEX('Map Calc'!$A$2:$A$1500,MATCH(LARGE('Map Calc'!$Q$2:$Q$1500,20),'Map Calc'!$Q$2:$Q$1500,0)),"") | T24: =IFERROR(INDEX('Map Calc'!$D$2:$D$1500,MATCH(LARGE('Map Calc'!$Q$2:$Q$1500,20),'Map Calc'!$Q$2:$Q$1500,0)),"") | V24: 1997 | W24: =COUNTIF('Map Calc'!$B$2:$B$1500,$V24) | X24: =COUNTIFS('Map Calc'!$B$2:$B$1500,$V24,'Map Calc'!$P$2:$P$1500,"Yes") | Y24: =COUNTIF('Map Calc'!$T$2:$T$2500,$V24) | AD24: 20 | AE24: =IFERROR(INDEX('Map Calc'!$A$2:$A$1500,MATCH(LARGE('Map Calc'!$AK$2:$AK$1500,20),'Map Calc'!$AK$2:$AK$1500,0)),"") | AF24: =IFERROR(INDEX('Map Calc'!$AG$2:$AG$1500,MATCH(LARGE('Map Calc'!$AK$2:$AK$1500,20),'Map Calc'!$AK$2:$AK$1500,0)),"") | AH24: 20 | AI24: =IFERROR(INDEX('Map Calc'!$A$2:$A$1500,MATCH(LARGE('Map Calc'!$AJ$2:$AJ$1500,20),'Map Calc'!$AJ$2:$AJ$1500,0)),"") | AJ24: =IFERROR(INDEX('Map Calc'!$AI$2:$AI$1500,MATCH(LARGE('Map Calc'!$AJ$2:$AJ$1500,20),'Map Calc'!$AJ$2:$AJ$1500,0)),"")
A25: Games on the map | B25: =COUNTIF('Map Calc'!$AH$2:$AH$1500,"Yes") | C25: Owned games in the main group: every game a default run's routes can reach | V25: 1998 | W25: =COUNTIF('Map Calc'!$B$2:$B$1500,$V25) | X25: =COUNTIFS('Map Calc'!$B$2:$B$1500,$V25,'Map Calc'!$P$2:$P$1500,"Yes") | Y25: =COUNTIF('Map Calc'!$T$2:$T$2500,$V25)
A26: Owned, off the map | B26: =B6-B25 | C26: Owned games no route reaches (islands and loners). Transmute's pool | V26: 1999 | W26: =COUNTIF('Map Calc'!$B$2:$B$1500,$V26) | X26: =COUNTIFS('Map Calc'!$B$2:$B$1500,$V26,'Map Calc'!$P$2:$P$1500,"Yes") | Y26: =COUNTIF('Map Calc'!$T$2:$T$2500,$V26)
A27: Rift pool | B27: =COUNTIFS('Map Calc'!$P$2:$P$1500,"Yes",'Map Calc'!$AG$2:$AG$1500,0) | C27: Owned games with no owned connection at all: what a rift can pull onto the map | V27: 2000 | W27: =COUNTIF('Map Calc'!$B$2:$B$1500,$V27) | X27: =COUNTIFS('Map Calc'!$B$2:$B$1500,$V27,'Map Calc'!$P$2:$P$1500,"Yes") | Y27: =COUNTIF('Map Calc'!$T$2:$T$2500,$V27)
A28: Connections on the map | B28: =SUM('Map Calc'!$AI$2:$AI$1500)/2 | C28: Influences with both ends on the map: the roads a run can walk | V28: 2001 | W28: =COUNTIF('Map Calc'!$B$2:$B$1500,$V28) | X28: =COUNTIFS('Map Calc'!$B$2:$B$1500,$V28,'Map Calc'!$P$2:$P$1500,"Yes") | Y28: =COUNTIF('Map Calc'!$T$2:$T$2500,$V28)
A29: Share of connections on the map | B29: =IF(B8=0,0,B28/B8) | C29: The rest touch a game you don't own, or an island | V29: 2002 | W29: =COUNTIF('Map Calc'!$B$2:$B$1500,$V29) | X29: =COUNTIFS('Map Calc'!$B$2:$B$1500,$V29,'Map Calc'!$P$2:$P$1500,"Yes") | Y29: =COUNTIF('Map Calc'!$T$2:$T$2500,$V29)
A30: Average degree on the map | B30: =IFERROR(SUM('Map Calc'!$AI$2:$AI$1500)/B25,0) | C30: Roads out of a map game, counting only roads to other map games — what a player on the map sees | V30: 2003 | W30: =COUNTIF('Map Calc'!$B$2:$B$1500,$V30) | X30: =COUNTIFS('Map Calc'!$B$2:$B$1500,$V30,'Map Calc'!$P$2:$P$1500,"Yes") | Y30: =COUNTIF('Map Calc'!$T$2:$T$2500,$V30)
A31: Median degree on the map | B31: =MEDIAN('Map Calc'!$AI$2:$AI$1500) | C31: Half of the map's games have this many roads or fewer | V31: 2004 | W31: =COUNTIF('Map Calc'!$B$2:$B$1500,$V31) | X31: =COUNTIFS('Map Calc'!$B$2:$B$1500,$V31,'Map Calc'!$P$2:$P$1500,"Yes") | Y31: =COUNTIF('Map Calc'!$T$2:$T$2500,$V31)
A32: Largest hub on the map | B32: =MAX('Map Calc'!$AI$2:$AI$1500) | C32: The most roads out of any one map game (see the table under AH) | V32: 2005 | W32: =COUNTIF('Map Calc'!$B$2:$B$1500,$V32) | X32: =COUNTIFS('Map Calc'!$B$2:$B$1500,$V32,'Map Calc'!$P$2:$P$1500,"Yes") | Y32: =COUNTIF('Map Calc'!$T$2:$T$2500,$V32)
A33: Dead ends on the map | B33: =COUNTIF('Map Calc'!$AI$2:$AI$1500,1) | C33: One road in and out. Two off the same hub are where a rift usually goes | V33: 2006 | W33: =COUNTIF('Map Calc'!$B$2:$B$1500,$V33) | X33: =COUNTIFS('Map Calc'!$B$2:$B$1500,$V33,'Map Calc'!$P$2:$P$1500,"Yes") | Y33: =COUNTIF('Map Calc'!$T$2:$T$2500,$V33)
A34: Dead-end share on the map | B34: =IF(B25=0,0,B33/B25) | C34: How much of the map is a cul-de-sac | V34: 2007 | W34: =COUNTIF('Map Calc'!$B$2:$B$1500,$V34) | X34: =COUNTIFS('Map Calc'!$B$2:$B$1500,$V34,'Map Calc'!$P$2:$P$1500,"Yes") | Y34: =COUNTIF('Map Calc'!$T$2:$T$2500,$V34)
A35: Unowned games touching the map | B35: =COUNTIF('Map Calc'!$AK$2:$AK$1500,">0") | C35: Games you don't own with a connection to one you do (best buys under AD) | V35: 2008 | W35: =COUNTIF('Map Calc'!$B$2:$B$1500,$V35) | X35: =COUNTIFS('Map Calc'!$B$2:$B$1500,$V35,'Map Calc'!$P$2:$P$1500,"Yes") | Y35: =COUNTIF('Map Calc'!$T$2:$T$2500,$V35)
A36: Cross-genre connections | B36: =IFERROR(SUM('Map Calc'!$AD$2:$AD$2500)/COUNT('Map Calc'!$AD$2:$AD$2500),0) | C36: Influences that cross from one genre to another | V36: 2009 | W36: =COUNTIF('Map Calc'!$B$2:$B$1500,$V36) | X36: =COUNTIFS('Map Calc'!$B$2:$B$1500,$V36,'Map Calc'!$P$2:$P$1500,"Yes") | Y36: =COUNTIF('Map Calc'!$T$2:$T$2500,$V36)
V37: 2010 | W37: =COUNTIF('Map Calc'!$B$2:$B$1500,$V37) | X37: =COUNTIFS('Map Calc'!$B$2:$B$1500,$V37,'Map Calc'!$P$2:$P$1500,"Yes") | Y37: =COUNTIF('Map Calc'!$T$2:$T$2500,$V37)
V38: 2011 | W38: =COUNTIF('Map Calc'!$B$2:$B$1500,$V38) | X38: =COUNTIFS('Map Calc'!$B$2:$B$1500,$V38,'Map Calc'!$P$2:$P$1500,"Yes") | Y38: =COUNTIF('Map Calc'!$T$2:$T$2500,$V38)
V39: 2012 | W39: =COUNTIF('Map Calc'!$B$2:$B$1500,$V39) | X39: =COUNTIFS('Map Calc'!$B$2:$B$1500,$V39,'Map Calc'!$P$2:$P$1500,"Yes") | Y39: =COUNTIF('Map Calc'!$T$2:$T$2500,$V39)
V40: 2013 | W40: =COUNTIF('Map Calc'!$B$2:$B$1500,$V40) | X40: =COUNTIFS('Map Calc'!$B$2:$B$1500,$V40,'Map Calc'!$P$2:$P$1500,"Yes") | Y40: =COUNTIF('Map Calc'!$T$2:$T$2500,$V40)
V41: 2014 | W41: =COUNTIF('Map Calc'!$B$2:$B$1500,$V41) | X41: =COUNTIFS('Map Calc'!$B$2:$B$1500,$V41,'Map Calc'!$P$2:$P$1500,"Yes") | Y41: =COUNTIF('Map Calc'!$T$2:$T$2500,$V41)
V42: 2015 | W42: =COUNTIF('Map Calc'!$B$2:$B$1500,$V42) | X42: =COUNTIFS('Map Calc'!$B$2:$B$1500,$V42,'Map Calc'!$P$2:$P$1500,"Yes") | Y42: =COUNTIF('Map Calc'!$T$2:$T$2500,$V42)
V43: 2016 | W43: =COUNTIF('Map Calc'!$B$2:$B$1500,$V43) | X43: =COUNTIFS('Map Calc'!$B$2:$B$1500,$V43,'Map Calc'!$P$2:$P$1500,"Yes") | Y43: =COUNTIF('Map Calc'!$T$2:$T$2500,$V43)
V44: 2017 | W44: =COUNTIF('Map Calc'!$B$2:$B$1500,$V44) | X44: =COUNTIFS('Map Calc'!$B$2:$B$1500,$V44,'Map Calc'!$P$2:$P$1500,"Yes") | Y44: =COUNTIF('Map Calc'!$T$2:$T$2500,$V44)
V45: 2018 | W45: =COUNTIF('Map Calc'!$B$2:$B$1500,$V45) | X45: =COUNTIFS('Map Calc'!$B$2:$B$1500,$V45,'Map Calc'!$P$2:$P$1500,"Yes") | Y45: =COUNTIF('Map Calc'!$T$2:$T$2500,$V45)
V46: 2019 | W46: =COUNTIF('Map Calc'!$B$2:$B$1500,$V46) | X46: =COUNTIFS('Map Calc'!$B$2:$B$1500,$V46,'Map Calc'!$P$2:$P$1500,"Yes") | Y46: =COUNTIF('Map Calc'!$T$2:$T$2500,$V46)
V47: 2020 | W47: =COUNTIF('Map Calc'!$B$2:$B$1500,$V47) | X47: =COUNTIFS('Map Calc'!$B$2:$B$1500,$V47,'Map Calc'!$P$2:$P$1500,"Yes") | Y47: =COUNTIF('Map Calc'!$T$2:$T$2500,$V47)
V48: 2021 | W48: =COUNTIF('Map Calc'!$B$2:$B$1500,$V48) | X48: =COUNTIFS('Map Calc'!$B$2:$B$1500,$V48,'Map Calc'!$P$2:$P$1500,"Yes") | Y48: =COUNTIF('Map Calc'!$T$2:$T$2500,$V48)
... V53: 2026 | W53: =COUNTIF('Map Calc'!$B$2:$B$1500,$V53) | X53: =COUNTIFS('Map Calc'!$B$2:$B$1500,$V53,'Map Calc'!$P$2:$P$1500,"Yes") | Y53: =COUNTIF('Map Calc'!$T$2:$T$2500,$V53)

Sheet amulets
A1: Name | B1: Type | C1: Tier | D1: Rarity | E1: Obtain Goals | F1: Effect | G1: Visuals | H1: Image
B2: Body | C2: 1-Low | D2: Common | E2: Get damaged by enemies a lot | F2: N/A | G2: battered shield
B3: Body | C3: 2-Medium | D3: Common | E3: Only take 10 or less damage from enemies | G3: slightly damaged shield
B4: Body | C4: 3-High | D4: Common | E4: Take no damage from enemies | G4: completely pristine shield
B5: Cord | C5: 1-Low | D5: Common | E5: End a run with 10 or less items | F5: N/A | G5: bare string
B6: Cord | C6: 2-Medium | D6: Common | E6: End a run with 11 - 20 items | G6: has some stuff on it
