Workbook

Sheet games
A1: Name | B1: Year | C1: Type | D1: Connected? | E1: Influencer? | F1: Tags | G1: File | H1: Owned | I1: File Location | J1: Steam Page
A2: [Redacted] | B2: 2024 | C2: Action | D2: =TRUE() -> TRUE | E2: =COUNTIF(connections!A:A, A2) > 0 -> FALSE | G2: redacted
A3: 100 Rogues | B3: 2010 | C3: Traditional | D3: =TRUE() -> TRUE | E3: =COUNTIF(connections!A:A, A3) > 0 -> TRUE | G3: 100-rogues
A4: 2 Fights in 2 Tight Spaces | B4: 2026 | C4: Deckbuilder | D4: =TRUE() -> TRUE | E4: =COUNTIF(connections!A:A, A4) > 0 -> FALSE | G4: 2-fights-in-2-tight-spaces | J4: https://store.steampowered.com/app/3734890/2_Fights_in_2_Tight_Spaces/
A5: 20 Minutes Till Dawn | B5: 2022 | C5: Action | D5: =TRUE() -> TRUE | E5: =COUNTIF(connections!A:A, A5) > 0 -> TRUE | G5: 20-minutes-till-dawn | H5: Yes | I5: C:\Users\Owner\Documents\Roguelike Roguelike\Roguelikes\20 Minutes Till Dawn.url | J5: https://store.steampowered.com/app/1966900/20_Minutes_Till_Dawn/
A6: 20XX | B6: 2017 | C6: Action | D6: =TRUE() -> TRUE | E6: =COUNTIF(connections!A:A, A6) > 0 -> TRUE | G6: 20xx | H6: Yes | I6: C:\Users\Owner\Documents\Roguelike Roguelike\Roguelikes\20XX.url | J6: https://store.steampowered.com/app/322110/20XX/
A7: 30XX | B7: 2021 | C7: Action | D7: =TRUE() -> TRUE | E7: =COUNTIF(connections!A:A, A7) > 0 -> FALSE | G7: 30xx | H7: Yes | I7: C:\Users\Owner\Documents\Roguelike Roguelike\Roguelikes\30XX.url | J7: https://store.steampowered.com/app/1029210/30XX/
A8: 33 Immortals | B8: 2026 | C8: Action | D8: =TRUE() -> TRUE | E8: =COUNTIF(connections!A:A, A8) > 0 -> FALSE | F8: hell | G8: 33-immortals | H8: Yes | I8: C:\Users\Owner\Documents\Roguelike Roguelike\Roguelikes\33 Immortals.url | J8: https://store.steampowered.com/app/958520/33_Immortals/
A9: 868-Back | B9: 2026 | C9: Traditional | D9: =TRUE() -> TRUE | E9: =COUNTIF(connections!A:A, A9) > 0 -> FALSE | G9: 868-back | J9: https://store.steampowered.com/app/3304110/868BACK/
A10: 868-Hack | B10: 2015 | C10: Traditional | D10: =TRUE() -> TRUE | E10: =COUNTIF(connections!A:A, A10) > 0 -> TRUE | G10: 868-hack | H10: Yes | I10: C:\Users\Owner\Documents\Roguelike Roguelike\Roguelikes\868-HACK.url | J10: https://store.steampowered.com/app/274700/868HACK/
A11: 9 Kings | B11: 2024 | C11: Deckbuilder | D11: =TRUE() -> TRUE | E11: =COUNTIF(connections!A:A, A11) > 0 -> TRUE | G11: 9-kings | H11: Yes | I11: C:\Users\Owner\Documents\Roguelike Roguelike\Roguelikes\9 Kings.url | J11: https://store.steampowered.com/app/2784470/9_Kings/
A12: 99 Levels to Hell | B12: 2013 | C12: Action | D12: =TRUE() -> TRUE | E12: =COUNTIF(connections!A:A, A12) > 0 -> FALSE | F12: hell | G12: 99-levels-to-hell
A13: A la Card | B13: 2025 | C13: Deckbuilder | D13: =TRUE() -> TRUE | E13: =COUNTIF(connections!A:A, A13) > 0 -> FALSE | G13: a-la-card
A14: A Robot Named Fight! | B14: 2017 | C14: Action | D14: =TRUE() -> TRUE | E14: =COUNTIF(connections!A:A, A14) > 0 -> FALSE | G14: a-robot-named-fight | H14: Yes | I14: C:\Users\Owner\Documents\Roguelike Roguelike\Roguelikes\A Robot Named Fight.url | J14: https://store.steampowered.com/app/603530/A_Robot_Named_Fight/
A15: Abandon Ship | B15: 2019 | C15: Strategy | D15: =TRUE() -> TRUE | E15: =COUNTIF(connections!A:A, A15) > 0 -> FALSE | G15: abandon-ship | H15: Yes | I15: C:\Users\Owner\Documents\Roguelike Roguelike\Roguelikes\Abandon Ship.url | J15: https://store.steampowered.com/app/551860/Abandon_Ship/
A16: Abandoned Archive | B16: 2025 | C16: Action | D16: =TRUE() -> TRUE | E16: =COUNTIF(connections!A:A, A16) > 0 -> FALSE | G16: abandoned-archive
A17: Absolum | B17: 2025 | C17: Action | D17: =TRUE() -> TRUE | E17: =COUNTIF(connections!A:A, A17) > 0 -> FALSE | F17: beat 'em up | G17: absolum | H17: Yes | I17: C:\Users\Owner\Documents\Roguelike Roguelike\Roguelikes\Absolum.url | J17: https://store.steampowered.com/app/1904480/Absolum/
A18: Abyssus | B18: 2025 | C18: Action | D18: =TRUE() -> TRUE | E18: =COUNTIF(connections!A:A, A18) > 0 -> FALSE | G18: abyssus | H18: Yes | I18: C:\Users\Owner\Documents\Roguelike Roguelike\Roguelikes\Abyssus.url | J18: https://store.steampowered.com/app/1721110/Abyssus/
A19: Aces & Adventures | B19: 2023 | C19: Deckbuilder | D19: =TRUE() -> TRUE | E19: =COUNTIF(connections!A:A, A19) > 0 -> FALSE | G19: aces-adventures | H19: Yes | I19: C:\Users\Owner\Documents\Roguelike Roguelike\Roguelikes\Aces and Adventures.url | J19: https://store.steampowered.com/app/1815570/Aces__Adventures/
A20: Across the Obelisk | B20: 2021 | C20: Deckbuilder | D20: =TRUE() -> TRUE | E20: =COUNTIF(connections!A:A, A20) > 0 -> TRUE | G20: across-the-obelisk | H20: Yes | I20: C:\Users\Owner\Documents\Roguelike Roguelike\Roguelikes\Across the Obelisk.url | J20: https://store.steampowered.com/app/1385380/Across_the_Obelisk/
A21: Aethermancer | B21: 2025 | C21: Strategy | D21: =TRUE() -> TRUE | E21: =COUNTIF(connections!A:A, A21) > 0 -> TRUE | G21: aethermancer | H21: Yes | I21: C:\Users\Owner\Documents\Roguelike Roguelike\Roguelikes\Aethermancer.url | J21: https://store.steampowered.com/app/2288470/Aethermancer/
A22: AK-xolotl | B22: 2023 | C22: Action | D22: =TRUE() -> TRUE | E22: =COUNTIF(connections!A:A, A22) > 0 -> FALSE | G22: ak-xolotl | H22: Yes | I22: C:\Users\Owner\Documents\Roguelike Roguelike\Roguelikes\AK-xolotl Together.url | J22: https://store.steampowered.com/app/1479140/AKxolotl_Together/
A23: Alina of the Arena | B23: 2022 | C23: Deckbuilder | D23: =TRUE() -> TRUE | E23: =COUNTIF(connections!A:A, A23) > 0 -> FALSE | G23: alina-of-the-arena | H23: Yes | I23: C:\Users\Owner\Documents\Roguelike Roguelike\Roguelikes\Alina of the Arena.url | J23: https://store.steampowered.com/app/1668690/Alina_of_the_Arena/
A24: An Amazing Wizard | B24: 2025 | C24: Action | D24: =TRUE() -> TRUE | E24: =COUNTIF(connections!A:A, A24) > 0 -> FALSE | G24: an-amazing-wizard | J24: https://store.steampowered.com/app/1372660/An_Amazing_Wizard/
A25: Ancient Domains of Mystery | B25: 1994 | C25: Traditional | D25: =TRUE() -> TRUE | E25: =COUNTIF(connections!A:A, A25) > 0 -> TRUE | G25: ancient-domains-of-mystery | H25: Yes | I25: C:\Users\Owner\Documents\Roguelike Roguelike\Roguelikes\ADOM (Ancient Domains Of Mystery).url | J25: https://store.steampowered.com/app/333300/ADOM_Ancient_Domains_Of_Mystery/
A26: Angband | B26: 1990 | C26: Traditional | D26: =TRUE() -> TRUE | E26: =COUNTIF(connections!A:A, A26) > 0 -> TRUE | G26: angband | H26: Yes | I26: C:\Users\Owner\Documents\Roguelike Roguelike\Roguelikes\angband.lnk
A27: Anomaly Collapse | B27: 2024 | C27: Strategy | D27: =TRUE() -> TRUE | E27: =COUNTIF(connections!A:A, A27) > 0 -> FALSE | G27: anomaly-collapse | J27: https://store.steampowered.com/app/2082410/Anomaly_Collapse/
A28: Another Farm Roguelike | B28: 2022 | C28: Strategy | D28: =FALSE() -> FALSE | E28: =COUNTIF(connections!A:A, A28) > 0 -> TRUE | F28: food | G28: another-farm-roguelike | H28: Yes | I28: C:\Users\Owner\Documents\Roguelike Roguelike\Roguelikes\Another Farm Roguelike.url | J28: https://store.steampowered.com/app/2116850/Another_Farm_Roguelike/
A29: Another Farm Roguelike: Rebirth | B29: 2025 | C29: Strategy | D29: =FALSE() -> FALSE | E29: =COUNTIF(connections!A:A, A29) > 0 -> FALSE | F29: food | G29: another-farm-roguelike-rebirth
A30: Aotenjo: Infinite Hands | B30: 2024 | C30: Deckbuilder | D30: =TRUE() -> TRUE | E30: =COUNTIF(connections!A:A, A30) > 0 -> FALSE | F30: mahjong | G30: aotenjo-infinite-hands
A31: Approaching Infinity | B31: 2020 | C31: Traditional | D31: =TRUE() -> TRUE | E31: =COUNTIF(connections!A:A, A31) > 0 -> FALSE | F31: space | G31: approaching-infinity
A32: Arc Seed | B32: 2024 | C32: Deckbuilder | D32: =TRUE() -> TRUE | E32: =COUNTIF(connections!A:A, A32) > 0 -> FALSE | F32: mecha | G32: arc-seed | H32: Yes | I32: C:\Users\Owner\Documents\Roguelike Roguelike\Roguelikes\ARC SEED.url | J32: https://store.steampowered.com/app/2332970/ARC_SEED/
A33: Arcane Trigger | B33: 2025 | C33: Action | D33: TRUE | E33: =COUNTIF(connections!A:A, A33) > 0 -> FALSE | G33: arcane-trigger
A34: Arcanium: Rise of Akhan | B34: 2020 | C34: Deckbuilder | D34: =TRUE() -> TRUE | E34: =COUNTIF(connections!A:A, A34) > 0 -> FALSE | G34: arcanium-rise-of-akhan | H34: Yes | I34: C:\Users\Owner\Documents\Roguelike Roguelike\Roguelikes\Arcanium.url | J34: https://store.steampowered.com/app/1056840/Arcanium_Rise_of_Akhan/
A35: Archon Soul | B35: 2026 | C35: Deckbuilder | D35: =TRUE() -> TRUE | E35: =COUNTIF(connections!A:A, A35) > 0 -> FALSE | G35: archon-soul | J35: https://store.steampowered.com/app/4252700/Archon_Soul/
A36: Archons | B36: 2024 | C36: Action | D36: =TRUE() -> TRUE | E36: =COUNTIF(connections!A:A, A36) > 0 -> FALSE | G36: archons | H36: Yes | I36: C:\Users\Owner\Documents\Roguelike Roguelike\Roguelikes\Archons.url | J36: https://store.steampowered.com/app/2779570/Archons/
A37: Arms of God | B37: 2026 | C37: Action | D37: =TRUE() -> TRUE | E37: =COUNTIF(connections!A:A, A37) > 0 -> FALSE | G37: arms-of-god | J37: https://store.steampowered.com/app/3100310/Arms_of_God/
A38: Army of Ruin | B38: 2022 | C38: Action | D38: =TRUE() -> TRUE | E38: =COUNTIF(connections!A:A, A38) > 0 -> FALSE | G38: army-of-ruin | H38: Yes | I38: C:\Users\Owner\Documents\Roguelike Roguelike\Roguelikes\Army of Ruin.url | J38: https://store.steampowered.com/app/1918040/Army_of_Ruin/
A39: Arrogue | B39: 2025 | C39: Deckbuilder | D39: =TRUE() -> TRUE | E39: =COUNTIF(connections!A:A, A39) > 0 -> FALSE | G39: arrogue
A40: As We Descend | B40: 2025 | C40: Deckbuilder | D40: =TRUE() -> TRUE | E40: =COUNTIF(connections!A:A, A40) > 0 -> FALSE | G40: as-we-descend
A41: Asgard's Fall: Viking Survivors | B41: 2025 | C41: Action | D41: =TRUE() -> TRUE | E41: =COUNTIF(connections!A:A, A41) > 0 -> FALSE | F41: viking | G41: asgards-fall-viking-survivors | H41: Yes | I41: C:\Users\Owner\Documents\Roguelike Roguelike\Roguelikes\Asgard's Fall — Viking Survivors.url | J41: https://store.steampowered.com/app/2780710/Asgards_Fall__Viking_Survivors/
A42: Asterogues | B42: 2023 | C42: Action | D42: =TRUE() -> TRUE | E42: =COUNTIF(connections!A:A, A42) > 0 -> FALSE | F42: space | G42: asterogues
A43: Astral Ascent | B43: 2022 | C43: Action | D43: =TRUE() -> TRUE | E43: =COUNTIF(connections!A:A, A43) > 0 -> FALSE | G43: astral-ascent | H43: Yes | I43: C:\Users\Owner\Documents\Roguelike Roguelike\Roguelikes\Astral Ascent.url | J43: https://store.steampowered.com/app/1280930/Astral_Ascent/
A44: Astrea: Six-Sided Oracles | B44: 2023 | C44: Deckbuilder | D44: =TRUE() -> TRUE | E44: =COUNTIF(connections!A:A, A44) > 0 -> FALSE | F44: dice | G44: astrea-six-sided-oracles | H44: Yes | I44: C:\Users\Owner\Documents\Roguelike Roguelike\Roguelikes\Astrea Six-Sided Oracles.url | J44: https://store.steampowered.com/app/1755830/Astrea_SixSided_Oracles/
A45: Astro Prospector | B45: 2025 | C45: Action | D45: =TRUE() -> TRUE | E45: =COUNTIF(connections!A:A, A45) > 0 -> FALSE | F45: space | G45: astro-prospector | H45: Yes | I45: C:\Users\Owner\Documents\Roguelike Roguelike\Roguelikes\Astro Prospector.url | J45: https://store.steampowered.com/app/3503440/Astro_Prospector/
A46: Astronarch | B46: 2020 | C46: Strategy | D46: =TRUE() -> TRUE | E46: =COUNTIF(connections!A:A, A46) > 0 -> TRUE | G46: astronarch | H46: Yes | I46: C:\Users\Owner\Documents\Roguelike Roguelike\Roguelikes\Astronarch.url | J46: https://store.steampowered.com/app/1234940/Astronarch/
A47: Atai no Gensoukyou | B47: 2010 | C47: Traditional | D47: =TRUE() -> TRUE | E47: =COUNTIF(connections!A:A, A47) > 0 -> FALSE | F47: touhou | G47: atai-no-gensoukyou
A48: Atomic Owl | B48: 2025 | C48: Action | D48: =TRUE() -> TRUE | E48: =COUNTIF(connections!A:A, A48) > 0 -> FALSE | G48: atomic-owl | J48: https://store.steampowered.com/app/2228490/Atomic_Owl/
A49: Atomicrops | B49: 2020 | C49: Action | D49: =TRUE() -> TRUE | E49: =COUNTIF(connections!A:A, A49) > 0 -> TRUE | F49: food | G49: atomicrops | H49: Yes | I49: C:\Users\Owner\Documents\Roguelike Roguelike\Roguelikes\Atomicrops.url | J49: https://store.steampowered.com/app/757320/Atomicrops/
A50: Auro: A Monster-Bumping Adventure | B50: 2014 | C50: Strategy | D50: =TRUE() -> TRUE | E50: =COUNTIF(connections!A:A, A50) > 0 -> TRUE | G50: auro-a-monster-bumping-adventure
A51: Auto Rogue | B51: 2025 | C51: Strategy | D51: =FALSE() -> FALSE | E51: =COUNTIF(connections!A:A, A51) > 0 -> FALSE | G51: auto-rogue
A52: Azure Dreams | B52: 1997 | C52: Traditional | D52: =TRUE() -> TRUE | E52: =COUNTIF(connections!A:A, A52) > 0 -> TRUE | G52: azure-dreams | H52: Yes | I52: C:\Users\Owner\Documents\Roguelike Roguelike\Roguelikes\Azure Dreams.lnk
A53: Backpack Battles | B53: 2023 | C53: Strategy | D53: =TRUE() -> TRUE | E53: =COUNTIF(connections!A:A, A53) > 0 -> TRUE | G53: backpack-battles | H53: Yes | I53: C:\Users\Owner\Documents\Roguelike Roguelike\Roguelikes\Backpack Battles.url | J53: https://store.steampowered.com/app/2427700/Backpack_Battles/
A54: Backpack Hero | B54: 2022 | C54: Deckbuilder | D54: =TRUE() -> TRUE | E54: =COUNTIF(connections!A:A, A54) > 0 -> TRUE | G54: backpack-hero | H54: Yes | I54: C:\Users\Owner\Documents\Roguelike Roguelike\Roguelikes\Backpack Hero.url | J54: https://store.steampowered.com/app/1970580/Backpack_Hero/
A55: Bad North | B55: 2018 | C55: Strategy | D55: =TRUE() -> TRUE | E55: =COUNTIF(connections!A:A, A55) > 0 -> TRUE | G55: bad-north | H55: Yes | I55: https://store.steampowered.com/app/688420/Bad_North_Jotunn_Edition/ | J55: https://store.steampowered.com/app/688420/Bad_North_Jotunn_Edition/
A56: Balatro | B56: 2023 | C56: Deckbuilder | D56: =TRUE() -> TRUE | E56: =COUNTIF(connections!A:A, A56) > 0 -> TRUE | F56: casino | G56: balatro | H56: Yes | I56: C:\Users\Owner\Documents\Roguelike Roguelike\Roguelikes\Balatro.url | J56: https://store.steampowered.com/app/2379780/Balatro/
A57: Baldi's Basics Plus | B57: 2020 | C57: Strategy | D57: =TRUE() -> TRUE | E57: =COUNTIF(connections!A:A, A57) > 0 -> FALSE | G57: baldis-basics-plus
A58: Ball x Pit | B58: 2025 | C58: Action | D58: =TRUE() -> TRUE | E58: =COUNTIF(connections!A:A, A58) > 0 -> TRUE | G58: ball-x-pit | H58: Yes | I58: C:\Users\Owner\Documents\Roguelike Roguelike\Roguelikes\BALL x PIT.url | J58: https://store.steampowered.com/app/2062430/BALL_x_PIT/
A59: Ballionaire | B59: 2024 | C59: Deckbuilder | D59: =TRUE() -> TRUE | E59: =COUNTIF(connections!A:A, A59) > 0 -> TRUE | F59: casino | G59: ballionaire | H59: Yes | I59: C:\Users\Owner\Documents\Roguelike Roguelike\Roguelikes\Ballionaire.url | J59: https://store.steampowered.com/app/2667120/Ballionaire/
A60: Banners of Ruin | B60: 2020 | C60: Deckbuilder | D60: =TRUE() -> TRUE | E60: =COUNTIF(connections!A:A, A60) > 0 -> FALSE | G60: banners-of-ruin | H60: Yes | I60: C:\Users\Owner\Documents\Roguelike Roguelike\Roguelikes\Banners of Ruin.url | J60: https://store.steampowered.com/app/1075740/Banners_of_Ruin/
A61: Barda | B61: 2026 | C61: Strategy | D61: =TRUE() -> TRUE | E61: =COUNTIF(connections!A:A, A61) > 0 -> FALSE | G61: barda | J61: https://store.steampowered.com/app/3664320/BARDA_Backpack_Roguelike/
A62: Barony | B62: 2015 | C62: Action | D62: =TRUE() -> TRUE | E62: =COUNTIF(connections!A:A, A62) > 0 -> FALSE | G62: barony | H62: Yes | I62: C:\Users\Owner\Documents\Roguelike Roguelike\Roguelikes\Barony.url | J62: https://store.steampowered.com/app/371970/Barony/
A63: Baroque | B63: 1998 | C63: Action | D63: =TRUE() -> TRUE | E63: =COUNTIF(connections!A:A, A63) > 0 -> TRUE | G63: baroque
A64: Baroque (2007) | B64: 2007 | C64: Action | D64: =FALSE() -> FALSE | E64: =COUNTIF(connections!A:A, A64) > 0 -> FALSE | G64: baroque-2007
A65: Batomon Showdown | B65: 2026 | C65: Strategy | D65: =TRUE() -> TRUE | E65: =COUNTIF(connections!A:A, A65) > 0 -> FALSE | G65: batomon-showdown | H65: Yes | I65: C:\Users\Owner\Documents\Roguelike Roguelike\Roguelikes\Batomon Showdown.url | J65: https://store.steampowered.com/app/4557380/Batomon_Showdown/
A66: Battle Brothers | B66: 2017 | C66: Strategy | D66: =TRUE() -> TRUE | E66: =COUNTIF(connections!A:A, A66) > 0 -> TRUE | G66: battle-brothers | H66: Yes | I66: C:\Users\Owner\Documents\Roguelike Roguelike\Roguelikes\BattleBrothers.lnk | J66: https://store.steampowered.com/app/365360/Battle_Brothers/
A67: Battle Shapers | B67: 2023 | C67: Action | D67: =TRUE() -> TRUE | E67: =COUNTIF(connections!A:A, A67) > 0 -> FALSE | G67: battle-shapers | H67: Yes | I67: C:\Users\Owner\Documents\Roguelike Roguelike\Roguelikes\Battle Shapers.url | J67: https://store.steampowered.com/app/1421290/Battle_Shapers/
A68: BAZR | B68: 2025 | C68: Deckbuilder | D68: =TRUE() -> TRUE | E68: =COUNTIF(connections!A:A, A68) > 0 -> FALSE | G68: bazr | H68: Yes | I68: C:\Users\Owner\Documents\Roguelike Roguelike\Roguelikes\BAZR.lnk
A69: Be My Horde | B69: 2024 | C69: Action | D69: =TRUE() -> TRUE | E69: =COUNTIF(connections!A:A, A69) > 0 -> FALSE | G69: be-my-horde | H69: Yes | I69: C:\Users\Owner\Documents\Roguelike Roguelike\Roguelikes\Be My Horde.url | J69: https://store.steampowered.com/app/2499520/Be_My_Horde/
A70: Beat Blast | B70: 2020 | C70: Action | D70: =FALSE() -> FALSE | E70: =COUNTIF(connections!A:A, A70) > 0 -> FALSE | F70: rhythm | G70: beat-blast | H70: Yes | I70: C:\Users\Owner\Documents\Roguelike Roguelike\Roguelikes\Beat Blast.url | J70: https://store.steampowered.com/app/1072640/Beat_Blast/
A71: Bella Wants Blood | B71: 2024 | C71: Strategy | D71: =TRUE() -> TRUE | E71: =COUNTIF(connections!A:A, A71) > 0 -> FALSE | F71: tower defense | G71: bella-wants-blood | H71: Yes | I71: C:\Users\Owner\Documents\Roguelike Roguelike\Roguelikes\Bella Wants Blood.url | J71: https://store.steampowered.com/app/3007660/Bella_Wants_Blood/
A72: Beneath Apple Manor | B72: 1978 | C72: Traditional | D72: =FALSE() -> FALSE | E72: =COUNTIF(connections!A:A, A72) > 0 -> FALSE | G72: beneath-apple-manor | H72: Yes | I72: C:\Users\Owner\Documents\Roguelike Roguelike\Roguelikes\Beneath Apple Manor.lnk
A73: Beneath Oresa | B73: 2022 | C73: Deckbuilder | D73: =TRUE() -> TRUE | E73: =COUNTIF(connections!A:A, A73) > 0 -> FALSE | G73: beneath-oresa | H73: Yes | I73: C:\Users\Owner\Documents\Roguelike Roguelike\Roguelikes\Beneath Oresa.url | J73: https://store.steampowered.com/app/1803400/Beneath_Oresa/
A74: Beyond the Long Night | B74: 2023 | C74: Action | D74: =TRUE() -> TRUE | E74: =COUNTIF(connections!A:A, A74) > 0 -> FALSE | G74: beyond-the-long-night | H74: Yes | I74: C:\Users\Owner\Documents\Roguelike Roguelike\Roguelikes\Beyond the Long Night.url | J74: https://store.steampowered.com/app/1730080/Beyond_the_Long_Night/
A75: Beyond Words | B75: 2026 | C75: Deckbuilder | D75: =TRUE() -> TRUE | E75: =COUNTIF(connections!A:A, A75) > 0 -> FALSE | G75: beyond-words | J75: https://store.steampowered.com/app/3823370/Beyond_Words/
A76: Bingle Bingle | B76: 2024 | C76: Deckbuilder | D76: =TRUE() -> TRUE | E76: =COUNTIF(connections!A:A, A76) > 0 -> FALSE | F76: casino | G76: bingle-bingle | H76: Yes | I76: C:\Users\Owner\Documents\Roguelike Roguelike\Roguelikes\Bingle Bingle.url | J76: https://store.steampowered.com/app/2789810/Bingle_Bingle/
A77: Bioprototype | B77: 2022 | C77: Action | D77: =TRUE() -> TRUE | E77: =COUNTIF(connections!A:A, A77) > 0 -> FALSE | G77: bioprototype | J77: https://store.steampowered.com/app/3689520/Bioprototype/
A78: Black Jacket | B78: 2026 | C78: Deckbuilder | D78: =TRUE() -> TRUE | E78: =COUNTIF(connections!A:A, A78) > 0 -> FALSE | F78: casino | G78: black-jacket | J78: https://store.steampowered.com/app/3100370/Black_Jacket/
A79: Blazing Beaks | B79: 2019 | C79: Action | D79: =TRUE() -> TRUE | E79: =COUNTIF(connections!A:A, A79) > 0 -> FALSE | G79: blazing-beaks | H79: Yes | I79: C:\Users\Owner\Documents\Roguelike Roguelike\Roguelikes\Blazing Beaks.url | J79: https://store.steampowered.com/app/585710/Blazing_Beaks/
A80: Bleak Sword | B80: 2019 | C80: Action | D80: =TRUE() -> TRUE | E80: =COUNTIF(connections!A:A, A80) > 0 -> TRUE | G80: bleak-sword | H80: Yes | I80: C:\Users\Owner\Documents\Roguelike Roguelike\Roguelikes\Bleak Sword DX.url | J80: https://store.steampowered.com/app/2193050/Bleak_Sword_DX/
A81: Block Tower TD | B81: 2023 | C81: Strategy | D81: =FALSE() -> FALSE | E81: =COUNTIF(connections!A:A, A81) > 0 -> TRUE | F81: tower defense | G81: block-tower-td | H81: Yes | I81: C:\Users\Owner\Documents\Roguelike Roguelike\Roguelikes\Block Tower TD.url | J81: https://store.steampowered.com/app/2427570/Block_Tower_TD/
A82: Block Tower TD 2 | B82: 2024 | C82: Strategy | D82: =FALSE() -> FALSE | E82: =COUNTIF(connections!A:A, A82) > 0 -> FALSE | F82: tower defense | G82: block-tower-td-2 | H82: Yes | I82: C:\Users\Owner\Documents\Roguelike Roguelike\Roguelikes\Block Tower TD 2.url | J82: https://store.steampowered.com/app/2837350/Block_Tower_TD_2/
A83: BloodDome99 | B83: 2023 | C83: Action | D83: =TRUE() -> TRUE | E83: =COUNTIF(connections!A:A, A83) > 0 -> FALSE | G83: blooddome99
A84: Bloodshed | B84: 2024 | C84: Action | D84: =TRUE() -> TRUE | E84: =COUNTIF(connections!A:A, A84) > 0 -> FALSE | G84: bloodshed | H84: Yes | I84: C:\Users\Owner\Documents\Roguelike Roguelike\Roguelikes\Bloodshed.url | J84: https://store.steampowered.com/app/2747550/Bloodshed/
A85: Bloons TD 6: Rogue Legends | B85: 2025 | C85: Strategy | D85: =FALSE() -> FALSE | E85: =COUNTIF(connections!A:A, A85) > 0 -> FALSE | F85: tower defense | G85: bloons-td-6-rogue-legends
A86: Blue Prince | B86: 2025 | C86: Strategy | D86: =FALSE() -> FALSE | E86: =COUNTIF(connections!A:A, A86) > 0 -> FALSE | G86: blue-prince
A87: Boneraiser Minions | B87: 2022 | C87: Action | D87: =TRUE() -> TRUE | E87: =COUNTIF(connections!A:A, A87) > 0 -> TRUE | F87: undead | G87: boneraiser-minions | H87: Yes | I87: C:\Users\Owner\Documents\Roguelike Roguelike\Roguelikes\Boneraiser Minions.url | J87: https://store.steampowered.com/app/1944570/Boneraiser_Minions/
A88: Book of Demons | B88: 2018 | C88: Deckbuilder | D88: =TRUE() -> TRUE | E88: =COUNTIF(connections!A:A, A88) > 0 -> TRUE | G88: book-of-demons
A89: Bounty of One | B89: 2022 | C89: Action | D89: =TRUE() -> TRUE | E89: =COUNTIF(connections!A:A, A89) > 0 -> TRUE | F89: western | G89: bounty-of-one | H89: Yes | I89: C:\Users\Owner\Documents\Roguelike Roguelike\Roguelikes\Bounty of One.url | J89: https://store.steampowered.com/app/1968730/Bounty_of_One/
A90: Boyfriend Dungeon | B90: 2021 | C90: Action | D90: =FALSE() -> FALSE | E90: =COUNTIF(connections!A:A, A90) > 0 -> FALSE | G90: boyfriend-dungeon | H90: Yes | I90: C:\Users\Owner\Documents\Roguelike Roguelike\Roguelikes\Boyfriend Dungeon.url | J90: https://store.steampowered.com/app/674930/Boyfriend_Dungeon/
A91: BPM: Bullets Per Minute | B91: 2020 | C91: Action | D91: =TRUE() -> TRUE | E91: =COUNTIF(connections!A:A, A91) > 0 -> FALSE | F91: rhythm | G91: bpm-bullets-per-minute | H91: Yes | I91: C:\Users\Owner\Documents\Roguelike Roguelike\Roguelikes\BPM BULLETS PER MINUTE.url | J91: https://store.steampowered.com/app/1286350/BPM_BULLETS_PER_MINUTE/
A92: Brawl Tactics: Origins | B92: 2023 | C92: Deckbuilder | D92: =TRUE() -> TRUE | E92: =COUNTIF(connections!A:A, A92) > 0 -> FALSE | G92: brawl-tactics-origins | J92: https://store.steampowered.com/app/2451820/Brawl_Tactics_Origins/
A93: Breach Wanderers | B93: 2021 | C93: Deckbuilder | D93: =TRUE() -> TRUE | E93: =COUNTIF(connections!A:A, A93) > 0 -> FALSE | G93: breach-wanderers | H93: Yes | I93: C:\Users\Owner\Documents\Roguelike Roguelike\Roguelikes\Breach Wanderers.url | J93: https://store.steampowered.com/app/1394130/Breach_Wanderers/
A94: Breachway | B94: 2024 | C94: Deckbuilder | D94: =TRUE() -> TRUE | E94: =COUNTIF(connections!A:A, A94) > 0 -> FALSE | F94: space | G94: breachway | H94: Yes | I94: C:\Users\Owner\Documents\Roguelike Roguelike\Roguelikes\Breachway.url | J94: https://store.steampowered.com/app/2118810/Breachway/
A95: Brew | B95: 2025 | C95: Action | D95: =TRUE() -> TRUE | E95: =COUNTIF(connections!A:A, A95) > 0 -> FALSE | G95: brew
A96: Brogue | B96: 2009 | C96: Traditional | D96: =TRUE() -> TRUE | E96: =COUNTIF(connections!A:A, A96) > 0 -> TRUE | G96: brogue | H96: Yes | I96: C:\Users\Owner\Documents\Roguelike Roguelike\Roguelikes\brogue.lnk
A97: BroomSweeper | B97: 2026 | C97: Strategy | D97: =TRUE() -> TRUE | E97: =COUNTIF(connections!A:A, A97) > 0 -> FALSE | G97: broomsweeper | H97: Yes | I97: C:\Users\Owner\Documents\Roguelike Roguelike\Roguelikes\BroomSweeper.url | J97: https://store.steampowered.com/app/3473250/BroomSweeper/
A98: Brotato | B98: 2022 | C98: Action | D98: =TRUE() -> TRUE | E98: =COUNTIF(connections!A:A, A98) > 0 -> TRUE | G98: brotato | H98: Yes | I98: C:\Users\Owner\Documents\Roguelike Roguelike\Roguelikes\Brotato.url | J98: https://store.steampowered.com/app/1942280/Brotato/
A99: Brutal Orchestra | B99: 2021 | C99: Strategy | D99: =TRUE() -> TRUE | E99: =COUNTIF(connections!A:A, A99) > 0 -> FALSE | G99: brutal-orchestra | H99: Yes | I99: C:\Users\Owner\Documents\Roguelike Roguelike\Roguelikes\Brutal Orchestra.url | J99: https://store.steampowered.com/app/1734320/Brutal_Orchestra/
A100: Buckshot Roulette | B100: 2023 | C100: Strategy | D100: =TRUE() -> TRUE | E100: =COUNTIF(connections!A:A, A100) > 0 -> TRUE | F100: horror | G100: buckshot-roulette | H100: Yes | I100: C:\Users\Owner\Documents\Roguelike Roguelike\Roguelikes\Buckshot Roulette.url | J100: https://store.steampowered.com/app/2835570/Buckshot_Roulette/
...

Sheet connections
A1: Influencer | B1: Influencee | C1: Influencer Time | D1: Dev/Series Relation | E1: Source | F1: Proof
A2: Hades | B2: [Redacted] | C2: 2019 | E2: look at it
A3: Mystery Dungeon 2: Shiren the Wanderer | B3: 100 Rogues | C3: 1995 | E3: https://www.gamedeveloper.com/business/marketing-on-the-app-store-the-cautionary-tale-of-i-100-rogues-i- | F3: mystery_dungeon_2_shiren_the_wanderer---100_rogues
A4: Powder | B4: 100 Rogues | C4: 2003 | E4: https://www.gamedeveloper.com/business/marketing-on-the-app-store-the-cautionary-tale-of-i-100-rogues-i- | F4: powder---100_rogues
A5: Fights in Tight Spaces | B5: 2 Fights in 2 Tight Spaces | C5: 2021 | D5: Yes
A6: Vampire Survivors | B6: 20 Minutes Till Dawn | C6: 2021 | E6: look at it
A7: Crypt of the NecroDancer | B7: 20XX | C7: 2015 | E7: https://www.reddit.com/r/IAmA/comments/4po4pn/i_am_the_developer_of_20xx_the_megaman_xinspired/ | F7: crypt_of_the_necrodancer---20xx
A8: The Binding of Isaac | B8: 20XX | C8: 2011 | E8: https://www.reddit.com/r/IAmA/comments/4po4pn/i_am_the_developer_of_20xx_the_megaman_xinspired/ | F8: the_binding_of_isaac---20xx
A9: 20XX | B9: 30XX | C9: 2017 | D9: Yes
A10: Realm of the Mad God | B10: 33 Immortals | C10: 2010 | E10: check folder | F10: realm_of_the_mad_god---33_immortals
A11: Sundered | B11: 33 Immortals | C11: 2017 | D11: Yes
A12: 868-Hack | B12: 868-Back | C12: 2015 | D12: Yes
A13: Rogue | B13: 868-Hack | C13: 1980 | E13: https://www.gamedeveloper.com/design/how-michael-brough-s-love-of-exploring-a-single-game-mechanic-beget-i-cinco-paus-i- | F13: rogue---868_hack
A14: Seraph's Last Stand | B14: 9 Kings | C14: 2022 | D14: Yes
A15: Slay the Spire | B15: 9 Kings | C15: 2017 | E15: https://www.youtube.com/watch?v=9fxnPkfyHuA
A16: Spelunky Classic | B16: 99 Levels to Hell | C16: 2008 | E16: https://youtu.be/wJ2cgBoxsi4
A17: The Binding of Isaac | B17: 99 Levels to Hell | C17: 2011 | E17: https://youtu.be/wJ2cgBoxsi4
A18: Slay the Spire | B18: A la Card | C18: 2017 | E18: check folder | F18: slay_the_spire---a_la_card
A19: The Binding of Isaac | B19: A Robot Named Fight! | C19: 2011 | E19: https://www.reddit.com/r/NintendoSwitch/comments/8jv8rd/im_matt_bitner_sole_developer_of_a_robot_named/#:~:text=I%20left%20my%20old%20job,as%20The%20Binding%20of%20Isaac. | F19: the_binding_of_isaac---a_robot_named_fight
A20: FTL | B20: Abandon Ship | C20: 2012 | E20: https://bigbossbattle.com/abandon-ship-interview-fireblade-softwares-gary-burchell/ | F20: ftl---abandon_ship
A21: Enter the Gungeon | B21: Abandoned Archive | C21: 2016 | E21: https://www.reddit.com/r/playmygame/comments/sqb852/our_spellcasting_roguelike_abandoned_archive_now/ | F21: enter_the_gungeon---abandoned_archive
A22: Wizard of Legend | B22: Abandoned Archive | C22: 2018 | E22: https://www.reddit.com/r/playmygame/comments/sqb852/our_spellcasting_roguelike_abandoned_archive_now/ | F22: wizard_of_legend---abandoned_archive
A23: Dead Cells | B23: Absolum | C23: 2018 | E23: https://www.polygon.com/absolum-roguelike-interview-dotemu-guard-crush/ | F23: dead_cells---absolum
A24: Gunfire Reborn | B24: Abyssus | C24: 2020 | E24: https://steamcommunity.com/app/1721110/discussions/0/600775708393865281/ | F24: gunfire_reborn---abyssus
A25: Nuclear Throne | B25: Abyssus | C25: 2015 | E25: https://steamcommunity.com/app/1721110/discussions/0/600775708393865281/ | F25: nuclear_throne---abyssus
A26: Roboquest | B26: Abyssus | C26: 2020 | E26: https://steamcommunity.com/app/1721110/discussions/0/600775708393865281/ | F26: roboquest---abyssus
A27: Popup Dungeon | B27: Aces & Adventures | C27: 2020 | E27: https://creators.spotify.com/pod/show/the-indie-diarist/episodes/Indie-Diary-5-Enrique-Dryere-Triple-B-Titles---Creativity-as-Sacrifice--Secrets-of-Inspiration--DnD-and----Poker-e207m5b
A28: Slay the Spire | B28: Aces & Adventures | C28: 2017 | E28: https://creators.spotify.com/pod/show/the-indie-diarist/episodes/Indie-Diary-5-Enrique-Dryere-Triple-B-Titles---Creativity-as-Sacrifice--Secrets-of-Inspiration--DnD-and----Poker-e207m5b
A29: Darkest Dungeon | B29: Across the Obelisk | C29: 2015 | E29: duh also check the folder for proof | F29: darkest_dungeon---across_the_obelisk
A30: Slay the Spire | B30: Across the Obelisk | C30: 2017 | E30: duh also the devs talk about loving sts in discord
A31: Dead Cells | B31: Aethermancer | C31: 2018 | E31: check folder | F31: dead_cells---aethermancer
A32: Enter the Gungeon | B32: AK-xolotl | C32: 2016 | E32: https://www.reddit.com/r/Games/comments/v2kcsr/ama_were_the_team_behind_akxolotl_a_cute_but/ | F32: enter_the_gungeon---ak_xolotl
A33: Nuclear Throne | B33: AK-xolotl | C33: 2015 | E33: https://www.reddit.com/r/Games/comments/v2kcsr/ama_were_the_team_behind_akxolotl_a_cute_but/ | F33: nuclear_throne---ak_xolotl
A34: Into the Breach | B34: Alina of the Arena | C34: 2018 | E34: https://store.steampowered.com/app/1668690/Alina_of_the_Arena/#:~:text=About%20This%20Game-,ABOUT,and%20'Into%20the%20Breach'. | F34: into_the_breach---alina_of_the_arena
A35: Slay the Spire | B35: Alina of the Arena | C35: 2017 | E35: https://store.steampowered.com/app/1668690/Alina_of_the_Arena/#:~:text=About%20This%20Game-,ABOUT,and%20'Into%20the%20Breach'. | F35: slay_the_spire---alina_of_the_arena
A36: Dead Cells | B36: An Amazing Wizard | C36: 2018 | E36: https://x.com/AnAmazingWizard/status/1489554155597352962?s=20 | F36: dead_cells---an_amazing_wizard
A37: Hades | B37: An Amazing Wizard | C37: 2019 | E37: https://x.com/AnAmazingWizard/status/1489554155597352962?s=20 | F37: hades---an_amazing_wizard
A38: The Binding of Isaac | B38: An Amazing Wizard | C38: 2011 | E38: https://x.com/AnAmazingWizard/status/1489554155597352962?s=20 | F38: the_binding_of_isaac---an_amazing_wizard
A39: Hack | B39: Ancient Domains of Mystery | C39: 1984 | E39: https://roguebasin.com/index.php/ADOM | F39: hack---ancient_domains_of_mystery
A40: NetHack | B40: Ancient Domains of Mystery | C40: 1987 | E40: https://www.gamedeveloper.com/design/-play-86-interview-with-adom-creator-dr-thomas-biskup | F40: nethack---ancient_domains_of_mystery
A41: Rogue | B41: Ancient Domains of Mystery | C41: 1980 | E41: https://www.gamedeveloper.com/design/-play-86-interview-with-adom-creator-dr-thomas-biskup | F41: rogue---ancient_domains_of_mystery
A42: Moria | B42: Angband | C42: 1983 | E42: https://roguebasin.com/index.php/Angband | F42: moria---angband
... A44: Into the Breach | B44: Anomaly Collapse | C44: 2018 | E44: https://www.facebook.com/groups/132728896890594/posts/2551615688335224/ | F44: into_the_breach---anomaly_collapse
A45: Another Farm Roguelike | B45: Another Farm Roguelike: Rebirth | C45: 2022 | D45: Yes
A46: Balatro | B46: Aotenjo: Infinite Hands | C46: 2023 | E46: https://steamcommunity.com/games/3066570/announcements/detail/4356754561281185320 | F46: balatro---aotenjo_infinite_hands
A47: Luck be a Landlord | B47: Aotenjo: Infinite Hands | C47: 2021 | E47: https://steamcommunity.com/games/3066570/announcements/detail/4356754561281185320 | F47: luck_be_a_landlord---aotenjo_infinite_hands
A48: Monster Train | B48: Aotenjo: Infinite Hands | C48: 2020 | E48: https://steamcommunity.com/games/3066570/announcements/detail/4356754561281185320 | F48: monster_train---aotenjo_infinite_hands
A49: Slay the Spire | B49: Aotenjo: Infinite Hands | C49: 2017 | E49: https://steamcommunity.com/games/3066570/announcements/detail/4356754561281185320 | F49: slay_the_spire---aotenjo_infinite_hands
A50: Caves of Qud | B50: Approaching Infinity | C50: 2010 | E50: check folder | F50: caves_of_qud---approaching_infinity
A51: For The Warp | B51: Arc Seed | C51: 2020 | D51: Yes
A52: Into the Breach | B52: Arc Seed | C52: 2018 | E52: look at it
A53: Endgame of Devil | B53: Arcane Trigger | C53: 2023 | D53: Yes
A54: FTL | B54: Arcanium: Rise of Akhan | C54: 2018 | E54: https://arcanium-rise-of-akhan.xsollasitebuilder.com/ | F54: ftl---arcanium_rise_of_akhan
A55: Slay the Spire | B55: Arcanium: Rise of Akhan | C55: 2017 | E55: https://arcanium-rise-of-akhan.xsollasitebuilder.com/ | F55: slay_the_spire---arcanium_rise_of_akhan
A56: Dicey Dungeons | B56: Archon Soul | C56: 2019 | E56: https://www.reddit.com/r/WebGames/comments/1m6esqf/archon_soul_its_been_a_year_and_a_half_of_hard/ | F56: dicey_dungeons---archon_soul
A57: Slay the Spire | B57: Archon Soul | C57: 2017 | E57: https://www.reddit.com/r/WebGames/comments/1m6esqf/archon_soul_its_been_a_year_and_a_half_of_hard/ | F57: slay_the_spire---archon_soul
A58: Vampire Survivors | B58: Archons | C58: 2021 | E58: look at it
A59: Brotato | B59: Arms of God | C59: 2022 | E59: https://steamcommunity.com/app/3100310/discussions/0/735910198043224446/#c735910198043297427 | F59: brotato---arms_of_god
A60: Diablo | B60: Arms of God | C60: 1996 | E60: https://steamcommunity.com/app/3100310/discussions/0/735910198042983690/#c758430178052462886 | F60: diablo---arms_of_god
A61: Vampire Survivors | B61: Arms of God | C61: 2021 | E61: https://steamcommunity.com/app/3100310/discussions/0/735910198043224446/#c735910198043297427 | F61: vampire_survivors---arms_of_god
A62: Vampire Survivors | B62: Army of Ruin | C62: 2021 | E62: check folder | F62: vampire_survivors---army_of_ruin
A63: Peglin | B63: Arrogue | C63: 2022 | E63: https://www.reddit.com/r/roguelites/comments/1ic44r5/my_angry_bird_roguelike_is_finally_out_on_steam/ | F63: peglin---arrogue
A64: Slay the Spire | B64: Arrogue | C64: 2017 | E64: https://www.reddit.com/r/roguelites/comments/1ic44r5/my_angry_bird_roguelike_is_finally_out_on_steam/ | F64: slay_the_spire---arrogue
A65: Darkest Dungeon | B65: As We Descend | C65: 2015 | D65: also mentioned in discord | E65: https://www.reddit.com/r/pcgaming/comments/1kxi8ze/as_we_descend_strategy_roguelike_deckbuilder/ | F65: darkest_dungeon---as_we_descend
A66: Slay the Spire | B66: As We Descend | C66: 2017 | E66: check folder | F66: slay_the_spire---as_we_descend
A67: Hades | B67: Asgard's Fall: Viking Survivors | C67: 2019 | E67: https://www.reddit.com/r/survivorslikes/comments/1jvtb6m/we_released_asgards_fall_on_steam/ | F67: hades---asgard_s_fall_viking_survivors
A68: Vampire Survivors | B68: Asgard's Fall: Viking Survivors | C68: 2021 | E68: look at it
A69: Enter the Gungeon | B69: Asterogues | C69: 2016 | E69: dev has mentioned playing both isaac and gungeon, and also look at it
A70: The Binding of Isaac | B70: Asterogues | C70: 2011 | E70: dev has mentioned playing both isaac and gungeon, and also look at it
A71: Children of Morta | B71: Astral Ascent | C71: 2019 | E71: https://www.scousegamer88.com/2021/03/31/astral-ascent-hibernian-workshop-interview/ | F71: children_of_morta---astral_ascent
A72: Dark Devotion | B72: Astral Ascent | C72: 2019 | D72: Yes | E72: https://www.scousegamer88.com/2021/03/31/astral-ascent-hibernian-workshop-interview/ | F72: dark_devotion---astral_ascent
A73: Dead Cells | B73: Astral Ascent | C73: 2018 | E73: https://www.scousegamer88.com/2021/03/31/astral-ascent-hibernian-workshop-interview/ | F73: dead_cells---astral_ascent
A74: Hades | B74: Astral Ascent | C74: 2019 | E74: https://www.scousegamer88.com/2021/03/31/astral-ascent-hibernian-workshop-interview/ | F74: hades---astral_ascent
A75: Slay the Spire | B75: Astral Ascent | C75: 2017 | E75: https://www.kickstarter.com/projects/hibernian-workshop/astral-ascent#:~:text=Inspired%20by%20rogue%2Dlite%20games,set%20of%20attacks%20and%20spells.
A76: Wizard of Legend | B76: Astral Ascent | C76: 2018 | E76: https://www.scousegamer88.com/2021/03/31/astral-ascent-hibernian-workshop-interview/ | F76: wizard_of_legend---astral_ascent
A77: Slay the Spire | B77: Astrea: Six-Sided Oracles | C77: 2017 | E77: https://indiecator.org/2022/09/26/astrea-six-sided-oracles-interview/ | F77: slay_the_spire---astrea_six_sided_oracles
A78: Brotato | B78: Astro Prospector | C78: 2022 | E78: check folder | F78: brotato---astro_prospector
A79: Enter the Gungeon | B79: Astro Prospector | C79: 2016 | E79: check folder | F79: enter_the_gungeon---astro_prospector
A80: Magicraft | B80: Astro Prospector | C80: 2023 | E80: check folder | F80: magicraft---astro_prospector
A81: Nuclear Throne | B81: Astro Prospector | C81: 2015 | E81: check folder | F81: nuclear_throne---astro_prospector
A82: Vampire Survivors | B82: Astro Prospector | C82: 2021 | E82: check folder | F82: vampire_survivors---astro_prospector
A83: Fushigi no Gensoukyou | B83: Atai no Gensoukyou | C83: 2010 | D83: Yes
A84: Dead Cells | B84: Atomic Owl | C84: 2018 | E84: https://x.com/monstertheaterx/status/1819715822203355558?s=20 | F84: dead_cells---atomic_owl
A85: Enter the Gungeon | B85: Atomicrops | C85: 2016 | E85: https://www.reddit.com/r/Games/comments/czn9i5/were_the_developers_of_atomicrops_an_action/#:~:text=I%20got%20addicted%20to%20Stardew,simply%20stat%20upgrades%20or%20something). | F85: enter_the_gungeon---atomicrops
A86: Nuclear Throne | B86: Atomicrops | C86: 2015 | E86: https://www.reddit.com/r/Games/comments/czn9i5/were_the_developers_of_atomicrops_an_action/#:~:text=I%20got%20addicted%20to%20Stardew,simply%20stat%20upgrades%20or%20something). | F86: nuclear_throne---atomicrops
A87: Slay the Spire | B87: Atomicrops | C87: 2017 | E87: https://www.reddit.com/r/Games/comments/czn9i5/were_the_developers_of_atomicrops_an_action/#:~:text=I%20got%20addicted%20to%20Stardew,simply%20stat%20upgrades%20or%20something). | F87: slay_the_spire---atomicrops
A88: 100 Rogues | B88: Auro: A Monster-Bumping Adventure | C88: 2010 | D88: Yes
A89: Torneko's Great Adventure: Mystery Dungeon | B89: Azure Dreams | C89: 1993 | E89: look at it
A90: Backpack Hero | B90: Backpack Battles | C90: 2022 | E90: https://www.reddit.com/r/IndieGaming/comments/13vr0mm/comment/jm7alk0/?context=3 | F90: backpack_hero---backpack_battles
A91: Super Auto Pets | B91: Backpack Battles | C91: 2021 | E91: check folder | F91: super_auto_pets---backpack_battles
A92: Dicey Dungeons | B92: Backpack Hero | C92: 2019 | E92: check folder | F92: dicey_dungeons---backpack_hero
A93: Inscryption | B93: Backpack Hero | C93: 2021 | E93: check folder | F93: inscryption---backpack_hero
A94: Into the Breach | B94: Backpack Hero | C94: 2018 | E94: https://en.wikipedia.org/wiki/Backpack_Hero#:~:text=Main%20developer%20Jasper%20Cole%20stated,inventory%20as%20an%20additional%20inspiration. | F94: into_the_breach---backpack_hero
A95: Luck be a Landlord | B95: Backpack Hero | C95: 2021 | E95: check folder | F95: luck_be_a_landlord---backpack_hero
A96: Slay the Spire | B96: Backpack Hero | C96: 2017 | E96: https://en.wikipedia.org/wiki/Backpack_Hero#:~:text=Main%20developer%20Jasper%20Cole%20stated,inventory%20as%20an%20additional%20inspiration. | F96: slay_the_spire---backpack_hero
A97: Luck be a Landlord | B97: Balatro | C97: 2021 | E97: https://en.wikipedia.org/wiki/Balatro | F97: luck_be_a_landlord---balatro
A98: ToeJam & Earl | B98: Baldi's Basics Plus | C98: 1991 | E98: https://baldis-basics-in-education-and-learning.fandom.com/wiki/Inspiration_and_reference | F98: toejam_earl---baldi_s_basics_plus
A99: Deep Rock Galactic: Survivor | B99: Ball x Pit | C99: 2024 | E99: https://www.ign.com/articles/city-of-balls-was-the-original-title-and-somehow-ball-x-pit-got-even-weirder-from-there | F99: deep_rock_galactic_survivor---ball_x_pit
A100: Vampire Survivors | B100: Ball x Pit | C100: 2021 | E100: https://www.ign.com/articles/city-of-balls-was-the-original-title-and-somehow-ball-x-pit-got-even-weirder-from-there | F100: vampire_survivors---ball_x_pit
A101: Luck be a Landlord | B101: Ballionaire | C101: 2021 | E101: check folder | F101: luck_be_a_landlord---ballionaire
...

Sheet characters
A1: Name | B1: Game | C1: Health | D1: Gold | E1: Bash | F1: Dash | G1: Push | H1: Transmute | I1: Scramble | J1: Bombs | K1: Keys | L1: Random | M1: Level Up | N1: Reward | O1: Description | P1: Starting loadout | Q1: File
A2: Antonio Belpaese | B2: Vampire Survivors | C2: 7 | D2: 3 | E2: 1 | F2: 0 | G2: 1 | H2: 0 | I2: 0 | J2: 0 | K2: 0 | L2: 0 | M2: Beat a game while having defeated a vampire | N2: Gain +1 Random Sized Chest | O2: What a wonderful night to hunt beasts! | P2: Whip | Q2: AntonioBelpaese
A3: Erratic Deck | B3: Balatro | C3: 7 | D3: 3 | E3: 0 | F3: 0 | G3: 0 | H3: 0 | I3: 0 | J3: 0 | K3: 0 | L3: 2 | M3: Beat a game while having selected a random starting build | N3: Gain +1 Random Card | O3: All Ranks and Suits in deck are randomized | P3: 1 random joker card | Q3: ErraticDeck
A4: Ironclad | B4: Slay the Spire | C4: 8 | D4: 3 | E4: 2 | F4: 0 | G4: 0 | H4: 0 | I4: 0 | J4: 0 | K4: 0 | L4: 0 | M4: Beat a game while having made a Faustian bargain | N4: Gain +1 Small Chest | O4: The remaining soldier of the Ironclads. Sold his soul to harness demonic energies. | P4: Burning Blood | Q4: Ironclad
A5: Isaac | B5: The Binding of Isaac | C5: 6 | D5: 3 | E5: 0 | F5: 0 | G5: 0 | H5: 0 | I5: 0 | J5: 1 | K5: 0 | L5: 0 | M5: Beat a game while having used sorrow or self-inflicted pain as a weapon | N5: Gain +1 Small Chest and +1 Scramble | O5: Who am I? | P5: D6 | Q5: Isaac
A6: Manager | B6: Raccoin: Coin Pusher Roguelike | C6: 7 | D6: 3 | E6: 0 | F6: 0 | G6: 2 | H6: 0 | I6: 0 | J6: 0 | K6: 0 | L6: 0 | M6: Beat a game while having collected 3 different types of currency | N6: Gain +1 Push and +1 Gold | O6: Master in using Math coins and earning tickets. | P6: N/A | Q6: Manager
A7: Minä | B7: Noita | C7: 7 | D7: 3 | E7: 0 | F7: 0 | G7: 0 | H7: 2 | I7: 0 | J7: 0 | K7: 0 | L7: 0 | M7: Beat a game while having crafted or combined a spell or weapon | N7: Gain +1 Transmute | O7: Why must you go destroying everything? Why? For glory? For your precious god of gods. Is it really worth all this? Is it? Is it really? | P7: 1 random wand | Q7: Minä
A8: Poe Ratcho | B8: Vampire Survivors | C8: 7 | D8: 3 | E8: 0 | F8: 0 | G8: 2 | H8: 0 | I8: 0 | J8: 0 | K8: 0 | L8: 0 | M8: Beat a game while being stinky | N8: Gain +1 Random Sized Chest | O8: A malodorous hero | P8: Pummarola | Q8: PoeRatcho
A9: Regent | B9: Slay the Spire 2 | C9: 7 | D9: 3 | E9: 0 | F9: 0 | G9: 1 | H9: 1 | I9: 0 | J9: 0 | K9: 0 | L9: 0 | M9: Beat a game while having made a friend | N9: Gain +1 Small Chest | O9: Heir to the Throne of Stars. Wields cosmic powers but his minions do the work. | P9: N/A | Q9: Regent
A10: Rodney | B10: Rogue | C10: 5 | D10: 3 | E10: 0 | F10: 0 | G10: 0 | H10: 0 | I10: 0 | J10: 0 | K10: 0 | L10: 2 | M10: Beat a game without meta progression | N10: Gain +1 Max Health and +1 Loot | O10: Now I abide here, searching endlessly for the precious Amulet... and finding a thousand horrors. | P10: N/A | Q10: Rodney
A11: Zagreus | B11: Hades | C11: 7 | D11: 3 | E11: 1 | F11: 1 | G11: 0 | H11: 0 | I11: 0 | J11: 0 | K11: 0 | L11: 0 | M11: Beat a game with the help of a God | N11: Gain +1 Large Chest | O11: ... All right, let's give it another shot. | P11: N/A | Q11: Zagreus
A12: Zoe | B12: Haste | C12: 7 | D12: 3 | E12: 0 | F12: 1 | G12: 1 | H12: 0 | I12: 0 | J12: 0 | K12: 0 | L12: 0 | M12: Perfect a game by beating it without losing | N12: Gain +1 Dash | O12: Express Delivery: Arrives with haste, before the world ends. | P12: N/A | Q12: Zoe

Sheet items
A1: Name | B1: Rating | C1: Type | D1: Description | E1: Effect | F1: Reference | G1: tags | H1: pools | I1: File | J1: Sorting
A2: Alien Baby | B2: Rare | C2: Pickup, Passive | D2: Gain +6 Max Health, but all enemies gain +1 Health | E2: item_acquired: gain_max_hp 6; passive: +1 enemy_health | F2: Brotato | G2: alien | I2: AlienBaby | J2: Health
A3: Anchor | B3: Common | C3: Triggered | D3: At the start of combat, Gain +1 Temporary Shield | E3: game_selected: gain_stat shields 1 | F3: Slay the Spire | G3: sea, ship | I3: Anchor | J3: Defense
A4: Ban Hammer | B4: Uncommon | C4: Pickup | D4: Gain +2 Bashes | E4: item_acquired: gain_stat bash 2 | F4: Yet Another Zombie Survivors | G4: tool, hammer | I4: BanHammer | J4: Stats
A5: Bionic Face Plating | B5: Uncommon | C5: Passive | D5: Gain +3 Speed, but this is destroyed when taking damage | E5: passive_status: speed 3; destroy_on_damage | F5: Mewgenics | G5: cybernetics | I5: BionicFacePlating | J5: Stats
A6: Blood Bag | B6: Event | C6: Pickup | D6: Gain +2 Max Health and +8 Health | E6: item_acquired: gain_max_hp 2; gain_hp 8 | F6: The Binding of Isaac | G6: blood | I6: BloodBag | J6: Health
A7: Blood Bombs | B7: Uncommon | C7: Pickup, Triggered | D7: Gain +1 Bomb. When using a Bomb, Gain +1 Health | E7: item_acquired: gain_stat bombs 1; bomb_used: gain_hp 1 | F7: The Binding of Isaac: Rebirth | G7: bomb, blood | I7: BloodBombs | J7: Bomb
A8: Brimstone Bombs | B8: Rare | C8: Pickup, Passive | D8: Gain +1 Bomb. Bombs now apply 1 Stun to all rows in the 4 cardinal directions | E8: item_acquired: gain_stat bombs 1; bomb_cardinal | F8: The Binding of Isaac: Rebirth | G8: bomb | H8: devil_room | I8: BrimstoneBombs | J8: Bomb, Grid
A9: Burning Blood | B9: Starter | C9: Triggered | D9: After beating a game, Gain +1 Health | E9: game_beaten: gain_hp 1 | F9: Slay the Spire | I9: BurningBlood | J9: Health
A10: Caffeine Pill | B10: Common | C10: Passive, Pickup | D10: Gain +1 Speed and +1 Pill | E10: passive_status: speed 1; item_acquired: gain_pill 1 | F10: The Binding of Isaac: Rebirth | G10: drugs, pills | I10: CaffeinePill | J10: Loot, Stats
A11: Calling Bell | B11: Boss | C11: Pickup | D11: Obtain Curse of the Bell and 3 random items — one Common, one Uncommon, one Rare | E11: item_acquired: add_curse curse_of_the_bell, gain_item_per_rarity 3 | F11: Slay the Spire | I11: CallingBell | J11: Special
A12: Cauldron | B12: Rare | C12: Pickup | D12: Gain +5 Potions | E12: item_acquired: gain_potion 5 | F12: Slay the Spire | G12: pot | H12: shop | I12: Cauldron | J12: Loot
A13: Censer | B13: Uncommon | C13: Passive | D13: Enemies in the 2 leftmost columns take no extra turns | E13: front_column_slow 2 | F13: The Binding of Isaac: Rebirth | G13: holy | H13: angel_room | I13: Censer | J13: Combat
A14: Charm of the Vampire | B14: Uncommon | C14: Triggered, Incremental | D14: When you defeat 3 enemies, Gain +1 Health | E14: enemy_killed: counter key=enemies_defeated every=3 -> gain_hp 1 | F14: The Binding of Isaac | G14: bat, vampire | I14: CharmOfTheVampire | J14: Health
A15: Clover | B15: Uncommon | C15: Passive | D15: Gain +1 Luck | E15: passive: +1 luck | F15: Vampire Survivors | G15: plant | I15: Clover | J15: Stats
A16: Crown | B16: Uncommon | C16: Triggered | D16: When Levelling Up, 50% chance to Level Up an additional time | E16: level_up: 50% | F16: Vampire Survivors | G16: wearable, hat, crown | I16: Crown | J16: Economy
A17: D10 | B17: Common | C17: Charged, 2 | D17: Reroll all non-boss enemies | E17: item_used: reroll_enemies | F17: The Binding of Isaac: Rebirth | G17: dice | I17: D10 | J17: Grid
A18: D6 | B18: Uncommon | C18: Charged, 2 | D18: Gain +1 Scramble | E18: item_used: gain_stat scramble 1 | F18: The Binding of Isaac | G18: dice | I18: D6 | J18: Stats
A19: Deck of Cards | B19: Uncommon | C19: Charged, 2 | D19: Gain +1 Card | E19: item_used: gain_card 1 | F19: The Binding of Isaac | I19: DeckOfCards | J19: Loot
A20: Dragon Fruit | B20: Rare | C20: Triggered | D20: Whenever you obtain any amount of gold, Gain +1 Max Health | E20: gold_gained: gain_max_hp 1 | F20: Slay the Spire 2 | G20: food, fruit | H20: shop | I20: DragonFruit | J20: Economy
A21: Echo Chamber | B21: Rare | C21: Passive | D21: Whenever you use Loot, you also use a copy of the last 3 Loot you used after picking up Echo Chamber | E21: echo_loot 3 | F21: The Binding of Isaac: Rebirth | I21: EchoChamber | J21: Loot
A22: Fanny Pack | B22: Uncommon | C22: Passive | D22: 50% chance to spawn 1 random loot on the grid when losing health | E22: health_lost: 50% chance drop_loot 1 | F22: The Binding of Isaac: Rebirth | G22: wearable, bag | I22: FannyPack | J22: Economy
A23: Fortune Necklace | B23: Common | C23: Triggered | D23: When selecting a game, Gain +1 Gold, but this is destroyed when taking damage | E23: game_selected: gain_gold 1; destroy_on_damage | F23: Mewgenics | G23: wearable, necklace | I23: FortuneNecklace | J23: Economy
A24: Gasoline | B24: Common | C24: Passive | D24: Whenever an Enemy is defeated, Add the Fire Tile Effect to the Tile it died on | E24: death_tile fire | F24: Risk of Rain 2 | G24: fire | I24: Gasoline | J24: Grid
A25: Golden Idol | B25: Event | C25: Passive | D25: All enemies drop +1 Gold | E25: gold_per_enemy: 1 | F25: Slay the Spire | G25: gold | I25: GoldenIdol | J25: Economy
A26: Hollow Heart | B26: Common | C26: Pickup | D26: Gain +4 Empty Max Health | E26: item_acquired: gain_empty_max_hp 4 | F26: Vampire Survivors | G26: heart | I26: HollowHeart | J26: Health
A27: Hot Bombs | B27: Uncommon | C27: Passive | D27: Gain +1 Bomb and Bombs Apply the Fire Tile | E27: item_acquired: gain_stat bombs 1; bomb_tile fire | F27: The Binding of Isaac: Rebirth | G27: bomb, fire | I27: HotBombs | J27: Bomb, Grid
A28: Infusion | B28: Uncommon | C28: Triggered | D28: Every time you defeat an Enemy, Gain +1 Empty Max Health | E28: enemy_killed: gain_empty_max_hp 1 | F28: Risk of Rain 2 | G28: blood | I28: Infusion | J28: Health
A29: IV Bag | B29: Event | C29: Usable, 0 | D29: Lose 1 Health and Gain +1 Gold | E29: item_used: lose_hp 1; gain_gold 1 | F29: The Binding of Isaac | G29: blood | I29: IvBag | J29: Economy
A30: Landmines | B30: Uncommon | C30: Passive | D30: After Combat ends, Apply the Landmine Unit to a random empty Tile | E30: game_beaten: apply_unit landmine target=random_empty | F30: Brotato | G30: bomb | I30: Landmines | J30: Grid
A31: Lord's Parasol | B31: Boss | C31: Passive | D31: When encountering a shop, purchase everything in it | E31: shop_sweep | F31: Slay the Spire 2 | G31: umbrella | I31: LordsParasol | J31: Special
A32: Lucky Foot | B32: Uncommon | C32: Passive, Pickup | D32: Gain +1 Luck, +1 Pill, and all negative pills become positive | E32: passive: +1 luck; item_acquired: gain_pill 1; pills_positive | F32: The Binding of Isaac | G32: foot | I32: LuckyFoot | J32: Loot, Stats
A33: Lucky Fysh | B33: Uncommon | C33: Triggered | D33: Whenever you obtain a Card, Gain +1 Gold | E33: card_obtained: gain_gold 1 | F33: Slay the Spire 2 | G33: fish | I33: LuckyFysh | J33: Economy
... A43: Philosophers Stone | B43: Boss | C43: Passive | D43: Increase the Grid length by 1, but give all spawned enemies +1 Strength | E43: grid_length; spawn_status strength 1 | F43: Slay the Spire | G43: stone | I43: PhilosophersStone | J43: Grid
A44: Piggy Bank | B44: Uncommon | C44: Passive | D44: Whenever you lose Health, Gain +1 Gold | E44: health_lost: gain_gold 1 | F44: The Binding of Isaac: Rebirth | G44: pig, bank | H44: shop | I44: PiggyBank | J44: Economy
A45: Pummarola | B45: Uncommon | C45: Triggered | D45: After beating a game, Gain +1 Health | E45: game_beaten: gain_hp 1 | F45: Vampire Survivors | G45: heart | I45: Pummarola | J45: Health
A46: Red Candle | B46: Common | C46: Charged, 1 | D46: Apply the Fire Tile to any tile within the columns 2 and 3 | E46: item_used: apply_tile fire target=tile cols=2-3 | F46: The Binding of Isaac: Rebirth | G46: fire | H46: shop | I46: RedCandle | J46: Grid
A47: Rejuvenation Rack | B47: Rare | C47: Passive | D47: Double the effect of all Healing | E47: heal_multiplier: 2 | F47: Risk of Rain 2 | I47: RejuvenationRack | J47: Health
A48: Reptile Trinket | B48: Uncommon | C48: Triggered | D48: Whenever you drink or throw a potion, Gain +3 Strength until the end of the next combat | E48: potion_used: apply_status strength 3 games=1 | F48: Slay the Spire 2 | I48: ReptileTrinket | J48: Loot, Stats
A49: Ripple Basin | B49: Uncommon | C49: Triggered | D49: If you lose a run before completing any goals, Gain +1 Temporary Shield | E49: run_lost if_goals=0: gain_stat shields 1 | F49: Slay the Spire 2 | I49: RippleBasin | J49: Combat
A50: Runic Dome | B50: Boss | C50: Passive | D50: Increase the Grid length by 1, but you can no longer see enemies that will spawn | E50: grid_length; hide_spawns | F50: Slay the Spire | I50: RunicDome | J50: Grid
A51: Sacred Bark | B51: Boss | C51: Passive | D51: Double the effect of all Loot consumables (Scrolls, Potions, etc) | E51: loot_multiplier: 2 | F51: Slay the Spire | G51: wood | I51: SacredBark | J51: Special
A52: Snowball | B52: Uncommon | C52: Triggered | D52: When you would Gain +1 Transmute, Gain +1 Transmute | E52: stat_gain_bonus: {transmute: 1} | F52: Brotato | G52: snow | I52: Snowball | J52: Stats
A53: Staff of Flame | B53: Rare | C53: Charged, 2 | D53: Apply +3 Burn to a target enemy | E53: item_used: apply_status burn 3 target=enemy | F53: Mewgenics | G53: magic, fire | I53: StaffOfFlame | J53: Grid
A54: Sticky Bombs | B54: Uncommon | C54: Pickup, Triggered | D54: Gain +1 Bomb and Bombs Apply the Web Tile | E54: item_acquired: gain_stat bombs 1; bomb_tile web | F54: The Binding of Isaac: Rebirth | G54: bomb, spider | I54: StickyBombs | J54: Bomb
A55: Stigmata | B55: Uncommon | C55: Pickup | D55: Gain +2 Max Health, Gain +2 Health, and +1 Bash | E55: item_acquired: gain_max_hp 2; gain_hp 2; gain_stat bash 1 | F55: The Binding of Isaac | G55: wood | H55: angel_room | I55: Stigmata | J55: Health, Stats
A56: The Mark | B56: Uncommon | C56: Pickup, Passive | D56: Gain +1 Bash and +1 Speed | E56: item_acquired: gain_stat bash 1; apply_status speed 1 | F56: The Binding of Isaac | G56: devilish | H56: devil_room | I56: TheMark | J56: Stats
A57: There's Options | B57: Uncommon | C57: Passive | D57: Increase the chest size dropped from bosses by 1 | E57: boss_chest_bonus: 1 | F57: The Binding of Isaac: Rebirth | H57: shop | I57: TheresOptions | J57: Stats
A58: Unstable Genome | B58: Uncommon | C58: Triggered | D58: When you beat a game, there's a 33% chance for this item to be destroyed and you may gain 1 of 3 random items | E58: game_beaten: 33% chance random_item_choice 3 destroy_self | F58: Caves of Qud | G58: mutation | I58: UnstableGenome | J58: Economy
A59: Vajra | B59: Common | C59: Status | D59: Gain +1 Strength | E59: item_acquired: apply_status strength 1 | F59: Slay the Spire | I59: Vajra | J59: Stats
A60: White Beast Statue | B60: Uncommon | C60: Passive | D60: Gain +1 Potion at the end of combat | E60: game_beaten: gain_potion 1 | F60: Slay the Spire | G60: statue | I60: WhiteBeastStatue | J60: Loot
A61: Wooden Nickel | B61: Common | C61: Charged, 1 | D61: 50% chance to Gain +1 Gold | E61: item_used: 50% chance gain_gold 1 | F61: The Binding of Isaac: Rebirth | G61: wood, coin | I61: WoodenNickel | J61: Economy

Sheet enemies
A1: Name | B1: Type | C1: Difficulty | D1: Size | E1: Game | F1: Health | G1: Damage | H1: Goal Type | I1: Goal | J1: Ability | K1: File | L1: Tag | M1: Ticked | N1: Count
A2: Attack Fly | B2: Action | C2: 1-Low | D2: 1x1 | E2: The Binding of Isaac | F2: 1 | G2: 1 | H2: Bounty | I2: Defeat 3 bugs | J2: N/A | K2: AttackFly | L2: bug, fly | M2: any time | N2: 3
A3: Baby Alien | B3: Action | C3: 1-Low | D3: 1x1 | E3: Brotato | F3: 1 | G3: 1 | H3: Bounty | I3: Defeat an enemy that is an alien | J3: N/A | K3: BabyAlien | L3: alien | M3: any time
A4: Bullat | B4: Action | C4: 1-Low | D4: 1x1 | E4: Enter the Gungeon | F4: 1 | G4: 1 | H4: Feat | I4: Shoot down a flying enemy | J4: N/A | K4: Bullat | L4: bat, bullet | M4: any time
A5: Doomvas | B5: Action | C5: 1-Low | D5: 1x1 | E5: Rogue Legacy | F5: 1 | G5: 1 | H5: Feat | I5: Destroy a painting | J5: N/A | K5: Doomvas | L5: art | M5: any time
A6: Flaming Fatty | B6: Action | C6: 1-Low | D6: 1x1 | E6: The Binding of Isaac: Rebirth | F6: 1 | G6: 1 | H6: Feat | I6: Push an enemy into fire | J6: Aftermath (Fire) | K6: FlamingFatty | L6: fire | M6: any time
A7: Keybullet Kin | B7: Action | C7: 1-Low | D7: 1x1 | E7: Enter the Gungeon | F7: 1 | G7: 1 | H7: Fetch | I7: Obtain a key | J7: N/A | K7: KeybulletKin | L7: bullet | M7: any time
A8: Lil Dave | B8: Action | C8: 1-Low | D8: 1x1 | E8: Muck | F8: 1 | G8: 1 | H8: Feat | I8: Destroy a wooden structure | J8: N/A | K8: LilDave | M8: any time
A9: Numbskull | B9: Action | C9: 1-Low | D9: 1x1 | E9: Hades | F9: 1 | G9: 1 | H9: Bounty | I9: Defeat an animated body part | J9: N/A | K9: Numbskull | L9: undead, skeleton | M9: any time
A10: Pacer | B10: Action | C10: 1-Low | D10: 1x1 | E10: The Binding of Isaac | F10: 1 | G10: 1 | H10: Bounty | I10: Defeat a headless enemy | J10: N/A | K10: Pacer | M10: any time
A11: Psychic Horf | B11: Action | C11: 1-Low | D11: 1x1 | E11: The Binding of Isaac: Rebirth | F11: 1 | G11: 1 | H11: Feat | I11: Use a homing attack | J11: Ranged (N/A) | K11: PsychicHorf | M11: any time
A12: Skeleton Warrior | B12: Action | C12: 1-Low | D12: 1x1 | E12: Ball x Pit | F12: 1 | G12: 1 | H12: Bounty | I12: Defeat a skeleton with a ball | J12: N/A | K12: SkeletonWarrior | L12: undead, skeleton | M12: any time
A13: Spider | B13: Action | C13: 1-Low | D13: 1x1 | E13: The Binding of Isaac | F13: 1 | G13: 1 | H13: Bounty | I13: Defeat 3 spiders | J13: N/A | K13: Spider | L13: bug, spider | M13: any time | N13: 3
A14: Wisp | B14: Action | C14: 1-Low | D14: 1x1 | E14: Risk of Rain | F14: 1 | G14: 1 | H14: Bounty | I14: Defeat an enemy made of fire | J14: N/A | K14: Wisp | L14: fire | M14: any time
A15: Wringer | B15: Action | C15: 1-Low | D15: 1x1 | E15: Hades | F15: 1 | G15: 1 | H15: Feat | I15: Grab an enemy | J15: N/A | K15: Wringer | L15: undead | M15: any time
A16: Bony | B16: Action | C16: 2-Medium | D16: 1x1 | E16: The Binding of Isaac: Rebirth | F16: 1 | G16: 2 | H16: Bounty | I16: Defeat 5 skeletons | J16: Ranged (3) | K16: Bony | L16: undead, skeleton | M16: any time | N16: 5
A17: Child | B17: Action | C17: 2-Medium | D17: 1x1 | E17: Risk of Rain | F17: 1 | G17: 2 | H17: Bounty | I17: Defeat a child | J17: N/A | K17: Child | L17: alien | M17: any time
A18: Coal Spider | B18: Action | C18: 2-Medium | D18: 1x1 | E18: The Binding of Isaac: Rebirth | F18: 1 | G18: 2 | H18: Feat | I18: Set a rock on fire | J18: N/A | K18: CoalSpider | L18: spider, rock, fire | M18: any time
A19: Flaming Hopper | B19: Action | C19: 2-Medium | D19: 1x1 | E19: The Binding of Isaac | F19: 1 | G19: 2 | H19: Bounty | I19: Defeat an enemy while on fire | J19: Infliction (2, Burn) | K19: FlamingHopper | L19: fire | M19: any time
A20: Fungun | B20: Action | C20: 2-Medium | D20: 1x1 | E20: Enter the Gungeon | F20: 1 | G20: 2 | H20: Feat | I20: Shoot a mushroom | J20: N/A | K20: Fungun | L20: mushroom | M20: any time
A21: King Bullat | B21: Action | C21: 2-Medium | D21: 1x1 | E21: Enter the Gungeon | F21: 1 | G21: 2 | H21: Feat | I21: Shoot down 2 flying enemies | J21: N/A | K21: KingBullat | L21: bat, bullet | M21: any time | N21: 2
A22: Skeletal Brute | B22: Action | C22: 2-Medium | D22: 1x2 | E22: Ball x Pit | F22: 1 | G22: 2 | H22: Bounty | I22: Defeat 2 skeletons with a ball | J22: N/A | K22: SkeletalBrute | L22: undead, skeleton | M22: any time | N22: 2
A23: Bishop | B23: Action | C23: 3-High | D23: 1x1 | E23: The Binding of Isaac: Rebirth | F23: 1 | G23: 3 | H23: Feat | I23: Block damage done to a friendly unit | J23: Bolster (1, Dexterity) | K23: Bishop | M23: any time
A24: Gigantic Vermin | B24: Action | C24: 3-High | D24: 2x2 | E24: Hades | F24: 1 | G24: 3 | H24: Bounty | I24: Defeat a large rodent | J24: N/A | K24: GiganticVermin | L24: rodent, rat | M24: any time
A25: Nemean Chariot | B25: Action | C25: 3-High | D25: 1x1 | E25: Hades | F25: 1 | G25: 3 | H25: Feat | I25: Hit an enemy with a vehicle | J25: Haste (1) | K25: NemeanChariot | M25: any time
A26: Skeletal Bastion | B26: Action | C26: 3-High | D26: 2x3 L 90 CC | E26: Ball x Pit | F26: 1 | G26: 3 | H26: Bounty | I26: Defeat 3 skeletons with a ball | J26: N/A | K26: SkeletalBastion | L26: undead, skeleton | M26: any time | N26: 3
A27: Cultist | B27: Deckbuilder | C27: 1-Low | D27: 1x1 | E27: Slay the Spire | F27: 1 | G27: 1 | H27: Feat | I27: Perform a religious act | J27: Ritual | K27: Cultist | M27: any time
A28: Fungi Beast | B28: Deckbuilder | C28: 1-Low | D28: 1x1 | E28: Slay the Spire | F28: 1 | G28: 1 | H28: Feat | I28: Get infected | J28: N/A | K28: FungiBeast | L28: mushroom | M28: any time
A29: Ice Slime | B29: Deckbuilder | C29: 1-Low | D29: 1x1 | E29: Dungeon Clawler | F29: 1 | G29: 1 | H29: Feat | I29: Freeze an enemy | J29: N/A | K29: IceSlime | L29: slime, ice | M29: any time
A30: Lava Slime | B30: Deckbuilder | C30: 1-Low | D30: 1x1 | E30: Dungeon Clawler | F30: 1 | G30: 1 | H30: Feat | I30: Touch lava | J30: Infliction (1, Burn) | K30: LavaSlime | L30: slime, lava | M30: any time
A31: Punch Construct | B31: Deckbuilder | C31: 1-Low | D31: 1x1 | E31: Slay the Spire 2 | F31: 1 | G31: 1 | H31: Feat | I31: Punch a robot | J31: N/A | K31: PunchConstruct | L31: robot | M31: any time
A32: Shrinker Beetle | B32: Deckbuilder | C32: 1-Low | D32: 1x1 | E32: Slay the Spire 2 | F32: 1 | G32: 1 | H32: Feat | I32: Shrink in size | J32: N/A | K32: ShrinkerBeetle | L32: bug, beetle | M32: any time
A33: Spike Slime (L) | B33: Deckbuilder | C33: 1-Low | D33: 2x2 | E33: Slay the Spire | F33: 1 | G33: 1 | H33: Bounty | I33: Defeat an enemy that splits into another enemy | J33: Split (2, slime tag) | K33: SpikeSlime(L) | L33: slime | M33: any time
A34: Shelled Parasite | B34: Deckbuilder | C34: 2-Medium | D34: 1x1 | E34: Slay the Spire | F34: 1 | G34: 2 | H34: Bounty | I34: Defeat an enemy that looks edible | J34: N/A | K34: ShelledParasite | M34: any time
A35: Snecko | B35: Deckbuilder | C35: 2-Medium | D35: 1x1 | E35: Slay the Spire | F35: 1 | G35: 2 | H35: Restriction | I35: Beat a game while having selected a random starting build | J35: N/A | K35: Snecko | M35: game beaten
A36: The Obscura | B36: Deckbuilder | C36: 2-Medium | D36: 1x1 | E36: Slay the Spire 2 | F36: 1 | G36: 2 | H36: Feat | I36: Create an illusion | J36: Illusionist (1, Random Medium) | K36: TheObscura | M36: any time
A37: Chosen | B37: Deckbuilder | C37: 3-High | D37: 1x1 | E37: Slay the Spire | F37: 1 | G37: 3 | H37: Restriction | I37: Beat a game without using magic | J37: Hexer | K37: Chosen | M37: game beaten
A38: Transient | B38: Deckbuilder | C38: 3-High | D38: 2x2 | E38: Slay the Spire | F38: 1 | G38: 3 | H38: Discovery | I38: Witness an enemy kill itself | J38: Tanky (8), Fading (3) | K38: Transient | M38: any time
A39: Carcass | B39: Strategy | C39: 1-Low | D39: 1x1 | E39: Mewgenics | F39: 1 | G39: 1 | H39: Bounty | I39: Destroy an enemy spawner | J39: Nested Spawner (1, fly tag) | K39: Carcass | M39: any time
A40: Cop Bot | B40: Strategy | C40: 1-Low | D40: 1x1 | E40: Mewgenics | F40: 1 | G40: 1 | H40: Feat | I40: Defy an officer of the law | J40: N/A | K40: CopBot | L40: robot, cop | M40: any time
A41: Goblin | B41: Strategy | C41: 1-Low | D41: 1x1 | E41: Gnomes | F41: 1 | G41: 1 | H41: Bounty | I41: Defeat 3 goblins | J41: N/A | K41: Goblin | L41: goblin | M41: any time | N41: 3
A42: Maggot | B42: Strategy | C42: 1-Low | D42: 1x1 | E42: Mewgenics | F42: 1 | G42: 1 | H42: Bounty | I42: Defeat an infested or rotted enemy | J42: N/A | K42: Maggot | L42: fly | M42: any time
A43: Mung | B43: Strategy | C43: 1-Low | D43: 1x1 | E43: Brutal Orchestra | F43: 1 | G43: 1 | H43: Fetch | I43: Obtain 1 fish | J43: N/A | K43: Mung | L43: fish | M43: any time
A44: Atomic Kitten | B44: Strategy | C44: 2-Medium | D44: 1x1 | E44: Mewgenics | F44: 1 | G44: 2 | H44: Bounty | I44: Defeat a radiated enemy | J44: N/A | K44: AtomicKitten | L44: cat, radiation | M44: any time
A45: Caveman Woman | B45: Strategy | C45: 2-Medium | D45: 1x1 | E45: Mewgenics | F45: 1 | G45: 2 | H45: Discovery | I45: Witness a birth | J45: Entry Summon (1, baby tag) | K45: CavemanWoman | M45: any time
A46: Fetus | B46: Strategy | C46: 2-Medium | D46: 1x1 | E46: Mewgenics | F46: 1 | G46: 2 | H46: Fetch | I46: Find a baby | J46: N/A | K46: Fetus | L46: baby | M46: any time
A47: Host | B47: Strategy | C47: 2-Medium | D47: 1x1 | E47: Mewgenics | F47: 1 | G47: 2 | H47: Feat | I47: Reflect a projectile | J47: Ranged (N/A), Immobile | K47: Host | M47: any time
A48: Love Bot | B48: Strategy | C48: 2-Medium | D48: 1x1 | E48: Mewgenics | F48: 1 | G48: 2 | H48: Feat | I48: Use technology to heal yourself | J48: Melee Ally Buff (1, Speed) | K48: LoveBot | L48: robot | M48: any time
A49: Revola | B49: Strategy | C49: 2-Medium | D49: 1x2 | E49: Brutal Orchestra | F49: 1 | G49: 2 | H49: Feat | I49: Body slam an enemy | J49: Defensive Stance | K49: Revola | M49: any time
A50: Robo-Cat | B50: Strategy | C50: 2-Medium | D50: 1x1 | E50: Mewgenics | F50: 1 | G50: 2 | H50: Bounty | I50: Defeat a robot designed to look like an animal | J50: N/A | K50: Robo-Cat | L50: cat, robot | M50: any time
A51: Sharky | B51: Strategy | C51: 2-Medium | D51: 1x1 | E51: Mewgenics | F51: 1 | G51: 2 | H51: Feat | I51: Bleed an enemy to death | J51: Predatory Scent, Infliction(1, Bleed) | K51: Sharky | L51: cat, fish | M51: any time
A52: Spiked Cat | B52: Strategy | C52: 2-Medium | D52: 1x1 | E52: Mewgenics | F52: 1 | G52: 2 | H52: Feat | I52: Break glass | J52: N/A | K52: SpikedCat | L52: cat | M52: any time
A53: Tornado | B53: Strategy | C53: 2-Medium | D53: 1x1 | E53: Forward: Escape the Fold | F53: 1 | G53: 2 | H53: Discovery | I53: Find a Tornado | J53: N/A | K53: Tornado | M53: any time
A54: Giggling Minister | B54: Strategy | C54: 3-High | D54: 1x1 | E54: Brutal Orchestra | F54: 1 | G54: 3 | H54: Discovery | I54: Get something stolen from you | J54: Theft (1, Item), Agile | K54: GigglingMinister | M54: any time
A55: Skeleton Cat | B55: Strategy | C55: 3-High | D55: 1x1 | E55: Mewgenics | F55: 1 | G55: 3 | H55: Bounty | I55: Defeat a skeleton animal | J55: Restless Remains | K55: SkeletonCat | L55: cat, undead, skeleton | M55: any time
A56: Spider Kitten | B56: Strategy | C56: 3-High | D56: 1x1 | E56: Mewgenics | F56: 1 | G56: 3 | H56: Feat | I56: Trap an enemy in place | J56: Infliction(1, Stun) | K56: SpiderKitten | L56: cat, bug, spider | M56: any time
A57: Gatekeeper | B57: Strategy | C57: 4-Insane | D57: 1x1 | E57: Mewgenics | F57: 1 | G57: 4 | H57: Feat | I57: Steal a soul | J57: Drain (2, Max Health), Entry Summon (1, skeleton tag) | K57: Gatekeeper | L57: undead | M57: any time
A58: Stem Cat | B58: Strategy | C58: 4-Insane | D58: 1x1 | E58: Mewgenics | F58: 1 | G58: 4 | H58: Bounty | I58: Defeat an enemy that clones itself | J58: N/A | K58: StemCat | L58: cat | M58: any time
A59: Floating Eye | B59: Traditional | C59: 1-Low | D59: 1x1 | E59: NetHack | F59: 1 | G59: 1 | H59: Restriction | I59: Beat a game without using melee attacks | J59: N/A | K59: FloatingEye | M59: game beaten
A60: Leprechaun | B60: Traditional | C60: 1-Low | D60: 1x1 | E60: NetHack | F60: 1 | G60: 1 | H60: Discovery | I60: Retrieve stolen currency or items | J60: Theft (2, Gold), Agile | K60: Leprechaun | M60: any time
A61: Monkey | B61: Traditional | C61: 1-Low | D61: 1x1 | E61: Crypt of the NecroDancer | F61: 1 | G61: 1 | H61: Bounty | I61: Defeat an enemy that latches on to you | J61: N/A | K61: Monkey | L61: monkey | M61: any time
A62: Rust Monster | B62: Traditional | C62: 2-Medium | D62: 1x1 | E62: NetHack | F62: 1 | G62: 2 | H62: Restriction | I62: Beat a game without using metal armor | J62: Degradation | K62: RustMonster | M62: game beaten
A63: Stalker | B63: Traditional | C63: 2-Medium | D63: 1x1 | E63: NetHack | F63: 1 | G63: 2 | H63: Feat | I63: Become undetectable | J63: Invisibility | K63: Stalker | M63: any time
A64: Chrome Pyramid | B64: Traditional | C64: 3-High | D64: 1x1 | E64: Caves of Qud | F64: 1 | G64: 3 | H64: Feat | I64: Get an achievement 5% or less of players have gotten | J64: N/A | K64: ChromePyramid | L64: robot | M64: any time
A65: Jabberwock | B65: Traditional | C65: 3-High | D65: 1x1 | E65: NetHack | F65: 1 | G65: 3 | H65: Feat | I65: Behead an enemy | J65: N/A | K65: Jabberwock | M65: any time

Sheet bosses
A1: Name | B1: Type | C1: Difficulty | D1: Size | E1: Game | F1: Health | G1: Damage | H1: Goal Type | I1: Goal | J1: Ability | K1: File | L1: Tag | M1: Phases | N1: Ticked | O1: Count
A2: Beholster | B2: Action | C2: 1-Low | D2: 2x2 | E2: Enter the Gungeon | F2: 1 | G2: 3 | H2: Fetch | I2: Have 6 Guns at once | J2: Ranged (4) | K2: Beholster | L2: gun | N2: any time
A3: Big Chunk | B3: Action | C3: 1-Low | D3: 2x2 | E3: Muck | F3: 1 | G3: 3 | H3: Bounty | I3: Defeat an enemy made of stone | J3: N/A | K3: BigChunk | L3: rock | N3: any time
A4: Colossus | B4: Action | C4: 1-Low | D4: 2x2 | E4: Risk of Rain | F4: 1 | G4: 3 | H4: Discovery | I4: Witness a living structure | J4: Trample | K4: Colossus | N4: any time
A5: Famine | B5: Action | C5: 1-Low | D5: 1x1 | E5: The Binding of Isaac | F5: 1 | G5: 3 | H5: Restriction | I5: Beat a game without eating any food | J5: Ranged (1) | K5: Famine | N5: game beaten
A6: Khidr | B6: Action | C6: 1-Low | D6: 2x2 | E6: Rogue Legacy | F6: 1 | G6: 3 | H6: Feat | I6: Poke an eye | J6: N/A | K6: Khidr | L6: eye | N6: any time
A7: Mega Fatty | B7: Action | C7: 1-Low | D7: 2x2 | E7: The Binding of Isaac: Rebirth | F7: 1 | G7: 3 | H7: Bounty | I7: Defeat an obese enemy | J7: Ranged (2) | K7: MegaFatty | N7: any time
A8: Megaera | B8: Action | C8: 1-Low | D8: 1x1 | E8: Hades | F8: 1 | G8: 3 | H8: Fetch | I8: Date someone | J8: N/A | K8: Megaera | N8: any time
A9: Steven | B9: Action | C9: 1-Low | D9: 1x1 | E9: The Binding of Isaac | F9: 1 | G9: 3 | H9: Discovery | I9: Be in a time loop | J9: N/A | K9: Steven | N9: any time
A10: The Rainmaker | B10: Action | C10: 1-Low | D10: 1x1 | E10: The Binding of Isaac: Rebirth | F10: 1 | G10: 3 | H10: Feat | I10: Take a shower | J10: N/A | K10: TheRainmaker | N10: any time
A11: Charon | B11: Action | C11: 2-Medium | D11: 2x1 | E11: Hades | F11: 1 | G11: 5 | H11: Fetch | I11: Steal from a shop | J11: N/A | K11: Charon | N11: any time
A12: Mom's Heart | B12: Action | C12: 2-Medium | D12: 1x1 | E12: The Binding of Isaac | F12: 1 | G12: 5 | H12: Feat | I12: Break a Heart | J12: N/A | K12: MomsHeart | N12: any time
A13: Resourceful Rat | B13: Action | C13: 2-Medium | D13: 1x1 | E13: Enter the Gungeon | F13: 1 | G13: 5 | H13: Feat | I13: Beat a mini-game inside of a game | J13: N/A | K13: ResourcefulRat | L13: rat | N13: any time
A14: Royal Phalanx | B14: Action | C14: 2-Medium | D14: 1x1 | E14: Ember Knights | F14: 1 | G14: 5 | H14: Feat | I14: Block an attack with an element | J14: Defensive Stance (2) | K14: RoyalPhalanx | N14: any time
A15: Scylla | B15: Action | C15: 2-Medium | D15: 1x1 | E15: Hades II | F15: 1 | G15: 5 | H15: Feat | I15: Perform a song | J15: N/A | K15: Scylla | N15: any time
A16: Wallmonger | B16: Action | C16: 2-Medium | D16: 2x3 | E16: Enter the Gungeon | F16: 1 | G16: 5 | H16: Feat | I16: Destroy a wall | J16: N/A | K16: Wallmonger | N16: any time
A17: Isaac | B17: Action | C17: 3-High | D17: 1x1 | E17: The Binding of Isaac | F17: 1 | G17: 7 | H17: Bounty | I17: Defeat yourself | J17: N/A | K17: Isaac | N17: any time
A18: Lich | B18: Action | C18: 4-Insane | D18: 1x2 | E18: Enter the Gungeon | F18: 1 | G18: 9 | H18: Bounty | I18: Defeat a magic enemy with a gun | J18: N/A | K18: Lich | L18: undead, skeleton | N18: any time
A19: The One Who Waits | B19: Action | C19: 4-Insane | D19: 2x2 | E19: Cult of the Lamb | F19: 1 | G19: 9 | H19: Feat | I19: Enter or Create a religion | J19: N/A | K19: TheOneWhoWaits | N19: any time
A20: Gremlin Nob | B20: Deckbuilder | C20: 1-Low | D20: 1x1 | E20: Slay the Spire | F20: 1 | G20: 3 | H20: Feat | I20: Taunt at someone | J20: N/A | K20: GremlinNob | N20: any time
A21: Lagavulin | B21: Deckbuilder | C21: 1-Low | D21: 2x2 | E21: Slay the Spire | F21: 1 | G21: 3 | H21: Feat | I21: Go to sleep | J21: N/A | K21: Lagavulin | N21: any time
A22: Vantom | B22: Deckbuilder | C22: 1-Low | D22: 1x1 | E22: Slay the Spire 2 | F22: 1 | G22: 3 | H22: Feat | I22: Use an attack that hits 4+ times | J22: Lacerator | K22: Vantom | N22: any time
A23: The Club | B23: Deckbuilder | C23: 2-Medium | D23: 1x1 | E23: Balatro | F23: 1 | G23: 5 | H23: Restriction | I23: Beat a game without backtracking | J23: N/A | K23: TheClub | N23: game beaten
A24: The Goad | B24: Deckbuilder | C24: 2-Medium | D24: 1x1 | E24: Balatro | F24: 1 | G24: 5 | H24: Restriction | I24: Beat a game without using a weapon | J24: N/A | K24: TheGoad | N24: game beaten
A25: The Head | B25: Deckbuilder | C25: 2-Medium | D25: 1x1 | E25: Balatro | F25: 1 | G25: 5 | H25: Restriction | I25: Beat a game without purposefully healing | J25: N/A | K25: TheHead | N25: game beaten
A26: The Insatiable | B26: Deckbuilder | C26: 2-Medium | D26: 2x2 | E26: Slay the Spire 2 | F26: 1 | G26: 5 | H26: Bounty | I26: Consume an enemy | J26: Ruthless, Devour Whole | K26: TheInsatiable | N26: any time
A27: The Window | B27: Deckbuilder | C27: 2-Medium | D27: 1x1 | E27: Balatro | F27: 1 | G27: 5 | H27: Restriction | I27: Beat a game without spending currency | J27: N/A | K27: TheWindow | N27: game beaten
A28: Cerulean Bell | B28: Deckbuilder | C28: 3-High | D28: 1x1 | E28: Balatro | F28: 1 | G28: 7 | H28: Restriction | I28: Beat a game while only taking the first option offered when taking reward options | J28: N/A | K28: CeruleanBell | N28: game beaten
A29: The Needle | B29: Deckbuilder | C29: 3-High | D29: 1x1 | E29: Balatro | F29: 1 | G29: 7 | H29: Restriction | I29: Beat a game while only using 1 hand | J29: N/A | K29: TheNeedle | N29: game beaten
A30: Time Eater | B30: Deckbuilder | C30: 3-High | D30: 1x1 | E30: Slay the Spire | F30: 1 | G30: 7 | H30: Restriction | I30: Beat the game in 2 hours or less | J30: Bolster (3, Speed) | K30: TimeEater | N30: game beaten
A31: Corrupt Heart | B31: Deckbuilder | C31: 4-Insane | D31: 2x2 | E31: Slay the Spire | F31: 1 | G31: 9 | H31: Feat | I31: Get the true ending on the hardest difficulty possible | J31: Hexer (2) | K31: CorruptHeart | N31: any time
A32: Giant Spider | B32: Strategy | C32: 1-Low | D32: 2x2 | E32: Forward: Escape the Fold | F32: 1 | G32: 3 | H32: Bounty | I32: Defeat a bug larger than you | J32: N/A | K32: GiantSpider | L32: bug, spider | N32: any time
A33: Hickory | B33: Strategy | C33: 1-Low | D33: 1x1 | E33: Brutal Orchestra | F33: 1 | G33: 3 | H33: Feat | I33: Light a liquid on fire | J33: Infliction (1, Burn) | K33: Hickory | L33: fire | N33: any time
A34: Marshmallow | B34: Strategy | C34: 1-Low | D34: 1x1 | E34: Mewgenics | F34: 1 | G34: 3 | H34: Feat | I34: Have an enemy defeat another enemy | J34: N/A | K34: Marshmallow | L34: cat | N34: any time
A35: Mobius | B35: Strategy | C35: 1-Low | D35: 2x2 | E35: Brutal Orchestra | F35: 1 | G35: 3 | H35: Fetch | I35: Obtain a large fish | J35: N/A | K35: Mobius | L35: fish | N35: any time
A36: Morana | B36: Strategy | C36: 1-Low | D36: 1x1 | E36: Mewgenics | F36: 1 | G36: 3 | H36: Feat | I36: Raise the dead | J36: Necromancy (1) | K36: Morana | L36: cat | N36: any time
A37: Trigger Fingers | B37: Strategy | C37: 1-Low | D37: 1x1 | E37: Brutal Orchestra | F37: 1 | G37: 3 | H37: Bounty | I37: Defeat a fascist | J37: N/A | K37: TriggerFingers | N37: any time
A38: Chubs & Nubs | B38: Strategy | C38: 2-Medium | D38: 1x2 | E38: Mewgenics | F38: 1 | G38: 5 | H38: Feat | I38: Eat something smelly | J38: N/A | K38: Chubs&Nubs | L38: dog | N38: any time
A39: Flushmaster | B39: Strategy | C39: 2-Medium | D39: 1x1 | E39: Mewgenics | F39: 1 | G39: 5 | H39: Feat | I39: Flush or get flushed | J39: N/A | K39: Flushmaster | N39: any time
A40: Guillatina | B40: Strategy | C40: 2-Medium | D40: 2x2 | E40: Mewgenics | F40: 1 | G40: 5 | H40: Feat/Feat/Bounty | I40: Eat a living creature/Throw a body part/Defeat a rotten enemy | J40: Trample, Undying (2) | K40: Guillotina, Guillotina2, Guillotina3 | L40: cat | M40: 3 | N40: any time
A41: Lord Bunga | B41: Strategy | C41: 2-Medium | D41: 2x1 | E41: Mewgenics | F41: 1 | G41: 5 | H41: Fetch | I41: Become a cannibal | J41: Ruthless, Devour Whole | K41: LordBunga | N41: any time
A42: Trampy | B42: Strategy | C42: 2-Medium | D42: 1x1 | E42: Mewgenics | F42: 1 | G42: 5 | H42: Feat | I42: Get drunk | J42: N/A | K42: Trampy | L42: cat | N42: any time
A43: The Man in the Moon | B43: Strategy | C43: 3-High | D43: 3x3 | E43: Mewgenics | F43: 1 | G43: 7 | H43: Discovery | I43: Go to a Moon | J43: Trample | K43: TheManInTheMoon | N43: any time
A44: Throbbing King | B44: Strategy | C44: 3-High | D44: 2x2 | E44: Mewgenics | F44: 1 | G44: 7 | H44: Fetch | I44: Steal a body part | J44: Ruthless | K44: ThrobbingKing | N44: any time
A45: The Creator | B45: Strategy | C45: 4-Insane | D45: 2x2 | E45: Mewgenics | F45: 1 | G45: 9 | H45: Bounty | I45: Defeat a God | J45: N/A | K45: TheCreator | L45: god | N45: any time
A46: Banshee | B46: Traditional | C46: 1-Low | D46: 1x1 | E46: Crypt of the NecroDancer | F46: 1 | G46: 3 | H46: Restriction | I46: Beat a game while having muted the game | J46: N/A | K46: Banshee | N46: game beaten
A47: Green Banshee | B47: Traditional | C47: 2-Medium | D47: 1x1 | E47: Crypt of the NecroDancer | F47: 1 | G47: 5 | H47: Restriction | I47: Beat a game while having muted the game | J47: N/A | K47: GreenBanshee | N47: game beaten
A48: Dragon | B48: Traditional | C48: 3-High | D48: 1x2 | E48: Rogue | F48: 1 | G48: 7 | H48: Bounty | I48: Slay a dragon boss | J48: Ranged (2), Fireproof, Infliction (1, Burn) | K48: Dragon | N48: any time

Sheet abilities
A1: Name | B1: Type | C1: Variables | D1: Description | E1: Effect
A2: Aftermath | B2: Death | C2: Tile Effect | D2: On Death, will Add X Tile Effect to the Tile it died on | E2: death: apply_tile Y
A3: Agile | B3: Movement | C3: N/A | D3: Can move diagonally if necessary | E3: passive: move_diagonal
A4: Bolster | B4: Buff | C4: Amount, Status Type | D4: Grants X amount of X Status to all other Enemies and Bosses until death | E4: passive: aura_status Y X
A5: Defensive Stance | B5: Intent | C5: Stacks | D5: Will Gain X Dexterity on it's first turn instead of moving or attacking | E5: first_turn: gain_status dexterity X
A6: Degradation | B6: Attack | C6: Amount | D6: When this Enemy attacks and deals damage, it will Destroy X amount of random obtained Loot | E6: hit: destroy_loot X
A7: Devour Whole | B7: Attack | C7: N/A | D7: When this Enemy attacks and deals damage, the target is eaten and dies, including the plaer | E7: hit: devour
A8: Drain | B8: Attack | C8: Amount, Stats | D8: When this Enemy attacks and deals damage, decrease by X the player's Y(Max Health, Luck, Scramble, Bash, Dash, Transmute) | E8: hit: drain_stat Y X
A9: Entry Summon | B9: Summoner | C9: Amount, Enemy Type | D9: Instead of moving or attacking on it's first turn, it will Summon X amount of Y Enemies to a random adjacent tile | E9: first_turn: summon_adjacent X Y
A10: Fading | B10: Death | C10: Amount | D10: Will die at the end of X amount of combats | E10: spawn: set_fades X
A11: Fireproof | B11: Resistance | C11: N/A | D11: Cannot be Burned | E11: passive: immune burn
A12: Haste | B12: Buff | C12: Stacks | D12: Spawns with X Speed | E12: spawn: gain_status speed X
... A32: Restless Remains | B32: Death | C32: N/A | D32: On Health depletion, will leave a corpse with 1 Max Health that will revive in it's current tile on game completion unless fully defeated | E32: death: leave_corpse 1 revive=game_end

Sheet statuses
A1: Name | B1: Type | C1: Game | D1: On Player | E1: On Player Effect | F1: On Enemy | G1: On Enemy Effect | H1: Combat | I1: Decrease | J1: EnemyOnly | K1: Enemy Combat Effect | L1: Stackable | M1: Image
A2: Burn | B2: Debuff | C2: Brutal Orchestra | D2: Gain "You must beat a game while skipping or trashing X items/upgrades or take 3 Damage." | E2: demand "skip or trash {X} [item/upgrade|items/upgrades]" else -> take_damage 3 | F2: Gains "or instead beat a game while skipping or trashing 4-X items/upgrades" | G2: instead "skip or trash {4-X} [item/upgrade|items/upgrades]" | H2: Half Damage dealt | I2: On Completion | J2: Yes | K2: damage_dealt x0.5 | L2: Max: 3 | M2: Burn
A3: Dexterity | B3: Buff | C3: Slay the Spire | D3: Gain "if X or all bosses were beaten without getting hit when beating a game, Gain a [chest reward]" | E3: goal "{X} or all bosses were beaten without getting hit" -> gain_chest reward {X} | F3: Gains "and you must beat X or all bosses without getting hit in the run you complete the goal in" | G3: clause "you must beat {X} or all bosses without getting hit" | H3: Gain +X Shields | I3: N/A | J3: Yes | K3: shield +{X} | L3: Intensity | M3: Dexterity
A4: Marked | B4: Debuff | C4: Mewgenics | D4: Gain "You must beat a game while getting X achievements or take 3 Damage." | E4: demand "get {X} [achievement|achievements]" else -> take_damage 3 | F4: Gains "and if you get X achievements in the run you complete the goal in, Gain a [chest reward]" | G4: bonus "you get {X} [achievement|achievements]" decay -> gain_chest reward {X} | H4: Damage taken increased by x2. Ignores shields. | I4: On Completion | J4: No | K4: damage_taken x2; pierce_shields | L4: Intensity | M4: Marked
A5: Speed | B5: Buff | C5: Mewgenics | D5: Gain "If beaten in 1+(1/2)^(X-2) hours or less, Gain a [chest reward] and 1 Dash" | E5: goal "beaten in {1+(1/2)^(X-2):hours} or less" -> gain_chest reward {X}; gain_stat dash 1 | F5: Gains "and the goal must be completed 1+(1/2)^(X-2) hours or less into that run" | G5: clause "the game must be beaten in {1+(1/2)^(X-2):hours} or less" | H5: Increase tile movement by X | I5: N/A | J5: Yes | K5: tile_move +{X} | L5: Intensity | M5: Speed
A6: Strength | B6: Buff | C6: Slay the Spire | D6: Gain "If beaten while the difficulty is increased X times or as much as possible, Gain a [chest reward] and 1 Bash" | E6: goal "the difficulty is increased {X} [time|times] or as much as possible" -> gain_chest reward {X}; gain_stat bash 1 | F6: Gains "and the difficulty must be increased X times or as much as possible in the run you complete the goal in" | G6: clause "the difficulty must be increased {X} [time|times] or as much as possible" | H6: Increase Damage Dealt by X | I6: N/A | J6: Yes | K6: damage_dealt +{X} | L6: Intensity | M6: Strength
A7: Bleed | B7: Debuff | C7: Mewgenics | D7: Gain "You must beat a game while not healing intentionally or take 3 Damage. This lasts for X games." | E7: demand "not heal intentionally" else -> take_damage 3 | F7: Gains "and if you didn't intentionally heal in the run you complete the goal in, Gain a [chest reward]" | G7: bonus "you didn't intentionally heal" -> gain_chest reward {X} | H7: 50% chance to take 1 Damage when attacking | I7: On Trigger | J7: Yes | K7: recoil +1 chance=50 | L7: Intensity | M7: Bleed
A8: Stun | B8: Debuff | C8: Slay the Spire | D8: Gain "You must beat a game twice in a row to set it as Completed or take 5 Damage. This lasts for X games." | E8: demand "beat a game twice in a row to set it as Completed" else -> take_damage 5 | F8: Gains "and if the goal was completed twice, Gain a [chest reward]" | G8: bonus "you beat the game twice in a row" -> gain_chest reward {X} | H8: Skip their turn | I8: Each Turn | J8: Yes | K8: skip_turn | L8: Intensity | M8: Stun

Sheet events
A1: Event | B1: Game | C1: Tier | D1: Where | E1: Requirement | F1: Trigger | G1: Rarity | H1: Image | I1: Prompt | J1: Opens With | K1: Goal Met | L1: Goal Missed | M1: Chance Won | N1: Chance Lost | O1: Choice 1 | P1: Repeat 1 | Q1: Result 1 | R1: Effect 1 | S1: Choice 2 | T1: Repeat 2 | U1: Result 2 | V1: Effect 2 | W1: Choice 3 | X1: Repeat 3 | Y1: Result 3 | Z1: Effect 3 | AA1: Choice 4 | AB1: Repeat 4 | AC1: Result 4 | AD1: Effect 4 | AE1: Choice 5 | AF1: Repeat 5 | AG1: Result 5 | AH1: Effect 5 | AI1: Choice 6 | AJ1: Repeat 6 | AK1: Result 6 | AL1: Effect 6
A2: Abyssal Baths | B2: Slay the Spire 2 | C2: All | F2: After | G2: Common | H2: AbyssalBaths | I2: You discover a secluded chamber. Steam rises from bubbling pools of hot liquid that shifts colors with hypnotic rhythm. Barnacled growths hang from the ceiling, dripping viscous fluid that hisses and writhes when it touches the surface. The air feels heavy, laden with salt and something unmistakably organic. As you approach the edge of the largest pool, the liquid ripples. The waters bubble more intensely as if anticipating your entry. | O2: Immerse | P2: Stay | Q2: The liquid burns against your skin, simultaneously freezing and scalding. Beneath the surface, something brushes against your legs—tendrils? Currents with purpose? But when the pain subsides, you feel... denser somehow. More substantial. | R2: gain_max_hp 1; lose_hp 2 | S2: Linger | T2: Again | U2: The temperature keeps rising! How long can you endure before the steam cooks you from within? || It keeps getting hotter! The pool's bubbling sounds like laughter. IT'S SO HOT! || You wonder if this is what it's like to live in the Village of Demons? You have bathed so long you have lost track of time and your mind... It's nice in here. Really fantastic. || If you bathe any longer you will die. | V2: needs Immerse > 0; gain_max_hp 1; lose_hp {3+X} | W2: Abstain | Y2: You decline the temptation of the waters, instead gathering crystalline salts that have formed along the edges. As you apply them to your skin, the pools churn and froth agitatedly. | Z2: needs Immerse = 0; gain_hp 3 | AA2: Exit Baths | AC2: The heat finally gets to you, and you hop out of the bath. | AD2: needs Immerse > 0; nothing
A3: Arcade Room | B3: The Binding of Isaac | C3: All | E3: gold>=1 | F3: After | G3: Common | H3: ArcadeRoom | O3: Enter | P3: Stay | R3: lose_gold 1; spawn_object tag=arcade 2-3 | S3: Leave | V3: nothing
A4: Battleworn Dummy | B4: Slay the Spire 2 | C4: All | F4: After | G4: Common | H4: BattlewornDummy | I4: As you approach, it begins to rumble and fizzle and lights up brilliantly! "BZZZT! TIME TO TRAIN!!! YOU HAVE 3 TURNS TO DEFEAT ME! CHOOSE A SETTING OR FACE LETHAL HUMILIATION." | K4: "YOU PASS THE TRAINING! YOU ARE NOW EQUIPPED TO DEFEND THIS FACTORY AGAINST INTRUDERS!! BE SURE TO HYDRATE AFTER TRAINING SESSIONS!" | L4: "YOU ARE WEAK!! HUMILIATION HAS BEEN ADMINISTERED!" The dummy is silent for a moment and— "Choose a lower setting next time." | O4: Setting 1 | R4: add_goal "beat a game in 5 attempts or fewer" for 3 games -> gain_potion 1 | S4: Setting 2 | V4: add_goal "beat a game in 3 attempts or fewer" for 3 games -> gain_chest small 1 | W4: Setting 3 | Z4: add_goal "beat a game in 1 attempt" for 3 games -> gain_chest large 1
A5: Golden Idol | B5: Slay the Spire | C5: All | F5: After | G5: Common | H5: GoldenIdol | I5: You come across an inconspicuous pedestal with a shining gold idol sitting peacefully atop. It looks incredibly valuable. You sure don't see any traps nearby. | O5: Take | P5: Stay | Q5: As you grab the Idol and stow it away, a giant boulder smashes through the ceiling into the ground next to you. You realize that the floor is slanted downwards as the boulder starts to roll towards you. | R5: gain_item golden_idol | S5: Leave | U5: If there was ever an obvious trap, this would be it. You decide not to interfere with objects placed upon pedestals. | V5: needs Take = 0; nothing | W5: Outrun | Y5: RUUUUUUUUUUN! You barely leap into a side passageway as the boulder rushes by. Unfortunately it feels like you sprained something however. | Z5: needs Take > 0; lose_hp {max(1,round(0.25*MAX_HP))} | AA5: Smash | AC5: You throw yourself at the boulder with everything you have. When the dust clears, you can make a safe way out. | AD5: needs Take > 0; add_curse injury | AE5: Hide | AG5: SQUISH! The boulder flattens you a little as it passes by, but otherwise you can get out of here. | AH5: needs Take > 0; lose_max_hp {max(1,round(0.08*MAX_HP))}
A6: Golden Monkey | B6: Tiny Rogues | C6: All | F6: After | G6: Common | H6: GoldenMonkey | O6: Touch the Golden Monkey | R6: gain_stat luck 1; add_curse random | S6: Leave | V6: nothing
A7: Jungle Maze Adventure | B7: Slay the Spire 2 | C7: All | F7: After | G7: Common | H7: JungleMazeAdventure | I7: In a clearing, you run into a Ragtag Group of Adventurers looking down and gesturing at a gigantic maze. They offer to join forces with you in an Epic Quest to loot the riches of this maze. As an experienced adventurer yourself, it's clear this maze is filled with deadly traps and guardians. It would be easier if you work together, but then you would have to split the loot. | O7: Solo Quest | Q7: Feeling misanthropic, you wordlessly walk past their now-frowning faces. One of them even shakes their fist at you. The maze is not welcoming. You fall into a spike trap, you are struck by a massive log with spikes, and feisty creatures with spiky clubs fight you along the entire journey. You are sick of spikes, and consider teamwork for the next adventure. | R7: gain_gold 3; lose_hp 2 | S7: Join Forces | U7: Everyone's face immediately lights up, including your own! One of the adventurers turns out to be a bard! You merrily waltz into the maze as Aquid the squid wizard effortlessly disarms traps, while you and the Grathorian fighter take out the spiky club-wielding guards with ease. This was the most joyous adventure of your life and you've made some truly Great Memories. | V7: gain_gold 1
A8: Morphic Grove | B8: Slay the Spire 2 | C8: All | E8: gold >=3 | F8: After | G8: Common | H8: MorphicGrove | I8: You enter a grove of crystalline trees, and they begin to quiver excitedly! A chorus of hellos and welcomes bombard you as a group of Morphics burst forth from trees. One of the Morphics is fidgeting in the corner, clearly not as sociable as the others. Approach the group or the loner? | O8: Group | Q8: You greet the chittering Morphics and they embrace you into their crystally arms. They share their combined knowledge and inject you with Morphic Magic, changing your nature... Such lovely creatures, these Morphics. One of them stole your gold. | R8: gain_stat transmute 2; lose_gold all | S8: Loner | U8: You reach out a hand to the lone Morphic, sympathizing with its nature. It gifts you a tiny crystal fruit, and you consume it, as is custom. The fruit clarifies your mind and purpose. You give thanks, then make your way onwards. | V8: gain_max_hp 1
A9: Potion Lab | B9: Tiny Rogues | C9: All | F9: After | G9: Rare | H9: PotionLab | J9: offer_loot potion 3 | O9: Leave | R9: nothing
A10: Punch Off | B10: Slay the Spire 2 | C10: All | E10: games >= 6 | F10: After | G10: Common | H10: PunchOff | I10: Two Punch Constructs are duking it out and you see some treasure in between them... Should you try to nab it? | O10: Nab | Q10: You successfully nab the relic! ...or so you thought. A right-hook clocks you in the face. | R10: add_curse injury; gain_chest small 1 | S10: I Can Take Them | U10: The Constructs turn to you menacingly! | V10: spawn_enemy tag=robot 1; play_game tag=mecha -> gain_loot 1; gain_chest small 2
A11: Ranwid the Elder | B11: Slay the Spire 2 | C11: All | E11: gold>=2 and potions>=1 and relics>=1 | F11: After | G11: Common | H11: RanwidTheElder | I11: You are approached by the oldest person you have ever seen. “We meet once more... it's me, Ranwid!” You do not know this man. | O11: Give 2 Gold | Q11: “Mag.. nificent...” Ranwid mumbles while chewing the gold. | R11: needs gold 2; lose_gold 2; gain_random_item 1 | S11: Give <potion> | U11: “Exquisite...” Glup glup glup. He downs the <potion> in one go. | V11: lose_potion; gain_random_item 1 | W11: Give <relic> | Y11: “Exemplary...” Ranwid observes the relic studiously for several minutes... Then eats the <relic>. | Z11: lose_relic; gain_random_item 2
A12: Relic Trader | B12: Slay the Spire 2 | C12: All | E12: relics >= 5 | F12: After | G12: Common | H12: RelicTrader | I12: You turn a corner and suddenly, a shadowy figure is just standing there. He pivots to face you. “Welcome! What're ya trading?” The figure inquires as he flares open his cloak to reveal a slew of suspicious wares. | O12: Take the Top One | Q12: “Hehehe Heh... Thank you!” | R12: trade_relic 1 | S12: Take the Middle One | U12: “Hehehe Heh... Thank you!” | V12: trade_relic 2 | W12: Take the Bottom One | Y12: “Hehehe Heh... Thank you!” | Z12: trade_relic 3
A13: Scrap Ooze | B13: Slay the Spire | C13: All | F13: After | G13: Common | H13: ScrapOoze | I13: As you walk into the room you hear a gurgling and the grinding of metals. Before you is a slime-like creature that ate too much scrap for its own good. From the center of the creature you see glints of strange light, perhaps something magical? It looks like you can get some treasure if you just reach inside its... opening. However, the acid and sharp objects may hurt. | M13: Success! After rummaging through the metal and burning acid, you finally grab hold of a relic and yank it out. You pull your way out of the ooze damaged but rewarded. | N13: Ouch! All you find is corroded metal and a bit of burning pain. However, you're still convinced there's a relic... | O13: Reach Inside | P13: Stay | R13: lose_hp 1; chance 25% -> gain_chest small 1 | S13: Deeper | T13: Again | V13: needs Reach Inside > 0; lose_hp {2+X}; chance {35+10*X}% -> gain_chest small 1 | W13: Leave | Y13: You decide to leave the area. The slime pays no attention, content with its meal. | Z13: nothing
A14: The Woman in Blue | B14: Slay the Spire | C14: All | E14: gold>=3 | F14: After | G14: Common | H14: TheWomanInBlue | I14: From the darkness, an arm pulls you into a small shop. As your eyes adjust, you see a pale woman in sharp clothes gesturing towards a wall of potions. Pale Woman: “Buy a potion. Now!” she states. | O14: Buy 1 Potion | Q14: Pale Woman: “Good. Now leave.” You exit the shop cautiously. | R14: needs gold 1; lose_gold 1; gain_potion 1 | S14: Buy 2 Potions | U14: Pale Woman: “Good. Now leave.” You exit the shop cautiously. | V14: needs gold 2; lose_gold 2; gain_potion 2 | W14: Buy 3 Potions | Y14: Pale Woman: “Good. Now leave.” You exit the shop cautiously. | Z14: needs gold 3; lose_gold 3; gain_potion 3 | AA14: Leave | AC14: WHAM. Her gloved fist collides with your face, nearly knocking you off your feet. Pale Woman: “Get out before I litter the floor with your guts.” You take her word and exit with your guts still safely in your body. | AD14: nothing
A15: Unrest Site | B15: Slay the Spire 2 | C15: All | E15: hp <= 70% | F15: After | G15: Common | H15: UnrestSite | I15: You find a secluded Rest Site and start a fire to get some rest. Once the fire is started, it begins to swell, reaching not upwards but sideways towards a grove of oil-seeping trees. | O15: Rest Anyways | Q15: All this adventuring has left you exhausted, and despite the oddities, you decide to sleep. You toss and turn as the fire roars and crackles through the night. The disgusting trees give off a wretched scent from their pitch-black sap. | R15: heal_full; add_curse poor_sleep | S15: Kill the Trees | U15: These trees are clearly malicious so you decide to get rid of them. Days later, you're covered in ash and oily goop. A massive flock of little byrd spirits rise from the slain trees and drop a small box at your feet. "Thank you for freeing us from those trees... cheep cheep!" | V15: lose_max_hp 2; gain_chest small 1
A16: We Meet Again! | B16: Slay the Spire | C16: All | E16: gold>=2 | F16: After | G16: Common | H16: WeMeetAgain | I16: “We meet again!” A cheery disheveled fellow approaches you gleefully. You do not know this man. “It's me, Ranwid! Have any goods for me today? The usual? A fella like me can't make it alone, you know?” You eye him suspiciously and consider your options... | O16: Give <potion> | Q16: Ranwid: “Exquisite! Was feeling parched.” Glup glup glup. He downs the potion in one go and lets out a satisfied burp. He rummages around his various pockets... Ranwid: “Here, look what I've got for you today! Take it take it!” | R16: lose_potion; gain_random_item 1 | S16: Give 2 Gold | U16: Ranwid: “Magnificent! This will be quite handy if I run into those mask wearing hoodlums again.” He rummages around his various pockets... Ranwid: “Here, look what I've got for you today! Take it take it!” | V16: needs gold 2; lose_gold 2; gain_random_item 1 | W16: Give <card> | Y16: Ranwid: “Exemplary! I shall study this further in my chambers.” He rummages around his various pockets... Ranwid: “Here, look what I've got for you today! Take it take it!” | Z16: lose_card uncommon+; gain_random_item 1 | AA16: Attack | AC16: Ranwid: “Aaaaagghh!! What a jerk you are sometimes!” He runs away. | AD16: nothing
A17: Whispering Hollow | B17: Slay the Spire 2 | C17: All | E17: gold >=1 | F17: After | G17: Common | H17: WhisperingHollow | I17: Making your way through a hollow of dead trees you happen upon a single bone-white tree. Clay baubles hang off its branches, which curve inward like protective ribs. Such a creepy tree. It whispers. ...make exchange..... | O17: Exchange Gold | Q17: You scatter some gold at the base of the tree and two of the clay vessels drop to the floor soundlessly. They break open, and contain perfectly intact potions within. You nab the potions and flee. | R17: lose_gold 1; gain_loot 2 | S17: Hug the Tree | U17: The whispering compels you to give it gold but you resist and give the tree a big hug instead! It thrashes about, scratching you with its branches, but eventually calms down. The tree-hugging experience transforms you. ...make hug.....? | V17: lose_hp 1; gain_stat transmute 1

Sheet cards
A1: Name | B1: Rarity | C1: Type | D1: Description | E1: Effect | F1: Tags | G1: Game | H1: Image | I1: Icon Image
A2: ? Card | B2: Uncommon | C2: Usable | D2: Copy the effect of a selected Usable Item in your inventory | E2: copy_item | G2: The Binding of Isaac: Rebirth | H2: QuestionMarkCard | I2: Isaac_Playing_Cards
A3: 0 - The Fool | B3: Uncommon | C3: Usable | D3: Teleport to the Starting Game | E3: teleport_start | F3: tarot | G3: The Binding of Isaac | H3: 0TheFool | I3: Isaac_Major_Arcana
A4: 2 of Clubs | B4: Rare | C4: Usable | D4: Double your Bombs, if you have no Bombs then Gain +2 | E4: double_stat bombs floor=2 | F4: playing_card | G4: The Binding of Isaac | H4: 2OfClubs | I4: Isaac_Playing_Cards
A5: 2 of Diamonds | B5: Rare | C5: Usable | D5: Double your Gold, if you have no Gold Gain +2 Gold | E5: double_stat gold floor=2 | F5: playing_card | G5: The Binding of Isaac | H5: 2OfDiamonds | I5: Isaac_Playing_Cards
A6: 2 of Hearts | B6: Rare | C6: Usable | D6: Double your Health | E6: double_stat hp | F6: playing_card | G6: The Binding of Isaac | H6: 2OfHearts | I6: Isaac_Playing_Cards
A7: Ancient Recall | B7: Rare | C7: Usable | D7: Gain +3 Random Cards | E7: gain_loot card 3 | G7: The Binding of Isaac: Rebirth | H7: AncientRecall | I7: Isaac_MTG_Cards
A8: Barricade | B8: Rare | C8: Passive | D8: When a game resolves, unspent Temporary Shields become Shields | E8: bank_shields | G8: Slay the Spire | H8: Barricade | I8: Slay_the_Spire_Ironclad_Rare
A9: Blueprint | B9: Rare | C9: Passive | D9: Copy the effect of the loot to the right of this if possible | E9: copy_right | F9: joker | G9: Balatro | H9: Blueprint | I9: Balatro_Playing_Cards
A10: Chaos the Clown | B10: Common | C10: Passive | D10: Whenever you enter a shop, Gain +1 Scramble | E10: shop_entered: gain_stat scramble 1 | F10: joker | G10: Balatro | H10: ChaosTheClown | I10: Balatro_Playing_Cards
A11: Echo Form | B11: Rare | C11: Passive | D11: The first loot you use each game plays an additional copy | E11: echo_first_loot 1 | G11: Slay the Spire | H11: EchoForm | I11: Slay_the_Spire_Defect_Rare
A12: IV - The Emperor | B12: Common | C12: Usable | D12: Spawn a random Boss from the current Game Type and Difficulty Tier | E12: spawn_boss | F12: tarot | G12: The Binding of Isaac | H12: IVTheEmperor | I12: Isaac_Major_Arcana
A13: IX - The Hermit | B13: Uncommon | C13: Usable | D13: Teleport to the nearest Shop | E13: teleport_shop | F13: tarot | G13: The Binding of Isaac | H13: IXTheHermit | I13: Isaac_Major_Arcana
A14: Queen of Hearts | B14: Rare | C14: Usable | D14: Gain from +1 to +20 Health | E14: gain_hp 1-20 | F14: playing_card | G14: The Binding of Isaac: Rebirth | H14: QueenOfHearts | I14: Isaac_Playing_Cards
A15: Ride the Bus | B15: Uncommon | C15: Usable | D15: Teleport to a random Deckbuilder Game | E15: teleport_type deckbuilder | F15: joker | G15: Balatro | H15: RideTheBus | I15: Balatro_Playing_Cards
A16: Rocket | B16: Uncommon | C16: Passive | D16: Whenever you complete a game, Gain +1 Gold. Increase Gold payout by 2 when you defeat a boss. | E16: game_won: gain_gold 1 plus=counter; enemy_killed if_boss: bump 2 | F16: joker | G16: Balatro | H16: Rocket | I16: Balatro_Playing_Cards
A17: To the Moon | B17: Uncommon | C17: Passive | D17: Whenever you complete a game, Gain +1 Gold for each 3 Gold you have. | E17: game_won: gain_gold 1 per=3 of=gold | F17: joker | G17: Balatro | H17: ToTheMoon | I17: Balatro_Playing_Cards
A18: Trading Card | B18: Uncommon | C18: Passive | D18: Once per game, Gain +2 Gold when trashing a card | E18: card_binned once_per_game: gain_gold 2 | F18: joker | G18: Balatro | H18: TradingCard | I18: Balatro_Playing_Cards
A19: V - The Hierophant | B19: Common | C19: Usable | D19: Gain +2 Shields | E19: gain_stat bonus_shields 2 | F19: tarot | G19: The Binding of Isaac | H19: VTheHierophant | I19: Isaac_Major_Arcana
A20: VI - The Lovers | B20: Common | C20: Usable | D20: Gain +2 Health | E20: gain_hp 2 | F20: tarot | G20: The Binding of Isaac | H20: VITheLovers | I20: Isaac_Major_Arcana
A21: XIV - Temperance | B21: Common | C21: Usable | D21: Spawn a Blood Donation Machine | E21: spawn_object blood_donation_machine | F21: tarot | G21: The Binding of Isaac | H21: XIVTemperance | I21: Isaac_Major_Arcana

Sheet scrolls
A1: Scrolls | B1: Game | C1: Preference | D1: Rarity | E1: Description | F1: Effect | G1: Tags | H1: File | I1: Notes | K1: Random Scroll Name | L1: Game | N1: Random Scroll Part | O1: Game
A2: Scroll of Aggravate Monsters | B2: Rogue | C2: Negative | D2: Common | E2: All current enemies Gain +1 Strength | F2: apply_status strength 1 all | K2: ANDOVA BEGARIN | L2: NetHack | N2: ah | O2: Rogue
A3: Scroll of Amnesia | B3: Hack | C3: Negative | D3: Uncommon | E3: Forget 1 random Identified Loot. | F3: forget loot 1 | H3: Amnesia | K3: DAIYEN FOOELS | L3: NetHack | N3: arek | O3: Rogue
A4: Scroll of Create Monster | B4: Rogue | C4: Negative | D4: Uncommon | E4: Spawn a Random Enemy with the current Difficulty | F4: spawn_enemy current | K4: DUAM XNAHT | L4: NetHack | N4: bahl | O4: Rogue
A5: Scroll of Identify | B5: Rogue | C5: Positive | D5: Common | E5: Choose 1 Loot to Identify. | F5: identify_loot choose 1 | H5: Identify | I5: Not rolled with the other scrolls: 10% of every loot drop is this one instead. | K5: ELAM EBOW | L5: NetHack | N5: bar | O5: Rogue
A6: Scroll of Scare Monster | B6: Rogue | C6: Positive | D6: Uncommon | E6: Apply +1 Stun to a target Enemy | F6: stun_enemies choose 1 | K6: ELBIB YLOH | L6: NetHack | N6: barf | O6: Rogue
A7: Scroll of Teleportation | B7: Rogue | C7: Neutral | D7: Common | E7: Teleport to a Random Space with roughly the same distance from the Amulet Game. (+ or - 2) | F7: teleport same 2 | H7: Teleportation | K7: FOOBIE BLETCH | L7: NetHack | N7: behil | O7: Rogue
A8: Scroll of Fire | B8: Hack | C8: Negative | D8: Uncommon | E8: Gain +3 Burn, Apply the Fire Tile and +3 Burn to all everything in the first column | F8: apply_status burn 3 player; apply_tile fire front; apply_status burn 3 front | G8: heat | K8: GARVEN DEH | L8: NetHack | N8: blech | O8: Rogue
A9: Scroll of Remove Curse | B9: Rogue | C9: Positive | D9: Rare | E9: Remove 1 target Curse | F9: remove_curse choose 1 | K9: HACKEM MUCHE | L9: NetHack | N9: blorp | O9: Rogue
K10: JUYED AWK YACC | L10: NetHack | N10: bloto | O10: Rogue
K11: KERNOD WEL | L11: NetHack | N11: caca | O11: Rogue
K12: KIRJE | L12: NetHack | N12: coph | O12: Rogue
K13: LEP GEX VEN ZEA | L13: NetHack | N13: druhl | O13: Rogue
K14: NR 9 | L14: NetHack | N14: erp | O14: Rogue
K15: PRATYAVAYAH | L15: NetHack | N15: festr | O15: Rogue
K16: PRIRUTSENIE | L16: NetHack | N16: flem | O16: Rogue
K17: READ ME | L17: NetHack | N17: foo | O17: Rogue
K18: TEMOV | L18: NetHack | N18: grit | O18: Rogue
K19: THARR | L19: NetHack | N19: ichi | O19: Rogue
K20: VE FORBRYDERNE | L20: NetHack | N20: ighr | O20: Rogue
K21: VELOX NEB | L21: NetHack | N21: iky | O21: Rogue
... K37: TIDDER ROF | L37: WazHack | N37: tims | O37: Rogue
N38: yuky | O38: Rogue
N39: zep | O39: Rogue
N40: zihr | O40: Rogue

Sheet pills
A1: Name | B1: Preference | C1: Description | D1: Effect | E1: Horse Description | F1: Horse Effect | G1: Notes
A2: 48 Hour Energy | B2: Positive | C2: Gain +3 Charges for random Chargeable Items and Loot | D2: charge random 3 | E2: Fully Charge 3 Random Chargeable Items and Loot | F2: charge random 3 full
A3: Amnesia | B3: Negative | C3: Gain a Random Curse and Forget 1 random Identified Loot | D3: add_curse random; forget loot 1 | E3: Gain a Random Curse and Forget all Identified loot | F3: add_curse random; forget loot all
A4: Bad Trip | B4: Negative | C4: Lose -2 Health | D4: lose_hp 2 lethal=heal_full | E4: Lose -4 Health | F4: lose_hp 4 lethal=heal_full | G4: When a Bad Trip pill when it would kill you, it becomes Full Health
A5: Balls of Steel | B5: Positive | C5: Gain +2 Shields | D5: gain_stat bonus_shields 2 | E5: Gain +4 Shields | F5: gain_stat bonus_shields 4
A6: Full Health | B6: Positive | C6: Heal to full health | D6: heal_full | E6: Heal to full health and Gain +3 Shields | F6: heal_full; gain_stat bonus_shields 3
A7: Health Down | B7: Negative | C7: Lose -2 Max Health | D7: lose_max_hp 2 | E7: Lose -4 Max Health | F7: lose_max_hp 4
A8: Health Up | B8: Positive | C8: Gain +2 Max Health | D8: gain_max_hp 2 | E8: Gain +4 Max Health | F8: gain_max_hp 4
A9: Luck Down | B9: Negative | C9: Lose -1 Luck | D9: lose_stat luck 1 | E9: Lose -2 Luck | F9: lose_stat luck 2
A10: Luck Up | B10: Positive | C10: Gain +1 Luck | D10: gain_stat luck 1 | E10: Gain +2 Luck | F10: gain_stat luck 2
A11: Telepills | B11: Neutral | C11: Teleport to a Random Space with roughly the same distance from the Amulet Game. (+ or - 2) | D11: teleport same 2 | E11: Teleport to a Random Space with a 1-3 distance from the Amulet Game | F11: teleport amulet 1 3

Sheet potions
A1: Name | B1: Rarity | C1: Preference | D1: On Player | E1: On Player Effect | F1: On Tile | G1: On Tile Effect | H1: Tags | I1: Reference | J1: File
A2: Fire Potion | B2: Common | C2: Negative | D2: Gain +3 Burn | E2: apply_status burn 3 player | F2: Apply the Fire tile and Apply +3 Burn to everything in a 3x3 area centered on this tile | G2: apply_tile fire area=3x3; apply_status burn 3 area=3x3 | H2: heat | I2: Slay the Spire | J2: FirePotion
A3: Block Potion | B3: Common | C3: Positive | D3: Gain +2 Shields | E3: gain_stat bonus_shields 2 | F3: Apply 2 Sheilds | G3: grant_shield 2 area=cell | I3: Slay the Spire | J3: BlockPotion
A4: Speed Potion | B4: Common | C4: Positive | D4: Gain +5 Dexterity until the end of the next combat | E4: apply_status dexterity 5 player games=1 | F4: Apply +5 Dexterity until the end of the next combat | G4: apply_status dexterity 5 area=cell games=1 | I4: Slay the Spire | J4: SpeedPotion
A5: Flex Potion | B5: Common | C5: Positive | D5: Gain +5 Strength until the end of the next combat | E5: apply_status strength 5 player games=1 | F5: Apply +5 Strength until the end of the next combat | G5: apply_status strength 5 area=cell games=1 | I5: Slay the Spire | J5: FlexPotion
A6: Fruit Juice | B6: Rare | C6: Positive | D6: Gain +2 Max Health | E6: gain_max_hp 2 | F6: Apply +2 Max Health | G6: grant_max_health 2 area=cell | I6: Slay the Spire | J6: FruitJuice
A7: Dexterity Potion | B7: Common | C7: Positive | D7: Gain +2 Dexterity until the end of the next combat | E7: apply_status dexterity 2 player games=1 | F7: Apply +1 Dexterity until the end of the next combat | G7: apply_status dexterity 1 area=cell games=1 | I7: Slay the Spire | J7: DexterityPotion
A8: Strength Potion | B8: Common | C8: Positive | D8: Gain +2 Strength until the end of the next combat | E8: apply_status strength 2 player games=1 | F8: Apply +1 Strength until the end of the next combat | G8: apply_status strength 1 area=cell games=1 | I8: Slay the Spire | J8: StrengthPotion
A9: Explosive Ampoule | B9: Common | C9: Negative | D9: Take 3 Damage | E9: take_damage 3 | F9: Deal 1 Damage everything on this tile and it's row | G9: deal_damage 1 area=row | I9: Slay the Spire | J9: ExplosiveAmpoule
A10: Fysh Oil | B10: Uncommon | C10: Positive | D10: Gain +1 Strength and +1 Dexterity until the end of the next combat | E10: apply_status strength 1 player games=1; apply_status dexterity 1 player games=1 | F10: Apply +1 Strength and +1 Dexterity until the end of the next combat | G10: apply_status strength 1 area=cell games=1; apply_status dexterity 1 area=cell games=1 | I10: Slay the Spire 2 | J10: FyshOil
A11: Potion of Healing | B11: Common | C11: Positive | D11: Gain +2 Health | E11: gain_hp 2 | F11: Apply +2 Health | G11: grant_health 2 area=cell | I11: Rogue | J11: N/A
A12: Potion of Raise Level | B12: Rare | C12: Positive | D12: Gain +1 Level | E12: gain_level 1 | F12: N/A | G12: none | I12: Rogue | J12: N/A
A13: Potion of Extra Healing | B13: Rare | C13: Positive | D13: Gain +5 Health | E13: gain_hp 5 | F13: Apply +5 Health | G13: grant_health 5 area=cell | I13: Rogue | J13: N/A
A14: Potion of Haste Self | B14: Uncommon | C14: Positive | D14: Gain +2 Speed until the end of the next combat | E14: apply_status speed 2 player games=1 | F14: Apply +2 Speed until the end of the next combat | G14: apply_status speed 2 area=cell games=1 | I14: Rogue | J14: N/A
... A16: Potion of Uselessness | B16: Uncommon | C16: Neutral | D16: Do nothing | E16: none | F16: Do nothing | G16: none | I16: Ancient Domains of Mystery | J16: N/A

Sheet wands
A1: Name | B1: Rarity | C1: Game | D1: Preference | E1: Type | F1: Charges | G1: Description | H1: Effect | I1: Tags | J1: File
A2: Wand of Cancellation | B2: Uncommon | C2: Rogue | D2: Positive | E2: Ray | F2: 2 | G2: Target Unit loses it's ability | H2: cancel_abilities | J2: N/A
A3: Wand of Create Monster | B3: Rare | C3: NetHack | D3: Negative | E3: Non-Directional | F3: 4 | G3: Spawn 1 Random Enemy to the Board | H3: spawn_enemy current | J3: N/A
A4: Wand of Death | B4: Legendary | C4: NetHack | D4: Positive | E4: Ray | F4: 1 | G4: Target Unit is instantly killed | H4: kill | J4: N/A
A5: Wand of Fire | B5: Rare | C5: Rogue | D5: Positive | E5: Ray | F5: 3 | G5: Apply +3 Burn to any Unit on target Tile and apply the Fire Tile to this Tile | H5: apply_status burn 3 target=enemy; apply_tile fire | I5: Heat | J5: N/A
A6: Wand of Haste Monster | B6: Common | C6: Rogue | D6: Negative | E6: Ray | F6: 3 | G6: Target Unit Gains +1 Speed | H6: apply_status speed 1 target=enemy | J6: N/A
A7: Wand of Invisibility | B7: Common | C7: Rogue | D7: Negative | E7: Ray | F7: 3 | G7: Target Unit becomes invisible | H7: grant_ability invisibility | J7: N/A
A8: Wand of Magic Missile | B8: Common | C8: Rogue | D8: Positive | E8: Ray | F8: 2 | G8: Target Unit takes 1 Damage | H8: deal_damage 1 | J8: N/A
A9: Wand of Nothing | B9: Common | C9: Rogue | D9: Neutral | E9: Random | F9: 4 | G9: Do nothing | H9: nothing | J9: N/A
A10: Wand of Plenty | B10: Uncommon | C10: Brogue | D10: Neutral | E10: Ray | F10: 2 | G10: Target Unit is split into two of the same Units with half Max Health if possible | H10: split | J10: N/A
A11: Wand of Polymorph | B11: Rare | C11: Rogue | D11: Positive | E11: Ray | F11: 3 | G11: Target Unit becomes a random Enemy of the same difficulty | H11: polymorph | J11: N/A
A12: Wand of Teleportation | B12: Rare | C12: Rogue | D12: Positive | E12: Ray | F12: 3 | G12: Target Unit is transported to a random Tile | H12: teleport | J12: N/A
A13: Wand of Wishing | B13: Legendary | C13: NetHack | D13: Positive | E13: Non-Directional | F13: 1 | G13: Obtain any one item in the game | H13: obtain_item any | J13: N/A

Sheet trinkets
A1: Name | B1: Rarity | C1: Size | D1: Type | E1: Description | F1: Effect | G1: Tag | H1: Game | I1: Image
A2: Bloody Penny | B2: Common | C2: 1x1 | D2: Passive | E2: 25% chance to Gain +1 Health when gaining Gold | F2: gold_gained: 25% chance gain_hp 1 | G2: coin, blood | H2: The Binding of Isaac | I2: BloodyPenny
A3: Broccoli | B3: Uncommon | C3: 2x1 | D3: Charged | E3: Whenever you defeat an enemy, Gain +1 Charge. On 6 Charges, Gain +2 Luck | F3: enemy_killed charges=6: gain_stat luck 2 | G3: food, vegetable | H3: Backpack Battles | I3: Broccoli
A4: Burnt Penny | B4: Uncommon | C4: 1x1 | D4: Passive | E4: 25% chance to Gain +1 Bomb when gaining Gold | F4: gold_gained: 25% chance gain_stat bombs 1 | G4: coin | H4: The Binding of Isaac | I4: BurntPenny
A5: Carrot | B5: Uncommon | C5: 1x2 | D5: Charged | E5: Whenever you defeat an enemy, Gain +1 Charge. On 3 Charges, Lose 1 Random Debuff | F5: enemy_killed charges=3: remove_random_debuff 1 | G5: food, vegetable | H5: Backpack Battles | I5: Carrot
A6: Charged Penny | B6: Uncommon | C6: 1x1 | D6: Passive | E6: 16% chance to Gain +1 Charge to a random Chargeable Item or Loot when gaining Gold | F6: gold_gained: 16% chance charge_random 1 | G6: coin | H6: The Binding of Isaac: Rebirth | I6: ChargedPenny
A7: Cheese | B7: Rare | C7: 1x2 | D7: Charged | E7: Whenever you defeat an enemy, Gain +1 Charge. On 4 Charges, Gain +5 Empty Max Health and Gain +1 Random Buff | F7: enemy_killed charges=4: gain_empty_max_hp 5; gain_random_buff 1 | G7: food, dairy | H7: Backpack Battles | I7: Cheese
A8: Counterfeit Penny | B8: Rare | C8: 1x1 | D8: Passive | E8: 50% chance to Gain +1 Gold when gaining Gold | F8: gold_gained: 50% chance gain_gold 1 | G8: coin | H8: The Binding of Isaac | I8: CounterfeitPenny
A9: Cupcake | B9: Rare | C9: 1x1 | D9: Charged | E9: Whenever you defeat an enemy, Gain +1 Charge. On 6 Charges, Gain +5 Health and Gain +1 Buff to the one you have the most of | F9: enemy_killed charges=6: gain_hp 5; gain_top_buff 1 | G9: food, sweets | H9: Backpack Battles | I9: Cupcake
A10: Duplicator | B10: Rare | C10: 1x1 | D10: Passive | E10: Adjacent Weapons trigger an extra time | F10: weapon_retrigger +1 dirs=adjacent | G10: ring | H10: Vampire Survivors | I10: Duplicator
A11: Endless Nameless | B11: Uncommon | C11: 1x1 | D11: Passive | E11: Whenever you use a loot, 25% chance to spawn a duplicate of that loot on the board | F11: loot_used: 25% chance drop_copy | H11: The Binding of Isaac: Rebirth | I11: EndlessNameless
A12: Garlic | B12: Common | C12: 2x1 | D12: Charged | E12: Whenever you defeat an enemy, Gain +1 Charge. On 4 Charges, Gain +3 Temporary Shield | F12: enemy_killed charges=4: gain_stat shields 3 | G12: food, vegetable, garlic | H12: Backpack Battles | I12: Garlic
A13: Goat Hoof | B13: Common | C13: 1x1 | D13: Passive | E13: Gain +1 Speed | F13: passive_status: speed 1 | H13: The Binding of Isaac | I13: GoatHoof
A14: Hairpin | B14: Common | C14: 1x1 | D14: Passive | E14: Fully Charge a random Chargeable Item or Loot when a Boss spawns | F14: boss_spawned: charge_random full | H14: The Binding of Isaac: Rebirth | I14: Hairpin
A15: Isaac's Fork | B15: Common | C15: 1x1 | D15: Passive | E15: 25% chance to Gain +1 Health when Completing a Game | F15: game_won: 25% chance gain_hp 1 | H15: The Binding of Isaac | I15: IsaacsFork
A16: Lucky Toe | B16: Uncommon | C16: 1x1 | D16: Passive | E16: Gain +1 Luck | F16: passive: +1 luck | H16: The Binding of Isaac | I16: LuckyToe
A17: Swallowed Penny | B17: Uncommon | C17: 1x1 | D17: Passive | E17: Gain +1 Gold when losing Health | F17: health_lost: gain_gold 1 | G17: coin | H17: The Binding of Isaac: Rebirth | I17: SwallowedPenny
A18: Whetstone | B18: Common | C18: 1x1 | D18: Passive | E18: Weapons above and below Gain +1 Stun | F18: weapon_stun +1 dirs=up,down | G18: stone, whetstone | H18: Backpack Battles | I18: Whetstone
A19: Wooden Cross | B19: Rare | C19: 1x1 | D19: Passive | E19: At the start of combat, Gain +1 Temporary Shield | F19: game_selected: gain_stat shields 1 | G19: wood | H19: The Binding of Isaac: Rebirth | I19: WoodenCross

Sheet weapons
A1: Name | B1: Rarity | C1: Size | D1: Aim | E1: Area | F1: Effect | G1: Type | H1: Passive | I1: Passive Effect | J1: Goal | K1: Charge | L1: Tag | M1: Game | N1: Image
A2: Bloody Tear | B2: Rare | C2: 2x2 | D2: front | E2: 4x1 | F2: stun 2 | G2: Melee | H2: Gain +1 Health for each enemy hit | I2: weapon_hit if_self: gain_hp 1 | J2: Defeat a vampire | K2: 3 | L2: blood | M2: Vampire Survivors | N2: BloodyTear
A3: Hero Longsword | B3: Rare | C3: 3x1 | D3: front | E3: 3x2 | F3: stun 2, push right 1 | G3: Melee | H3: Every Weapon adjacent to this Gains +2 Stun | I3: weapon_stun +2 dirs=adjacent | J3: Be a hero | K3: 3 | M3: Backpack Battles | N3: HeroLongsword
A4: Hero Sword | B4: Uncommon | C4: 2x1 | D4: front | E4: 2x1 | F4: stun 1 | G4: Melee | H4: Every Weapon adjacent to this Gains +1 Stun | I4: weapon_stun +1 dirs=adjacent | J4: Be a hero | K4: 3 | M4: Backpack Battles | N4: HeroSword
A5: King Bomber | B5: Rare | C5: 1x2 | D5: any | E5: plus | F5: stun 2 | G5: Ranged | H5: Gain +1 Gold for each enemy Stunned with this weapon | I5: weapon_stunned if_self: gain_gold 1 | J5: Explode an enemy with a cannon ball | K5: 3 | M5: Enter the Gungeon | N5: KingBomber
A6: Lightning Ring | B6: Uncommon | C6: 1x1 | D6: random | E6: 1x1 | F6: stun 1 | G6: Ranged | H6: Gains +1 Replay after each use (Max 4 times) | I6: replay_on_use +1 max=4 | J6: Defeat an enemy with a lightning bolt | K6: 3 | L6: ring, lightning | M6: Vampire Survivors | N6: LightningRing
A7: Lil' Bomber | B7: Common | C7: 1x2 | D7: any | E7: plus | F7: stun 1 | G7: Ranged | H7: N/A | J7: Explode an enemy with a cannon ball | K7: 3 | M7: Enter the Gungeon | N7: LilBomber
A8: Stankus' Toothpick | B8: Rare | C8: 2x1 | D8: front | E8: 2x1 | F8: stun 1 | G8: Melee | H8: Every 2 Food adjacent to this weapon gives this +1 Stun | I8: stun_per_food +1 per=2 | J8: Attack an enemy with food | K8: 3 | M8: Backpack Battles | N8: StankusToothpick
A9: Thunder Loop | B9: Rare | C9: 1x1 | D9: random | E9: plus | F9: stun 1 | G9: Ranged | H9: Gains +1 Replay after each use (Max 4 times) | I9: replay_on_use +1 max=4 | J9: Defeat an enemy with a lightning bolt | K9: 3 | L9: ring, lightning | M9: Vampire Survivors | N9: ThunderLoop
A10: Whip | B10: Common | C10: 2x2 | D10: front | E10: 3x1 | F10: stun 1 | G10: Melee | H10: N/A | J10: Defeat a vampire | K10: 3 | M10: Vampire Survivors | N10: Whip
A11: Wooden Sword | B11: Common | C11: 2x1 | D11: front | E11: 2x1 | F11: stun 1 | G11: Melee | H11: N/A | J11: Defeat an enemy with wooden gear on | K11: 3 | L11: wood | M11: Backpack Battles | N11: WoodenSword

Sheet evolutions
A1: Name | B1: Requirement 1 | C1: Requirement 2 | D1: Outcome
A2: Hero Longsword | B2: Hero Sword | C2: Any 2 Items or Trinkets with "whetstone" | D2: Consume All
A3: Hero Sword | B3: Wooden Sword | C3: Any Item or Trinket with "whetstone" | D3: Consume All
A4: King Bomber | B4: Lil' Bomber | C4: Any Item or Trinket with "crown" | D4: Consume None
A5: Stankus' Toothpick | B5: Hero Sword | C5: Any Item or Trinket with "garlic" | D5: Consume All
A6: Thunder Loop | B6: Lightning Ring | C6: Duplicator | D6: Consume None
A7: Bloody Tear | B7: Whip | C7: Any Item or Trinket with "heart" | D7: Consume None

Sheet bags
A1: Name | B1: Rarity | C1: Size | D1: Description | E1: Effect | F1: Game | G1: Image
A2: Fanny Pack | B2: Common | C2: 1x2 | D2: When Loot inside this bag would Gain +1 Charge, it has a +10% chance to Gain +1 Charge | E2: charge_bonus 10% | F2: Backpack Battles | G2: FannyPack
A3: Holdall | B3: Rare | C3: 2x3 | D3: At the start of combat, Gain +1 Temporary Shield for every 2 Unidentified Loot in this bag | E3: game_selected: gain_stat shields 1 per=2 of=unidentified_in_bag | F3: Backpack Battles | G3: Holdall
A4: Leather Bag | B4: Common | C4: 2x2 | D4: N/A | E4: N/A | F4: Backpack Battles | G4: LeatherBag
A5: Potion Belt | B5: Rare | C5: 4x1 | D5: The first time a potion is consumed while inside this bag, Gain +1 Random Buff. Every 4 Potions consumed in this bag removes a random Debuff on the player. | E5: loot_used if_loot=potion if_in_bag once_per_game: gain_random_buff 1; loot_used if_loot=potion if_in_bag every=4: remove_random_debuff 1 | F5: Backpack Battles | G5: PotionBelt
A6: Protective Purse | B6: Uncommon | C6: 1x1 | D6: At the start of combat, Gain +1 Temporary Shield | E6: game_selected: gain_stat shields 1 | F6: Backpack Battles | G6: ProtectivePurse

Sheet objects
A1: Name | B1: Game | C1: Tag | D1: Image | E1: Rarity | F1: Limit | G1: Unique | H1: Where | I1: Requirement | J1: Trigger | K1: Prompt | L1: Chance Won | M1: Chance Lost | N1: Choice 1 | O1: Repeat 1 | P1: Result 1 | Q1: Effect 1 | R1: Choice 2 | S1: Repeat 2 | T1: Result 2 | U1: Effect 2 | V1: Choice 3 | W1: Repeat 3 | X1: Result 3 | Y1: Effect 3 | Z1: Choice 4 | AA1: Repeat 4 | AB1: Result 4 | AC1: Effect 4 | AD1: Choice 5 | AE1: Repeat 5 | AF1: Result 5 | AG1: Effect 5 | AH1: Choice 6 | AI1: Repeat 6 | AJ1: Result 6 | AK1: Effect 6
A2: Blood Donation Machine | B2: The Binding of Isaac | C2: arcade | D2: BloodDonationMachine | E2: Common | L2: The machine exploded, and {ITEM} appeared. | N2: Give Blood | O2: Again | Q2: lose_hp 1; chance 6.7% -> gain_item_of blood_bag|iv_bag; destroy_object else gain_gold 1 | R2: Bomb | U2: needs bombs 1; spend_bomb 1; gain_pickups 2-4 hp|gold; destroy_object
A3: Donation Machine | B3: The Binding of Isaac: Rebirth | C3: arcade | D3: DonationMachine | E3: Common | G3: Yes | N3: Give Gold | O3: Again | Q3: needs gold 1; needs not_jammed; needs bank_space; donate_gold 1; roll 5% gain_stat luck 1; roll {1+X}% jam_object | R3: Bomb | U3: needs bombs 1; spend_bomb 1; bank_payout 2-5; destroy_object run

Sheet curses
A1: Curse | B1: Game | C1: Condition | D1: Penalty | E1: Timer | F1: Image
A2: Curse of the Bell | B2: Slay the Spire | C2: you don't ring a bell | D2: spawn_enemy | E2: N/A | F2: CurseOfTheBell
A3: Injury | B3: Slay the Spire 2 | C3: you go below half health | D3: spawn_enemy | E3: 3 | F3: Injury
A4: Poor Sleep | B4: Slay the Spire 2 | C4: you use a rest site to replenish health | D4: spawn_enemy | E4: 3 | F4: PoorSleep

Sheet tiles
A1: Name | B1: Description | C1: Effect | D1: Interactions | E1: Decay | F1: Img
A2: Fire | B2: Apply +1 Burn to enemies who enter or start their turn on this tile | C2: enemy_enters: apply_status burn 1; enemy_turn_start: apply_status burn 1 | E2: 3 Games | F2: Fire
A3: Web | B3: Apply +1 Stun to enemies who enter or start their turn on this tile | C3: enemy_enters: apply_status stun 1; enemy_turn_start: apply_status stun 1 | E3: Until Triggered | F3: Web

Sheet units
A1: Name | B1: Type | C1: Description | D1: Effect | E1: Interactions | F1: Health | G1: Img
A2: Landmine | B2: Inanimate | C2: On contact with an enemy, or when it takes damage, destroy itself, explode, and trigger your bomb effects | D2: enemy_enters: detonate; damaged: detonate | E2: tile fire: detonate_unit; remove_tile | F2: 1 | G2: Landmine

Sheet goals
A1: Goal | B1: Type | C1: Difficulty | D1: Owner Sheet | E1: Owner | F1: Owner Detail | G1: Relation | H1: Ticked | I1: Count | J1: Tags
A2: Be in a time loop | B2: Discovery | C2: 1-Low | D2: boss | E2: Steven | G2: has | H2: any time
A3: beat a game twice in a row to set it as Completed | D3: status | E3: Stun | F3: on player | G3: modifies | H3: game beaten
A4: Beat a game without meta progression | D4: character | E4: Rodney | G4: has | H4: game beaten
A5: Beat a mini-game inside of a game | B5: Feat | C5: 2-Medium | D5: boss | E5: Resourceful Rat | G5: has | H5: any time
A6: beat a game while not healing intentionally | D6: status | E6: Bleed | F6: on player | G6: modifies | H6: game beaten
A7: beat a game while skipping or trashing X items/upgrades | D7: status | E7: Burn | F7: on player | G7: modifies | H7: game beaten
A8: Beat the game in 2 hours or less | B8: Restriction | C8: 3-High | D8: boss | E8: Time Eater | G8: has | H8: game beaten
A9: beat a game while getting X achievements | D9: status | E9: Marked | F9: on player | G9: modifies | H9: game beaten
A10: Become a cannibal | B10: Fetch | C10: 2-Medium | D10: boss | E10: Lord Bunga | G10: has | H10: any time
A11: Become undetectable | B11: Feat | C11: 2-Medium | D11: enemy | E11: Stalker | G11: has | H11: any time
A12: Behead an enemy | B12: Feat | C12: 3-High | D12: enemy | E12: Jabberwock | G12: has | H12: any time
A13: Bleed an enemy to death | B13: Feat | C13: 2-Medium | D13: enemy | E13: Sharky | G13: has | H13: any time
A14: Block an attack with an element | B14: Feat | C14: 2-Medium | D14: boss | E14: Royal Phalanx | G14: has | H14: any time
A15: Block damage done to a friendly unit | B15: Feat | C15: 3-High | D15: enemy | E15: Bishop | G15: has | H15: any time
A16: Body slam an enemy | B16: Feat | C16: 2-Medium | D16: enemy | E16: Revola | G16: has | H16: any time
A17: Break a Heart | B17: Feat | C17: 2-Medium | D17: boss | E17: Mom's Heart | G17: has | H17: any time
A18: Break glass | B18: Feat | C18: 2-Medium | D18: enemy | E18: Spiked Cat | G18: has | H18: any time
A19: Beat a game while having collected 3 different types of currency | D19: character | E19: Manager | G19: has | H19: game beaten
A20: Consume an enemy | B20: Bounty | C20: 2-Medium | D20: boss | E20: The Insatiable | G20: has | H20: any time
A21: Beat a game while having crafted or combined a spell or weapon | D21: character | E21: Minä | G21: has | H21: game beaten
A22: Create an illusion | B22: Feat | C22: 2-Medium | D22: enemy | E22: The Obscura | G22: has | H22: any time
A23: Date someone | B23: Fetch | C23: 1-Low | D23: boss | E23: Megaera | G23: has | H23: any time
A24: Defeat 3 bugs | B24: Bounty | C24: 1-Low | D24: enemy | E24: Attack Fly | G24: has | H24: any time | I24: 3
A25: Defeat 3 goblins | B25: Bounty | C25: 1-Low | D25: enemy | E25: Goblin | G25: has | H25: any time | I25: 3
A26: Defeat 5 skeletons | B26: Bounty | C26: 2-Medium | D26: enemy | E26: Bony | G26: has | H26: any time | I26: 5
A27: Defeat 3 spiders | B27: Bounty | C27: 1-Low | D27: enemy | E27: Spider | G27: has | H27: any time | I27: 3
A28: Defeat a bug larger than you | B28: Bounty | C28: 1-Low | D28: boss | E28: Giant Spider | G28: has | H28: any time
A29: Defeat a child | B29: Bounty | C29: 2-Medium | D29: enemy | E29: Child | G29: has | H29: any time
A30: Defeat a fascist | B30: Bounty | C30: 1-Low | D30: boss | E30: Trigger Fingers | G30: has | H30: any time
A31: Defeat a headless enemy | B31: Bounty | C31: 1-Low | D31: enemy | E31: Pacer | G31: has | H31: any time
A32: Defeat a large rodent | B32: Bounty | C32: 3-High | D32: enemy | E32: Gigantic Vermin | G32: has | H32: any time
A33: Defeat a magic enemy with a gun | B33: Bounty | C33: 4-Insane | D33: boss | E33: Lich | G33: has | H33: any time
A34: Defeat a radiated enemy | B34: Bounty | C34: 2-Medium | D34: enemy | E34: Atomic Kitten | G34: has | H34: any time
A35: Defeat a robot designed to look like an animal | B35: Bounty | C35: 2-Medium | D35: enemy | E35: Robo-Cat | G35: has | H35: any time
A36: Defeat a rotten enemy | B36: Bounty | C36: 2-Medium | D36: boss | E36: Guillatina | F36: phase 3 of 3 | G36: has | H36: any time
A37: Defeat a skeleton animal | B37: Bounty | C37: 3-High | D37: enemy | E37: Skeleton Cat | G37: has | H37: any time
A38: Defeat a skeleton with a ball | B38: Bounty | C38: 1-Low | D38: enemy | E38: Skeleton Warrior | G38: has | H38: any time
A39: Defeat 2 skeletons with a ball | B39: Bounty | C39: 2-Medium | D39: enemy | E39: Skeletal Brute | G39: has | H39: any time | I39: 2
A40: Defeat 3 skeletons with a ball | B40: Bounty | C40: 3-High | D40: enemy | E40: Skeletal Bastion | G40: has | H40: any time | I40: 3
A41: Defeat an animated body part | B41: Bounty | C41: 1-Low | D41: enemy | E41: Numbskull | G41: has | H41: any time
A42: Defeat an enemy made of fire | B42: Bounty | C42: 1-Low | D42: enemy | E42: Wisp | G42: has | H42: any time
A43: Defeat an enemy made of stone | B43: Bounty | C43: 1-Low | D43: boss | E43: Big Chunk | G43: has | H43: any time
A44: Defeat an enemy that clones itself | B44: Bounty | C44: 4-Insane | D44: enemy | E44: Stem Cat | G44: has | H44: any time
A45: Defeat an enemy that is an alien | B45: Bounty | C45: 1-Low | D45: enemy | E45: Baby Alien | G45: has | H45: any time
A46: Defeat an enemy that latches on to you | B46: Bounty | C46: 1-Low | D46: enemy | E46: Monkey | G46: has | H46: any time
A47: Defeat an enemy that looks edible | B47: Bounty | C47: 2-Medium | D47: enemy | E47: Shelled Parasite | G47: has | H47: any time
A48: Defeat an enemy that splits into another enemy | B48: Bounty | C48: 1-Low | D48: enemy | E48: Spike Slime (L) | G48: has | H48: any time
A49: Defeat an enemy while on fire | B49: Bounty | C49: 2-Medium | D49: enemy | E49: Flaming Hopper | G49: has | H49: any time
A50: Defeat an infested or rotted enemy | B50: Bounty | C50: 1-Low | D50: enemy | E50: Maggot | G50: has | H50: any time
A51: Defeat an obese enemy | B51: Bounty | C51: 1-Low | D51: boss | E51: Mega Fatty | G51: has | H51: any time
A52: Defeat yourself | B52: Bounty | C52: 3-High | D52: boss | E52: Isaac | G52: has | H52: any time
... A65: Beat a game without eating any food | B65: Restriction | C65: 1-Low | D65: boss | E65: Famine | G65: has | H65: game beaten
A66: Eat a living creature | B66: Feat | C66: 2-Medium | D66: boss | E66: Guillatina | F66: phase 1 of 3 | G66: has | H66: any time
A67: Eat something smelly | B67: Feat | C67: 2-Medium | D67: boss | E67: Chubs & Nubs | G67: has | H67: any time
A68: Enter or Create a religion | B68: Feat | C68: 4-Insane | D68: boss | E68: The One Who Waits | G68: has | H68: any time
A69: Find a baby | B69: Fetch | C69: 2-Medium | D69: enemy | E69: Fetus | G69: has | H69: any time
A70: Find a Tornado | B70: Discovery | C70: 2-Medium | D70: enemy | E70: Tornado | G70: has | H70: any time
A71: Flush or get flushed | B71: Feat | C71: 2-Medium | D71: boss | E71: Flushmaster | G71: has | H71: any time
A72: Freeze an enemy | B72: Feat | C72: 1-Low | D72: enemy | E72: Ice Slime | G72: has | H72: any time
A73: Get an achievement 5% or less of players have gotten | B73: Feat | C73: 3-High | D73: enemy | E73: Chrome Pyramid | G73: has | H73: any time
A74: Get drunk | B74: Feat | C74: 2-Medium | D74: boss | E74: Trampy | G74: has | H74: any time
A75: Beat a game with the help of a God | D75: character | E75: Zagreus | G75: has | H75: game beaten
A76: Get infected | B76: Feat | C76: 1-Low | D76: enemy | E76: Fungi Beast | G76: has | H76: any time
A77: Get something stolen from you | B77: Discovery | C77: 3-High | D77: enemy | E77: Giggling Minister | G77: has | H77: any time
A78: Get the true ending on the hardest difficulty possible | B78: Feat | C78: 4-Insane | D78: boss | E78: Corrupt Heart | G78: has | H78: any time
A79: Go to a Moon | B79: Discovery | C79: 3-High | D79: boss | E79: The Man in the Moon | G79: has | H79: any time
A80: Go to sleep | B80: Feat | C80: 1-Low | D80: boss | E80: Lagavulin | G80: has | H80: any time
A81: Grab an enemy | B81: Feat | C81: 1-Low | D81: enemy | E81: Wringer | G81: has | H81: any time
A82: Have an enemy defeat another enemy | B82: Feat | C82: 1-Low | D82: boss | E82: Marshmallow | G82: has | H82: any time
A83: Hit an enemy with a vehicle | B83: Feat | C83: 3-High | D83: enemy | E83: Nemean Chariot | G83: has | H83: any time
A84: If beaten in 1+(1/2)^(X-2) hours or less | D84: status | E84: Speed | F84: on player | G84: modifies | H84: game beaten
A85: If beaten while the difficulty is increased X times or as much as possible | D85: status | E85: Strength | F85: on player | G85: modifies | H85: game beaten
A86: if X or all bosses were beaten without getting hit when beating a game | D86: status | E86: Dexterity | F86: on player | G86: modifies | H86: game beaten
A87: Defeat a God | B87: Bounty | C87: 4-Insane | D87: boss | E87: The Creator | G87: has | H87: any time
A88: Beat a game while having defeated a vampire | D88: character | E88: Antonio Belpaese | G88: has | H88: game beaten
A89: Light a liquid on fire | B89: Feat | C89: 1-Low | D89: boss | E89: Hickory | G89: has | H89: any time
A90: Beat a game while having made a Faustian bargain | D90: character | E90: Ironclad | G90: has | H90: game beaten
A91: Beat a game while having made a friend | D91: character | E91: Regent | G91: has | H91: game beaten
A92: Beat a game while having muted the game | B92: Restriction | C92: 1-Low | D92: boss | E92: Banshee | G92: has | H92: game beaten
A93: Beat a game while having muted the game | B93: Restriction | C93: 2-Medium | D93: boss | E93: Green Banshee | G93: has | H93: game beaten
A94: Obtain 1 fish | B94: Fetch | C94: 1-Low | D94: enemy | E94: Mung | G94: has | H94: any time
A95: Obtain a key | B95: Fetch | C95: 1-Low | D95: enemy | E95: Keybullet Kin | G95: has | H95: any time
A96: Have 6 Guns at once | B96: Fetch | C96: 1-Low | D96: boss | E96: Beholster | G96: has | H96: any time
A97: Obtain a large fish | B97: Fetch | C97: 1-Low | D97: boss | E97: Mobius | G97: has | H97: any time
A98: Beat a game while only using 1 hand | B98: Restriction | C98: 3-High | D98: boss | E98: The Needle | G98: has | H98: game beaten
A99: Perfect a game by beating it without losing | D99: character | E99: Zoe | G99: has | H99: game beaten
A100: Perform a religious act | B100: Feat | C100: 1-Low | D100: enemy | E100: Cultist | G100: has | H100: any time
A101: Perform a song | B101: Feat | C101: 2-Medium | D101: boss | E101: Scylla | G101: has | H101: any time
A102: Poke an eye | B102: Feat | C102: 1-Low | D102: boss | E102: Khidr | G102: has | H102: any time
A103: Punch a robot | B103: Feat | C103: 1-Low | D103: enemy | E103: Punch Construct | G103: has | H103: any time
A104: Push an enemy into fire | B104: Feat | C104: 1-Low | D104: enemy | E104: Flaming Fatty | G104: has | H104: any time
A105: Raise the dead | B105: Feat | C105: 1-Low | D105: boss | E105: Morana | G105: has | H105: any time
A106: Beat a game while having selected a random starting build | D106: character | E106: Erratic Deck | G106: has | H106: game beaten
A107: Reflect a projectile | B107: Feat | C107: 2-Medium | D107: enemy | E107: Host | G107: has | H107: any time
A108: Retrieve stolen currency or items | B108: Discovery | C108: 1-Low | D108: enemy | E108: Leprechaun | G108: has | H108: any time
A109: Set a rock on fire | B109: Feat | C109: 2-Medium | D109: enemy | E109: Coal Spider | G109: has | H109: any time
A110: Shoot a mushroom | B110: Feat | C110: 2-Medium | D110: enemy | E110: Fungun | G110: has | H110: any time
A111: Shoot down a flying enemy | B111: Feat | C111: 1-Low | D111: enemy | E111: Bullat | G111: has | H111: any time
A112: Shoot down 2 flying enemies | B112: Feat | C112: 2-Medium | D112: enemy | E112: King Bullat | G112: has | H112: any time | I112: 2
...

Sheet Map Analysis
A1: Influence Graph — live analysis
A2: Every figure is a formula over the games and connections sheets. Add a row to either and these update on open.
A4: Measure | B4: Value | C4: What it means | E4: Degree | F4: Games | G4: Owned | I4: Genre | J4: Games | K4: Owned | L4: Owned % | N4: Rank | O4: Game | P4: Degree | R4: Rank | S4: Game you own | T4: Degree | V4: Year | W4: Games | X4: Owned | Y4: Connections | AA4: Edge span | AB4: Connections
A5: Games | B5: =COUNTA(games!$A$2:$A$950) -> 895 | C5: Nodes in the graph | E5: 0 | F5: =COUNTIF('Map Calc'!$D$2:$D$950,0) -> 59 | G5: =COUNTIFS('Map Calc'!$D$2:$D$950,0,'Map Calc'!$P$2:$P$950,"Yes") -> 34 | I5: Action | J5: =COUNTIF(games!$C$2:$C$950,$I5) -> 386 | K5: =COUNTIFS(games!$C$2:$C$950,$I5,games!$H$2:$H$950,"Yes") -> 258 | L5: =IF($J5=0,0,$K5/$J5) -> 0.66839378 | N5: 1 | O5: =IFERROR(INDEX('Map Calc'!$A$2:$A$950,MATCH(LARGE('Map Calc'!$O$2:$O$950,1),'Map Calc'!$O$2:$O$950,0)),"") -> Slay the Spire | P5: =IFERROR(INDEX('Map Calc'!$D$2:$D$950,MATCH(LARGE('Map Calc'!$O$2:$O$950,1),'Map Calc'!$O$2:$O$950,0)),"") -> 156 | R5: 1 | S5: =IFERROR(INDEX('Map Calc'!$A$2:$A$950,MATCH(LARGE('Map Calc'!$Q$2:$Q$950,1),'Map Calc'!$Q$2:$Q$950,0)),"") -> Slay the Spire | T5: =IFERROR(INDEX('Map Calc'!$D$2:$D$950,MATCH(LARGE('Map Calc'!$Q$2:$Q$950,1),'Map Calc'!$Q$2:$Q$950,0)),"") -> 156 | V5: 1978 | W5: =COUNTIF(games!$B$2:$B$950,$V5) -> 1 | X5: =COUNTIFS(games!$B$2:$B$950,$V5,games!$H$2:$H$950,"Yes") -> 1 | Y5: =COUNTIF('Map Calc'!$T$2:$T$1400,$V5) -> 0 | AA5: 0 | AB5: =COUNTIF('Map Calc'!$V$2:$V$1400,$AA5) -> 13
A6: Games owned | B6: =COUNTIF(games!$H$2:$H$950,"Yes") -> 563 | C6: Marked Owned — the catalog a default run draws from | E6: 1 | F6: =COUNTIF('Map Calc'!$D$2:$D$950,1) -> 329 | G6: =COUNTIFS('Map Calc'!$D$2:$D$950,1,'Map Calc'!$P$2:$P$950,"Yes") -> 199 | I6: Strategy | J6: =COUNTIF(games!$C$2:$C$950,$I6) -> 157 | K6: =COUNTIFS(games!$C$2:$C$950,$I6,games!$H$2:$H$950,"Yes") -> 100 | L6: =IF($J6=0,0,$K6/$J6) -> 0.63694268 | N6: 2 | O6: =IFERROR(INDEX('Map Calc'!$A$2:$A$950,MATCH(LARGE('Map Calc'!$O$2:$O$950,2),'Map Calc'!$O$2:$O$950,0)),"") -> Vampire Survivors | P6: =IFERROR(INDEX('Map Calc'!$D$2:$D$950,MATCH(LARGE('Map Calc'!$O$2:$O$950,2),'Map Calc'!$O$2:$O$950,0)),"") -> 96 | R6: 2 | S6: =IFERROR(INDEX('Map Calc'!$A$2:$A$950,MATCH(LARGE('Map Calc'!$Q$2:$Q$950,2),'Map Calc'!$Q$2:$Q$950,0)),"") -> Vampire Survivors | T6: =IFERROR(INDEX('Map Calc'!$D$2:$D$950,MATCH(LARGE('Map Calc'!$Q$2:$Q$950,2),'Map Calc'!$Q$2:$Q$950,0)),"") -> 96 | V6: 1979 | W6: =COUNTIF(games!$B$2:$B$950,$V6) -> 0 | X6: =COUNTIFS(games!$B$2:$B$950,$V6,games!$H$2:$H$950,"Yes") -> 0 | Y6: =COUNTIF('Map Calc'!$T$2:$T$1400,$V6) -> 0 | AA6: 1 | AB6: =COUNTIF('Map Calc'!$V$2:$V$1400,$AA6) -> 111
A7: Owned share | B7: =IF(B5=0,0,B6/B5) -> 0.62905028 | C7: How much of the sheet a run can actually be sent to | E7: 2 | F7: =COUNTIF('Map Calc'!$D$2:$D$950,2) -> 210 | G7: =COUNTIFS('Map Calc'!$D$2:$D$950,2,'Map Calc'!$P$2:$P$950,"Yes") -> 118 | I7: Deckbuilder | J7: =COUNTIF(games!$C$2:$C$950,$I7) -> 186 | K7: =COUNTIFS(games!$C$2:$C$950,$I7,games!$H$2:$H$950,"Yes") -> 99 | L7: =IF($J7=0,0,$K7/$J7) -> 0.53225806 | N7: 3 | O7: =IFERROR(INDEX('Map Calc'!$A$2:$A$950,MATCH(LARGE('Map Calc'!$O$2:$O$950,3),'Map Calc'!$O$2:$O$950,0)),"") -> The Binding of Isaac | P7: =IFERROR(INDEX('Map Calc'!$D$2:$D$950,MATCH(LARGE('Map Calc'!$O$2:$O$950,3),'Map Calc'!$O$2:$O$950,0)),"") -> 78 | R7: 3 | S7: =IFERROR(INDEX('Map Calc'!$A$2:$A$950,MATCH(LARGE('Map Calc'!$Q$2:$Q$950,3),'Map Calc'!$Q$2:$Q$950,0)),"") -> The Binding of Isaac | T7: =IFERROR(INDEX('Map Calc'!$D$2:$D$950,MATCH(LARGE('Map Calc'!$Q$2:$Q$950,3),'Map Calc'!$Q$2:$Q$950,0)),"") -> 78 | V7: 1980 | W7: =COUNTIF(games!$B$2:$B$950,$V7) -> 1 | X7: =COUNTIFS(games!$B$2:$B$950,$V7,games!$H$2:$H$950,"Yes") -> 1 | Y7: =COUNTIF('Map Calc'!$T$2:$T$1400,$V7) -> 29 | AA7: 2 | AB7: =COUNTIF('Map Calc'!$V$2:$V$1400,$AA7) -> 177
A8: Connections | B8: =COUNTA(connections!$A$2:$A$1473) -> 1472 | C8: Authored influence edges | E8: 3 | F8: =COUNTIF('Map Calc'!$D$2:$D$950,3) -> 128 | G8: =COUNTIFS('Map Calc'!$D$2:$D$950,3,'Map Calc'!$P$2:$P$950,"Yes") -> 91 | I8: Traditional | J8: =COUNTIF(games!$C$2:$C$950,$I8) -> 166 | K8: =COUNTIFS(games!$C$2:$C$950,$I8,games!$H$2:$H$950,"Yes") -> 106 | L8: =IF($J8=0,0,$K8/$J8) -> 0.63855422 | N8: 4 | O8: =IFERROR(INDEX('Map Calc'!$A$2:$A$950,MATCH(LARGE('Map Calc'!$O$2:$O$950,4),'Map Calc'!$O$2:$O$950,0)),"") -> Hades | P8: =IFERROR(INDEX('Map Calc'!$D$2:$D$950,MATCH(LARGE('Map Calc'!$O$2:$O$950,4),'Map Calc'!$O$2:$O$950,0)),"") -> 69 | R8: 4 | S8: =IFERROR(INDEX('Map Calc'!$A$2:$A$950,MATCH(LARGE('Map Calc'!$Q$2:$Q$950,4),'Map Calc'!$Q$2:$Q$950,0)),"") -> Hades | T8: =IFERROR(INDEX('Map Calc'!$D$2:$D$950,MATCH(LARGE('Map Calc'!$Q$2:$Q$950,4),'Map Calc'!$Q$2:$Q$950,0)),"") -> 69 | V8: 1981 | W8: =COUNTIF(games!$B$2:$B$950,$V8) -> 0 | X8: =COUNTIFS(games!$B$2:$B$950,$V8,games!$H$2:$H$950,"Yes") -> 0 | Y8: =COUNTIF('Map Calc'!$T$2:$T$1400,$V8) -> 0 | AA8: 3 | AB8: =COUNTIF('Map Calc'!$V$2:$V$1400,$AA8) -> 166
A9: Average degree | B9: =IF(B5=0,0,2*B8/B5) -> 3.2893855 | C9: Connections per game — under 3 means a sparse graph | E9: 4 | F9: =COUNTIF('Map Calc'!$D$2:$D$950,4) -> 63 | G9: =COUNTIFS('Map Calc'!$D$2:$D$950,4,'Map Calc'!$P$2:$P$950,"Yes") -> 38 | I9: All | J9: =SUM(J5:J8) -> 895 | K9: =SUM(K5:K8) -> 563 | L9: =IF($J9=0,0,$K9/$J9) -> 0.62905028 | N9: 5 | O9: =IFERROR(INDEX('Map Calc'!$A$2:$A$950,MATCH(LARGE('Map Calc'!$O$2:$O$950,5),'Map Calc'!$O$2:$O$950,0)),"") -> Balatro | P9: =IFERROR(INDEX('Map Calc'!$D$2:$D$950,MATCH(LARGE('Map Calc'!$O$2:$O$950,5),'Map Calc'!$O$2:$O$950,0)),"") -> 60 | R9: 5 | S9: =IFERROR(INDEX('Map Calc'!$A$2:$A$950,MATCH(LARGE('Map Calc'!$Q$2:$Q$950,5),'Map Calc'!$Q$2:$Q$950,0)),"") -> Balatro | T9: =IFERROR(INDEX('Map Calc'!$D$2:$D$950,MATCH(LARGE('Map Calc'!$Q$2:$Q$950,5),'Map Calc'!$Q$2:$Q$950,0)),"") -> 60 | V9: 1982 | W9: =COUNTIF(games!$B$2:$B$950,$V9) -> 1 | X9: =COUNTIFS(games!$B$2:$B$950,$V9,games!$H$2:$H$950,"Yes") -> 0 | Y9: =COUNTIF('Map Calc'!$T$2:$T$1400,$V9) -> 1 | AA9: 4 | AB9: =COUNTIF('Map Calc'!$V$2:$V$1400,$AA9) -> 161
A10: Average degree (owned) | B10: =IFERROR(SUMIFS('Map Calc'!$D$2:$D$950,games!$H$2:$H$950,"Yes")/B6,0) -> 4.062167 | C10: The same figure over the owned catalog — the graph a run walks | E10: 5 | F10: =COUNTIF('Map Calc'!$D$2:$D$950,5) -> 30 | G10: =COUNTIFS('Map Calc'!$D$2:$D$950,5,'Map Calc'!$P$2:$P$950,"Yes") -> 16 | N10: 6 | O10: =IFERROR(INDEX('Map Calc'!$A$2:$A$950,MATCH(LARGE('Map Calc'!$O$2:$O$950,6),'Map Calc'!$O$2:$O$950,0)),"") -> Spelunky Classic | P10: =IFERROR(INDEX('Map Calc'!$D$2:$D$950,MATCH(LARGE('Map Calc'!$O$2:$O$950,6),'Map Calc'!$O$2:$O$950,0)),"") -> 45 | R10: 6 | S10: =IFERROR(INDEX('Map Calc'!$A$2:$A$950,MATCH(LARGE('Map Calc'!$Q$2:$Q$950,6),'Map Calc'!$Q$2:$Q$950,0)),"") -> Spelunky Classic | T10: =IFERROR(INDEX('Map Calc'!$D$2:$D$950,MATCH(LARGE('Map Calc'!$Q$2:$Q$950,6),'Map Calc'!$Q$2:$Q$950,0)),"") -> 45 | V10: 1983 | W10: =COUNTIF(games!$B$2:$B$950,$V10) -> 1 | X10: =COUNTIFS(games!$B$2:$B$950,$V10,games!$H$2:$H$950,"Yes") -> 1 | Y10: =COUNTIF('Map Calc'!$T$2:$T$1400,$V10) -> 3 | AA10: 5 | AB10: =COUNTIF('Map Calc'!$V$2:$V$1400,$AA10) -> 137
A11: Median degree | B11: =MEDIAN('Map Calc'!$D$2:$D$950) -> 2 | C11: Half of all games sit at or below this | E11: 6-9 | F11: =COUNTIFS('Map Calc'!$D$2:$D$950,">=6",'Map Calc'!$D$2:$D$950,"<=9") -> 38 | G11: =COUNTIFS('Map Calc'!$D$2:$D$950,">=6",'Map Calc'!$D$2:$D$950,"<=9",'Map Calc'!$P$2:$P$950,"Yes") -> 29 | N11: 7 | O11: =IFERROR(INDEX('Map Calc'!$A$2:$A$950,MATCH(LARGE('Map Calc'!$O$2:$O$950,7),'Map Calc'!$O$2:$O$950,0)),"") -> FTL | P11: =IFERROR(INDEX('Map Calc'!$D$2:$D$950,MATCH(LARGE('Map Calc'!$O$2:$O$950,7),'Map Calc'!$O$2:$O$950,0)),"") -> 44 | R11: 7 | S11: =IFERROR(INDEX('Map Calc'!$A$2:$A$950,MATCH(LARGE('Map Calc'!$Q$2:$Q$950,7),'Map Calc'!$Q$2:$Q$950,0)),"") -> FTL | T11: =IFERROR(INDEX('Map Calc'!$D$2:$D$950,MATCH(LARGE('Map Calc'!$Q$2:$Q$950,7),'Map Calc'!$Q$2:$Q$950,0)),"") -> 44 | V11: 1984 | W11: =COUNTIF(games!$B$2:$B$950,$V11) -> 1 | X11: =COUNTIFS(games!$B$2:$B$950,$V11,games!$H$2:$H$950,"Yes") -> 1 | Y11: =COUNTIF('Map Calc'!$T$2:$T$1400,$V11) -> 6 | AA11: 6 | AB11: =COUNTIF('Map Calc'!$V$2:$V$1400,$AA11) -> 104
A12: Largest hub | B12: =MAX('Map Calc'!$D$2:$D$950) -> 156 | C12: Degree of the single most connected game | E12: 10-24 | F12: =COUNTIFS('Map Calc'!$D$2:$D$950,">=10",'Map Calc'!$D$2:$D$950,"<=24") -> 21 | G12: =COUNTIFS('Map Calc'!$D$2:$D$950,">=10",'Map Calc'!$D$2:$D$950,"<=24",'Map Calc'!$P$2:$P$950,"Yes") -> 21 | N12: 8 | O12: =IFERROR(INDEX('Map Calc'!$A$2:$A$950,MATCH(LARGE('Map Calc'!$O$2:$O$950,8),'Map Calc'!$O$2:$O$950,0)),"") -> NetHack | P12: =IFERROR(INDEX('Map Calc'!$D$2:$D$950,MATCH(LARGE('Map Calc'!$O$2:$O$950,8),'Map Calc'!$O$2:$O$950,0)),"") -> 36 | R12: 8 | S12: =IFERROR(INDEX('Map Calc'!$A$2:$A$950,MATCH(LARGE('Map Calc'!$Q$2:$Q$950,8),'Map Calc'!$Q$2:$Q$950,0)),"") -> NetHack | T12: =IFERROR(INDEX('Map Calc'!$D$2:$D$950,MATCH(LARGE('Map Calc'!$Q$2:$Q$950,8),'Map Calc'!$Q$2:$Q$950,0)),"") -> 36 | V12: 1985 | W12: =COUNTIF(games!$B$2:$B$950,$V12) -> 0 | X12: =COUNTIFS(games!$B$2:$B$950,$V12,games!$H$2:$H$950,"Yes") -> 0 | Y12: =COUNTIF('Map Calc'!$T$2:$T$1400,$V12) -> 0 | AA12: 7 | AB12: =COUNTIF('Map Calc'!$V$2:$V$1400,$AA12) -> 97
A13: Leaves (degree 1) | B13: =COUNTIF('Map Calc'!$D$2:$D$950,1) -> 329 | C13: Dead ends — one way in, the same way out | E13: 25+ | F13: =COUNTIF('Map Calc'!$D$2:$D$950,">=25") -> 17 | G13: =COUNTIFS('Map Calc'!$D$2:$D$950,">=25",'Map Calc'!$P$2:$P$950,"Yes") -> 17 | N13: 9 | O13: =IFERROR(INDEX('Map Calc'!$A$2:$A$950,MATCH(LARGE('Map Calc'!$O$2:$O$950,9),'Map Calc'!$O$2:$O$950,0)),"") -> Enter the Gungeon | P13: =IFERROR(INDEX('Map Calc'!$D$2:$D$950,MATCH(LARGE('Map Calc'!$O$2:$O$950,9),'Map Calc'!$O$2:$O$950,0)),"") -> 34 | R13: 9 | S13: =IFERROR(INDEX('Map Calc'!$A$2:$A$950,MATCH(LARGE('Map Calc'!$Q$2:$Q$950,9),'Map Calc'!$Q$2:$Q$950,0)),"") -> Enter the Gungeon | T13: =IFERROR(INDEX('Map Calc'!$D$2:$D$950,MATCH(LARGE('Map Calc'!$Q$2:$Q$950,9),'Map Calc'!$Q$2:$Q$950,0)),"") -> 34 | V13: 1986 | W13: =COUNTIF(games!$B$2:$B$950,$V13) -> 1 | X13: =COUNTIFS(games!$B$2:$B$950,$V13,games!$H$2:$H$950,"Yes") -> 1 | Y13: =COUNTIF('Map Calc'!$T$2:$T$1400,$V13) -> 1 | AA13: 8 | AB13: =COUNTIF('Map Calc'!$V$2:$V$1400,$AA13) -> 76
A14: Isolated (degree 0) | B14: =COUNTIF('Map Calc'!$D$2:$D$950,0) -> 59 | C14: Unreachable; can never appear on a route | N14: 10 | O14: =IFERROR(INDEX('Map Calc'!$A$2:$A$950,MATCH(LARGE('Map Calc'!$O$2:$O$950,10),'Map Calc'!$O$2:$O$950,0)),"") -> Diablo | P14: =IFERROR(INDEX('Map Calc'!$D$2:$D$950,MATCH(LARGE('Map Calc'!$O$2:$O$950,10),'Map Calc'!$O$2:$O$950,0)),"") -> 33 | R14: 10 | S14: =IFERROR(INDEX('Map Calc'!$A$2:$A$950,MATCH(LARGE('Map Calc'!$Q$2:$Q$950,10),'Map Calc'!$Q$2:$Q$950,0)),"") -> Diablo | T14: =IFERROR(INDEX('Map Calc'!$D$2:$D$950,MATCH(LARGE('Map Calc'!$Q$2:$Q$950,10),'Map Calc'!$Q$2:$Q$950,0)),"") -> 33 | V14: 1987 | W14: =COUNTIF(games!$B$2:$B$950,$V14) -> 3 | X14: =COUNTIFS(games!$B$2:$B$950,$V14,games!$H$2:$H$950,"Yes") -> 3 | Y14: =COUNTIF('Map Calc'!$T$2:$T$1400,$V14) -> 39 | AA14: 9 | AB14: =COUNTIF('Map Calc'!$V$2:$V$1400,$AA14) -> 68
A15: Leaves + isolated | B15: =B13+B14 -> 388 | C15: Share of the map that carries no routing information | N15: 11 | O15: =IFERROR(INDEX('Map Calc'!$A$2:$A$950,MATCH(LARGE('Map Calc'!$O$2:$O$950,11),'Map Calc'!$O$2:$O$950,0)),"") -> Dead Cells | P15: =IFERROR(INDEX('Map Calc'!$D$2:$D$950,MATCH(LARGE('Map Calc'!$O$2:$O$950,11),'Map Calc'!$O$2:$O$950,0)),"") -> 31 | R15: 11 | S15: =IFERROR(INDEX('Map Calc'!$A$2:$A$950,MATCH(LARGE('Map Calc'!$Q$2:$Q$950,11),'Map Calc'!$Q$2:$Q$950,0)),"") -> Dead Cells | T15: =IFERROR(INDEX('Map Calc'!$D$2:$D$950,MATCH(LARGE('Map Calc'!$Q$2:$Q$950,11),'Map Calc'!$Q$2:$Q$950,0)),"") -> 31 | V15: 1988 | W15: =COUNTIF(games!$B$2:$B$950,$V15) -> 0 | X15: =COUNTIFS(games!$B$2:$B$950,$V15,games!$H$2:$H$950,"Yes") -> 0 | Y15: =COUNTIF('Map Calc'!$T$2:$T$1400,$V15) -> 0 | AA15: 10 | AB15: =COUNTIF('Map Calc'!$V$2:$V$1400,$AA15) -> 33
A16: Owned & routable | B16: =COUNTIFS(games!$H$2:$H$950,"Yes",'Map Calc'!$D$2:$D$950,">1") -> 330 | C16: Owned games with more than one way out — real junctions on a route | N16: 12 | O16: =IFERROR(INDEX('Map Calc'!$A$2:$A$950,MATCH(LARGE('Map Calc'!$O$2:$O$950,12),'Map Calc'!$O$2:$O$950,0)),"") -> Nuclear Throne | P16: =IFERROR(INDEX('Map Calc'!$D$2:$D$950,MATCH(LARGE('Map Calc'!$O$2:$O$950,12),'Map Calc'!$O$2:$O$950,0)),"") -> 30 | R16: 12 | S16: =IFERROR(INDEX('Map Calc'!$A$2:$A$950,MATCH(LARGE('Map Calc'!$Q$2:$Q$950,12),'Map Calc'!$Q$2:$Q$950,0)),"") -> Nuclear Throne | T16: =IFERROR(INDEX('Map Calc'!$D$2:$D$950,MATCH(LARGE('Map Calc'!$Q$2:$Q$950,12),'Map Calc'!$Q$2:$Q$950,0)),"") -> 30 | V16: 1989 | W16: =COUNTIF(games!$B$2:$B$950,$V16) -> 0 | X16: =COUNTIFS(games!$B$2:$B$950,$V16,games!$H$2:$H$950,"Yes") -> 0 | Y16: =COUNTIF('Map Calc'!$T$2:$T$1400,$V16) -> 0 | AA16: 11-20 | AB16: =COUNTIFS('Map Calc'!$V$2:$V$1400,">=11",'Map Calc'!$V$2:$V$1400,"<=20") -> 149
A17: Owned dead ends | B17: =COUNTIFS(games!$H$2:$H$950,"Yes",'Map Calc'!$D$2:$D$950,"<=1") -> 233 | C17: Owned games the run can only reach and turn around in | N17: 13 | O17: =IFERROR(INDEX('Map Calc'!$A$2:$A$950,MATCH(LARGE('Map Calc'!$O$2:$O$950,13),'Map Calc'!$O$2:$O$950,0)),"") -> Rogue | P17: =IFERROR(INDEX('Map Calc'!$D$2:$D$950,MATCH(LARGE('Map Calc'!$O$2:$O$950,13),'Map Calc'!$O$2:$O$950,0)),"") -> 29 | R17: 13 | S17: =IFERROR(INDEX('Map Calc'!$A$2:$A$950,MATCH(LARGE('Map Calc'!$Q$2:$Q$950,13),'Map Calc'!$Q$2:$Q$950,0)),"") -> Rogue | T17: =IFERROR(INDEX('Map Calc'!$D$2:$D$950,MATCH(LARGE('Map Calc'!$Q$2:$Q$950,13),'Map Calc'!$Q$2:$Q$950,0)),"") -> 29 | V17: 1990 | W17: =COUNTIF(games!$B$2:$B$950,$V17) -> 3 | X17: =COUNTIFS(games!$B$2:$B$950,$V17,games!$H$2:$H$950,"Yes") -> 3 | Y17: =COUNTIF('Map Calc'!$T$2:$T$1400,$V17) -> 12 | AA17: 21+ | AB17: =COUNTIF('Map Calc'!$V$2:$V$1400,">=21") -> 103
A18: Backward in time | B18: =SUMPRODUCT(('Map Calc'!$V$2:$V$1400<>"")*('Map Calc'!$V$2:$V$1400<0)) -> 3 | C18: MUST BE 0 — an influence cannot point at an older game | N18: 14 | O18: =IFERROR(INDEX('Map Calc'!$A$2:$A$950,MATCH(LARGE('Map Calc'!$O$2:$O$950,14),'Map Calc'!$O$2:$O$950,0)),"") -> Darkest Dungeon | P18: =IFERROR(INDEX('Map Calc'!$D$2:$D$950,MATCH(LARGE('Map Calc'!$O$2:$O$950,14),'Map Calc'!$O$2:$O$950,0)),"") -> 29 | R18: 14 | S18: =IFERROR(INDEX('Map Calc'!$A$2:$A$950,MATCH(LARGE('Map Calc'!$Q$2:$Q$950,14),'Map Calc'!$Q$2:$Q$950,0)),"") -> Darkest Dungeon | T18: =IFERROR(INDEX('Map Calc'!$D$2:$D$950,MATCH(LARGE('Map Calc'!$Q$2:$Q$950,14),'Map Calc'!$Q$2:$Q$950,0)),"") -> 29 | V18: 1991 | W18: =COUNTIF(games!$B$2:$B$950,$V18) -> 2 | X18: =COUNTIFS(games!$B$2:$B$950,$V18,games!$H$2:$H$950,"Yes") -> 2 | Y18: =COUNTIF('Map Calc'!$T$2:$T$1400,$V18) -> 2
A19: Same year | B19: =SUMPRODUCT(('Map Calc'!$V$2:$V$1400<>"")*('Map Calc'!$V$2:$V$1400=0)) -> 13 | C19: Legal: a demo influencing something shipped the same year | N19: 15 | O19: =IFERROR(INDEX('Map Calc'!$A$2:$A$950,MATCH(LARGE('Map Calc'!$O$2:$O$950,15),'Map Calc'!$O$2:$O$950,0)),"") -> Into the Breach | P19: =IFERROR(INDEX('Map Calc'!$D$2:$D$950,MATCH(LARGE('Map Calc'!$O$2:$O$950,15),'Map Calc'!$O$2:$O$950,0)),"") -> 28 | R19: 15 | S19: =IFERROR(INDEX('Map Calc'!$A$2:$A$950,MATCH(LARGE('Map Calc'!$Q$2:$Q$950,15),'Map Calc'!$Q$2:$Q$950,0)),"") -> Into the Breach | T19: =IFERROR(INDEX('Map Calc'!$D$2:$D$950,MATCH(LARGE('Map Calc'!$Q$2:$Q$950,15),'Map Calc'!$Q$2:$Q$950,0)),"") -> 28 | V19: 1992 | W19: =COUNTIF(games!$B$2:$B$950,$V19) -> 2 | X19: =COUNTIFS(games!$B$2:$B$950,$V19,games!$H$2:$H$950,"Yes") -> 2 | Y19: =COUNTIF('Map Calc'!$T$2:$T$1400,$V19) -> 2
A20: Median edge span | B20: =MEDIAN('Map Calc'!$V$2:$V$1400) -> 5 | C20: Years between an influencer and what it influenced | N20: 16 | O20: =IFERROR(INDEX('Map Calc'!$A$2:$A$950,MATCH(LARGE('Map Calc'!$O$2:$O$950,16),'Map Calc'!$O$2:$O$950,0)),"") -> Torneko's Great Adventure: Mystery Dungeon | P20: =IFERROR(INDEX('Map Calc'!$D$2:$D$950,MATCH(LARGE('Map Calc'!$O$2:$O$950,16),'Map Calc'!$O$2:$O$950,0)),"") -> 27 | V20: 1993 | W20: =COUNTIF(games!$B$2:$B$950,$V20) -> 2 | X20: =COUNTIFS(games!$B$2:$B$950,$V20,games!$H$2:$H$950,"Yes") -> 1 | Y20: =COUNTIF('Map Calc'!$T$2:$T$1400,$V20) -> 22
A21: Dev/Series flagged | B21: =COUNTIF(connections!$D$2:$D$1473,"Yes") -> 151 | C21: Sequel / same-devs links, distinct from plain influence | N21: 17 | O21: =IFERROR(INDEX('Map Calc'!$A$2:$A$950,MATCH(LARGE('Map Calc'!$O$2:$O$950,17),'Map Calc'!$O$2:$O$950,0)),"") -> Luck be a Landlord | P21: =IFERROR(INDEX('Map Calc'!$D$2:$D$950,MATCH(LARGE('Map Calc'!$O$2:$O$950,17),'Map Calc'!$O$2:$O$950,0)),"") -> 27 | V21: 1994 | W21: =COUNTIF(games!$B$2:$B$950,$V21) -> 3 | X21: =COUNTIFS(games!$B$2:$B$950,$V21,games!$H$2:$H$950,"Yes") -> 3 | Y21: =COUNTIF('Map Calc'!$T$2:$T$1400,$V21) -> 21
A22: With a source | B22: =COUNTA(connections!$E$2:$E$1473) -> 1321 | C22: Connections carrying a URL or note as evidence | N22: 18 | O22: =IFERROR(INDEX('Map Calc'!$A$2:$A$950,MATCH(LARGE('Map Calc'!$O$2:$O$950,18),'Map Calc'!$O$2:$O$950,0)),"") -> Brotato | P22: =IFERROR(INDEX('Map Calc'!$D$2:$D$950,MATCH(LARGE('Map Calc'!$O$2:$O$950,18),'Map Calc'!$O$2:$O$950,0)),"") -> 22 | V22: 1995 | W22: =COUNTIF(games!$B$2:$B$950,$V22) -> 2 | X22: =COUNTIFS(games!$B$2:$B$950,$V22,games!$H$2:$H$950,"Yes") -> 2 | Y22: =COUNTIF('Map Calc'!$T$2:$T$1400,$V22) -> 14
A23: Owned, no Steam page | B23: =COUNTIFS(games!$H$2:$H$950,"Yes",games!$J$2:$J$950,"") -> 89 | C23: Owned rows with nothing to link to — a gap in the sheet, not the graph | N23: 19 | O23: =IFERROR(INDEX('Map Calc'!$A$2:$A$950,MATCH(LARGE('Map Calc'!$O$2:$O$950,19),'Map Calc'!$O$2:$O$950,0)),"") -> Ancient Domains of Mystery | P23: =IFERROR(INDEX('Map Calc'!$D$2:$D$950,MATCH(LARGE('Map Calc'!$O$2:$O$950,19),'Map Calc'!$O$2:$O$950,0)),"") -> 22 | V23: 1996 | W23: =COUNTIF(games!$B$2:$B$950,$V23) -> 2 | X23: =COUNTIFS(games!$B$2:$B$950,$V23,games!$H$2:$H$950,"Yes") -> 2 | Y23: =COUNTIF('Map Calc'!$T$2:$T$1400,$V23) -> 30
N24: 20 | O24: =IFERROR(INDEX('Map Calc'!$A$2:$A$950,MATCH(LARGE('Map Calc'!$O$2:$O$950,20),'Map Calc'!$O$2:$O$950,0)),"") -> Risk of Rain 2 | P24: =IFERROR(INDEX('Map Calc'!$D$2:$D$950,MATCH(LARGE('Map Calc'!$O$2:$O$950,20),'Map Calc'!$O$2:$O$950,0)),"") -> 20 | V24: 1997 | W24: =COUNTIF(games!$B$2:$B$950,$V24) -> 2 | X24: =COUNTIFS(games!$B$2:$B$950,$V24,games!$H$2:$H$950,"Yes") -> 2 | Y24: =COUNTIF('Map Calc'!$T$2:$T$1400,$V24) -> 4
V25: 1998 | W25: =COUNTIF(games!$B$2:$B$950,$V25) -> 5 | X25: =COUNTIFS(games!$B$2:$B$950,$V25,games!$H$2:$H$950,"Yes") -> 4 | Y25: =COUNTIF('Map Calc'!$T$2:$T$1400,$V25) -> 12
V26: 1999 | W26: =COUNTIF(games!$B$2:$B$950,$V26) -> 1 | X26: =COUNTIFS(games!$B$2:$B$950,$V26,games!$H$2:$H$950,"Yes") -> 1 | Y26: =COUNTIF('Map Calc'!$T$2:$T$1400,$V26) -> 2
V27: 2000 | W27: =COUNTIF(games!$B$2:$B$950,$V27) -> 2 | X27: =COUNTIFS(games!$B$2:$B$950,$V27,games!$H$2:$H$950,"Yes") -> 2 | Y27: =COUNTIF('Map Calc'!$T$2:$T$1400,$V27) -> 4
V28: 2001 | W28: =COUNTIF(games!$B$2:$B$950,$V28) -> 3 | X28: =COUNTIFS(games!$B$2:$B$950,$V28,games!$H$2:$H$950,"Yes") -> 2 | Y28: =COUNTIF('Map Calc'!$T$2:$T$1400,$V28) -> 3
V29: 2002 | W29: =COUNTIF(games!$B$2:$B$950,$V29) -> 6 | X29: =COUNTIFS(games!$B$2:$B$950,$V29,games!$H$2:$H$950,"Yes") -> 5 | Y29: =COUNTIF('Map Calc'!$T$2:$T$1400,$V29) -> 11
V30: 2003 | W30: =COUNTIF(games!$B$2:$B$950,$V30) -> 3 | X30: =COUNTIFS(games!$B$2:$B$950,$V30,games!$H$2:$H$950,"Yes") -> 2 | Y30: =COUNTIF('Map Calc'!$T$2:$T$1400,$V30) -> 4
V31: 2004 | W31: =COUNTIF(games!$B$2:$B$950,$V31) -> 2 | X31: =COUNTIFS(games!$B$2:$B$950,$V31,games!$H$2:$H$950,"Yes") -> 2 | Y31: =COUNTIF('Map Calc'!$T$2:$T$1400,$V31) -> 0
V32: 2005 | W32: =COUNTIF(games!$B$2:$B$950,$V32) -> 3 | X32: =COUNTIFS(games!$B$2:$B$950,$V32,games!$H$2:$H$950,"Yes") -> 3 | Y32: =COUNTIF('Map Calc'!$T$2:$T$1400,$V32) -> 7
V33: 2006 | W33: =COUNTIF(games!$B$2:$B$950,$V33) -> 8 | X33: =COUNTIFS(games!$B$2:$B$950,$V33,games!$H$2:$H$950,"Yes") -> 8 | Y33: =COUNTIF('Map Calc'!$T$2:$T$1400,$V33) -> 18
V34: 2007 | W34: =COUNTIF(games!$B$2:$B$950,$V34) -> 7 | X34: =COUNTIFS(games!$B$2:$B$950,$V34,games!$H$2:$H$950,"Yes") -> 6 | Y34: =COUNTIF('Map Calc'!$T$2:$T$1400,$V34) -> 4
V35: 2008 | W35: =COUNTIF(games!$B$2:$B$950,$V35) -> 4 | X35: =COUNTIFS(games!$B$2:$B$950,$V35,games!$H$2:$H$950,"Yes") -> 3 | Y35: =COUNTIF('Map Calc'!$T$2:$T$1400,$V35) -> 46
V36: 2009 | W36: =COUNTIF(games!$B$2:$B$950,$V36) -> 2 | X36: =COUNTIFS(games!$B$2:$B$950,$V36,games!$H$2:$H$950,"Yes") -> 2 | Y36: =COUNTIF('Map Calc'!$T$2:$T$1400,$V36) -> 9
... V53: 2026 | W53: =COUNTIF(games!$B$2:$B$950,$V53) -> 108 | X53: =COUNTIFS(games!$B$2:$B$950,$V53,games!$H$2:$H$950,"Yes") -> 18 | Y53: =COUNTIF('Map Calc'!$T$2:$T$1400,$V53) -> 1

Sheet amulets
A1: Name | B1: Type | C1: Tier | D1: Rarity | E1: Obtain Goals | F1: Effect | G1: Visuals | H1: Image
B2: Body | C2: 1-Low | D2: Common | E2: Get damaged by enemies a lot | F2: N/A | G2: battered
B3: Body | C3: 2-Medium | D3: Common | E3: Only take 10 or less damage from enemies | G3: slightly damaged
B4: Body | C4: 3-High | D4: Common | E4: Take no damage from enemies | G4: completely pristine
B5: Cord | C5: 1-Low | D5: Common | E5: End a run with 10 or less items | F5: N/A | G5: bare
B6: Cord | C6: 2-Medium | D6: Common | E6: End a run with 11 - 20 items | G6: has some stuff on it
B7: Cord | C7: 3-High | D7: Common | E7: End a run with over 20 items | G7: ornaments and stuff on it
B8: Decoration | C8: 1-Low | D8: Common | E8: Beat a low tier boss | F8: N/A
B9: Decoration | C9: 2-Medium | D9: Common | E9: Beat a medium tier boss
B10: Decoration | C10: 3-High | D10: Common | E10: Beat a high tier boss
B11: Decoration | C11: 4-Insane | D11: Common | E11: Beat an insane tier boss | G11: up to you to decide how these look, but I think they should be a gem that gets bigger and the 4th tier one should be magical

Sheet locations
A1: Name | B1: Game | C1: Difficulty | D1: Goal Type | E1: Goal | F1: Goal Effect | G1: Limit | H1: Extra Effect | I1: Enemy Type
A2: Burning Basement | B2: The Binding of Isaac: Rebirth | C2: 1-Low | D2: Feat | E2: Set 10+ enemies on fire | F2: Gain +1 Small Chest | G2: None | H2: When entered, spawn 1 random enemy with the fire tag | I2: fire
A3: Dross | B3: The Binding of Isaac: Rebirth | C3: 1-Low | D3: Bounty | E3: Defeat a stinky enemy | F3: Gain +1 Small Chest | G3: None | I3: stinky

Sheet chart
A1: Node | B1: Otainable | C1: Node Type | D1: System 1 | E1: Subsystem 1 | F1: Trigger1 | G1: Dir 1 | H1: System 2 | I1: Subsystem 2 | J1: Trigger 2 | K1: Dir 2 | L1: System 3 | M1: Subsystem 3 | N1: Trigger 3 | O1: Dir 3 | P1: System 4 | Q1: Subsystem 4 | R1: Trigger 4 | S1: Dir 4 | U1: Subsystem | V1: Good Dir | W1: Groups
A2: ? Card | B2: Enemy Defeat; Game Completion | C2: Card | D2: Items | E2: Item Copy | F2: Card Use | G2: Up | U2: Bash | V2: Up
A3: 0 - The Fool | B3: Enemy Defeat; Game Completion | C3: Card | D3: Movement | E3: Teleport Start Game | F3: Card Use | G3: Up | U3: Bomb Amount | V3: Up | W3: Resource
A4: 2 of Clubs | B4: Enemy Defeat; Game Completion | C4: Card | D4: Bombs | E4: Bomb Amount | F4: Card Use | G4: Up | U4: Bomb Size | V4: Up | W4: Stats
A5: 2 of Diamonds | B5: Enemy Defeat; Game Completion | C5: Card | D5: Economy | E5: Gold | F5: Card Use | G5: Up | U5: Burn on Enemy | V5: Up | W5: Health
A6: 2 of Hearts | B6: Enemy Defeat; Game Completion | C6: Card | D6: Health | E6: Health Amount | F6: Card Use | G6: Up | U6: Burn on Player | V6: Down | W6: Bombs
A7: Ancient Recall | B7: Enemy Defeat; Game Completion | C7: Card | D7: Cards | E7: Card Amount | F7: Card Use | G7: Up | U7: Card Amount | V7: Up | W7: Collectables
A8: Barricade | B8: Enemy Defeat; Game Completion | C8: Card | D8: Shields | E8: Shield Amount | F8: Combat End | G8: Up | U8: Chest Size | V8: Up | W8: Shields
A9: Echo Form | B9: Enemy Defeat; Game Completion | C9: Card | D9: Loot | E9: Loot Copy | F9: Card Use | G9: Up | U9: Curse | V9: Down | W9: Gold
A10: IX - The Hermit | B10: Enemy Defeat; Game Completion | C10: Card | D10: Movement | E10: Teleport Nearby Hub | F10: Card Use | G10: Up | U10: Dash | V10: Up
A11: Queen of Hearts | B11: Enemy Defeat; Game Completion | C11: Card | D11: Health | E11: Health Amount | F11: Card Use | G11: Up | U11: Dexterity on Enemy | V11: Down | W11: Collectables
A12: Ride the Bus | B12: Enemy Defeat; Game Completion | C12: Card | D12: Movement | E12: Teleport Random Deckbuilder | F12: Card Use | G12: Up | U12: Dexterity on Player | V12: Up | W12: Items
A13: V - The Hierophant | B13: Enemy Defeat; Game Completion | C13: Card | D13: Shields | E13: Shield Amount | F13: Card Use | G13: Up | U13: Dexterity on Player | V13: Up | W13: Loot
A14: VI - The Lovers | B14: Enemy Defeat; Game Completion | C14: Card | D14: Health | E14: Health Amount | F14: Card Use | G14: Up | U14: Enemy Amount | V14: Down
A15: XIV - Temperance | B15: Enemy Defeat; Game Completion | C15: Card | D15: Objects | E15: Object Spawn | F15: Card Use | G15: Up | U15: Enemy Health | V15: Down | W15: Loot
A16: Aftermath | B16: Enemy Spawn | C16: Enemy Ability | D16: Tiles | E16: Fire Tile | F16: Enemy Defeat | G16: Up | U16: Enemy Max Health | V16: Down | W16: Pills
A17: Agile | B17: Enemy Spawn | C17: Enemy Ability | D17: Enemies | E17: Enemy Position | F17: Enemy Movement | G17: Down | U17: Enemy Position | V17: Up | W17: Scrolls
A18: Bolster | B18: Enemy Spawn | C18: Enemy Ability | D18: Statuses | E18: Buff on Enemy | F18: Enemy Passive | G18: Up | U18: Enemy Variety | V18: Up | W18: Potions
A19: Defensive Stance | B19: Enemy Spawn | C19: Enemy Ability | D19: Statuses | E19: Dexterity on Enemy | F19: Enemy Turn | G19: Up | U19: Fire Tile | V19: Up | W19: Cards
A20: Degradation | B20: Enemy Spawn | C20: Enemy Ability | D20: Loot | E20: Loot Amount | F20: Enemy Attack | G20: Down | U20: Friendly Unit Spawn | V20: Up | W20: Wands
A21: Devour Whole | B21: Enemy Spawn | C21: Enemy Ability | D21: Run | E21: End Run | F21: Enemy Attack | G21: Up | U21: Gold | V21: Up
A22: Drain | B22: Enemy Spawn | C22: Enemy Ability | D22: Health | E22: Max Health | F22: Enemy Attack | G22: Down | U22: Greater Item Choice | V22: Up
A23: Entry Summon | B23: Enemy Spawn | C23: Enemy Ability | D23: Enemies | E23: Enemy Amount | F23: Enemy Turn | G23: Up | H23: Loot | I23: Loot Amount | J23: Enemy Defeat | K23: Up | L23: Economy | M23: Gold | N23: Enemy Defeat | O23: Up | P23: Goals | Q23: Goal Amount | R23: Enemy Turn | S23: Up | U23: Grid Height | V23: Down
A24: Fading | B24: Enemy Spawn | C24: Enemy Ability | D24: Enemies | E24: Enemy Health | F24: Enemy Turn | G24: Down | U24: Grid Width | V24: Up
A25: Fireproof | B25: Enemy Spawn | C25: Enemy Ability | D25: Statuses | E25: Burn on Enemy | F25: Enemy Passive | G25: Down | U25: Health Amount | V25: Up
A26: Haste | B26: Enemy Spawn | C26: Enemy Ability | D26: Statuses | E26: Dexterity on Enemy | F26: Enemy Spawn | G26: Up | I26: Speed on Enemy | U26: Item Amount | V26: Up
A27: Hexer | B27: Enemy Spawn | C27: Enemy Ability | D27: Goals | E27: Curse | F27: Enemy Attack | G27: Up | U27: Item Copy | V27: Up
A28: Illusion | B28: Enemy Spawn | C28: Enemy Ability | D28: N/A | U28: Level Up | V28: Up
A29: Illusionist | B29: Enemy Spawn | C29: Enemy Ability | D29: Enemies | E29: Enemy Amount | F29: Enemy Turn | G29: Up | H29: Loot | I29: Loot Amount | J29: Enemy Defeat | K29: Up | L29: Economy | M29: Gold | N29: Enemy Defeat | O29: Up | P29: Goals | Q29: Goal Amount | R29: Enemy Turn | S29: Up | U29: Loot Amount | V29: Up
A30: Immobile | B30: Enemy Spawn | C30: Enemy Ability | D30: Enemies | E30: Enemy Position | F30: Enemy Passive | G30: Up | U30: Loot Copy | V30: Up
A31: Infliction | B31: Enemy Spawn | C31: Enemy Ability | D31: Statuses | E31: Debuff on Player | F31: Enemy Attack | G31: Up | U31: Luck | V31: Up
A32: Invisibility | B32: Enemy Spawn | C32: Enemy Ability | D32: Enemies | E32: Enemy Visibility | F32: Enemy Spawn | G32: Down | U32: Max Health | V32: Up
A33: Lacerator | B33: Enemy Spawn | C33: Enemy Ability | D33: Goals | E33: Curse | F33: Enemy Attack | G33: Up | U33: Object Spawn | V33: Up
A34: Melee Ally Buff | B34: Enemy Spawn | C34: Enemy Ability | D34: Statuses | E34: Buff on Enemy | F34: Enemy Turn | G34: Up | U34: Pill Amount | V34: Up
A35: Necromancy | B35: Enemy Spawn | C35: Enemy Ability | D35: Enemies | E35: Enemy Amount | F35: Enemy Turn | G35: Up | H35: Loot | I35: Loot Amount | J35: Enemy Defeat | K35: Up | L35: Economy | M35: Gold | N35: Enemy Defeat | O35: Up | P35: Goals | Q35: Goal Amount | R35: Enemy Turn | S35: Up | U35: Potion Amount | V35: Up
A36: Nested Spawner | B36: Enemy Spawn | C36: Enemy Ability | D36: Enemies | E36: Enemy Amount | F36: Enemy Turn | G36: Up | H36: Loot | I36: Loot Amount | J36: Enemy Defeat | K36: Up | L36: Economy | M36: Gold | N36: Enemy Defeat | O36: Up | P36: Goals | Q36: Goal Amount | R36: Enemy Turn | S36: Up | U36: Potion Copy | V36: Up
A37: Predatory Scent | B37: Enemy Spawn | C37: Enemy Ability | D37: Enemies | E37: Enemy Turn | F37: On Player Debuff | G37: Up | U37: Pre-Combat Enemy Visibility | V37: Up
A38: Ranged | B38: Enemy Spawn | C38: Enemy Ability | D38: Enemies | E38: Enemy Range | F38: Enemy Passive | G38: Up | U38: Random Charges | V38: Up
A39: Ritual | B39: Enemy Spawn | C39: Enemy Ability | D39: Statuses | E39: Strength on Enemy | F39: Enemy Turn | G39: Up | U39: Scramble | V39: Up
A40: Ruthless | B40: Enemy Spawn | C40: Enemy Ability | D40: Enemies | E40: Enemy Health | F40: Enemy Turn | G40: Down | U40: Shield Amount | V40: Up
A41: Split | B41: Enemy Spawn | C41: Enemy Ability | D41: Enemies | E41: Enemy Amount | F41: Enemy Defeat | G41: Up | H41: Loot | I41: Loot Amount | J41: Enemy Defeat | K41: Up | L41: Economy | M41: Gold | N41: Enemy Defeat | O41: Up | P41: Goals | Q41: Goal Amount | R41: Enemy Defeat | S41: Up | U41: Shield on Enemy | V41: Down
A42: Tanky | B42: Enemy Spawn | C42: Enemy Ability | D42: Enemies | E42: Enemy Health | F42: Enemy Spawn | G42: Up | U42: Speed on Enemy | V42: Down
A43: Theft | B43: Enemy Spawn | C43: Enemy Ability | D43: Items | E43: Item Amount | F43: Enemy Attack | G43: Down | H43: Loot | I43: Loot Amount | J43: Enemy Attack | K43: Down | L43: Economy | M43: Gold | N43: Enemy Attack | O43: Down | U43: Speed on Player | V43: Up
A44: Trample | B44: Enemy Spawn | C44: Enemy Ability | D44: Enemies | E44: Enemy Position | F44: Enemy Turn | G44: Up | U44: Strength on Enemy | V44: Down
A45: Undying | B45: Enemy Spawn | C45: Enemy Ability | D45: Enemies | E45: Enemy Amount | F45: Enemy Defeat | G45: Up | U45: Strength on Player | V45: Up
A46: Arcade Room | B46: Game Completion | C46: Event | D46: Objects | E46: Object Spawn | F46: Gold Use | G46: Up | U46: Stun on Enemy | V46: Up
A47: Alien Baby | B47: Chest | C47: Item | D47: Health | E47: Max Health | F47: Item Pickup | G47: Up | H47: Health | I47: Health Amount | J47: Item Pickup | K47: Up | L47: Enemies | M47: Enemy Max Health | N47: Enemy Spawn | O47: Up | U47: Teleport Nearby Hub | V47: Up
A48: Anchor | B48: Chest | C48: Item | D48: Shields | E48: Temporary Shield Amount | F48: Combat Start | G48: Up | U48: Teleport Random Close | V48: Up
A49: Ban Hammer | B49: Chest | C49: Item | D49: Stats | E49: Bash | F49: Item Pickup | G49: Up | U49: Teleport Random Deckbuilder | V49: Up
A50: Bionic Face Plating | B50: Chest | C50: Item | D50: Statuses | E50: Speed on Player | F50: Passive | G50: Up | H50: Items | I50: Item Amount | J50: Damage Taken | K50: Down | U50: Teleport Start Game | V50: Down
A51: Blood Bag | B51: Object: Blood Donation Machine | C51: Item | D51: Health | E51: Max Health | F51: Item Pickup | G51: Up | H51: Health | I51: Health Amount | J51: Item Pickup | K51: Up | U51: Temporary Shield Amount | V51: Up
A52: Blood Bombs | B52: Chest | C52: Item | D52: Bombs | E52: Bomb Amount | F52: Item Pickup | G52: Up | H52: Health | I52: Health Amount | J52: Bomb Use | K52: Up | U52: Transmute | V52: Up
A53: Brimstone Bombs | B53: Chest | C53: Item | D53: Bombs | E53: Bomb Amount | F53: Item Pickup | G53: Up | H53: Bombs | I53: Bomb Size | J53: Passive | K53: Up | U53: Web Tile | V53: Up
A54: Burning Blood | B54: Starter | C54: Item | D54: Health | E54: Health Amount | F54: Combat End | G54: Up | U54: Identification | V54: Up
A55: Caffeine Pill | B55: Chest | C55: Item | D55: Statuses | E55: Speed on Player | F55: Passive | G55: Up | H55: Pills | I55: Pill Amount | J55: Item Pickup | K55: Up | U55: Enemy Ability | V55: Down
A56: Calling Bell | B56: Boss Chest | C56: Item | D56: Goals | E56: Curse | F56: Item Pickup | G56: Up | H56: Items | I56: Item Amount | J56: Item Pickup | K56: Up | U56: Pill Preference | V56: Up
A57: Cauldron | B57: Chest | C57: Item | D57: Potions | E57: Potion Amount | F57: Item Pickup | G57: Up | U57: Buff on Enemy | V57: Down
A58: Charm of the Vampire | B58: Chest | C58: Item | D58: Health | E58: Health Amount | F58: Enemy Defeat | G58: Up | U58: Debuff on Player | V58: Down
A59: Clover | B59: Chest | C59: Item | D59: Stats | E59: Luck | F59: Passive | G59: Up | U59: Enemy Visibility | V59: Up
A60: Crown | B60: Chest | C60: Item | D60: Goals | E60: Level Up | F60: On Level Up | G60: Up | U60: Enemy Turn | V60: Down
A61: D10 | B61: Chest | C61: Item | D61: Enemies | E61: Enemy Variety | F61: Item Use | G61: Up | U61: Enemy Range | V61: Down
A62: D6 | B62: Starter, Chest | C62: Item | D62: Stats | E62: Scramble | F62: Item Use | G62: Up | U62: End Run | V62: Down
A63: Echo Chamber | B63: Chest | C63: Item | D63: Loot | E63: Loot Copy | F63: Loot Use | G63: Up | U63: Goal Amount | V63: Down
A64: Fortune Necklace | B64: Chest | C64: Item | D64: Stats | E64: Luck | F64: Passive | G64: Up | H64: Items | I64: Item Amount | J64: Damage Taken | K64: Down
A65: Golden Idol | B65: Event: Golden Idol | C65: Item | D65: Economy | E65: Gold | F65: Enemy Defeat | G65: Up
A66: Hollow Heart | B66: Chest | C66: Item | D66: Health | E66: Max Health | F66: Item Pickup | G66: Up
A67: Hot Bombs | B67: Chest | C67: Item | D67: Bombs | E67: Bomb Amount | F67: Item Pickup | G67: Up | H67: Tiles | I67: Fire Tile | J67: Bomb Use | K67: Up
A68: IV Bag | B68: Object: Blood Donation Machine | C68: Item | D68: Health | E68: Health Amount | F68: Item Pickup | G68: Down | H68: Economy | I68: Gold | J68: Item Use | K68: Up
A69: Landmines | B69: Chest | C69: Item | D69: Grid | E69: Friendly Unit Spawn | F69: Combat End | G69: Up
A70: Lord's Parasol | B70: Boss Chest | C70: Item | D70: Items | E70: Item Amount | F70: Shop Purchase | G70: Up
A71: Lucky Foot | B71: Chest | C71: Item | D71: Stats | E71: Luck | F71: Passive | G71: Up | H71: Pills | I71: Pill Preference | J71: Passive | K71: Up
A72: Lucky Hat | B72: Chest | C72: Item | D72: Stats | E72: Luck | F72: Passive | G72: Up | H72: Items | I72: Item Amount | J72: Damage Taken | K72: Down
A73: Lunch | B73: Chest | C73: Item | D73: Health | E73: Max Health | F73: Item Pickup | G73: Up | H73: Health | I73: Health Amount | J73: Item Pickup | K73: Up
A74: Mango | B74: Chest | C74: Item | D74: Health | E74: Max Health | F74: Item Pickup | G74: Up | H74: Health | I74: Health Amount | J74: Item Pickup | K74: Up
A75: Meat on the Bone | B75: Chest | C75: Item | D75: Health | E75: Health Amount | F75: Combat End | G75: Up
A76: Mine-r Construction | B76: Chest | C76: Item | D76: Grid | E76: Grid Height | F76: Item Pickup | G76: Up | H76: Grid | I76: Grid Width | J76: Item Pickup | K76: Up
A77: Mom's Bottle of Pills | B77: Chest | C77: Item | D77: Pills | E77: Pill Amount | F77: Item Use | G77: Up
A78: Mom's Coin Purse | B78: Chest | C78: Item | D78: Pills | E78: Pill Amount | F78: Item Pickup | G78: Up
A79: Oddly Smooth Stone | B79: Chest | C79: Item | D79: Statuses | E79: Dexterity on Player | F79: Passive | G79: Up
A80: Old Coin | B80: Chest | C80: Item | D80: Economy | E80: Gold | F80: Item Pickup | G80: Up
A81: Philosophers Stone | B81: Boss Chest | C81: Item | D81: Statuses | E81: Strength on Enemy | F81: Passive | G81: Up | H81: Grid | I81: Grid Width | J81: Item Pickup | K81: Up
A82: Piggy Bank | B82: Chest | C82: Item | D82: Economy | E82: Gold | F82: Health Lost | G82: Up
A83: Pummarola | B83: Chest; Character Start: Poe Ratcho | C83: Item | D83: Health | E83: Health Amount | F83: Combat End | G83: Up
A84: Red Candle | B84: Chest | C84: Item | D84: Tiles | E84: Fire Tile | F84: Item Use | G84: Up
A85: Reptile Trinket | B85: Chest | C85: Item | D85: Statuses | E85: Strength on Player | F85: Potion Quaff | G85: Up
A86: Ripple Basin | B86: Chest | C86: Item | D86: Shields | E86: Temporary Shield Amount | F86: Game Loss | G86: Up
A87: Runic Dome | B87: Boss Chest | C87: Item | D87: Game Choices | E87: Pre-Combat Enemy Visibility | F87: Passive | G87: Down | H87: Grid | I87: Grid Width | J87: Item Pickup | K87: Up
A88: Sacred Bark | B88: Boss Chest | C88: Item | D88: Potions | E88: Potion Copy | F88: Passive | G88: Up
A89: Snowball | B89: Chest | C89: Item | D89: Stats | E89: Transmute | F89: On Transmute Gain | G89: Up
A90: Staff of Flame | B90: Chest | C90: Item | D90: Tiles | E90: Fire Tile | F90: Item Use | G90: Up
A91: Sticky Bombs | B91: Chest | C91: Item | D91: Bombs | E91: Bomb Amount | F91: Item Pickup | G91: Up | H91: Tiles | I91: Web Tile | J91: Bomb Use | K91: Up
A92: Stigmata | B92: Chest | C92: Item | D92: Health | E92: Max Health | F92: Item Pickup | G92: Up | H92: Health | I92: Health Amount | J92: Item Pickup | K92: Up | L92: Stats | M92: Bash | N92: Item Pickup | O92: Up
A93: The Mark | B93: Chest | C93: Item | D93: Stats | E93: Bash | F93: Item Pickup | G93: Up | H93: Statuses | I93: Speed on Player | J93: Passive | K93: Up
A94: There's Options | B94: Chest | C94: Item | D94: Chest | E94: Chest Size | F94: Passive | G94: Up
A95: Unstable Genome | B95: Chest | C95: Item | D95: Items | E95: Item Amount | F95: Game Completion | G95: Up
A96: Vajra | B96: Chest | C96: Item | D96: Statuses | E96: Strength on Player | F96: Passive | G96: Up
A97: White Beast Statue | B97: Chest | C97: Item | D97: Potions | E97: Potion Amount | F97: Game Completion | G97: Up
A98: Wooden Nickel | B98: Chest | C98: Item | D98: Economy | E98: Gold | F98: Item Use | G98: Up
A99: Blood Donation Machine | B99: Event: Arcade Room; Loot: XIV - Temperance | C99: Object | D99: Economy | E99: Gold | F99: Object Use, Bomb Use | G99: Up | H99: Health | I99: Health Amount | J99: Object Use | K99: Down | L99: Health | M99: Health Amount | N99: Bomb Use | O99: Up
A100: Donation Machine | B100: Event: Arcade Room | C100: Object | D100: Economy | E100: Gold | F100: Object Use | G100: Down | H100: Economy | I100: Gold | J100: Bomb Use | K100: Up
...

Sheet locationsold
A1: Name | B1: Difficulty | C1: Game | D1: Type | E1: Effect
A2: Keep of the Lead Lord | B2: Low | C2: Enter the Gungeon | D2: Building | E2: Guns are 20% more likely to show up
A3: Black Powder Mine | B3: Medium | C3: Enter the Gungeon | D3: Underground | E3: Guns are 20% more likely to show up
A4: Hollow | B4: Medium | C4: Enter the Gungeon | D4: Icy | E4: Guns are 20% more likely to show up
A5: Forge | B5: Hard | C5: Enter the Gungeon | D5: Firey | E5: Guns are 20% more likely to show up
A6: Bullet Hell | B6: Hard | C6: Enter the Gungeon | D6: Undead | E6: Guns are 20% more likely to show up
A7: Basement | B7: Low | C7: The Binding of Isaac | D7: Building | E7: All games in this Location will either be Holy, Devilish, or Stinky (At least one of each if possible)
A8: Burning Basement | B8: Low | C8: The Binding of Isaac | D8: Fiery | E8: All games in this Location will either be Holy, Devilish, or Stinky (At least one of each if possible)
A9: Dross | B9: Low | C9: The Binding of Isaac | D9: Sewage | E9: All games in this Location will either be Holy, Devilish, or Stinky (At least one of each if possible)
A10: Caves | B10: Medium | C10: The Binding of Isaac | D10: Underground | E10: All games in this Location will either be Holy, Devilish, or Stinky (At least one of each if possible)
A11: Flooded Caves | B11: Medium | C11: The Binding of Isaac | D11: Watery | E11: All games in this Location will either be Holy, Devilish, or Stinky (At least one of each if possible)
A12: Necropolis | B12: Medium | C12: The Binding of Isaac | D12: Undead | E12: All games in this Location will either be Holy, Devilish, or Stinky (At least one of each if possible)
... A39: The Garden | B39: Hard | C39: Brutal Orchestra | D39: Chaos | E39: All Enemies Gain Pigment Rich at the start of combat.

Sheet itemsold
A1: Name | B1: Rating | C1: Type | D1: Description | E1: Effect | F1: Reference | G1: tags | H1: File | I1: Requirement | J1: Sorting
A2: Alien Baby | B2: Rare | C2: Pickup, Triggered | D2: Gain +25 Max Health, but at the start of combat, all enemies gain +3 Max HP | E2: item_acquired: gain_max_hp 25; enemy_spawned: +3 enemy_max_hp | F2: Brotato | G2: alien | H2: AlienBaby | I2: N/A | J2: Health
A3: Anchor | B3: Common | C3: Triggered | D3: At the start of combat, Gain +10 Block | E3: combat_start: +10 block | F3: Slay the Spire | G3: sea, ship | H3: Anchor | I3: N/A | J3: Defense
A4: Bag o' Glitter | B4: Uncommon | C4: Weapon | D4: Add the Card "Bag o' Glitter" into your Deck. If you obtain something glittery at least one time, "Bag o' Glitter" Gains (+1/+2) Blind | E4: weapon: bag_o_glitter; verify: Did you obtain something glittery? => +1/+2 Blind | F4: Mewgenics | G4: bag | H4: BagO'Glitter | I4: N/A | J4: Defense
A5: Ballistic Boots | B5: Common | C5: Passive | D5: Gain +1 Speed | E5: passive: +1 speed | F5: Enter the Gungeon | G5: wearable, shoes | H5: BallisticBoots | I5: N/A | J5: Stats
A6: Barrel | B6: Uncommon | C6: Weapon | D6: Add the Card "Barrel" into your Deck. If you obtain at least 1 fish, Gain (1/2) random fish | E6: weapon: barrel; verify: Did you obtain at least 1 fish? => 1/2 random fish | F6: Enter the Gungeon | G6: gun, fish | H6: Barrel | I6: N/A | J6: Offense, Economy
A7: Bear Trap Mask | B7: Uncommon | C7: Triggered | D7: At the start of combat, Gain +4 Block and +1 Bleed Thorns | E7: combat_start: +4 block, +1 bleed_thorns | F7: Mewgenics | G7: wearable, mask | H7: BearTrapMask | I7: N/A | J7: Defense
A8: Beefy Ring | B8: Rare | C8: Scaling | D8: Gain scaling +1 Strength per 20 max health | E8: scaling: +1 strength per 20 max_hp | F8: Megabonk | G8: wearable, ring | H8: BeefyRing | I8: N/A | J8: Stats
A9: Bird Head | B9: Rare | C9: Triggered | D9: Your Strikes inflict Soul Link. | E9: card_grant if_tag=strike: +1 soul_link (enemy) | F9: Mewgenics | G9: bird, evil, animal corpse | H9: BirdHead | I9: N/A | J9: Offense
A10: Bird-Faced Urn | B10: Rare | C10: Triggered | D10: When you play a power, gain +2 Health | E10: card_played if_type=power: +2 hp | F10: Slay the Spire | G10: bird | H10: BirdFacedUrn | I10: N/A | J10: Health
A11: Blasma Pistol | B11: Common | C11: Weapon | D11: Add the Card "Blasma Pistol" into your Deck. If you open more than 10 chests, Gain (10/20) Gold | E11: weapon: blasma_pistol; verify: Did you open more than 10 chests? => gain_gold 10/20 | F11: Flinthook | G11: gun | H11: BlasmaPistol | I11: N/A | J11: Offense, Economy
A12: Blood Magic | B12: Rare | C12: Weapon | D12: Add the Card "Blood Magic" into your Deck. If you create or use a magic circle, "Blood Magic" Gains (+1/+2/) Infuse | E12: weapon: blood_magic; verify: Did you create or use a magic circle? => bump effect#0.infuse +1/+2 | F12: Megabonk | H12: BloodMagic | I12: N/A | J12: Offense, Health
A13: Blood Vial | B13: Common | C13: Triggered | D13: At the start of combat, gain +2 Health | E13: combat_start: +2 hp | F13: Slay the Spire | G13: blood | H13: BloodVial | I13: N/A | J13: Health
A14: Boiling Water | B14: Common | C14: Pickup, Passive | D14: Gain +4 Intelligence and -3 Max Health | E14: passive: +4 intelligence; item_acquired: gain_max_hp -3 | F14: Brotato | G14: drink, water | H14: BoilingWater | I14: N/A | J14: Stats
A15: Boon of Aphrodite | B15: N/A | C15: Boon | D15: If the player charms an enemy gain +1 to all combat roll bonus stats, but 1 of the game choices will be Charmed | F15: Hades | H15: BoonOfAphrodite | I15: N/A | J15: Boon
A16: Boon of Artemis | B16: N/A | C16: Boon | D16: If the player uses ranged strategies primarlity to win the run gain +1 to all combat roll bonus stats, but 1 of the game choices will be Marked | F16: Hades | H16: BoonOfArtemis | I16: N/A | J16: Boon
A17: Boon of Athena | B17: N/A | C17: Boon | D17: If the player negates damage with a shield 5+ times gain +1 to all combat roll bonus stats, but 1 of the game choices will be Shielded | F17: Hades | H17: BoonOfAthena | I17: N/A | J17: Boon
A18: Boon of Hermes | B18: N/A | C18: Boon | D18: If the player beats a game within an hour gain +1 to all combat roll bonus stats, but 1 of the game choices will be Timed | F18: Hades | H18: BoonOfHermes | I18: N/A | J18: Boon
A19: Boon of Poseidon | B19: N/A | C19: Boon | D19: If the player defeats an enemy underwater gain +1 to all combat roll bonus stats, but 1 of the game choices will be Soaked | F19: Hades | H19: BoonOfPoseidon | I19: N/A | J19: Boon
A20: Boon of Zeus | B20: N/A | C20: Boon | D20: If the player defeats an enemy with lightning in their run gain +1 to all combat roll bonus stats, but 1 of the game choices will be Shocked | F20: Hades | H20: BoonOfZeus | I20: N/A | J20: Boon
A21: Bowler Hat | B21: Uncommon | C21: Passive | D21: Gain +3 Luck and 18 Harvesting, but -3% Crit Chance | E21: passive: +3 luck, +18 harvesting, -3 crit_chance | F21: Brotato | G21: wearable, hat | H21: BowlerHat | I21: N/A | J21: Stats, Economy
A22: Brain Candy | B22: Common | C22: Usable | D22: Gain +5 Intelligence this combat/event | E22: item_used: temp_stat intelligence +5 | F22: Mewgenics | G22: drug, pill, consumable | H22: BrainCandy | I22: N/A | J22: Stats
A23: Brass Knuckles | B23: Rare | C23: Triggered | D23: Your Strikes inflict Bruise | E23: card_grant if_tag=strike: +1 bruise (enemy) | F23: Mewgenics | H23: BrassKnuckles | I23: N/A | J23: Offense
A24: Broken Window | B24: Rare | C24: Triggered | D24: At the start of combat, Gain +3 Bleed Thorns and +1 Bleed | E24: combat_start: +3 bleed_thorns, +1 bleed | F24: Mewgenics | G24: glass, wood | H24: BrokenWindow | I24: N/A | J24: Defense
A25: Bronze Scales | B25: Uncommon | C25: Triggered | D25: At the start of combat, Gain +3 Thorns | E25: combat_start: +3 thorns | F25: Slay the Spire | G25: metal | H25: BronzeScales | I25: N/A | J25: Offense
A26: Burning Blood | B26: Starter | C26: Triggered | D26: At the end of combat, Gain +6 Health | E26: combat_end: +6 hp | F26: Slay the Spire | H26: BurningBlood | I26: N/A | J26: Health
A27: Busted Crown | B27: Rare | C27: Passive | D27: Gain +1 Max Energy, but -2 Discovery | E27: passive: +1 max_energy, -2 discovery | F27: Slay the Spire | G27: wearable, hat, crown | H27: BustedCrown | I27: N/A | J27: Energy
A28: Campfire | B28: Uncommon | C28: Passive | D28: Gain +3 Intelligence and +1 Regeneration, but -1 Speed | E28: passive: +3 intelligence, +1 regeneration, -1 speed | F28: Brotato | H28: Campfire | I28: N/A | J28: Stats
A29: Captain's Wheel | B29: Rare | C29: Triggered | D29: Start the 3rd turn of combat with +18 Block | E29: turn_started if_turn=3: +18 block (self) | F29: Slay the Spire | G29: sea, ship | H29: Captain'sWheel | I29: N/A | J29: Defense
A30: Charm of the Vampire | B30: Uncommon | C30: Triggered | D30: When you defeat an enemy, 50% chance to Heal +2 Health | E30: enemy_killed: 50% chance +2 hp | F30: The Binding of Isaac | H30: CharmOfTheVampire | I30: N/A | J30: Health
A31: Clover | B31: Common | C31: Usable | D31: Gain +5 Luck this combat/event | E31: item_used: temp_stat luck +5 | F31: Mewgenics | G31: drug, pill, consumable | H31: Clover | I31: N/A | J31: Stats
A32: Clown Shoes | B32: Uncommon | C32: Triggered | D32: Whenever you don't Perfect a game, (beat a game/combat without losing a run) 50% chance to treat it like you did | E32: perfect: verify Did you Perfect this game? => 50% to treat a non-perfect game as perfected | F32: Haste | G32: wearable, shoes, clown | H32: ClownShoes | I32: N/A | J32: Perfect
A33: Cricket's Head | B33: Rare | C33: Passive | D33: Gain +1 Strength. Multiply all Strength by 1.5 | E33: passive: +1 strength; stat_multiply: strength 1.5 | F33: The Binding of Isaac | G33: dog, animal corpse | H33: CricketsHead | I33: N/A | J33: Stats
A34: Crown | B34: Uncommon | C34: Triggered | D34: When Levelling Up, 50% chance to Level Up an additional time | E34: level_up: 50% chance to Level Up an additional time | F34: Vampire Survivors | G34: wearable, hat, crown | H34: Crown | I34: N/A | J34: Economy
A35: D6 | B35: Uncommon | C35: Charged, 4 | D35: Gain +1 Reroll | E35: charged (charge_cost 4); item_used: gain_stat reroll +1 (adds a Reroll charge, spendable on any reward/shop reroll) | F35: The Binding of Isaac | G35: dice | H35: D6 | I35: N/A | J35: Stats
A36: Darkstone Periapt | B36: Uncommon | C36: Triggered | D36: Gain +6 Max Health whenever you obtain a Curse | E36: curse_applied: gain_max_hp 6 | F36: Slay the Spire | G36: stone, necklace, wearable | H36: DarkstonePeriapt | I36: N/A | J36: Health, Curse
A37: Dead Eye | B37: Rare | C37: Incremental | D37: Every time you hit with an Attack on the same target, every Attack Gains +1 Dmg. Bonus goes away when you miss or change targets. | E37: attack_landed: +1 dead_eye streak (same target); attack_missed: reset dead_eye | F37: The Binding of Isaac | G37: eye | H37: DeadEye | I37: N/A | J37: Offense
A38: Dead Sea Scrolls | B38: Uncommon | C38: Charged, 2 | D38: Trigger the effect of a Random Scroll / Outside of Combat | F38: The Binding of Isaac | G38: historical | H38: DeadSeaScrolls | I38: N/A | J38: Random
A39: Death Orb | B39: Uncommon | C39: Triggered | D39: When you play a power, deal Xx2 damage to each enemy where X is the number of Curses you have | E39: card_played if_type=power: dmg all_enemies value_from=curses x2 type=true (X = curse COUNT, not curse cards; true damage) | F39: Forward: Escape the Fold | G39: orb, evil | H39: DeathOrb | I39: N/A | J39: Power, Curse
A40: Dexecutioner | B40: Uncommon | C40: Weapon | D40: Add the Card "Dexecutioner" into your Deck. If you kill an enemy with a piercing attack at least one time, "Dexecutioner" Gains (+1/+2) Dmg | E40: weapon: dexecutioner; verify: Did you kill an enemy with a piercing attack? => 1/2 dmg | F40: Megabonk | H40: Dexecutioner | I40: N/A | J40: Offense
A41: Disco Biscuit | B41: Common | C41: Usable | D41: Gain +5 Charisma this combat/event | E41: item_used: temp_stat charisma +5 | F41: Mewgenics | G41: drug, pill, consumable | H41: DiscoBiscuit | I41: N/A | J41: Stats
A42: Duplicator | B42: Rare | C42: Triggered | D42: Your Weapon Attack Cards gain Replay 1 | E42: card_grant if_tag=weapon if_type=attack: +Replay 1 (re-resolves the card 1 extra time) | F42: Vampire Survivors | G42: wearable, ring | H42: Duplicator | I42: N/A | J42: Offense
A43: Du-Vu Doll | B43: Rare | C43: Triggered | D43: At the start of each combat, Gain X Power where X is the number of curses you have | E43: combat_started: +X power (self) stacks_from=curses (X = curse COUNT, not curse cards) | F43: Slay the Spire | G43: doll | H43: Du-VuDoll | I43: N/A | J43: Power
A44: Empty Syringe | B44: Rare | C44: Triggered | D44: When Inflicting Bleed or Poison, Inflict +1 Bleed or Poison | E44: status_amplify: +1 bleed, +1 poison (when inflicted on an enemy) | F44: Mewgenics | G44: syringe | H44: EmptySyringe | I44: N/A | J44: Offense
A45: Empty Tome | B45: Uncommon | C45: Triggered | D45: At the start of combat, a random Weapon Attack card in your deck costs 1 less for the rest of the combat. | E45: combat_started: reduce_card_cost 1 tag=weapon type=attack | F45: Vampire Survivors | G45: book | H45: EmptyTome | I45: N/A | J45: Stats
A46: Focus Crystal | B46: Common | C46: Passive | D46: Melee Attacks deal +1 Dmg | E46: attack_damage_bonus: {melee: 1} (player melee attacks deal +1) | F46: Risk of Rain 2 | G46: crystal | H46: FocusCrystal | I46: N/A | J46: Stats
A47: Frozen Egg | B47: Uncommon | C47: Triggered | D47: Whenever you add a Power card to your deck, Upgrade it | E47: upgrade_card_types: power (auto-upgrade Power cards added to deck) | F47: Slay the Spire | G47: egg | H47: FrozenEgg | I47: N/A | J47: Economy
A48: Garlic | B48: Uncommon | C48: Triggered | D48: At the start of combat, gain +1 Brace | E48: combat_started: +1 brace (self) | F48: Super Auto Pets | G48: food, vegetable | H48: Garlic | I48: N/A | J48: Defense
A49: Ginger | B49: Rare | C49: Triggered | D49: You can no longer Gain Weak | E49: status_immunity: weak | F49: Slay the Spire | G49: food | H49: Ginger | I49: N/A | J49: Defense
A50: Glass Eye | B50: Common | C50: Passive | D50: Gain +2 Strength and +1 Luck | E50: passive: +2 strength, +1 luck | F50: The Binding of Isaac | G50: eye, glass | H50: GlassEye | I50: N/A | J50: Stats
A51: Golden Beetle | B51: Rare | C51: Triggered | D51: Whenever you get rid of a Curse or Curse Card, gain one Chest | E51: curse_removed: gain_chest 1; curse_card_removed: gain_chest 1 (a chest = an item reward; counts both curses AND curse cards) | F51: Forward: Escape the Fold | G51: bug | H51: GoldenBeetle | I51: N/A | J51: Curse, Economy
A52: Gremlin Horn | B52: Uncommon | C52: Triggered | D52: When an enemy dies, Gain +1 Energy and Draw 1 card | E52: enemy_killed: gain_energy 1, draw 1 | F52: Slay the Spire | H52: GremlinHorn | I52: N/A | J52: Energy, Draw
A53: Handcuffs | B53: Rare | C53: Passive | D53: Gain +3 Strength, +3 Dexterity, and +3 Intelligence. Your Max Health is capped at its current value | E53: passive: +3 strength, +3 dexterity, +3 intelligence; caps_max_hp: locks max_hp at its current value while owned (held via GameState.max_hp_cap; cleared when the item leaves) | F53: Brotato | G53: military | H53: Handcuffs | I53: N/A | J53: Stats
A54: Happy Flower | B54: Common | C54: Incremental | D54: Every 3 turns, Gain +1 energy | E54: turn_tick: counter key=turns every=3 -> gain_energy 1 | F54: Slay the Spire | G54: flower | H54: HappyFlower | I54: N/A | J54: Energy
A55: Head of the Keeper | B55: Uncommon | C55: Triggered | D55: When you deal Dmg to an Enemy, 5% to Gain 1 Gold | E55: attack_landed: 5% chance gain_gold 1 | F55: The Binding of Isaac | G55: coin | H55: HeadOfTheKeeper | I55: N/A | J55: Economy
A56: Hollow Heart | B56: Common | C56: Pickup | D56: Gain +12 Max Health | E56: item_acquired: gain_max_hp 6 | F56: Vampire Survivors | G56: heart | H56: HollowHeart | I56: N/A | J56: Health
A57: Holy Mantle | B57: Legendary | C57: Triggered | D57: At the start of combat, Gain +1 Buffer | E57: combat_start: +1 buffer (self) | F57: The Binding of Isaac | G57: holy | H57: HolyMantle | I57: N/A | J57: Defense
A58: Horn Cleat | B58: Uncommon | C58: Triggered | D58: Start the 2nd turn of combat with +14 Block | E58: turn_started if_turn=2: +14 block (self) | F58: Slay the Spire | G58: sea, ship | H58: HornCleat | I58: N/A | J58: Defense
A59: Ice Cream | B59: Rare | C59: Triggered | D59: When you end your turn with energy, gain that much energy on your next energy | E59: carries_leftover_energy: true (deckbuilder carries leftover energy to next turn; strategy banks an empower charge on a turn the ability is skipped; action n/a) | F59: Slay the Spire | G59: food | H59: IceCream | I59: N/A | J59: Energy
A60: Jar of Leeches | B60: Rare | C60: Triggered | D60: Your Strikes inflict Leeches | E60: card_grant if_tag=strike: +1 leeches (enemy). Leeches drains the enemy each turn and heals you | F60: Mewgenics | G60: leech, jar | H60: JarOfLeeches | I60: N/A | J60: Offense, Health
A61: Jelly | B61: Common | C61: Scaling | D61: Gain +2 Max Health per Weapon Card in your Deck | E61: scaling: +2 max_hp per weapon card in deck (of: deck_tag:weapon) | F61: Brotato | G61: food | H61: Jelly | I61: N/A | J61: Health
A62: Keeper's Sack | B62: Rare | C62: Triggered | D62: Gain 5 Gold. Whenever you spend 10 Gold, Gain +1 to a Random Stat | E62: item_acquired: gain_gold 5; gold_spend_stat_per=10 (+1 random core stat per 10 gold spent) | F62: The Binding of Isaac | H62: Keeper'sSack | I62: N/A | J62: Economy, Stats
A63: Leech Brood | B63: Rare | C63: Triggered | D63: At the start of combat, inflict +1 Leeches to all enemies. If you start combat above 50% health, lose 10 health | E63: combat_started: +1 leeches (all_enemies); if_hp above 0.5 -> lose_hp 10 (non_lethal, self) | F63: Mewgenics | G63: leech | H63: LeechBrood | I63: N/A | J63: Offense, Health
A64: Leeching Seed | B64: Uncommon | C64: Passive | D64: Your Strikes Gain Heal 1 | E64: card_grant if_tag=strike: heal 1 (self) | F64: Risk of Rain 2 | G64: seed | H64: LeechingSeed | I64: N/A | J64: Health
A65: Lil' Bomber | B65: Common | C65: Weapon | D65: Add the Card "Lil' Bomber" into your Deck. If you kill an enemy with a bomb at least one time, "Lil' Bomber" Gains (+1/+2) Dmg | E65: weapon: lil_bomber; verify: Did you kill an enemy with a bomb? => 1/2 dmg | F65: Enter the Gungeon | G65: gun | H65: LilBomber | I65: N/A | J65: Offense
A66: Little Knife | B66: Uncommon | C66: Scaling | D66: Attacks deal 25% more Dmg to targets with lower Health | E66: lower_hp_damage_mult: 1.25 (player attacks deal x1.25 Dmg, ceil, to targets below player HP) | F66: Brutal Orchestra | G66: knife | H66: LittleKnife | I66: N/A | J66: Offense
A67: Lower Case r | B67: Common | C67: Weapon | D67: Add the Card "Lower Case r" into your Deck. If you beat a game with the letter "R" in the title, "Lower Case r" Gains (+1/+2) Dmg | E67: weapon: lower_case_r; verify: Did you beat a game with the letter R in the title? => 1/2 dmg | F67: Enter the Gungeon | G67: gun | H67: LowerCaseR | I67: N/A | J67: Offense
A68: Lucky Toe | B68: Common | C68: Passive | D68: Gain +2 Luck | E68: passive: +2 luck | F68: The Binding of Isaac | H68: LuckyToe | I68: N/A | J68: Stats
A69: Lunch | B69: Common | C69: Pickup | D69: Gain +8 Max Health and +8 Health | E69: item_acquired: gain_max_hp 6, gain_hp 6 | F69: The Binding of Isaac | G69: food | H69: Lunch | I69: N/A | J69: Health
A70: Mango | B70: Rare | C70: Pickup | D70: Gain + 14 Max Health and +14 Health | E70: item_acquired: gain_max_hp 14, gain_hp 14 | F70: Slay the Spire | G70: food, fruit | H70: Mango | I70: N/A | J70: Health
A71: Meat on the Bone | B71: Uncommon | C71: Triggered | D71: Whenever your Health is at 50% or below Max Health at the end of combat, gain +12 Health | E71: combat_ended: if_hp below 0.5 -> gain_hp 12 (heal when at/below 50% HP) | F71: Slay the Spire | G71: food, meat | H71: MeatOnTheBone | I71: N/A | J71: Health
A72: Mercury Hourglass | B72: Uncommon | C72: Triggered | D72: At the start of your turn, Deal 3 Dmg to all enemies | E72: turn_started: dmg 3 (all_enemies) | F72: Slay the Spire | H72: MercuryHourglass | I72: N/A | J72: Offense
A73: Metal Plate | B73: Uncommon | C73: Triggered | D73: When you kill an enemy, Gain +1 Brace | E73: enemy_killed: +1 brace (self) | F73: Mewgenics | G73: scrap, metal | H73: MetalPlate | I73: N/A | J73: Defense
A74: Molten Egg | B74: Uncommon | C74: Triggered | D74: Whenever you add an Attack card to your deck, Upgrade it | E74: upgrade_card_types: attack (auto-upgrade Attack cards added to deck) | F74: Slay the Spire | G74: egg | H74: MoltenEgg | I74: N/A | J74: Economy
A75: More Options | B75: Uncommon | C75: Passive | D75: Gain +1 Field of View, get an extra option in the space choice | E75: passive: +1 fov_bonus (an extra overworld portal option) | F75: The Binding of Isaac | H75: MoreOptions | I75: N/A | J75: Stats
A76: Mummified Hand | B76: Rare | C76: Triggered | D76: When you play a power, a random card in your hand becomes free to play this turn | E76: card_played if_type=power: free_random_hand_card (deckbuilder: random hand card costs 0 this turn; strategy: a random other ability needs no play this turn, still spends a use; action: slashes attack cooldowns) | F76: Slay the Spire | G76: mummy | H76: MummifiedHand | I76: N/A | J76: Power, Energy
A77: Nunchaku | B77: Common | C77: Incremental | D77: Every time you play 10 attacks, gain +1 Energy | E77: card_played if_type=attack: counter key=attacks_total every=10 -> gain_energy 1 | F77: Slay the Spire | G77: ninja | H77: Nunchaku | I77: N/A | J77: Offense, Energy
A78: Oddly Smooth Stone | B78: Common | C78: Passive | D78: Gain +3 Dexterity | E78: passive: +3 dexterity | F78: Slay the Spire | G78: stone | H78: OddlySmoothStone | I78: N/A | J78: Stats
A79: Old Coin | B79: Rare | C79: Pickup | D79: Gain 100 Gold | E79: item_acquired: gain_gold 100 | F79: Slay the Spire | G79: coin | H79: OldCoin | I79: N/A | J79: Economy
A80: Ornamental Fan | B80: Uncommon | C80: Incremental | D80: Every time you play 4 attacks in a single turn, Gain +4 Block | E80: card_played if_type=attack: counter key=attacks_this_turn every=4 -> +4 block (self) | F80: Slay the Spire | G80: japan | H80: OrnamentalFan | I80: N/A | J80: Defense
A81: Panda | B81: Rare | C81: Pickup, Passive | D81: Gain +20 Max Health and +2 Luck, but -2 Strength | E81: item_acquired: gain_max_hp 20; passive: +2 luck, -2 strength | F81: Brotato | H81: Panda | I81: N/A | J81: Health, Stats
A82: Paper Bag | B82: Rare | C82: Scaling | D82: Your Charisma is equal to your highest stat | E82: stat_mirror: {charisma: [strength, dexterity, intelligence, charisma]} | F82: Mewgenics | G82: wearable, paper | H82: PaperBag | I82: N/A | J82: Stats
A83: Pen Nib | B83: Common | C83: Incremental | D83: Every 10th attack you play deals double damage | E83: card_played if_type=attack: counter key=attacks_total every=10 -> attack_double | F83: Slay the Spire | H83: PenNib | I83: N/A | J83: Offense
A84: Percs | B84: Common | C84: Usable | D84: Gain +10 Block | E84: item_used: block 10 (self) | F84: Mewgenics | G84: drug, pill, consumable | H84: Percs | I84: N/A | J84: Defense
A85: Performance Based Health Insurance | B85: Common | C85: Triggered | D85: Whenever you perfect a game (beat a game/combat without losing a run), Gain +5 Health | E85: perfect: gain_hp 5 | F85: Haste | H85: PerformanceBasedHealthInsurance | I85: N/A | J85: Perfect, Health
A86: Philosopher's Stone | B86: Rare | C86: Passive | D86: Gain +1 Max Energy, but all enemies start with 1 Power | E86: passive: +1 max_energy; enemy_spawned: +1 power (enemy) | F86: Slay the Spire | G86: stone | H86: PhilosophersStone | I86: N/A | J86: Energy
A87: Prayer Beads | B87: Rare | C87: Triggered | D87: Whenever you take damage, Gain Temporary +3 Brace until end of this turn | E87: damage_taken: +3 brace temp until end of turn (self) | F87: Mewgenics | G87: monk, wearable, necklace | H87: PrayerBeads | I87: N/A | J87: Defense
A88: Prayer Card | B88: Rare | C88: Triggered | D88: 33% chance to gain +1 Buffer each time you take damage | E88: damage_taken: 33% chance +1 buffer (self) | F88: Mewgenics | G88: card, paper, holy, cardboard | H88: PrayerCard | I88: N/A | J88: Defense
A89: Propeller Hat | B89: Common | C89: Passive | D89: Gain +3 Luck, but -1 Strength | E89: passive: +3 luck, -1 strength | F89: Brotato | G89: wearable, hat | H89: PropellerHat | I89: N/A | J89: Stats
A90: Pummarola | B90: Common | C90: Triggered | D90: At the start of combat, Gain +1 Regeneration | E90: combat_started: +1 regeneration (self) | F90: Vampire Survivors | G90: heart | H90: Pummarola | I90: N/A | J90: Health
A91: Raven Feather | B91: Rare | C91: Triggered | D91: At the start of combat, inflict Soul Link on 2 random enemies | E91: combat_started: +1 soul_link (random_enemies count=2) | F91: Mewgenics | G91: bird | H91: RavenFeather | I91: N/A | J91: Offense
A92: Reactive Trauma Plate | B92: Rare | C92: Triggered | D92: If the player would take lethal damage, negate that damage and destroy this item | E92: negate_lethal: negate a lethal hit, then destroy this item | F92: Caves of Qud | G92: cybernetics | H92: ReactiveTraumaPlate | I92: N/A | J92: Health
